Workbook

Sheet затраты 14.07
C2: https://datalens.yandex-team.ru/wbenuos6lxv4o-subsidy-details-advanced?tab=8Z&state=d05e49c91134 | D2: неделя с 14.07
B3: Zone | C3: на русском | D3: sub/GMV | E3: dXgY | F3: MFG | G3: MFGgeo | H3: Substotal
B4: ekb | C4: =VLOOKUP(B4,'население 2023'!C:D,2,0) -> Екб | D4: 0.063 | E4: 894180 | F4: 20839 | G4: 0 | H4: 918519
B5: spb | C5: =VLOOKUP(B5,'население 2023'!C:D,2,0) -> СПб | D5: 0.011 | E5: 648907 | F5: 5839 | G5: 0 | H5: 658746
B6: novosibirsk | C6: =VLOOKUP(B6,'население 2023'!C:D,2,0) -> Нск | D6: 0.037 | E6: 496835 | F6: 76202 | G6: 0 | H6: 573037
B7: nizhnynovgorod | C7: =VLOOKUP(B7,'население 2023'!C:D,2,0) -> НиНо | D7: 0.089 | E7: 483540 | F7: 29437 | G7: 0 | H7: 518977
B8: rostovondon | C8: =VLOOKUP(B8,'население 2023'!C:D,2,0) -> РнД | D8: 0.031 | E8: 298373 | F8: 24087 | G8: 0 | H8: 322460
B9: krasnodar | C9: =VLOOKUP(B9,'население 2023'!C:D,2,0) -> Краснодар | D9: 0.014 | E9: 276300 | F9: 38621 | G9: 0 | H9: 314921
B10: perm | C10: =VLOOKUP(B10,'население 2023'!C:D,2,0) -> Пермь | D10: 0.085 | E10: 246662 | F10: 54031 | G10: 0 | H10: 305693
B11: kazan | C11: =VLOOKUP(B11,'население 2023'!C:D,2,0) -> Казань | D11: 0.028 | E11: 209530 | F11: 37619 | G11: 0 | H11: 247149
B12: samara | C12: =VLOOKUP(B12,'население 2023'!C:D,2,0) -> Самара | D12: 0.05 | E12: 163371 | F12: 52545 | G12: 0 | H12: 215916
B13: volgograd | C13: =VLOOKUP(B13,'население 2023'!C:D,2,0) -> Влг | D13: 0.086 | E13: 173514 | F13: 10760 | G13: 0 | H13: 184274
B14: sochi | C14: =VLOOKUP(B14,'население 2023'!C:D,2,0) -> Сочи | D14: 0.109 | E14: 88780 | F14: 42638 | G14: 0 | H14: 136465
B15: chelyabinsk | C15: =VLOOKUP(B15,'население 2023'!C:D,2,0) -> Члб | D15: 0.02 | E15: 112047 | F15: 15831 | G15: 0 | H15: 127878
... B103: nakhabino | C103: =VLOOKUP(B103,'население 2023'!C:D,2,0) -> #N/A | D103: 0 | E103: 0 | F103: 304 | G103: 0 | H103: 304

Sheet затраты 07.07
B2: https://datalens.yandex-team.ru/wbenuos6lxv4o-subsidy-details-advanced?tab=8Z&state=cc583fdb1134 | D2: неделя с 07.07
B3: Zone | C3: на русском | D3: sub/GMV | E3: dXgY | F3: MFG | G3: MFGgeo | H3: Substotal
B4: ekb | C4: =VLOOKUP(B4,'население 2023'!C:D,2,0) -> Екб | D4: 0.063 | E4: 855628 | F4: 21412 | G4: 0 | H4: 877040
B5: spb | C5: =VLOOKUP(B5,'население 2023'!C:D,2,0) -> СПб | D5: 0.011 | E5: 593670 | F5: 6043 | G5: 0 | H5: 599713
B6: novosibirsk | C6: =VLOOKUP(B6,'население 2023'!C:D,2,0) -> Нск | D6: 0.044 | E6: 547588 | F6: 124483 | G6: 0 | H6: 680574
B7: nizhnynovgorod | C7: =VLOOKUP(B7,'население 2023'!C:D,2,0) -> НиНо | D7: 0.082 | E7: 460734 | F7: 26875 | G7: 0 | H7: 487609
B8: krasnodar | C8: =VLOOKUP(B8,'население 2023'!C:D,2,0) -> Краснодар | D8: 0.021 | E8: 426600 | F8: 41430 | G8: 0 | H8: 468030
B9: rostovondon | C9: =VLOOKUP(B9,'население 2023'!C:D,2,0) -> РнД | D9: 0.03 | E9: 267994 | F9: 17883 | G9: 0 | H9: 285877
B10: perm | C10: =VLOOKUP(B10,'население 2023'!C:D,2,0) -> Пермь | D10: 0.086 | E10: 250382 | F10: 49825 | G10: 0 | H10: 300207
B11: kazan | C11: =VLOOKUP(B11,'население 2023'!C:D,2,0) -> Казань | D11: 0.025 | E11: 203270 | F11: 32284 | G11: 0 | H11: 235554
B12: volgograd | C12: =VLOOKUP(B12,'население 2023'!C:D,2,0) -> Влг | D12: 0.088 | E12: 179548 | F12: 12564 | G12: 0 | H12: 192112
B13: samara | C13: =VLOOKUP(B13,'население 2023'!C:D,2,0) -> Самара | D13: 0.043 | E13: 150974 | F13: 44420 | G13: 0 | H13: 195394
B14: omsk | C14: =VLOOKUP(B14,'население 2023'!C:D,2,0) -> Омск | D14: 0.053 | E14: 116796 | F14: 2971 | G14: 0 | H14: 119767
B15: chelyabinsk | C15: =VLOOKUP(B15,'население 2023'!C:D,2,0) -> Члб | D15: 0.018 | E15: 91713 | F15: 22115 | G15: 0 | H15: 113828
... B103: shakhty | C103: =VLOOKUP(B103,'население 2023'!C:D,2,0) -> Шахты | D103: 0.014 | E103: 0 | F103: 387 | G103: 0 | H103: 387

Sheet затраты 30.06
B2: https://datalens.yandex-team.ru/wbenuos6lxv4o-subsidy-details-advanced?tab=8Z&state=25c95e031134 | D2: неделя с 30.06
B3: Zone | C3: на русском | D3: sub/GMV | E3: dXgY | F3: MFG | G3: MFGgeo | H3: Substotal | I3: Итого
B4: ekb | C4: =VLOOKUP(B4,'население 2023'!C:D,2,0) -> Екб | D4: 0.058 | E4: 827573 | F4: 21756 | G4: 0 | H4: 851892 | I4: снизить цели
B5: spb | C5: =VLOOKUP(B5,'население 2023'!C:D,2,0) -> СПб | D5: 0.011 | E5: 599473 | F5: 9077 | G5: 0 | H5: 608550 | I5: цели 5т закончились 09.07, а что xl2?
B6: nizhnynovgorod | C6: =VLOOKUP(B6,'население 2023'!C:D,2,0) -> НиНо | D6: 0.091 | E6: 505612 | F6: 32658 | G6: 0 | H6: 538270 | I6: снизить цели
B7: novosibirsk | C7: =VLOOKUP(B7,'население 2023'!C:D,2,0) -> Нск | D7: 0.038 | E7: 468833 | F7: 114164 | G7: 0 | H7: 582997 | I7: добавить искл. тег и снизить мфг в m и l кузовах
B8: krasnodar | C8: =VLOOKUP(B8,'население 2023'!C:D,2,0) -> Краснодар | D8: 0.022 | E8: 447080 | F8: 25202 | G8: 0 | H8: 472282 | I8: сделали недельные цели xl2
B9: rostovondon | C9: =VLOOKUP(B9,'население 2023'!C:D,2,0) -> РнД | D9: 0.027 | E9: 258189 | F9: 23509 | G9: 0 | H9: 281698 | I9: пересмотр целей
B10: perm | C10: =VLOOKUP(B10,'население 2023'!C:D,2,0) -> Пермь | D10: 0.082 | E10: 219276 | F10: 50635 | G10: 0 | H10: 269911
B11: volgograd | C11: =VLOOKUP(B11,'население 2023'!C:D,2,0) -> Влг | D11: 0.097 | E11: 186176 | F11: 9938 | G11: 0 | H11: 196114 | I11: пересмотр целей
B12: kazan | C12: =VLOOKUP(B12,'население 2023'!C:D,2,0) -> Казань | D12: 0.024 | E12: 166300 | F12: 34508 | G12: 0 | H12: 200808 | I12: пересмотр целей и проверить МФГ
B13: samara | C13: =VLOOKUP(B13,'население 2023'!C:D,2,0) -> Самара | D13: 0.042 | E13: 137816 | F13: 41160 | G13: 0 | H13: 178976
B14: omsk | C14: =VLOOKUP(B14,'население 2023'!C:D,2,0) -> Омск | D14: 0.051 | E14: 111866 | F14: 3544 | G14: 0 | H14: 115410
B15: chelyabinsk | C15: =VLOOKUP(B15,'население 2023'!C:D,2,0) -> Члб | D15: 0.017 | E15: 83559 | F15: 17834 | G15: 0 | H15: 101393
B16: kaliningrad | C16: =VLOOKUP(B16,'население 2023'!C:D,2,0) -> Калининград | D16: 0.102 | E16: 82920 | F16: 21362 | G16: 0 | H16: 104282
B17: tumen | C17: =VLOOKUP(B17,'население 2023'!C:D,2,0) -> Тюмень | D17: 0.026 | E17: 70619 | F17: 7037 | G17: 0 | H17: 77656
B18: krasnoyarsk | C18: =VLOOKUP(B18,'население 2023'!C:D,2,0) -> Красноярск | D18: 0.038 | E18: 61526 | F18: 8245 | G18: 0 | H18: 69771
B19: saratov | C19: =VLOOKUP(B19,'население 2023'!C:D,2,0) -> Саратов | D19: 0.055 | E19: 60740 | F19: 26743 | G19: 0 | H19: 88541
B20: ufa | C20: =VLOOKUP(B20,'население 2023'!C:D,2,0) -> Уфа | D20: 0.022 | E20: 60021 | F20: 22978 | G20: 0 | H20: 82999
B21: stavropol | C21: =VLOOKUP(B21,'население 2023'!C:D,2,0) -> Ставрополь | D21: 0.227 | E21: 57727 | F21: 26025 | G21: 0 | H21: 83752 | I21: =IF(D21>15%,"???","") -> ???
B22: moscow | C22: =VLOOKUP(B22,'население 2023'!C:D,2,0) -> Москва | D22: 0.001 | E22: 56910 | F22: 35428 | G22: 1752 | H22: 101025
B23: voronezh | C23: =VLOOKUP(B23,'население 2023'!C:D,2,0) -> Воронеж | D23: 0.015 | E23: 37000 | F23: 8908 | G23: 0 | H23: 45908
B24: irkutsk | C24: =VLOOKUP(B24,'население 2023'!C:D,2,0) -> Иркутск | D24: 0.114 | E24: 34700 | F24: 5806 | G24: 0 | H24: 40506 | I24: =IF(D24>15%,"???","")
B25: astrakhan | C25: =VLOOKUP(B25,'население 2023'!C:D,2,0) -> Астрахань | D25: 0.147 | E25: 27500 | F25: 8423 | G25: 116 | H25: 36039 | I25: =IF(D25>15%,"???","")
B26: barnaul | C26: =VLOOKUP(B26,'население 2023'!C:D,2,0) -> Барнаул | D26: 0.162 | E26: 27391 | F26: 6217 | G26: 0 | H26: 33608 | I26: =IF(D26>15%,"???","") -> ???
B27: orel | C27: =VLOOKUP(B27,'население 2023'!C:D,2,0) -> Орел | D27: 0.137 | E27: 27100 | F27: 9733 | G27: 0 | H27: 36833 | I27: =IF(D27>15%,"???","")
B28: tula | C28: =VLOOKUP(B28,'население 2023'!C:D,2,0) -> Тула | D28: 0.097 | E28: 26200 | F28: 258 | G28: 0 | H28: 26458 | I28: =IF(D28>15%,"???","")
B29: orenburg | C29: =VLOOKUP(B29,'население 2023'!C:D,2,0) -> Оренбург | D29: 0.161 | E29: 23132 | F29: 6849 | G29: 0 | H29: 33781 | I29: =IF(D29>15%,"???","") -> ???
B30: vladivostok | C30: =VLOOKUP(B30,'население 2023'!C:D,2,0) -> Владивосток | D30: 0.123 | E30: 22485 | F30: 1570 | G30: 0 | H30: 24055 | I30: =IF(D30>15%,"???","")
B31: togliatti | C31: =VLOOKUP(B31,'население 2023'!C:D,2,0) -> Тольятти | D31: 0.155 | E31: 20300 | F31: 5038 | G31: 0 | H31: 25338 | I31: =IF(D31>15%,"???","") -> ???
B32: vologda | C32: =VLOOKUP(B32,'население 2023'!C:D,2,0) -> Вологда | D32: 0.276 | E32: 19571 | F32: 2322 | G32: 0 | H32: 21893 | I32: =IF(D32>15%,"???","") -> ???
B33: ryazan | C33: =VLOOKUP(B33,'население 2023'!C:D,2,0) -> Рязань | D33: 0.14 | E33: 19338 | F33: 1780 | G33: 0 | H33: 21118 | I33: =IF(D33>15%,"???","")
B34: krasnoe_selo | C34: =VLOOKUP(B34,'население 2023'!C:D,2,0) -> #N/A | D34: 0.013 | E34: 18610 | F34: 41 | G34: 0 | H34: 18651 | I34: =IF(D34>15%,"???","")
B35: ulianovsk | C35: =VLOOKUP(B35,'население 2023'!C:D,2,0) -> Ульяновск | D35: 0.104 | E35: 14771 | F35: 2441 | G35: 0 | H35: 17212 | I35: =IF(D35>15%,"???","")
... B37: cheboksary | C37: =VLOOKUP(B37,'население 2023'!C:D,2,0) -> Чебоксары | D37: 0.096 | E37: 13467 | F37: 980 | G37: 0 | H37: 14447 | I37: =IF(D37>15%,"???","")
B38: sochi | C38: =VLOOKUP(B38,'население 2023'!C:D,2,0) -> Сочи | D38: 0.04 | E38: 12859 | F38: 38138 | G38: 0 | H38: 50997
B39: volzhskiy | C39: =VLOOKUP(B39,'население 2023'!C:D,2,0) -> Волжский | D39: 0.054 | E39: 12752 | F39: 1423 | G39: 0 | H39: 14175 | I39: =IF(D39>15%,"???","")
B40: akademgorod | C40: =VLOOKUP(B40,'население 2023'!C:D,2,0) -> #N/A | D40: 0.018 | E40: 11103 | F40: 2808 | G40: 0 | H40: 13911 | I40: =IF(D40>15%,"???","")
B41: ivanovo | C41: =VLOOKUP(B41,'население 2023'!C:D,2,0) -> Иваново | D41: 0.158 | E41: 10917 | F41: 20060 | G41: 0 | H41: 30977 | I41: =IF(D41>15%,"???","") -> ???
B42: izhevsk | C42: =VLOOKUP(B42,'население 2023'!C:D,2,0) -> Ижевск | D42: 0.09 | E42: 9555 | F42: 2426 | G42: 0 | H42: 11981 | I42: =IF(D42>15%,"???","")
B43: tomsk | C43: =VLOOKUP(B43,'население 2023'!C:D,2,0) -> Томск | D43: 0.087 | E43: 9500 | F43: 117 | G43: 0 | H43: 9617 | I43: =IF(D43>15%,"???","")
B44: makhachkala | C44: =VLOOKUP(B44,'население 2023'!C:D,2,0) -> Макхачкала | D44: 0.093 | E44: 8218 | F44: 920 | G44: 0 | H44: 9138 | I44: =IF(D44>15%,"???","")
B45: pushkin | C45: =VLOOKUP(B45,'население 2023'!C:D,2,0) -> #N/A | D45: 0.006 | E45: 7652 | F45: 102 | G45: 0 | H45: 7755 | I45: =IF(D45>15%,"???","")
B46: odincovo | C46: =VLOOKUP(B46,'население 2023'!C:D,2,0) -> Одинцово | D46: 0.001 | E46: 7395 | F46: 1713 | G46: 0 | H46: 9108 | I46: =IF(D46>15%,"???","")
B47: vsevolozhsk | C47: =VLOOKUP(B47,'население 2023'!C:D,2,0) -> #N/A | D47: 0.006 | E47: 7193 | F47: 482 | G47: 0 | H47: 7675 | I47: =IF(D47>15%,"???","")
B48: naberezhnyechelny | C48: =VLOOKUP(B48,'население 2023'!C:D,2,0) -> Набережные Челны | D48: 0.144 | E48: 6700 | F48: 5191 | G48: 0 | H48: 11891 | I48: =IF(D48>15%,"???","")
B49: yaroslavl | C49: =VLOOKUP(B49,'население 2023'!C:D,2,0) -> Ярославль | D49: 0.112 | E49: 4500 | F49: 1653 | G49: 0 | H49: 6153 | I49: =IF(D49>15%,"???","")
B50: dzerzhinsky | C50: =VLOOKUP(B50,'население 2023'!C:D,2,0) -> #N/A | D50: 0.001 | E50: 4487 | F50: 3096 | G50: 107 | H50: 7689 | I50: =IF(D50>15%,"???","")
... B103: troick | C103: =VLOOKUP(B103,'население 2023'!C:D,2,0) -> #N/A | D103: 0 | E103: 0 | F103: 265 | G103: 0 | H103: 265 | I103: =IF(D103>15%,"???","")
B104: krasnayapolyana | C104: Красная поляна | D104: 0 | E104: 0 | F104: 0 | G104: 0 | H104: 0

Sheet Итого. субсидии
D2: Параметры целей | L2: Метрики крайней недели
D3: Текущие цели | H3: Предыдущие цели | M3: Из выгрузки | O3: Из доходимости (без отсева) | T3: Файл города
B4: Город | C4: Кузов / Опция | D4: Дата запуска | E4: Дата закрытия | F4: Время работы | G4: Лесенка | H4: Дата запуска | I4: Дата закрытия | J4: Лесенка | K4: dxgy города с 21.07 | L4: крайняя неделя | M4: CDR | N4: NI/GMV опции | O4: SR | P4: SR 3 ступени | Q4: sub dxgy | R4: sub dxgy / gmv опции | S4: sub dxgy / gmv total | T4: Ссылка | U4: Кто? | V4: Итог | W4: Экипажи и опция | X4: Квот в неделю
B5: Мск | C5: XXL2 | D5: 04.08 (ПН) | F5: 7-10 | G5: 2 - 3 500 3 - 7 500 | T5: https://docs.google.com/spreadsheets/d/1L0y7ob_1Aq6VlMgj15NmCKz4X6XGx90-gYNb6ULAbb8/edit?gid=0#gid=0 | U5: Аня | V5: с 04.08 запустили, пока наблюдаем
B6: СПб | C6: XL2 | D6: 19.06 (ЧТ) | E6: - | F6: 7-10 | G6: 16 - 6000 23 - 12000 30 - 20000 | I6: 05.08(ВТ) | J6: 2 - 1200 3 - 2500 4 - 4000 | K6: =VLOOKUP($B6,'затраты 21.07'!$C:$E,3,0) -> 756818 | L6: 45859 | M6: 0.73 | N6: 0.07 | O6: 0.61 | P6: 0.1 | Q6: 616700 | R6: 0.468 | S6: 0.01 | T6: https://docs.google.com/spreadsheets/d/1czRoI-UDhvvJur9xfSI1PxPVCvuaZ04gs3XWKWhPxOQ/edit?gid=0#gid=0 | U6: Илья | V6: с 04.08 перевели на недельные | W6: нет
B7: СПб | C7: XXL | D7: 16.07 (СР) | E7: - | F7: 7-10 | G7: 2- 2000 3- 4000 4- 6000 | H7: 18.06 (СР) | I7: 09.07 (СР) | J7: 2 - 2000 3 - 3000 | K7: =VLOOKUP($B7,'затраты 21.07'!$C:$E,3,0) -> 756818 | L7: 45859 | M7: 0.69 | N7: 0.1 | O7: 0.37 | P7: 0.03 | Q7: 189000 | R7: 0.246 | S7: 0.003 | T7: https://docs.google.com/spreadsheets/d/1czRoI-UDhvvJur9xfSI1PxPVCvuaZ04gs3XWKWhPxOQ/edit?gid=1949845219#gid=1949845219 | U7: Илья | V7: с 04.08 повысили | W7: нет
B8: Екб | C8: S | D8: 10.06 (ВТ) | E8: 45860 | F8: 0-0 | G8: 25 - 2200 35 - 3500 45 - 5000 | H8: 10.06 (ВТ) | I8: 22.07 (ВТ) | J8: 25 - 2200 35 - 3500 45 - 5000 | K8: =VLOOKUP($B8,'затраты 21.07'!$C:$E,3,0) -> 698190 | L8: 45860 | M8: 0.92 | N8: 0.14 | O8: 0.21 | P8: 0.06 | Q8: 0 | R8: 0 | S8: 0 | T8: https://docs.google.com/spreadsheets/d/1GSOUyFNsvVQA-Q_TCpoHkGeW96anrZpdU3rS3pGOfuI/edit?gid=1203612246#gid=1203612246 | U8: Илья | V8: с 22.07 закрыли и запустили на s2 | W8: нет
B9: Екб | C9: S2 | D9: 22.07 (ВТ) | E9: - | F9: 0-0 | G9: 18 - 3500 24 - 5000 30 - 7000 | K9: =VLOOKUP($B9,'затраты 21.07'!$C:$E,3,0) -> 698190 | L9: 45860 | M9: 0.81 | N9: 0.13 | O9: 0.47 | P9: 0.24 | Q9: 45000 | R9: 0.333 | S9: 0.003 | T9: https://docs.google.com/spreadsheets/d/1GSOUyFNsvVQA-Q_TCpoHkGeW96anrZpdU3rS3pGOfuI/edit?gid=1203612246#gid=1203612246 | U9: Илья | V9: с 22.07 запустили | W9: нет
B10: Екб | C10: M | D10: 06.06 (ПТ) | E10: - | F10: 0-0 | G10: 18 - 3000 24 - 4800 30 - 6900 | K10: =VLOOKUP($B10,'затраты 21.07'!$C:$E,3,0) -> 698190 | L10: 45863 | M10: 0.93 | N10: 0.1 | O10: 0.21 | P10: 0.04 | Q10: 242600 | R10: 0.043 | S10: 0.017 | T10: https://docs.google.com/spreadsheets/d/1GSOUyFNsvVQA-Q_TCpoHkGeW96anrZpdU3rS3pGOfuI/edit?gid=689502523#gid=689502523 | U10: Илья | V10: c 18.07 усложнили, снизив доплаты с 08.08 закрыли и запустили цели на m2 | W10: нет
B11: Екб | C11: M2 | V11: с 08.08 запустили
B12: Екб | C12: L | D12: 06.06 (ПТ) | E12: - | F12: 0-0 | G12: 15 - 3000 20 - 4800 25 - 7000 | K12: =VLOOKUP($B12,'затраты 21.07'!$C:$E,3,0) -> 698190 | L12: 45863 | M12: 0.91 | N12: 0.13 | O12: 0.28 | P12: 0.12 | Q12: 0 | R12: 0 | S12: 0 | T12: https://docs.google.com/spreadsheets/d/1GSOUyFNsvVQA-Q_TCpoHkGeW96anrZpdU3rS3pGOfuI/edit?gid=1825489637#gid=1825489637 | U12: Илья | V12: c 25.07 закрыли | W12: 4.0 L2 | X12: 28
B13: Екб | C13: XL2 | D13: 16.06 (ПН) | E13: - | F13: 0-0 | G13: 2 - 1800 3 - 3600 | K13: =VLOOKUP($B13,'затраты 21.07'!$C:$E,3,0) -> 698190 | L13: 45859 | M13: 0.76 | N13: 0.06 | O13: 0.62 | P13: 0.24 | Q13: 226800 | R13: 0.719 | S13: 0.017 | T13: https://docs.google.com/spreadsheets/d/1GSOUyFNsvVQA-Q_TCpoHkGeW96anrZpdU3rS3pGOfuI/edit?gid=648592715#gid=648592715 | U13: Илья | V13: c 04.08 перевели на недельные | W13: нет
B14: Екб | C14: XXL | D14: 09.06 (ПН) | E14: - | F14: 8-10 | G14: 2 - 3000 3 - 4000 4 - 5000 | H14: до 26.05 | J14: 2 - 2000 3 - 3000 4 - 4000 | K14: =VLOOKUP($B14,'затраты 21.07'!$C:$E,3,0) -> 698190 | L14: 45859 | M14: 0.71 | N14: 0.09 | O14: 0.08 | P14: 0 | Q14: 21000 | R14: 0.099 | S14: 0.002 | T14: https://docs.google.com/spreadsheets/d/1GSOUyFNsvVQA-Q_TCpoHkGeW96anrZpdU3rS3pGOfuI/edit?gid=1784196008#gid=1784196008 | U14: Илья | V14: c 04.08 скорректировали | W14: нет
B15: НиНо | C15: M | D15: 06.06 (ПТ) | E15: - | F15: 0-0 | G15: 20 - 3000 25 - 4000 30 - 6000 | K15: =VLOOKUP($B15,'затраты 21.07'!$C:$E,3,0) -> 475066 | L15: 45856 | M15: 0.79 | N15: 0.1 | O15: 0.17 | P15: 0.08 | Q15: 90000 | R15: 0.029 | S15: 0.013 | T15: https://docs.google.com/spreadsheets/d/16MDhDw0nOzJBuAupcd5ZcgtQ7xKgEeScEm9A-AyXTMc/edit?gid=0#gid=0 | U15: Аня | V15: поддерживаем водителей (проблемы со связью и погода) | W15: 4.0 M2 | X15: 18
B16: НиНо | C16: L | D16: 06.06 (ПТ) | E16: - | F16: 0-0 | G16: 15 - 2700 20 - 4000 25 - 6000 | K16: =VLOOKUP($B16,'затраты 21.07'!$C:$E,3,0) -> 475066 | L16: 45856 | M16: 0.75 | N16: 0.08 | O16: 0.21 | P16: 0.08 | Q16: 78300 | R16: 0.048 | S16: 0.011 | T16: https://docs.google.com/spreadsheets/d/16MDhDw0nOzJBuAupcd5ZcgtQ7xKgEeScEm9A-AyXTMc/edit?gid=136358845#gid=136358845 | U16: Аня | V16: поддерживаем водителей (проблемы со связью и погода) | W16: 4.0 L2 | X16: 41
B17: НиНо | C17: XL2 | D17: 20.06 (ПТ) | F17: 8-10 | G17: 7- 3500 12- 6000 17- 9000 | I17: 01.08 (ПТ) | J17: 2 - 1500 3 - 3000 | K17: =VLOOKUP($B17,'затраты 21.07'!$C:$E,3,0) -> 475066 | L17: 45856 | M17: 0.75 | N17: 0.09 | O17: 0.71 | P17: 0.29 | Q17: 88200 | R17: 0.992 | S17: 0.012 | T17: https://docs.google.com/spreadsheets/d/16MDhDw0nOzJBuAupcd5ZcgtQ7xKgEeScEm9A-AyXTMc/edit?gid=777348995#gid=777348995 | U17: Аня | V17: с 01.08 перевели на недельные
B18: НиНо | C18: XXL | D18: 26.05 (ПН) | E18: - | F18: 8-10 | G18: 2 - 2500 3 - 4000 4 - 6000 | K18: =VLOOKUP($B18,'затраты 21.07'!$C:$E,3,0) -> 475066 | L18: 45856 | M18: 0.74 | N18: 0 | O18: 1 | P18: 0.33 | Q18: 25000 | R18: 0.386 | S18: 0.003 | T18: https://docs.google.com/spreadsheets/d/16MDhDw0nOzJBuAupcd5ZcgtQ7xKgEeScEm9A-AyXTMc/edit?gid=545071466#gid=545071466 | U18: Аня | V18: пока норм | W18: 3.0 | X18: 14
B19: Нск | C19: S | D19: 10.06 (ВТ) | E19: 22.07 (ВТ) | F19: 0-0 | G19: 32 - 3000 42 - 4500 52 - 6000 | K19: =VLOOKUP($B19,'затраты 21.07'!$C:$E,3,0) -> 321639 | L19: 45846 | M19: 0.93 | N19: 0.11 | O19: 0.17 | P19: 0.06 | Q19: 223500 | R19: 0.042 | S19: 0.014 | T19: https://docs.google.com/spreadsheets/d/1iA1pnBTSGLeEVcD669DyUKOptWEry9G75QplhINUT_8/edit?gid=52078899#gid=52078899 | U19: Ира | V19: с 22.07 закрыли и запустили цели на s2 | W19: нет
B20: Нск | C20: S2 | D20: 22.07 (ВТ) | F20: 0-0 | G20: 15 - 2200 20 - 3800 25 - 5800 | K20: =VLOOKUP($B20,'затраты 21.07'!$C:$E,3,0) -> 321639 | L20: 45860 | M20: 0.78 | N20: 0.15 | O20: 0.47 | P20: 0.18 | Q20: 34800 | R20: 0.317 | S20: 0.002 | T20: https://docs.google.com/spreadsheets/d/1iA1pnBTSGLeEVcD669DyUKOptWEry9G75QplhINUT_8/edit?gid=644584907#gid=644584907 | U20: Ира | V20: с 22.07 запустили | W20: нет
B21: Нск | C21: M1 | D21: 18.06 (СР) | E21: - | F21: 0-0 | G21: 30 - 3000 35 - 4000 40 - 5000 | K21: =VLOOKUP($B21,'затраты 21.07'!$C:$E,3,0) -> 321639 | L21: 45861 | M21: 0.89 | N21: 0.13 | O21: 0.05 | P21: 0.02 | Q21: 17000 | R21: 0.017 | S21: 0.001 | T21: https://docs.google.com/spreadsheets/d/1iA1pnBTSGLeEVcD669DyUKOptWEry9G75QplhINUT_8/edit?gid=1949640804#gid=1949640804 | U21: Ира | V21: пока норм (внимательно на след. неделе) | W21: нет
B22: Нск | C22: M2 | D22: 18.06 (СР) | E22: - | F22: 0-0 | G22: 20 - 4000 25 - 5200 30 - 7000 | K22: =VLOOKUP($B22,'затраты 21.07'!$C:$E,3,0) -> 321639 | L22: 45861 | M22: 0.85 | N22: 0.07 | O22: 0.43 | P22: 0.25 | Q22: 69000 | R22: 0.086 | S22: 0.004 | T22: https://docs.google.com/spreadsheets/d/1iA1pnBTSGLeEVcD669DyUKOptWEry9G75QplhINUT_8/edit?gid=1980684084#gid=1980684084 | U22: Ира | V22: пока норм | W22: нет
B23: Нск | C23: L1 | D23: 18.06 (СР) | E23: - | F23: 0-0 | G23: 25 - 3200 30 - 4000 35 - 5200 | K23: =VLOOKUP($B23,'затраты 21.07'!$C:$E,3,0) -> 321639 | L23: 45861 | M23: 0.79 | N23: 0.11 | O23: 0.21 | P23: 0.08 | Q23: 20000 | R23: 0.055 | S23: 0.001 | T23: https://docs.google.com/spreadsheets/d/1iA1pnBTSGLeEVcD669DyUKOptWEry9G75QplhINUT_8/edit?gid=934551811#gid=934551811 | U23: Ира | V23: пока норм | W23: 4.0 L2 | X23: 35
B24: Нск | C24: L2 | D24: 23.07 (СР) | E24: - | F24: 0-0 | G24: 20 - 5500 25 - 7000 30 - 8500 | H24: 18.06 (СР) | J24: 20 - 4500 25 - 6000 30 - 7500 | K24: =VLOOKUP($B24,'затраты 21.07'!$C:$E,3,0) -> 321639 | L24: 45861 | M24: 0.78 | N24: 0.04 | O24: 0.29 | P24: 0.07 | Q24: 51500 | R24: 0.083 | S24: 0.003 | T24: https://docs.google.com/spreadsheets/d/1iA1pnBTSGLeEVcD669DyUKOptWEry9G75QplhINUT_8/edit?gid=552174696#gid=552174696 | U24: Ира | V24: с 23.07 подняли бонусы на 1к | W24: 4.0 L2 | X24: 35
B25: Нск | C25: XXL | D25: 26.05 (ПН) | E25: - | F25: 8-10 | G25: 2 - 2000 3 - 3000 4 - 4000 | K25: =VLOOKUP($B25,'затраты 21.07'!$C:$E,3,0) -> 321639 | L25: 45866 | M25: 0.76 | N25: 0.05 | O25: 0.8 | P25: 0.4 | Q25: 98000 | R25: 0.581 | S25: 0.006 | T25: https://docs.google.com/spreadsheets/d/1iA1pnBTSGLeEVcD669DyUKOptWEry9G75QplhINUT_8/edit?gid=1987691835#gid=1987691835 | U25: Ира | V25: норм | W25: нет
B26: Краснодар | C26: XL2 | D26: 14.07 (ПН) | E26: - | F26: 0-0 | G26: 10 - 4000 15 - 6700 20 - 10000 | H26: 16.06 (ПН) | I26: 14.07 (ПН) | J26: 2 - 1800 3 - 3600 | K26: =VLOOKUP($B26,'затраты 21.07'!$C:$E,3,0) -> 253000 | L26: 45866 | M26: 0.75 | N26: 0.07 | O26: 0.55 | P26: 0.23 | Q26: 120800 | R26: 0.242 | S26: 0.006 | T26: https://docs.google.com/spreadsheets/d/1TuWobhfnRPIiTHBvnE25v82b1WFheH4ZP7MAwtDgQm4/edit?gid=0#gid=0 | U26: Илья | V26: с 14.07 перевели на дешевые недельные | W26: нет
B27: Краснодар | C27: XXL | D27: 04.08(ПН) | E27: - | F27: 8-10 | G27: 2 - 3000 3 - 5000 4 - 6000 | H27: 25.04 (ПТ) | K27: =VLOOKUP($B27,'затраты 21.07'!$C:$E,3,0) -> 253000 | L27: 45866 | M27: 0.8 | N27: 0 | O27: 0.5 | P27: 0 | Q27: 287000 | R27: 0.501 | S27: 0.014 | T27: https://docs.google.com/spreadsheets/d/1TuWobhfnRPIiTHBvnE25v82b1WFheH4ZP7MAwtDgQm4/edit?gid=182988229#gid=182988229 | U27: Илья | V27: с 04.08 перевели на недельные | W27: нет
B28: Пермь | C28: M | D28: 18.06 (СР) | E28: - | F28: 0-0 | G28: 16 - 3100 21 - 4500 26 - 5800 | K28: =VLOOKUP($B28,'затраты 21.07'!$C:$E,3,0) -> 246709 | L28: 45847 | M28: 0.91 | N28: 0.04 | O28: 0.34 | P28: 0.18 | Q28: 150400 | R28: 0.086 | S28: 0.042 | T28: https://docs.google.com/spreadsheets/d/1vNDpP86H9Ix43HThliS4SflbtuEXzIeeJUFv5YooVuo/edit?gid=0#gid=0 | U28: Ира | V28: с 30.07 закрыли | W28: 4.0 M2 | X28: 6
B29: Пермь | C29: М2 | D29: 28.07 (ПН) | F29: 0-0 | G29: 15 - 4000 20 - 5500 25 - 8000 | K29: =VLOOKUP($B29,'затраты 21.07'!$C:$E,3,0) -> 246709 | L29: 45866 | M29: 0.9 | N29: 0.03 | O29: 0.36 | P29: 0.14 | Q29: 28000 | R29: 0.129 | S29: 0.007 | T29: https://docs.google.com/spreadsheets/d/1vNDpP86H9Ix43HThliS4SflbtuEXzIeeJUFv5YooVuo/edit?gid=1894564267#gid=1894564267 | U29: Ира | V29: с 28.07 запустили, ждем первые недели | W29: 4.0 M2 | X29: 6
B30: Пермь | C30: L | D30: 18.06 (СР) | E30: - | F30: 0-0 | G30: 15 - 3500 20 - 5000 25 - 7000 | K30: =VLOOKUP($B30,'затраты 21.07'!$C:$E,3,0) -> 246709 | L30: 45861 | M30: 0.91 | N30: 0.09 | O30: 0.33 | P30: 0.1 | Q30: 86000 | R30: 0.111 | S30: 0.024 | T30: https://docs.google.com/spreadsheets/d/1vNDpP86H9Ix43HThliS4SflbtuEXzIeeJUFv5YooVuo/edit?gid=1675272907#gid=1675272907 | U30: Ира | V30: норм | W30: нет
B31: Пермь | C31: L2 | D31: 04.08 (ПН) | F31: 0-0 | G31: 10 - 4000 15 - 7000 20 - 10000 | K31: =VLOOKUP($B31,'затраты 21.07'!$C:$E,3,0) -> 246709 | T31: https://docs.google.com/spreadsheets/d/1vNDpP86H9Ix43HThliS4SflbtuEXzIeeJUFv5YooVuo/edit?gid=846966812#gid=846966812 | U31: Ира | V31: с 04.08 запустили | W31: нет
B32: Казань | C32: XXL | D32: 10.06 (ВТ) | E32: - | F32: 45938 | G32: 2 - 2000 3 - 3000 4 - 4000 | K32: =VLOOKUP($B32,'затраты 21.07'!$C:$E,3,0) -> 203000 | L32: 45860 | M32: 0.84 | N32: 0.04 | O32: 0.2 | P32: 0 | Q32: 56000 | R32: 0.607 | S32: 0.006 | T32: https://docs.google.com/spreadsheets/d/1OqzNl9qrNvyJyfxhZgbB7gQpJqh63bSXw8g1V34SDl4/edit?gid=0#gid=0 | U32: Илья | V32: c 07.08 повысили бонусы | W32: 3.0 XXL0 | X32: 21
B33: Самара | C33: S2 | D33: 18.06 (СР) | E33: - | F33: 0-0 | G33: 14 - 2500 19 - 3500 24 - 4800 | K33: =VLOOKUP($B33,'затраты 21.07'!$C:$E,3,0) -> 198851 | L33: 45861 | M33: 0.8 | N33: 0.11 | O33: 0.5 | P33: 0.25 | Q33: 30000 | R33: 0.338 | S33: 0.007 | T33: https://docs.google.com/spreadsheets/d/1N92gj8zaiRTTIOlHH0d-jqlQXdXx47QqJ7X_p4JnLJs/edit?gid=95711931#gid=95711931 | U33: Илья | V33: с 23.07 повысили бонусы | W33: нет
B34: Самара | C34: M2 | D34: 18.06 (СР) | E34: - | F34: 0-0 | G34: 15 - 3000 20 - 4500 25 - 5900 | K34: =VLOOKUP($B34,'затраты 21.07'!$C:$E,3,0) -> 198851 | L34: 45861 | M34: 0.8 | N34: 0.08 | O34: 0.45 | P34: 0.27 | Q34: 29800 | R34: 0.098 | S34: 0.007 | T34: https://docs.google.com/spreadsheets/d/1N92gj8zaiRTTIOlHH0d-jqlQXdXx47QqJ7X_p4JnLJs/edit?gid=35461677#gid=35461677 | U34: Илья | V34: с 23.07 повысили бонусы | W34: нет
B35: Самара | C35: L | D35: 18.06 (СР) | E35: - | F35: 0-0 | G35: 20 - 4000 25 - 5000 30 - 6500 | K35: =VLOOKUP($B35,'затраты 21.07'!$C:$E,3,0) -> 198851 | L35: 45861 | M35: 0.87 | N35: 0.12 | O35: 0.21 | P35: 0.03 | Q35: 0 | R35: 0 | S35: 0 | T35: https://docs.google.com/spreadsheets/d/1N92gj8zaiRTTIOlHH0d-jqlQXdXx47QqJ7X_p4JnLJs/edit?gid=1230488956#gid=1230488956 | U35: Илья | V35: с 30.07 закрыть для l и запустить на l1 | W35: нет
B36: Самара | C36: L1 | D36: 30.07 (СР) | F36: 0-0 | G36: 18 - 4000 26 - 6000 34 - 8000 | K36: =VLOOKUP($B36,'затраты 21.07'!$C:$E,3,0) -> 198851 | L36: 45861 | M36: 0.82 | N36: 0.14 | O36: 0.29 | P36: 0 | Q36: 8000 | R36: 0.102 | S36: 0.002 | T36: https://docs.google.com/spreadsheets/d/1N92gj8zaiRTTIOlHH0d-jqlQXdXx47QqJ7X_p4JnLJs/edit?gid=1760356234#gid=1760356234 | U36: Илья | V36: с 30.07 запустили
B37: Самара | C37: L2 | D37: 14.07 (ПН) | E37: - | F37: 45938 | G37: 7 - 2500 11 - 4000 15 - 6000 | H37: 24.03 (ПН) | I37: 14.07 (ПН) | J37: 6 - 2000 9 - 3500 12 - 5000 | K37: =VLOOKUP($B37,'затраты 21.07'!$C:$E,3,0) -> 198851 | L37: 45859 | M37: 0.59 | N37: 0.08 | O37: 0.8 | P37: 0.8 | Q37: 24000 | R37: 0.245 | S37: 0.005 | T37: https://docs.google.com/spreadsheets/d/1N92gj8zaiRTTIOlHH0d-jqlQXdXx47QqJ7X_p4JnLJs/edit?gid=643337644#gid=643337644 | U37: Илья | V37: с 14.07 подняли лесенку с 04.08 подняли лесенку | W37: нет
B38: Самара | C38: XL | D38: 18.06 (СР) | E38: - | F38: 0-0 | G38: 20 - 4500 25 - 5800 30 - 7000 | K38: =VLOOKUP($B38,'затраты 21.07'!$C:$E,3,0) -> 198851 | L38: 45861 | M38: 0.75 | N38: 0.15 | O38: 0.15 | P38: 0.12 | Q38: 32500 | R38: 0.176 | S38: 0.008 | T38: https://docs.google.com/spreadsheets/d/1N92gj8zaiRTTIOlHH0d-jqlQXdXx47QqJ7X_p4JnLJs/edit?gid=1880382121#gid=1880382121 | U38: Илья | V38: с 06.08 упростили, повысив доплаты | W38: нет
B39: РнД | C39: M2 | D39: 17.06 (ВТ) | E39: - | F39: 0-0 | G39: 15 - 3500 20 - 5000 25 - 6500 | H39: 29.07(ВТ) | J39: 20-5000 25-7000 30-9000 | K39: =VLOOKUP($B39,'затраты 21.07'!$C:$E,3,0) -> 177603 | L39: 45846 | M39: 0.78 | N39: 0.12 | O39: 0.37 | P39: 0.15 | Q39: 53000 | R39: 0.185 | S39: 0.008 | T39: https://docs.google.com/spreadsheets/d/18AVdPrLcJZrUzdQEUvrE4fCsoubl_u2WBWKPLhsb6R8/edit?gid=0#gid=0 | U39: Аня | V39: c 29.07 усложнили лесенку+повысили бонусы | W39: нет
B40: РнД | C40: L2 | D40: 17.06 (ВТ) | E40: - | F40: 0-0 | G40: 15 - 4000 20 - 5500 25 - 7000 | H40: 29.07(ВТ) | J40: 20-5500 25-7500 30-10000 | K40: =VLOOKUP($B40,'затраты 21.07'!$C:$E,3,0) -> 177603 | L40: 45846 | M40: 0.85 | N40: 0.17 | O40: 0.39 | P40: 0.11 | Q40: 37000 | R40: 0.103 | S40: 0.005 | T40: https://docs.google.com/spreadsheets/d/18AVdPrLcJZrUzdQEUvrE4fCsoubl_u2WBWKPLhsb6R8/edit?gid=108554741#gid=108554741 | U40: Аня | V40: c 29.07 усложнили лесенку+повысили бонусы | W40: нет
B41: РнД | C41: XL2 | D41: 22.07(ВТ) | E41: - | F41: 0-0 | G41: 7 -3000 12 -5500 17 -8500 | H41: 16.06 (ПН) | I41: 21.07(ПН) | J41: 2 - 1800 3 - 3600 | K41: =VLOOKUP($B41,'затраты 21.07'!$C:$E,3,0) -> 177603 | L41: 45846 | M41: 0.66 | N41: 0.02 | O41: 0.36 | P41: 0.09 | Q41: 63000 | R41: 1.247 | S41: 0.009 | T41: https://docs.google.com/spreadsheets/d/18AVdPrLcJZrUzdQEUvrE4fCsoubl_u2WBWKPLhsb6R8/edit?gid=188909213#gid=188909213 | U41: Аня | V41: с 22.07 перевели на недельные цели возможно, с 5 поднять бонусы | W41: нет
B42: РнД | C42: XXL | D42: 29.05 (ЧТ) | E42: - | F42: 8-10 | G42: 2 - 3000 3 - 5000 | K42: =VLOOKUP($B42,'затраты 21.07'!$C:$E,3,0) -> 177603 | L42: 45860 | M42: 0.77 | N42: 0.01 | O42: 0.38 | P42: 0 | Q42: 63000 | R42: 0.398 | S42: 0.006 | T42: https://docs.google.com/spreadsheets/d/18AVdPrLcJZrUzdQEUvrE4fCsoubl_u2WBWKPLhsb6R8/edit?gid=127809949#gid=127809949 | U42: Аня | V42: пока норм | W42: нет
B43: Влг | C43: S | D43: 22.07 (ВТ) | E43: - | F43: 0-0 | G43: 20 - 2500 25 - 3500 30 - 5000 | H43: 17.06 (ВТ) | I43: 22.07 (ВТ) | J43: 10 - 1700 15 - 3000 20 - 4500 | K43: =VLOOKUP($B43,'затраты 21.07'!$C:$E,3,0) -> 129219 | L43: 45867 | M43: 0.89 | N43: 0.06 | O43: 0.28 | P43: 0.07 | Q43: 55500 | R43: 0.085 | S43: 0.028 | T43: https://docs.google.com/spreadsheets/d/17RbyFXZEw411mBewVwYnr5338Cu7ZnlGM4-9iv5PfiU/edit?gid=0#gid=0 | U43: Илья | V43: с 22.07 усложнили, снизив доплаты | W43: нет
B44: Влг | C44: M2 | D44: 22.07 (ВТ) | E44: - | F44: 0-0 | G44: 15 - 3500 20 - 5000 25 - 7000 | H44: 17.06 (ВТ) | I44: 22.07 (ВТ) | J44: 16 - 3000 20 - 4000 24 - 5500 | K44: =VLOOKUP($B44,'затраты 21.07'!$C:$E,3,0) -> 129219 | L44: 45867 | M44: 0.72 | N44: 0 | O44: 0.71 | P44: 0.29 | Q44: 26000 | R44: 0.186 | S44: 0.013 | T44: https://docs.google.com/spreadsheets/d/17RbyFXZEw411mBewVwYnr5338Cu7ZnlGM4-9iv5PfiU/edit?gid=918920042#gid=918920042 | U44: Илья | V44: с 22.07 повысили | W44: 4.0 M2 | X44: 13
B45: Влг | C45: L | D45: 22.07 (ВТ) | E45: - | F45: 0-0 | G45: 15 - 2600 20 - 3600 25 - 5200 | H45: 17.06 (ВТ) | I45: 22.07 (ВТ) | J45: 12 - 1700 17 - 2700 22 - 4000 | K45: =VLOOKUP($B45,'затраты 21.07'!$C:$E,3,0) -> 129219 | L45: 45867 | M45: 0.76 | N45: 0.07 | O45: 0.24 | P45: 0.14 | Q45: 37400 | R45: 0.106 | S45: 0.019 | T45: https://docs.google.com/spreadsheets/d/17RbyFXZEw411mBewVwYnr5338Cu7ZnlGM4-9iv5PfiU/edit?gid=1524953876#gid=1524953876 | U45: Илья | V45: с 22.07 повысили | W45: нет
B46: Омск | C46: S | D46: 23.06 (ПН) | E46: - | F46: 0-0 | G46: 15 - 1200 20 - 2000 25 - 3000 | K46: =VLOOKUP($B46,'затраты 21.07'!$C:$E,3,0) -> 103592 | L46: 45866 | M46: 0.92 | N46: 0.06 | O46: 0.28 | P46: 0.15 | Q46: 52100 | R46: 0.089 | S46: 0.025 | T46: https://docs.google.com/spreadsheets/d/19EziZnFFdo0ob0PbflK_wBvlGL24rKE3oxYLaVFGRWo/edit?gid=1675272907#gid=1675272907 | U46: Ира | V46: норм (пересмотреть на след.неделе)
B47: Омск | C47: M | D47: 19.06 (ЧТ) | E47: - | F47: 0-0 | G47: 15 - 2800 20 - 4200 25 - 5800 | K47: =VLOOKUP($B47,'затраты 21.07'!$C:$E,3,0) -> 103592 | L47: 45862 | M47: 0.86 | N47: 0.08 | O47: 0.34 | P47: 0.12 | Q47: 99600 | R47: 0.096 | S47: 0.051 | T47: https://docs.google.com/spreadsheets/d/19EziZnFFdo0ob0PbflK_wBvlGL24rKE3oxYLaVFGRWo/edit?gid=1487637572#gid=1487637572 | U47: Ира | V47: с 26.07 упростили и повысили доплаты | W47: нет
B48: Омск | C48: M2 | D48: 28.07 (ПН) | F48: 0-0 | G48: 10 -2300 15 -4000 20-5800 | K48: =VLOOKUP($B48,'затраты 21.07'!$C:$E,3,0) -> 103592 | L48: 45866 | M48: 0.69 | N48: 0.11 | O48: 0.36 | P48: 0.09 | Q48: 16100 | R48: 0.073 | S48: 0.008 | T48: https://docs.google.com/spreadsheets/d/19EziZnFFdo0ob0PbflK_wBvlGL24rKE3oxYLaVFGRWo/edit?gid=872020010#gid=872020010 | U48: Ира | V48: c 28.07 запустили, ждем первые недели
B49: Омск | C49: L | D49: 28.07 (ПН) | F49: 0-0 | G49: 10 -1700 15 -3500 20 -6000 | K49: =VLOOKUP($B49,'затраты 21.07'!$C:$E,3,0) -> 103592 | L49: 45866 | M49: 0.74 | N49: 0.11 | O49: 0.37 | P49: 0.09 | Q49: 55200 | R49: 0.14 | S49: 0.026 | T49: https://docs.google.com/spreadsheets/d/19EziZnFFdo0ob0PbflK_wBvlGL24rKE3oxYLaVFGRWo/edit?gid=1154961347#gid=1154961347 | U49: Ира | V49: c 28.07 запустили, ждем первые недели
B50: Члб | C50: M2 | D50: 17.06 (ВТ) | E50: - | F50: 0-0 | G50: 20 - 3000 25 - 4000 30 - 6000 | H50: 29.07(ВТ) | J50: 25 -4000 30 -5500 35 -7000 | K50: =VLOOKUP($B50,'затраты 21.07'!$C:$E,3,0) -> 90265 | L50: 45846 | M50: 0.8 | N50: 0.05 | O50: 0.38 | P50: 0.38 | Q50: 30000 | R50: 0.107 | S50: 0.006 | T50: https://docs.google.com/spreadsheets/d/1OfYWuJt43x1-av1P9U1r-GW1ZaX2y-EEC_LKJi8cKoc/edit?gid=773532169#gid=773532169 | U50: Аня | V50: c 29.07 усложнили лесенку | W50: нет
B51: Члб | C51: L2 | D51: 17.06 (ВТ) | E51: - | F51: 0-0 | G51: 20 - 3500 25 - 5000 30 - 7000 | H51: 29.07(ВТ) | J51: 22 -4000 27 -5500 32 -7500 | K51: =VLOOKUP($B51,'затраты 21.07'!$C:$E,3,0) -> 90265 | L51: 45846 | M51: 0.63 | N51: 0.05 | O51: 0.58 | P51: 0.25 | Q51: 39500 | R51: 0.337 | S51: 0.008 | T51: https://docs.google.com/spreadsheets/d/1OfYWuJt43x1-av1P9U1r-GW1ZaX2y-EEC_LKJi8cKoc/edit?gid=1286383306#gid=1286383306 | U51: Аня | V51: c 29.07 усложнили лесенку | W51: 4.0 L2 | X51: 28
B52: Сочи | C52: S | D52: 14.07(ПН) | E52: - | F52: 0-0 | G52: 15-1800 20-2700 25-3700 | K52: =VLOOKUP($B52,'затраты 21.07'!$C:$E,3,0) -> 78595 | L52: 45852 | M52: 0.77 | N52: 0.11 | O52: 0.25 | P52: 0.1 | Q52: 28300 | R52: 0.0387 | S52: 0.0164 | T52: https://docs.google.com/spreadsheets/d/17j7atKraLC6Cygf8t42ScZmS45St2QfYmHFfZWBq2oU/edit?gid=1026787686#gid=1026787686 | U52: Аня | V52: с 14.07 запустили | W52: нет
B53: Сочи | C53: M | D53: 14.07(ПН) | E53: - | F53: 0-0 | G53: 14-2200 19-3200 24-4200 | K53: =VLOOKUP($B53,'затраты 21.07'!$C:$E,3,0) -> 78595 | L53: 45852 | M53: 0.85 | N53: 0.13 | O53: 0.38 | P53: 0.18 | Q53: 63800 | R53: 0.0872 | S53: 0.037 | T53: https://docs.google.com/spreadsheets/d/17j7atKraLC6Cygf8t42ScZmS45St2QfYmHFfZWBq2oU/edit?gid=0#gid=0 | U53: Аня | V53: с 14.07 запустили | W53: нет
B54: Сочи | C54: L | D54: 18.06 (СР) | E54: - | F54: 0-0 | G54: 12-2400 17-4000 22-5500 | K54: =VLOOKUP($B54,'затраты 21.07'!$C:$E,3,0) -> 78595 | L54: 45840 | M54: 0.59 | N54: 0.11 | O54: 0.21 | P54: 0 | Q54: 11200 | R54: 0.077 | S54: 0.009 | T54: https://docs.google.com/spreadsheets/d/17j7atKraLC6Cygf8t42ScZmS45St2QfYmHFfZWBq2oU/edit?gid=924916616#gid=924916616 | U54: Аня | V54: с 16.07 упростили, повысив доплаты | W54: 3.0 L2 | X54: 28
B55: Уфа | C55: M1 | D55: 08.07 (ВТ) | E55: - | F55: 0-0 | G55: 17-3000 22-4500 27-6000 | H55: 29.07(ВТ) | J55: 15-2700 20-4100 25-5700 | K55: =VLOOKUP($B55,'затраты 21.07'!$C:$E,3,0) -> 76599 | L55: 45860 | M55: 0.91 | N55: 0.1 | O55: 0.32 | P55: 0.04 | Q55: 27400 | R55: 0.1 | S55: 0.008 | T55: https://docs.google.com/spreadsheets/d/1DpW6EQc0CoEBZd58eJWchlgUYn1H3z1lUK_xK-r93Tg/edit?gid=0#gid=0 | U55: Аня | V55: с 05.08 усложнили, снизив доплаты | W55: нет
B56: Уфа | C56: M2 | D56: 10.06 (ВТ) | E56: - | F56: 0-0 | G56: 15 - 3000 20 - 4500 25 - 6500 | K56: =VLOOKUP($B56,'затраты 21.07'!$C:$E,3,0) -> 76599 | L56: 45860 | M56: 0.78 | N56: 0.14 | O56: 0.64 | P56: 0.36 | Q56: 36500 | R56: 0.166 | S56: 0.01 | T56: https://docs.google.com/spreadsheets/d/1DpW6EQc0CoEBZd58eJWchlgUYn1H3z1lUK_xK-r93Tg/edit?gid=0#gid=0 | U56: Аня | V56: пересмотреть | W56: нет
B57: Уфа | C57: L2 | D57: 10.06 (ВТ) | E57: - | F57: 0-0 | G57: 12 - 2700 17 - 4500 22 - 6500 | K57: =VLOOKUP($B57,'затраты 21.07'!$C:$E,3,0) -> 76599 | L57: 45860 | M57: 0.86 | N57: 0.16 | O57: 0.44 | P57: 0 | Q57: 12600 | R57: 0.108 | S57: 0.003 | T57: https://docs.google.com/spreadsheets/d/1DpW6EQc0CoEBZd58eJWchlgUYn1H3z1lUK_xK-r93Tg/edit?gid=1736252366#gid=1736252366 | U57: Аня | V57: пересмотреть | W57: 3.0 L2 | X57: 35
B58: Уфа | C58: XL | D58: 10.06 (ВТ) | E58: - | F58: 0-0 | G58: 12 - 2000 17 - 3500 22 - 5000 | H58: 29.07(ВТ) | J58: 12-2800 17-4200 22-6000 | K58: =VLOOKUP($B58,'затраты 21.07'!$C:$E,3,0) -> 76599 | L58: 45860 | M58: 0.84 | N58: 0.13 | O58: 0.43 | P58: 0.04 | Q58: 29000 | R58: 0.174 | S58: 0.008 | T58: https://docs.google.com/spreadsheets/d/1DpW6EQc0CoEBZd58eJWchlgUYn1H3z1lUK_xK-r93Tg/edit?gid=38963826#gid=38963826 | U58: Аня | V58: с 29.07 подняли бонусы, лесенку оставили прежнюю | W58: нет
B59: Саратов | C59: M2 | D59: 02.06 (ПН) | E59: - | F59: 0-0 | G59: 10-2500 15-4500 20-6500 | I59: 04.08(ПН) | J59: 10 - 2300 15 - 4000 20 - 6000 | K59: =VLOOKUP($B59,'затраты 21.07'!$C:$E,3,0) -> 55191 | L59: 45866 | M59: 0.68 | N59: 0.12 | O59: 0.67 | P59: 0.5 | Q59: 22000 | R59: 0.319 | S59: 0.014 | T59: https://docs.google.com/spreadsheets/d/1SEfStE9sTlQ6ELlMtSN7f5X5MctL6hKP9p7TOywBZiU/edit?gid=1161881018#gid=1161881018 | U59: Илья | V59: с 04.08 повысили бонусы | W59: нет
B60: Саратов | C60: L | D60: 02.06 (ПН) | E60: - | F60: 0-0 | G60: 14- 3500 19- 5700 24- 7800 | I60: 04.08(ПН) | J60: 10 - 2500 15 - 4500 20 - 6500 | K60: =VLOOKUP($B60,'затраты 21.07'!$C:$E,3,0) -> 55191 | L60: 45866 | M60: 0.75 | N60: 0.11 | O60: 0.43 | P60: 0.18 | Q60: 74500 | R60: 0.249 | S60: 0.047 | T60: https://docs.google.com/spreadsheets/d/1SEfStE9sTlQ6ELlMtSN7f5X5MctL6hKP9p7TOywBZiU/edit?gid=0#gid=0 | U60: Илья | V60: с 04.08 усложнили цели | W60: нет
B61: Красноярск | C61: S | D61: 14.07 (ПН) | E61: - | F61: 0-0 | G61: 14 - 1200 19 - 1900 24 - 2600 | K61: =VLOOKUP($B61,'затраты 21.07'!$C:$E,3,0) -> 49586 | L61: 45866 | M61: 0.76 | N61: 0.1 | O61: 0.22 | P61: 0.09 | Q61: 13300 | R61: 0.037 | S61: 0.012 | T61: https://docs.google.com/spreadsheets/d/18-1W6ClhM2wlDXxhfooLWl3f6kPu5DRiH73mOFWO71k/edit?gid=381639436#gid=381639436 | U61: Ира | V61: с 14.07 запустили
B62: Красноярск | C62: M | D62: 25.06 (СР) | E62: - | F62: 0-0 | G62: 12 - 2000 17 - 3000 23 - 4500 | K62: =VLOOKUP($B62,'затраты 21.07'!$C:$E,3,0) -> 49586 | L62: 45861 | M62: 0.72 | N62: 0.14 | O62: 0.11 | P62: 0.03 | Q62: 20000 | R62: 0.032 | S62: 0.017 | T62: https://docs.google.com/spreadsheets/d/18-1W6ClhM2wlDXxhfooLWl3f6kPu5DRiH73mOFWO71k/edit?gid=757892196#gid=757892196 | U62: Ира | V62: пока норм (пролемы со связью)
B63: Красноярск | C63: L | D63: 10.06 (ВТ) | E63: - | F63: 0-0 | G63: 10 - 2000 15 - 3000 20 - 4000 | K63: =VLOOKUP($B63,'затраты 21.07'!$C:$E,3,0) -> 49586 | L63: 45860 | M63: 0.66 | N63: 0.16 | O63: 0.37 | P63: 0 | Q63: 25000 | R63: 0.1 | S63: 0.018 | T63: https://docs.google.com/spreadsheets/d/18-1W6ClhM2wlDXxhfooLWl3f6kPu5DRiH73mOFWO71k/edit?gid=253840735#gid=253840735 | U63: Ира | V63: пока норм (пролемы со связью) | W63: 3.0 L1 и L2 | X63: 21 и 5
B64: Воронеж | C64: S2 | D64: 17.06 (ВТ) | E64: - | F64: 0-0 | G64: 15 - 2400 20 - 3600 25 - 5000 | K64: =VLOOKUP($B64,'затраты 21.07'!$C:$E,3,0) -> 26347 | L64: 45860 | M64: 0.76 | N64: 0.15 | O64: 0.5 | P64: 0.5 | Q64: 10000 | R64: 0.621 | S64: 0.005 | T64: https://docs.google.com/spreadsheets/d/1iJ-64gEpgAh3iaBBpycilmEhR8boXTlZ6eoEqcKsNEU/edit?gid=349295540#gid=349295540 | U64: Ира | V64: норм | W64: нет
B65: Воронеж | C65: M2 | D65: 17.06 (ВТ) | E65: - | F65: 0-0 | G65: 15 - 3000 20 - 4400 25 - 6000 | K65: =VLOOKUP($B65,'затраты 21.07'!$C:$E,3,0) -> 26347 | L65: 45860 | M65: 0.65 | N65: 0.17 | O65: 0.19 | P65: 0.06 | Q65: 12000 | R65: 0.07 | S65: 0.004 | T65: https://docs.google.com/spreadsheets/d/1iJ-64gEpgAh3iaBBpycilmEhR8boXTlZ6eoEqcKsNEU/edit?gid=2004762737#gid=2004762737 | U65: Ира | V65: норм | W65: нет
B66: Воронеж | C66: L1 | D66: 02.12 (ПН) | E66: - | F66: 8-8 | G66: 7 - 1500 12 - 2800 17 - 4900 | H66: 04.08(ПН) | J66: 15- 2700 20- 4000 25- 5500 | K66: =VLOOKUP($B66,'затраты 21.07'!$C:$E,3,0) -> 26347 | L66: 45859 | M66: 0.8 | N66: 0.12 | O66: 0.79 | P66: 0.43 | Q66: 36900 | R66: 0.258 | S66: 0.012 | T66: https://docs.google.com/spreadsheets/d/1iJ-64gEpgAh3iaBBpycilmEhR8boXTlZ6eoEqcKsNEU/edit?gid=1736349620#gid=1736349620 | U66: Ира | V66: с 04.08 усложнили, снизив доплаты | W66: нет
B67: Красная поляна | C67: S | D67: 14.07(ПН) | E67: - | F67: 0-0 | G67: 2-600 3-1200 | K67: =VLOOKUP($B67,'затраты 21.07'!$C:$E,3,0) -> 277 | T67: https://docs.google.com/spreadsheets/d/1TKHE9u1YekcehpH97885IMzMfNmkuirhnIL2WL0D_yg/edit?gid=1311022860#gid=1311022860 | U67: Аня | V67: перевели на дневные | W67: нет
B68: Красная поляна | C68: M | D68: 14.07(ПН) | E68: - | F68: 0-0 | G68: 2-800 3-1800 | K68: =VLOOKUP($B68,'затраты 21.07'!$C:$E,3,0) -> 277 | T68: https://docs.google.com/spreadsheets/d/1TKHE9u1YekcehpH97885IMzMfNmkuirhnIL2WL0D_yg/edit?gid=1311022860#gid=1311022860 | U68: Аня | V68: перевели на дневные | W68: нет

Sheet население 2023
B2: Агломерация / город | C2: Зона / город | D2: Город (рус) | E2: Тип города | F2: Топ по населению | G2: Популяция | H2: Расположение от центра | I2: Км от центра | J2: Субъект РФ, в состав которого входит город | K2: Население, тыс (2023 год)
B3: Moscow | C3: moscow | D3: Москва | E3: Москва | F3: 1 | G3: Москва | H3: Центр | I3: 0 | J3: Город федерального значения Москва | K3: 13104
B4: Saint-Petersburg | C4: spb | D4: СПб | E4: СПб | F4: 2 | G4: СПб | H4: Центр | I4: 0 | J4: Город федерального значения Санкт-Петербург | K4: 5400
B5: Novosibirsk | C5: novosibirsk | D5: Нск | E5: Кор | F5: 3 | G5: 1 млн+ | H5: Центр | I5: 0 | J5: Новосибирская область | K5: 1635
B6: Ekaterinburg | C6: ekb | D6: Екб | E6: Кор | F6: 4 | G6: 1 млн+ | H6: Центр | I6: 0 | J6: Свердловская область | K6: 1539
B7: Kazan | C7: kazan | D7: Казань | E7: Кор | F7: 5 | G7: 1 млн+ | H7: Центр | I7: 0 | J7: Республика Татарстан | K7: 1315
B8: Nizhny Novgorod | C8: nizhnynovgorod | D8: НиНо | E8: Кор | F8: 6 | G8: 1 млн+ | H8: Центр | I8: 0 | J8: Нижегородская область | K8: 1213
B9: Krasnoyarsk | C9: krasnoyarsk | D9: Красноярск | E9: Кор | F9: 7 | G9: 1 млн+ | H9: Центр | I9: 0 | J9: Красноярский край | K9: 1197
B10: Chelyabinsk | C10: chelyabinsk | D10: Члб | E10: Кор | F10: 8 | G10: 1 млн+ | H10: Центр | I10: 0 | J10: Челябинская область | K10: 1183
B11: Samara | C11: samara | D11: Самара | E11: Кор | F11: 9 | G11: 1 млн+ | H11: Центр | I11: 0 | J11: Самарская область | K11: 1164
B12: Ufa | C12: ufa | D12: Уфа | E12: Кор | F12: 10 | G12: 1 млн+ | H12: Центр | I12: 0 | J12: Республика Башкортостан | K12: 1158
B13: Rostov-on-Don | C13: rostovondon | D13: РнД | E13: Кор | F13: 11 | G13: 1 млн+ | H13: Центр | I13: 0 | J13: Ростовская область | K13: 1136
B14: Krasnodar | C14: krasnodar | D14: Краснодар | E14: Кор | F14: 12 | G14: 1 млн+ | H14: Центр | I14: 0 | J14: Краснодарский край | K14: 1121
... B20: Tyumen | C20: tumen | D20: Тюмень | E20: Кор | F20: 18 | G20: 800+ | H20: Центр | I20: 0 | J20: Тюменская область без автономных округов | K20: 856
B21: Togliatti | C21: togliatti | D21: Тольятти | E21: остальные | F21: 19 | G21: 600+ | H21: Центр | I21: 0 | J21: Самарская область | K21: 675
B22: Barnaul | C22: barnaul | D22: Барнаул | E22: остальные | F22: 20 | G22: 600+ | H22: Центр | I22: 0 | J22: Алтайский край | K22: 623
B23: Makhachkala | C23: makhachkala | D23: Макхачкала | E23: остальные | F23: 21 | G23: 600+ | H23: Центр | I23: 0 | J23: Республика Дагестан | K23: 623
B24: Izhevsk | C24: izhevsk | D24: Ижевск | E24: остальные | F24: 22 | G24: 600+ | H24: Центр | I24: 0 | J24: Удмуртская Республика | K24: 621
B25: Khabarovsk | C25: khabarovsk | D25: Хабаровск | E25: остальные | F25: 23 | G25: 600+ | H25: Центр | I25: 0 | J25: Хабаровский край | K25: 617
B26: Ulianovsk | C26: ulianovsk | D26: Ульяновск | E26: остальные | F26: 24 | G26: 600+ | H26: Центр | I26: 0 | J26: Ульяновская область | K26: 613
B27: Irkutsk | C27: irkutsk | D27: Иркутск | E27: остальные | F27: 25 | G27: 600+ | H27: Центр | I27: 0 | J27: Иркутская область | K27: 611
B28: Vladivostok | C28: vladivostok | D28: Владивосток | E28: остальные | F28: 26 | G28: 500+ | H28: Центр | I28: 0 | J28: Приморский край | K28: 597
B29: Yaroslavl | C29: yaroslavl | D29: Ярославль | E29: остальные | F29: 27 | G29: 500+ | H29: Центр | I29: 0 | J29: Ярославская область | K29: 571
B30: - | C30: севастополь | D30: Севастополь | E30: остальные | F30: 28 | G30: 500+ | H30: Центр | I30: 0 | J30: Город федерального значения Севастополь | K30: 558
B31: Tomsk | C31: tomsk | D31: Томск | E31: остальные | F31: 29 | G31: 500+ | H31: Центр | I31: 0 | J31: Томская область | K31: 552
B32: Stavropol | C32: stavropol | D32: Ставрополь | E32: остальные | F32: 30 | G32: 500+ | H32: Центр | I32: 0 | J32: Ставропольский край | K32: 550
... B45: Tula | C45: tula | D45: Тула | E45: остальные | F45: 43 | G45: 400+ | H45: Центр | I45: 0 | J45: Тульская область | K45: 467
B46: Sochi | C46: sochi | D46: Сочи | E46: Кор | F46: 44 | G46: 400+ | H46: Центр | I46: 0 | J46: Краснодарский край | K46: 447
D47: Красная поляна
B48: - | C48: ulanude | D48: Улан-Удэ | E48: остальные | F48: 45 | G48: 400+ | H48: Центр | I48: 0 | J48: Республика Бурятия | K48: 436
B49: Kursk | C49: kursk | D49: Курск | E49: остальные | F49: 46 | G49: 400+ | H49: Центр | I49: 0 | J49: Курская область | K49: 435
B50: Tver | C50: tver | D50: Тверь | E50: остальные | F50: 47 | G50: 400+ | H50: Центр | I50: 0 | J50: Тверская область | K50: 415
B51: Magnitogorsk | C51: magnitogorsk | D51: Магнитогорск | E51: остальные | F51: 48 | G51: 400+ | H51: Центр | I51: 0 | J51: Челябинская область | K51: 409
B52: Surgut | C52: surgut | D52: Сургут | E52: остальные | F52: 49 | G52: 400+ | H52: Центр | I52: 0 | J52: Ханты-Мансийский автономный округ - Югра | K52: 407
B53: Bryansk | C53: bryansk | D53: Брянск | E53: остальные | F53: 50 | G53: 300+ | H53: Центр | I53: 0 | J53: Брянская область | K53: 376
B54: - | C54: yakutsk | D54: Якутск | E54: остальные | F54: 51 | G54: 300+ | H54: Центр | I54: 0 | J54: Республика Саха (Якутия) | K54: 361
B55: Ivanovo | C55: ivanovo | D55: Иваново | E55: остальные | F55: 52 | G55: 300+ | H55: Центр | I55: 0 | J55: Ивановская область | K55: 361
B56: Vladimir | C56: vladimir | D56: Владимир | E56: остальные | F56: 53 | G56: 300+ | H56: Центр | I56: 0 | J56: Владимирская область | K56: 347
B57: - | C57: симферополь | D57: Симферополь | E57: остальные | F57: 54 | G57: 300+ | H57: Центр | I57: 0 | J57: Республика Крым | K57: 338
B58: Nizhny Tagil | C58: nizhnytagil | D58: Нижний Тагил | E58: остальные | F58: 55 | G58: 300+ | H58: Центр | I58: 0 | J58: Свердловская область | K58: 334
B59: Kaluga | C59: kaluga | D59: Калуга | E59: остальные | F59: 56 | G59: 300+ | H59: Центр | I59: 0 | J59: Калужская область | K59: 334
... B62: - | C62: grozniy | D62: Грозный | E62: остальные | F62: 59 | G62: 300+ | H62: Центр | I62: 0 | J62: Чеченская Республика | K62: 331
B63: Volzhskiy | C63: volzhskiy | D63: Волжский | E63: спутник Влг | F63: 60 | G63: 300+ (отдельный спутник) | H63: Восток | I63: 20 | J63: Волгоградская область | K63: 317
B64: Smolensk | C64: smolensk | D64: Смоленск | E64: остальные | F64: 61 | G64: 300+ | H64: Центр | I64: 0 | J64: Смоленская область | K64: 313
B65: Moscow | C65: podolsk | D65: Подольск | E65: СМО | F65: 62 | G65: 300+ (CМО) | H65: Юг | I65: 20 | J65: Московская область | K65: 312
B66: Saransk | C66: saransk | D66: Саранск | E66: остальные | F66: 63 | G66: 300+ | H66: Центр | I66: 0 | J66: Республика Мордовия | K66: 312
B67: Vologda | C67: vologda | D67: Вологда | E67: остальные | F67: 64 | G67: 300+ | H67: Центр | I67: 0 | J67: Вологодская область | K67: 312
B68: Kurgan | C68: kurgan | D68: Курган | E68: остальные | F68: 65 | G68: 300+ | H68: Центр | I68: 0 | J68: Курганская область | K68: 306
B69: Cherepovets | C69: cherepovets | D69: Череповец | E69: остальные | F69: 66 | G69: 300+ | H69: Центр | I69: 0 | J69: Вологодская область | K69: 301
B70: - | C70: arkhangelsk | D70: Архангельск | E70: остальные | F70: 67 | G70: 200+ | H70: Центр | I70: 0 | J70: Архангельская область без Ненецкого | K70: 299
B71: Orel | C71: orel | D71: Орел | E71: остальные | F71: 68 | G71: 200+ | H71: Центр | I71: 0 | J71: Орловская область | K71: 297
B72: Vladikavkaz | C72: vladikavkaz | D72: Владикавказ | E72: остальные | F72: 69 | G72: 200+ | H72: Центр | I72: 0 | J72: Республика Северная Осетия-Алания | K72: 293
B73: Nizhnevartovsk | C73: nizhnevartovsk | D73: Нижневартовск | E73: остальные | F73: 70 | G73: 200+ | H73: Центр | I73: 0 | J73: Ханты-Мансийский автономный округ - Югра | K73: 287
B74: Yoshkar Ola | C74: yoshkarola | D74: Йошкар-Ола | E74: остальные | F74: 71 | G74: 200+ | H74: Центр | I74: 0 | J74: Республика Марий Эл | K74: 283
B75: Sterlitamak | C75: sterlitamak | D75: Стерлитамак | E75: остальные | F75: 72 | G75: 200+ | H75: Центр | I75: 0 | J75: Республика Башкортостан | K75: 279
B76: Murmansk | C76: murmansk | D76: Мурманск | E76: остальные | F76: 73 | G76: 200+ | H76: Центр | I76: 0 | J76: Мурманская область | K76: 267
B77: Moscow | C77: mytishchi | D77: Мытищи | E77: БМО | F77: 74 | G77: 200+ (БМО) | H77: Северо-восток | I77: 0 | J77: Московская область | K77: 266
B78: Kostroma | C78: kostroma | D78: Кострома | E78: остальные | F78: 75 | G78: 200+ | H78: Центр | I78: 0 | J78: Костромская область | K78: 266
B79: Novorossiysk | C79: novorossiysk | D79: Новороссийск | E79: остальные | F79: 76 | G79: 200+ | H79: Центр | I79: 0 | J79: Краснодарский край | K79: 262
B80: Tambov | C80: tambov | D80: Тамбов | E80: остальные | F80: 77 | G80: 200+ | H80: Центр | I80: 0 | J80: Тамбовская область | K80: 259
B81: Moscow | C81: himki | D81: Химки | E81: БМО | F81: 78 | G81: 200+ (БМО) | H81: Север | I81: 0 | J81: Московская область | K81: 257
B82: Nalchik | C82: nalchik | D82: Нальчик | E82: остальные | F82: 79 | G82: 200+ | H82: Центр | I82: 0 | J82: Кабардино-Балкарская Республика | K82: 246
B83: Taganrog | C83: taganrog | D83: Таганрог | E83: остальные | F83: 80 | G83: 200+ | H83: Центр | I83: 0 | J83: Ростовская область | K83: 242
B84: Nizhnekamsk | C84: nizhnekamsk | D84: Нижнекамск | E84: остальные | F84: 81 | G84: 200+ | H84: Центр | I84: 0 | J84: Республика Татарстан | K84: 241
B85: Blagoveshchensk | C85: blagoveshchensk | D85: Благовещенск | E85: остальные | F85: 82 | G85: 200+ | H85: Центр | I85: 0 | J85: Амурская область | K85: 241
B86: - | C86: komsomolsknaamure | D86: Комсомольск-на-Амуре | E86: остальные | F86: 83 | G86: 200+ | H86: Центр | I86: 0 | J86: Хабаровский край | K86: 236
B87: Petrozavodsk | C87: petrozavodsk | D87: Петрозаводск | E87: остальные | F87: 84 | G87: 200+ | H87: Центр | I87: 0 | J87: Республика Карелия | K87: 236
B88: Moscow | C88: lyberci | D88: Люберцы | E88: БМО | F88: 85 | G88: 200+ (БМО) | H88: Юго-восток | I88: 0 | J88: Московская область | K88: 230
B89: Moscow | C89: korolev | D89: Королев | E89: СМО | F89: 86 | G89: 200+ (CМО) | H89: Северо-восток | I89: 7 | J89: Московская область | K89: 227
B90: Saratov | C90: engels | D90: Энгельс | E90: спутник Саратова | F90: 87 | G90: 200+ (спутник) | H90: Юго-восток | I90: 5 | J90: Саратовская область | K90: 223
B91: Velikij Novgorod | C91: velikynovgorod | D91: Великий Новгород | E91: остальные | F91: 88 | G91: 200+ | H91: Центр | I91: 0 | J91: Новгородская область | K91: 223
B92: Shakhty | C92: shakhty | D92: Шахты | E92: остальные | F92: 89 | G92: 200+ | H92: Центр | I92: 0 | J92: Ростовская область | K92: 222
B93: - | C93: bratsk | D93: Братск | E93: остальные | F93: 90 | G93: 200+ | H93: Центр | I93: 0 | J93: Иркутская область | K93: 221
B94: Syktyvkar | C94: syktyvkar | D94: Сыктывкар | E94: остальные | F94: 91 | G94: 200+ | H94: Центр | I94: 0 | J94: Республика Коми | K94: 220
B95: - | C95: angarsk | D95: Ангарск | E95: остальные | F95: 92 | G95: 200+ | H95: Центр | I95: 0 | J95: Иркутская область | K95: 218
B96: Stariy Oskol | C96: stariyoskol | D96: Старый Оскол | E96: остальные | F96: 93 | G96: 200+ | H96: Центр | I96: 0 | J96: Белгородская область | K96: 218
B97: Dzerzhinsk | C97: dzerzhinsk | D97: Дзержинск | E97: спутник НиНо | F97: 94 | G97: 200+ (отдельный спутник) | H97: Запад | I97: 30 | J97: Нижегородская область | K97: 217
B98: - | C98: pskov | D98: Псков | E98: остальные | F98: 95 | G98: 100+ | H98: Центр | I98: 0 | J98: Псковская область | K98: 189
B99: Moscow | C99: krasnogorsk | D99: Красногорск | E99: БМО | F99: 96 | G99: 100+ (БМО) | H99: Северо-запад | I99: 0 | J99: Московская область | K99: 189
B100: Orsk | C100: orsk | D100: Орск | E100: остальные | F100: 97 | G100: 100+ | H100: Центр | I100: 0 | J100: Оренбургская область | K100: 188
B101: Moscow | C101: odincovo | D101: Одинцово | E101: БМО | F101: 98 | G101: 100+ (БМО) | H101: Запад | I101: 0 | J101: Московская область | K101: 186
B102: - | C102: abakan | D102: Абакан | E102: остальные | F102: 99 | G102: 100+ | H102: Центр | I102: 0 | J102: Республика Хакасия | K102: 185
B103: - | C103: armavir | D103: Армавир | E103: остальные | F103: 100 | G103: 100+ | H103: Центр | I103: 0 | J103: Краснодарский край | K103: 184
B104: - | C104: balakovo | D104: Балаково | E104: остальные | F104: 101 | G104: 100+ | H104: Центр | I104: 0 | J104: Саратовская область | K104: 183
B105: - | C105: biysk | D105: Бийск | E105: остальные | F105: 102 | G105: 100+ | H105: Центр | I105: 0 | J105: Алтайский край | K105: 182
B106: - | C106: южно-сахалинск | D106: Южно-Сахалинск | E106: остальные | F106: 103 | G106: 100+ | H106: Центр | I106: 0 | J106: Сахалинская область | K106: 180
B107: - | C107: ussuriysk | D107: Уссурийск | E107: остальные | F107: 104 | G107: 100+ | H107: Центр | I107: 0 | J107: Приморский край | K107: 180
B108: - | C108: prokopyevsk | D108: Прокопьевск | E108: остальные | F108: 105 | G108: 100+ | H108: Центр | I108: 0 | J108: Кемеровская область | K108: 175
B109: - | C109: norilsk | D109: Норильск | E109: остальные | F109: 106 | G109: 100+ | H109: Центр | I109: 0 | J109: Красноярский край | K109: 175
B110: - | C110: rybinsk | D110: Рыбинск | E110: остальные | F110: 107 | G110: 100+ | H110: Центр | I110: 0 | J110: Ярославская область | K110: 174
B111: - | C111: volgodonsk | D111: Волгодонск | E111: остальные | F111: 108 | G111: 100+ | H111: Центр | I111: 0 | J111: Ростовская область | K111: 166
B112: - | C112: almetevsk | D112: Альметьевск | E112: остальные | F112: 109 | G112: 100+ | H112: Центр | I112: 0 | J112: Республика Татарстан | K112: 164
B113: - | C113: syzran | D113: Сызрань | E113: остальные | F113: 110 | G113: 100+ | H113: Центр | I113: 0 | J113: Самарская область | K113: 163
... B119: - | C119: severodvinsk | D119: Северодвинск | E119: остальные | F119: 116 | G119: 100+ | H119: Центр | I119: 0 | J119: Архангельская область без Ненецкого | K119: 156
B120: Moscow | C120: dme | D120: Домодедово | E120: СМО | F120: 117 | G120: 100+ (СМО) | H120: Юг | I120: 20 | J120: Московская область | K120: 155
B121: - | C121: керчь | D121: Керчь | E121: остальные | F121: 118 | G121: 100+ | H121: Центр | I121: 0 | J121: Республика Крым | K121: 153
B122: - | C122: miass | D122: Миасс | E122: остальные | F122: 119 | G122: 100+ | H122: Центр | I122: 0 | J122: Челябинская область | K122: 147
B123: - | C123: salavat | D123: Салават | E123: остальные | F123: 120 | G123: 100+ | H123: Центр | I123: 0 | J123: Республика Башкортостан | K123: 147
B124: - | C124: копейск | D124: Копейск | E124: остальные | F124: 121 | G124: 100+ | H124: Центр | I124: 0 | J124: Челябинская область | K124: 146
B125: - | C125: pjatygorsk | D125: Пятигорск | E125: остальные | F125: 122 | G125: 100+ | H125: Центр | I125: 0 | J125: Ставропольский край | K125: 145
...

Sheet Город+опция
A1: Zone | B1: Fire | C1: Статус | D1: Кто | F1: Цвет | G1: Статус
A2: Krasnoyarsk | B2: S | C2: клиентское | D2: Илья | G2: уже запущено
A3: Krasnoyarsk | B3: L | C3: Готово | D3: Илья | G3: согласовано, но не запущено
A4: Ufa | B4: m_1 | C4: Готово | D4: Аня
A5: Ufa | B5: m_2 | C5: Готово | D5: Аня
A6: Ufa | B6: l_1 | C6: клиентское | D6: Аня | G6: Цели M2 Ростов | S6: Цели M2 Челябинск | AE6: Цели L Красноярск
A7: Ufa | B7: l_2 | C7: Готово | D7: Аня | G7: вручений | H7: бонус | I7: доплата за вручение | J7: водители на ступени | K7: SR | L7: Затраты | M7: sub/gmv | N7: Метрика | O7: lcv_M2 | S7: вручений | T7: бонус | U7: доплата за вручение | V7: водители на ступени | W7: SR | X7: Затраты | Y7: sub/gmv | Z7: Метрика | AA7: lcv_M2 | AE7: вручений | AF7: бонус | AG7: доплата за вручение | AH7: водители на ступени | AI7: SR | AJ7: Затраты | AK7: sub/gmv | AL7: Метрика | AM7: lcv_l_0
A8: Ufa | B8: xl_0 | C8: Готово | D8: Аня | G8: 15 | H8: 3500 | I8: 233.33333 | J8: 3 | K8: 0.09375 | L8: 10500 | N8: AVG Fare. Май | O8: 2730 | S8: 20 | T8: 3000 | U8: 150 | V8: 2 | W8: 0.125 | X8: 6000 | Z8: AVG Fare. Май | AA8: 2256 | AE8: 10 | AF8: 2000 | AG8: 200 | AH8: 4 | AI8: 0.14814815 | AJ8: 8000 | AL8: AVG Fare. Май | AM8: 1544.0027
A9: Rostov-on-Don | B9: m_2 | C9: Готово | D9: Аня | G9: 20 | H9: 5000 | I9: 250 | J9: 3 | K9: 0.09375 | L9: 15000 | S9: 25 | T9: 4000 | U9: 160 | V9: 0 | W9: 0 | X9: 0 | AE9: 15 | AF9: 3000 | AG9: 200 | AH9: 2 | AI9: 0.074074074 | AJ9: 6000 | AL9: 10% от Ср. Чека | AM9: 154.40027
A10: Rostov-on-Don | B10: l_1 | C10: клиентское | D10: Аня | G10: 25 | H10: 6500 | I10: 260 | J10: 3 | K10: 0.09375 | L10: 19500 | N10: GMV. 26.05 | O10: 557000 | S10: 30 | T10: 6000 | U10: 200 | V10: 3 | W10: 0.1875 | X10: 18000 | Z10: GMV. 26.05 | AA10: 270000 | AE10: 20 | AF10: 4000 | AG10: 200 | AH10: 0 | AI10: 0 | AJ10: 0 | AL10: GMV. 26.05 | AM10: 243405.6
A11: Rostov-on-Don | B11: l_2 | C11: готово | D11: Аня | J11: Всего: | K11: 0.28125 | L11: 45000 | M11: 0.080789946 | V11: Всего: | W11: 0.3125 | X11: 24000 | Y11: 0.088888889 | AH11: Всего: | AI11: 0.22222222 | AJ11: 14000 | AK11: 0.057517165
A12: Novosibirsk | B12: van_2 | C12: готово | D12: Ира
A13: Novosibirsk | B13: m_1 | C13: готово | D13: Ира | G13: Цели L2 Ростов | S13: Цели L2 Челябинск
A14: Novosibirsk | B14: m_2 | C14: готово | D14: Ира | G14: вручений | H14: бонус | I14: доплата за вручение | J14: водители на ступени | K14: SR | L14: Затраты | M14: sub/gmv | N14: Метрика | O14: lcv_l2 | S14: вручений | T14: бонус | U14: доплата за вручение | V14: водители на ступени | W14: SR | X14: Затраты | Y14: sub/gmv | Z14: Метрика | AA14: lcv_l2
A15: Novosibirsk | B15: l_1 | C15: готово | D15: Ира | G15: 15 | H15: 4000 | I15: 266.66667 | J15: 5 | K15: 0.17857143 | L15: 20000 | N15: AVG Fare. Май | O15: 2940 | S15: 20 | T15: 3500 | U15: 175 | V15: 0 | W15: 0 | X15: 0 | Z15: AVG Fare. Май | AA15: 3060
A16: Novosibirsk | B16: l_2 | C16: готово | D16: Ира | G16: 20 | H16: 5500 | I16: 275 | J16: 1 | K16: 0.035714286 | L16: 5500 | S16: 25 | T16: 5000 | U16: 200 | V16: 1 | W16: 0.071428571 | X16: 5000
A17: Chelyabinsk | B17: m_1 | C17: клиентское | D17: Аня | G17: 25 | H17: 7000 | I17: 280 | J17: 3 | K17: 0.10714286 | L17: 21000 | N17: GMV. 26.05 | O17: 636500 | S17: 30 | T17: 7000 | U17: 233.33333 | V17: 3 | W17: 0.21428571 | X17: 21000 | Z17: GMV. 26.05 | AA17: 210000
A18: Chelyabinsk | B18: m_2 | C18: Готово | D18: Аня | J18: Всего: | K18: 0.32142857 | L18: 46500 | M18: 0.073055774 | V18: Всего: | W18: 0.28571429 | X18: 26000 | Y18: 0.12380952
A19: Chelyabinsk | B19: l_1 | C19: клиентское | D19: Аня
A20: Chelyabinsk | B20: l_2 | C20: Готово | D20: Аня
A21: Volgograd | B21: S | C21: Готово | D21: Аня
A22: Volgograd | B22: M2 | C22: Готово | D22: Аня
A23: Volgograd | B23: L | C23: Готово | D23: Аня
A24: Krasnodar | B24: van_2 | C24: Готово | D24: Вова | G24: Цели Van2 Краснодар | S24: Цели Van2 Казань | AE24: Цели Van Волгоград
A25: Krasnodar | B25: m_2 | C25: Клиентские | D25: Вова | G25: вручений | H25: бонус | I25: доплата за вручение | J25: водители на ступени | K25: SR | L25: Затраты | M25: sub/gmv | N25: Метрика | S25: вручений | T25: бонус | U25: доплата за вручение | V25: водители на ступени | W25: SR | X25: Затраты | Y25: sub/gmv | Z25: Метрика | AB25: 10%: | AE25: вручений | AF25: бонус | AG25: доплата за вручение | AH25: водители на ступени | AI25: SR | AJ25: Затраты | AK25: sub/gmv | AL25: Метрика
A26: Krasnodar | B26: L2 | C26: Готово | D26: Вова | G26: 12 | H26: 1500 | I26: 125 | J26: 5 | K26: 0.119 | L26: 7 500 | M26: 0.034 | N26: AVG Fare. Май | O26: 2 300 | S26: 10 | T26: 1700 | U26: 170 | V26: 4 | W26: 0.2222 | X26: 6 800 | Y26: 0.068 | Z26: AVG Fare. Май | AA26: 2 400 | AB26: 240 | AE26: 10 | AF26: 1700 | AG26: 170 | AH26: 4 | AI26: 0.2222 | AJ26: 6 800 | AK26: 0.068 | AL26: AVG Fare. Май | AM26: 2 400
A27: Krasnodar | B27: xl | C27: Готово | D27: Вова | G27: 17 | H27: 2500 | I27: 147 | J27: 3 | K27: 0.0714 | L27: 7 500 | M27: 0.034 | S27: 15 | T27: 3000 | U27: 200 | V27: 1 | W27: 0.0556 | X27: 3 000 | Y27: 0.03 | AE27: 15 | AF27: 3000 | AG27: 200 | AH27: 1 | AI27: 0.0556 | AJ27: 3 000 | AK27: 0.03
A28: Kazan | B28: van_2 | C28: Готово | D28: Вова | G28: 22 | H28: 4000 | I28: 182 | J28: 1 | K28: 0.0238 | L28: 4 000 | M28: 0.018 | N28: GMV. 26.05 | O28: 220 000 | S28: 20 | T28: 4500 | U28: 225 | V28: 0 | W28: 0 | X28: - | Y28: 0 | Z28: GMV. 26.05 | AA28: 100 000 | AE28: 20 | AF28: 4500 | AG28: 225 | AH28: 0 | AI28: 0 | AJ28: - | AK28: 0 | AL28: GMV. 26.05 | AM28: 100 000
A29: Kazan | B29: m_2 | C29: Готово | D29: Вова | J29: Всего: | K29: 0.2143 | L29: 19 000 | M29: 0.086 | V29: Всего: | W29: 0.2778 | X29: 9 800 | Y29: 0.098 | AH29: Всего: | AI29: 0.2778 | AJ29: 9 800 | AK29: 0.093366093
A30: Kazan | B30: l_2 | D30: Вова
A31: Kazan | B31: xl_1 | D31: Вова | G31: Цели L2 Краснодар | S31: Цели M2 Казань | AE31: Цели M2 Волгоград
A32: Perm | B32: M | C32: готово | D32: Ира | G32: вручений | H32: бонус | I32: доплата за вручение | J32: водители на ступени | K32: SR | L32: Затраты | M32: sub/gmv | N32: Метрика | S32: вручений | T32: бонус | U32: доплата за вручение | V32: водители на ступени | W32: SR | X32: Затраты | Y32: sub/gmv | Z32: Метрика | AE32: вручений | AF32: бонус | AG32: доплата за вручение | AH32: водители на ступени | AI32: SR | AJ32: Затраты | AK32: sub/gmv | AL32: Метрика | AM32: lcv_M2
A33: Perm | B33: L | C33: готово | D33: Ира | G33: 5 | H33: 1000 | I33: 200 | J33: 30 | K33: 0.1899 | L33: 30 000 | M33: 0.03 | N33: AVG Fare. Май | O33: 3 500 | S33: 10 | T33: 2000 | U33: 200 | V33: 7 | W33: 0.0909 | X33: 14 000 | Y33: 0.028 | Z33: AVG Fare. Май | AA33: 2 700 | AE33: 16 | AF33: 3000 | AG33: 187.5 | AH33: 2 | AI33: 0.28571429 | AJ33: 6000 | AL33: AVG Fare. Май | AM33: 2980
A34: Saratov | B34: S | C34: в работе | D34: Ира | G34: 10 | H34: 2500 | I34: 250 | J34: 9 | K34: 0.057 | L34: 22 500 | M34: 0.023 | S34: 15 | T34: 3500 | U34: 233 | V34: 3 | W34: 0.039 | X34: 10 500 | Y34: 0.021 | AE34: 20 | AF34: 4000 | AG34: 200 | AH34: 1 | AI34: 0.14285714 | AJ34: 4000
A35: Saratov | B35: m_1 | C35: в работе | D35: Ира | G35: 15 | H35: 4500 | I35: 300 | J35: 3 | K35: 0.019 | L35: 13 500 | M35: 0.014 | N35: GMV. 26.05 | O35: 1 000 000 | S35: 20 | T35: 5500 | U35: 275 | V35: 2 | W35: 0.026 | X35: 11 000 | Y35: 0.022 | Z35: GMV. 26.05 | AA35: 500 000 | AE35: 24 | AF35: 5500 | AG35: 229.16667 | AH35: 0 | AI35: 0 | AJ35: 0 | AL35: GMV. 26.05 | AM35: 143110
A36: Saratov | B36: m_2 | C36: готово | D36: Аня | J36: Всего: | K36: 0.2658 | L36: 66 000 | M36: 0.066 | V36: Всего: | W36: 0.1558 | X36: 35 500 | Y36: 0.071 | AH36: Всего: | AI36: 0.42857143 | AJ36: 10000 | AK36: 0.024570025
A37: Saratov | B37: L | C37: готово | D37: Аня
A38: Voronezh | B38: van_2 | C38: готово | D38: Ира | G38: Цели XL Краснодар | AE38: Цели L Волгоград
A39: Voronezh | B39: M | C39: готово | D39: Ира | G39: вручений | H39: бонус | I39: доплата за вручение | J39: водители на ступени | K39: SR | L39: Затраты | M39: sub/gmv | N39: Метрика | AE39: вручений | AF39: бонус | AG39: доплата за вручение | AH39: водители на ступени | AI39: SR | AJ39: Затраты | AK39: sub/gmv | AL39: Метрика | AM39: lcv_l
A40: Voronezh | B40: L | C40: готово | D40: Ира | G40: 5 | H40: 900 | I40: 180 | J40: 107 | K40: 0.1907 | L40: 96 300 | M40: 0.064 | N40: AVG Fare. Май | O40: 2 500 | AE40: 12 | AF40: 1700 | AG40: 141.66667 | AH40: 5 | AI40: 0.090909091 | AJ40: 8500 | AL40: AVG Fare. Май | AM40: 1320
A41: Samara | B41: van_2 | C41: готово | D41: Ира | G41: 10 | H41: 2000 | I41: 200 | J41: 12 | K41: 0.0214 | L41: 24 000 | M41: 0.016 | AE41: 17 | AF41: 2700 | AG41: 158.82353 | AH41: 1 | AI41: 0.018181818 | AJ41: 2700
A42: Samara | B42: m_2 | C42: готово | D42: Ира | G42: 15 | H42: 3500 | I42: 233 | J42: 5 | K42: 0.0089 | L42: 17 500 | M42: 0.012 | N42: GMV. 26.05 | O42: 1 500 000 | AE42: 22 | AF42: 4000 | AG42: 181.81818 | AH42: 6 | AI42: 0.10909091 | AJ42: 24000 | AL42: GMV. 26.05 | AM42: 390000
A43: Samara | B43: L | C43: готово | D43: Ира | J43: Всего: | K43: 0.221 | L43: 137 800 | M43: 0.092 | AH43: Всего: | AI43: 0.21818182 | AJ43: 35200 | AK43: 0.09025641
A44: Samara | B44: xl_0 | C44: готово | D44: Ира
A45: Sochi | B45: L | C45: готово | D45: Илья
G49: Цели M1 Уфа | S49: Цели S Новосибирск | AE49: Цели Van Екатеринбург
G50: вручений | H50: бонус | I50: доплата за вручение | J50: водители на ступени | K50: SR | L50: Затраты | M50: sub/gmv | N50: Метрика | O50: lcv_M1 | S50: вручений | T50: бонус | U50: доплата за вручение | V50: водители на ступени | W50: SR | X50: Затраты | Y50: sub/gmv | Z50: Метрика | AA50: lcv_s | AE50: вручений | AF50: бонус | AG50: доплата за вручение | AH50: водители на ступени | AI50: SR | AJ50: Затраты | AK50: sub/gmv | AL50: Метрика | AM50: S
G51: 17 | H51: 2500 | I51: 147.05882 | J51: 3 | K51: 0.1 | L51: 7500 | N51: AVG Fare. Май | O51: 1910 | S51: 32 | T51: 3000 | U51: 93.75 | V51: 23 | W51: 0.073248408 | X51: 69000 | Z51: AVG Fare. Май | AA51: 857 | AE51: 25 | AF51: 2200 | AG51: 88 | AH51: 33 | AI51: 0.1245283 | AJ51: 72600 | AL51: AVG Fare. Май | AM51: 900
G52: 22 | H52: 3500 | I52: 159.09091 | J52: 2 | K52: 0.066666667 | L52: 7000 | S52: 42 | T52: 4500 | U52: 107.14286 | V52: 14 | W52: 0.044585987 | X52: 63000 | AE52: 35 | AF52: 3500 | AG52: 100 | AH52: 20 | AI52: 0.075471698 | AJ52: 70000
G53: 27 | H53: 5000 | I53: 185.18519 | J53: 2 | K53: 0.066666667 | L53: 10000 | N53: GMV. 26.05 | O53: 256365 | S53: 52 | T53: 6000 | U53: 115.38462 | V53: 14 | W53: 0.044585987 | X53: 84000 | Z53: GMV. 26.05 | AA53: 3872500 | AE53: 45 | AF53: 5000 | AG53: 111.11111 | AH53: 12 | AI53: 0.045283019 | AJ53: 60000 | AL53: GMV. 26.05 | AM53: 3240000
J54: Всего: | K54: 0.23333333 | L54: 24500 | M54: 0.095566868 | V54: Всего: | W54: 0.16242038 | X54: 216000 | Y54: 0.055777921 | AH54: Всего: | AI54: 0.24528302 | AJ54: 202600 | AK54: 0.062530864
G56: Цели M2 Уфа | S56: Цели S2 Новосибирск | AE56: Цели М Екатеринбург
G57: вручений | H57: бонус | I57: доплата за вручение | J57: водители на ступени | K57: SR | L57: Затраты | M57: sub/gmv | N57: Метрика | O57: lcv_M2 | S57: вручений | T57: бонус | U57: доплата за вручение | V57: водители на ступени | W57: SR | X57: Затраты | Y57: sub/gmv | Z57: Метрика | AA57: lcv_s2 | AE57: вручений | AF57: бонус | AG57: доплата за вручение | AH57: водители на ступени | AI57: SR | AJ57: Затраты | AK57: sub/gmv | AL57: Метрика
G58: 15 | H58: 3000 | I58: 200 | J58: 1 | K58: 0.125 | L58: 3000 | N58: AVG Fare. Май | O58: 2643 | S58: 15 | T58: 2200 | U58: 146.66667 | V58: 2 | W58: 0.18181818 | X58: 4400 | Z58: AVG Fare. Май | AA58: 2218 | AE58: 18 | AF58: 3000 | AG58: 170 | AH58: 21 | AI58: 0.079545455 | AJ58: 63000 | AK58: 0.03 | AL58: AVG Fare. Май | AM58: 1270
G59: 20 | H59: 4500 | I59: 225 | J59: 0 | K59: 0 | L59: 0 | S59: 20 | T59: 3000 | U59: 150 | V59: 1 | W59: 0.090909091 | X59: 3000 | AE59: 24 | AF59: 4800 | AG59: 200 | AH59: 11 | AI59: 0.041666667 | AJ59: 52800 | AK59: 0.023
G60: 25 | H60: 6500 | I60: 260 | J60: 1 | K60: 0.125 | L60: 6500 | N60: GMV. 26.05 | O60: 201331 | S60: 25 | T60: 4500 | U60: 180 | V60: 1 | W60: 0.090909091 | X60: 4500 | Z60: GMV. 26.05 | AA60: 87500 | AE60: 30 | AF60: 6900 | AG60: 230 | AH60: 19 | AI60: 0.071969697 | AJ60: 131100 | AK60: 0.014 | AL60: GMV. 26.05 | AM60: 3010000
J61: Всего: | K61: 0.25 | L61: 9500 | M61: 0.047185977 | V61: Всего: | W61: 0.36363636 | X61: 11900 | Y61: 0.136 | AH61: Сумма | AI61: 0.19318182 | AJ61: 246900 | AK61: 0.082026578
G63: Цели L2 Уфа | S63: Цели M1 Новосибирск | AE63: Цели L Екаеринбург
G64: вручений | H64: бонус | I64: доплата за вручение | J64: водители на ступени | K64: SR | L64: Затраты | M64: sub/gmv | N64: Метрика | O64: lcv_l_2 | S64: вручений | T64: бонус | U64: доплата за вручение | V64: водители на ступени | W64: SR | X64: Затраты | Y64: sub/gmv | Z64: Метрика | AA64: lcv_m1 | AE64: вручений | AF64: бонус | AG64: доплата за вручение | AH64: водители на ступени | AI64: SR | AJ64: Затраты | AK64: sub/gmv | AL64: Метрика
G65: 10 | H65: 2700 | I65: 270 | J65: 2 | K65: 0.25 | L65: 5400 | N65: AVG Fare. Май | O65: 3430 | S65: 22 | T65: 2500 | U65: 113.63636 | V65: 2 | W65: 0.021978022 | X65: 5000 | Z65: AVG Fare. Май | AA65: 1764.59 | AE65: 15 | AF65: 3000 | AG65: 200 | AH65: 13 | AI65: 0.077380952 | AJ65: 39000 | AK65: 0.064 | AL65: AVG Fare. Май | AM65: 1870
G66: 15 | H66: 4500 | I66: 300 | J66: 1 | K66: 0.125 | L66: 4500 | S66: 32 | T66: 3500 | U66: 109.375 | V66: 11 | W66: 0.12087912 | X66: 38500 | AE66: 20 | AF66: 4800 | AG66: 240 | AH66: 0 | AI66: 0 | AJ66: 0 | AK66: 0.016
G67: 20 | H67: 6500 | I67: 325 | J67: 1 | K67: 0.125 | L67: 6500 | N67: GMV. 26.05 | O67: 124342 | S67: 42 | T67: 5000 | U67: 119.04762 | V67: 9 | W67: 0.098901099 | X67: 45000 | Z67: GMV. 26.05 | AA67: 1018599 | AE67: 25 | AF67: 7000 | AG67: 280 | AH67: 16 | AI67: 0.095238095 | AJ67: 112000 | AK67: 0.012 | AL67: GMV. 26.05 | AM67: 1574300
J68: Всего: | K68: 0.5 | L68: 16400 | M68: 0.13189429 | V68: Всего: | W68: 0.24175824 | X68: 88500 | Y68: 0.086884044 | AH68: Сумма | AI68: 0.17261905 | AJ68: 151000 | AK68: 0.092
G70: Цели XL Уфа | S70: Цели M2 Новосибирск | AE70: Цели XL2 Екаеринбург
G71: вручений | H71: бонус | I71: доплата за вручение | J71: водители на ступени | K71: SR | L71: Затраты | M71: sub/gmv | N71: Метрика | O71: lcv_xl | S71: вручений | T71: бонус | U71: доплата за вручение | V71: водители на ступени | W71: SR | X71: Затраты | Y71: sub/gmv | Z71: Метрика | AA71: lcv_m2 | AE71: вручений | AF71: бонус | AG71: доплата за вручение | AH71: водители на ступени | AI71: SR | AJ71: Затраты | AK71: sub/gmv | AL71: Метрика
G72: 12 | H72: 2500 | I72: 208.33333 | J72: 6 | K72: 0.20689655 | L72: 15000 | N72: AVG Fare. Май | O72: 2230 | S72: 20 | T72: 4000 | U72: 200 | V72: 3 | W72: 0.06122449 | X72: 12000 | Z72: AVG Fare. Май | AA72: 2569 | AE72: 2 | AF72: 1800 | AG72: 900 | AH72: 2 | AI72: 1 | AJ72: 3600 | AK72: 0.064 | AL72: AVG Fare. Май | AM72: 3636
G73: 17 | H73: 4000 | I73: 235.29412 | J73: 0 | K73: 0 | L73: 0 | S73: 25 | T73: 5200 | U73: 208 | V73: 6 | W73: 0.12244898 | X73: 31200 | AE73: 3 | AF73: 3600 | AG73: 1200 | AH73: 0 | AI73: 0 | AJ73: 0 | AK73: 0.016 | AL73: GMV. | AM73: 35000
G74: 22 | H74: 6500 | I74: 295.45455 | J74: 2 | K74: 0.068965517 | L74: 13000 | N74: GMV. 26.05 | O74: 181233 | S74: 30 | T74: 7000 | U74: 233.33333 | V74: 2 | W74: 0.040816327 | X74: 14000 | Z74: GMV. 26.05 | AA74: 976401 | AH74: Сумма | AI74: 1 | AJ74: =SUM(AJ72:AJ73) -> 3600 | AK74: 0.092
J75: Всего: | K75: 0.27586207 | L75: 28000 | M75: 0.15449725 | V75: Всего: | W75: 0.2244898 | X75: 57200 | Y75: 0.058582488
S77: Цели L1 Новосибирск
S78: вручений | T78: бонус | U78: доплата за вручение | V78: водители на ступени | W78: SR | X78: Затраты | Y78: sub/gmv | Z78: Метрика | AA78: lcv_l1
S79: 25 | T79: 3000 | U79: 120 | V79: 2 | W79: 0.060606061 | X79: 6000 | Z79: AVG Fare. Май | AA79: 2457
S80: 30 | T80: 4000 | U80: 133.33333 | V80: 3 | W80: 0.090909091 | X80: 12000
G81: Цели Van 2 Воронеж | S81: 35 | T81: 5000 | U81: 142.85714 | V81: 3 | W81: 0.090909091 | X81: 15000 | Z81: GMV. 26.05 | AA81: 265392
G82: вручений | H82: бонус | I82: доплата за вручение | J82: водители на ступени | K82: SR | L82: Затраты | M82: sub/gmv | N82: Метрика | O82: lcv_s2 | V82: Всего: | W82: 0.24242424 | X82: 33000 | Y82: 0.12434437
G83: 4 | H83: 800 | I83: 200 | J83: 0 | K83: 0 | L83: 0 | N83: AVG Fare. Май | O83: 2303
G84: 8 | H84: 1800 | I84: 225 | J84: 1 | K84: 0.33333333 | L84: 1800 | S84: Цели L2 Новосибирск
G85: 12 | H85: 3000 | I85: 250 | J85: 1 | K85: 0.33333333 | L85: 3000 | N85: GMV. 26.05 | O85: 50655 | S85: вручений | T85: бонус | U85: доплата за вручение | V85: водители на ступени | W85: SR | X85: Затраты | Y85: sub/gmv | Z85: Метрика | AA85: lcv_l2
J86: Всего: | K86: 0.66666667 | L86: 4800 | M86: 0.094758662 | S86: 20 | T86: 3000 | U86: 150 | V86: 2 | W86: 0.057142857 | X86: 6000 | Z86: AVG Fare. Май | AA86: 4025
S87: 27 | T87: 4500 | U87: 166.66667 | V87: 3 | W87: 0.085714286 | X87: 13500
G88: Цели M2 Воронеж | S88: 34 | T88: 6000 | U88: 176.47059 | V88: 6 | W88: 0.17142857 | X88: 36000 | Z88: GMV. 26.05 | AA88: 648142
G89: вручений | H89: бонус | I89: доплата за вручение | J89: водители на ступени | K89: SR | L89: Затраты | M89: sub/gmv | N89: Метрика | O89: lcv_M2 | V89: Всего: | W89: 0.31428571 | X89: 55500 | Y89: 0.085629384
G90: 15 | H90: 3000 | I90: 200 | J90: 0 | K90: 0 | L90: 0 | N90: AVG Fare. Май | O90: 2825
G91: 20 | H91: 4500 | I91: 225 | J91: 3 | K91: 0.25 | L91: 13500
G92: 25 | H92: 6000 | I92: 240 | J92: 1 | K92: 0.083333333 | L92: 6000 | N92: GMV. 26.05 | O92: 155373
J93: Всего: | K93: 0.33333333 | L93: 19500 | M93: 0.12550443
G95: Цели L Воронеж
G96: вручений | H96: бонус | I96: доплата за вручение | J96: водители на ступени | K96: SR | L96: Затраты | M96: sub/gmv | N96: Метрика | O96: lcv_l
G97: 10 | H97: 1500 | I97: 150 | J97: 11 | K97: 0.12790698 | L97: 16500 | N97: AVG Fare. Май | O97: 1590
G98: 15 | H98: 2500 | I98: 166.66667 | J98: 10 | K98: 0.11627907 | L98: 25000
G99: 20 | H99: 3500 | I99: 175 | J99: 5 | K99: 0.058139535 | L99: 17500 | N99: GMV. 26.05 | O99: 777000
J100: Всего: | K100: 0.30232558 | L100: 59000 | M100: 0.075933076

Sheet затраты 21.07
C2: https://datalens.yandex-team.ru/wbenuos6lxv4o-subsidy-details-advanced?tab=8Z&state=9c372b401134 | D2: неделя с 21.07
B3: Zone | C3: на русском | D3: sub/GMV | E3: dXgY | F3: MFG | G3: MFGgeo | H3: Substotal
B4: spb | C4: =VLOOKUP(B4,'население 2023'!C:D,2,0) -> СПб | D4: 0.013 | E4: 756818 | F4: 8098 | G4: 0 | H4: 764916
B5: ekb | C5: =VLOOKUP(B5,'население 2023'!C:D,2,0) -> Екб | D5: 0.05 | E5: 698190 | F5: 18906 | G5: 0 | H5: 717096
B6: nizhnynovgorod | C6: =VLOOKUP(B6,'население 2023'!C:D,2,0) -> НиНо | D6: 0.092 | E6: 475066 | F6: 32126 | G6: 0 | H6: 507191
B7: novosibirsk | C7: =VLOOKUP(B7,'население 2023'!C:D,2,0) -> Нск | D7: 0.027 | E7: 321639 | F7: 91550 | G7: 0 | H7: 415189
B8: krasnodar | C8: =VLOOKUP(B8,'население 2023'!C:D,2,0) -> Краснодар | D8: 0.015 | E8: 253000 | F8: 39950 | G8: 0 | H8: 294699
B9: perm | C9: =VLOOKUP(B9,'население 2023'!C:D,2,0) -> Пермь | D9: 0.082 | E9: 246709 | F9: 43963 | G9: 0 | H9: 290672
B10: samara | C10: =VLOOKUP(B10,'население 2023'!C:D,2,0) -> Самара | D10: 0.056 | E10: 198851 | F10: 43859 | G10: 0 | H10: 242711
B11: kazan | C11: =VLOOKUP(B11,'население 2023'!C:D,2,0) -> Казань | D11: 0.027 | E11: 203000 | F11: 29646 | G11: 0 | H11: 232646
B12: rostovondon | C12: =VLOOKUP(B12,'население 2023'!C:D,2,0) -> РнД | D12: 0.02 | E12: 177603 | F12: 17948 | G12: 0 | H12: 195551
B13: volgograd | C13: =VLOOKUP(B13,'население 2023'!C:D,2,0) -> Влг | D13: 0.071 | E13: 129219 | F13: 9543 | G13: 0 | H13: 138763
B14: sochi | C14: =VLOOKUP(B14,'население 2023'!C:D,2,0) -> Сочи | D14: 0.089 | E14: 78595 | F14: 32947 | G14: 0 | H14: 111542
B15: omsk | C15: =VLOOKUP(B15,'население 2023'!C:D,2,0) -> Омск | D15: 0.053 | E15: 103592 | F15: 3614 | G15: 0 | H15: 107206
... B42: penza | C42: =VLOOKUP(B42,'население 2023'!C:D,2,0) -> Пенза | D42: 0.017 | E42: 0 | F42: 11382 | G42: 0 | H42: 11382
B43: krasnoe_selo | C43: Красное село | D43: 0.008 | E43: 10983 | F43: 170 | G43: 0 | H43: 11153
B44: akademgorod | C44: =VLOOKUP(B44,'население 2023'!C:D,2,0) -> #N/A | D44: 0.014 | E44: 4230 | F44: 3106 | G44: 0 | H44: 10336
B45: odincovo | C45: =VLOOKUP(B45,'население 2023'!C:D,2,0) -> Одинцово | D45: 0.001 | E45: 5446 | F45: 1855 | G45: 0 | H45: 7302
B46: tomsk | C46: =VLOOKUP(B46,'население 2023'!C:D,2,0) -> Томск | D46: 0.061 | E46: 7100 | F46: 116 | G46: 0 | H46: 7216
B47: podolsk | C47: =VLOOKUP(B47,'население 2023'!C:D,2,0) -> Подольск | D47: 0.001 | E47: 0 | F47: 5514 | G47: 1437 | H47: 6951
B48: pushkin | C48: =VLOOKUP(B48,'население 2023'!C:D,2,0) -> #N/A | D48: 0.005 | E48: 6803 | F48: 26 | G48: 0 | H48: 6830
B49: yaroslavl | C49: =VLOOKUP(B49,'население 2023'!C:D,2,0) -> Ярославль | D49: 0.11 | E49: 6200 | F49: 530 | G49: 0 | H49: 6730
B50: lipetsk | C50: =VLOOKUP(B50,'население 2023'!C:D,2,0) -> Липецк | D50: 0.164 | E50: 5300 | F50: 852 | G50: 0 | H50: 6152
B51: makhachkala | C51: =VLOOKUP(B51,'население 2023'!C:D,2,0) -> Макхачкала | D51: 0.093 | E51: 5246 | F51: 660 | G51: 0 | H51: 5906
B52: ryazan | C52: =VLOOKUP(B52,'население 2023'!C:D,2,0) -> Рязань | D52: 0.03 | E52: 4295 | F52: 970 | G52: 0 | H52: 5265
B53: kostroma | C53: =VLOOKUP(B53,'население 2023'!C:D,2,0) -> Кострома | D53: 0.232 | E53: 2000 | F53: 3065 | G53: 0 | H53: 5065
B54: tver | C54: =VLOOKUP(B54,'население 2023'!C:D,2,0) -> Тверь | D54: 0.008 | E54: 0 | F54: 4963 | G54: 0 | H54: 4963
B55: taganrog | C55: =VLOOKUP(B55,'население 2023'!C:D,2,0) -> Таганрог | D55: 0.081 | E55: 3955 | F55: 734 | G55: 0 | H55: 4689
... B100: istra | C100: =VLOOKUP(B100,'население 2023'!C:D,2,0) -> Истра | D100: 0 | E100: 0 | F100: 318 | G100: 0 | H100: 318
B101: krasnayapolyana | C101: Красная поляна | D101: 0.01 | E101: 277 | F101: 0 | G101: 0 | H101: 277
B102: monino | C102: =VLOOKUP(B102,'население 2023'!C:D,2,0) -> #N/A | D102: 0 | E102: 0 | F102: 239 | G102: 0 | H102: 239
B103: kaspiysk | C103: =VLOOKUP(B103,'население 2023'!C:D,2,0) -> Каспийск | D103: 0.014 | E103: 156 | F103: 0 | G103: 0 | H103: 156

Sheet доставки за июнь
B2: Агломерация | C2: Популяция | D2: доставки за июнь | E2: тарифная зона
B3: Moscow | C3: Москва | D3: 441709 | E3: moscow
B4: Saint-Petersburg | C4: СПб | D4: 126609 | E4: spb
B5: Krasnodar | C5: 1 млн+ | D5: 63368 | E5: krasnodar
B6: Novosibirsk | C6: 1 млн+ | D6: 50424 | E6: novosibirsk
B7: Ekaterinburg | C7: 1 млн+ | D7: 40797 | E7: ekb
B8: Rostov-on-Don | C8: 1 млн+ | D8: 33209 | E8: rostovondon
B9: Kazan | C9: 1 млн+ | D9: 26018 | E9: kazan
B10: Chelyabinsk | C10: 1 млн+ | D10: 23161 | E10: chelyabinsk
B11: Nizhny Novgorod | C11: 1 млн+ | D11: 22951 | E11: nizhnynovgorod
B12: Samara | C12: 1 млн+ | D12: 15860 | E12: samara
B13: Perm | C13: 1 млн+ | D13: 11226 | E13: perm
B14: Ufa | C14: 1 млн+ | D14: 11060 | E14: ufa
... B114: Shatura | C114: 100- (ДМО) | D114: 1 | E114: shatura

Sheet Цели Красноярск S
A1: Доходимость S за 02.07 | D1: Доходимость S за 25.06 | K1: Cancels indicators - Cancels: Corporate Clients & C2C - Yandex DataLens
A2: Итого | B2: COUNTA из executor_profile_id | D2: Итого | E2: COUNTA из executor_profile_id
A3: 1 | B3: 4 | C3: =A3*B3 -> 4 | D3: 1 | E3: 4 | F3: =D3*E3 -> 4
A4: 2 | B4: 2 | C4: =A4*B4 -> 4 | D4: 3 | E4: 1 | F4: =D4*E4 -> 3
A5: 3 | B5: 3 | C5: =A5*B5 -> 9 | D5: 5 | E5: 1 | F5: =D5*E5 -> 5
A6: 4 | B6: 1 | C6: =A6*B6 -> 4 | D6: 6 | E6: 2 | F6: =D6*E6 -> 12
A7: 5 | B7: 1 | C7: =A7*B7 -> 5 | D7: 7 | E7: 2 | F7: =D7*E7 -> 14
A8: 6 | B8: 2 | C8: =A8*B8 -> 12 | D8: 8 | E8: 2 | F8: =D8*E8 -> 16
A9: 7 | B9: 4 | C9: =A9*B9 -> 28 | D9: 9 | E9: 2 | F9: =D9*E9 -> 18
A10: 8 | B10: 4 | C10: =A10*B10 -> 32 | D10: 10 | E10: 3 | F10: =D10*E10 -> 30
A11: 11 | B11: 3 | C11: =A11*B11 -> 33 | D11: 12 | E11: 1 | F11: =D11*E11 -> 12
A12: 14 | B12: 1 | C12: =A12*B12 -> 14 | D12: 14 | E12: 1 | F12: =D12*E12 -> 14
A13: 16 | B13: 1 | C13: =A13*B13 -> 16 | D13: 15 | E13: 1 | F13: =D13*E13 -> 15
A14: 17 | B14: 2 | C14: =A14*B14 -> 34 | D14: 16 | E14: 3 | F14: =D14*E14 -> 48
... A16: 21 | B16: 2 | C16: =A16*B16 -> 42 | D16: 21 | E16: 1 | F16: =D16*E16 -> 21
A17: Итого | B17: 33 | C17: =SUM(C3:C16) -> 294 | D17: 24 | E17: 1 | F17: =D17*E17 -> 24
D18: 31 | E18: 1 | F18: =D18*E18 -> 31
D19: Итого | E19: 27 | F19: =SUM(F3:F18) -> 285
A23: 45840 | K23: 45833
A24: Цели S вариант 1 | H24: Метрика | I24: lcv_s | K24: вручений | L24: бонус | M24: доплата за вручение | N24: водители на ступени | O24: SR
A25: вручений | B25: бонус | C25: доплата за вручение | D25: водители на ступени | E25: SR | F25: Затраты | G25: sub/gmv | H25: AVG Fare. Июнь | I25: 1021 | K25: 15 | L25: 1400 | M25: =L25/K25 -> 93.333333 | N25: 5 | O25: =N25/27 -> 0.18518519
A26: 15 | B26: 1400 | C26: =B26/A26 -> 93.333333 | D26: 6 | E26: =D26/$B$17 -> 0.18181818 | F26: =B26*D26 -> 8400 | H26: 10% от Ср. Чека | I26: 102 | K26: 20 | L26: 2200 | M26: =L26/K26 -> 110 | N26: 2 | O26: =N26/27 -> 0.074074074
A27: 20 | B27: 2200 | C27: =B27/A27 -> 110 | D27: 2 | E27: =D27/$B$17 -> 0.060606061 | F27: =B27*D27 -> 4400 | H27: GMV. 02/07 | I27: 476692 | K27: 25 | L27: 3000 | M27: =L27/K27 -> 120 | N27: 1 | O27: =N27/27 -> 0.037037037
A28: 25 | B28: 3000 | C28: =B28/A28 -> 120 | D28: 0 | E28: =D28/$B$17 -> 0 | F28: =B28*D28 -> 0 | I28: 1686003 | N28: Всего: | O28: =SUM(O25:O27) -> 0.2962963
D29: Всего: | E29: =SUM(E26:E28) -> 0.24242424 | F29: =SUM(F26:F28) -> 12800 | G29: =F29/I27 -> 0.02685172 | H29: =F29/I28 -> 0.0075919201
K30: Цели S вариант 2
A31: Цели S вариант 2 | H31: Метрика | I31: lcv_s | K31: вручений | L31: бонус | M31: доплата за вручение | N31: водители на ступени | O31: SR
A32: вручений | B32: бонус | C32: доплата за вручение | D32: водители на ступени | E32: SR | F32: Затраты | G32: sub/gmv | H32: AVG Fare. Июнь | I32: 1021 | K32: 14 | L32: 1200 | M32: =L32/K32 -> 85.714286 | N32: 6 | O32: =N32/27 -> 0.22222222
A33: 14 | B33: 1200 | C33: =B33/A33 -> 85.714286 | D33: 6 | E33: =D33/$B$17 -> 0.18181818 | F33: =B33*D33 -> 7200 | H33: 10% от Ср. Чека | I33: 102 | K33: 19 | L33: 1900 | M33: =L33/K33 -> 100 | N33: 1 | O33: =N33/27 -> 0.037037037
A34: 19 | B34: 1900 | C34: =B34/A34 -> 100 | D34: 1 | E34: =D34/$B$17 -> 0.03030303 | F34: =B34*D34 -> 1900 | H34: GMV. 02/07 | I34: 476692 | K34: 24 | L34: 2600 | M34: =L34/K34 -> 108.33333 | N34: 2 | O34: =N34/27 -> 0.074074074
A35: 24 | B35: 2600 | C35: =B35/A35 -> 108.33333 | D35: 2 | E35: =D35/$B$17 -> 0.060606061 | F35: =B35*D35 -> 5200 | I35: 1686003 | N35: Всего: | O35: =SUM(O32:O34) -> 0.33333333
D36: Всего: | E36: =SUM(E33:E35) -> 0.27272727 | F36: =SUM(F33:F35) -> 14300 | G36: =F36/I34 -> 0.029998406 | H36: =F36/I35 -> 0.0084815982
A41: Доходимость S2 за 25.06 | D41: Доходимость S2 за 17.06 | G41: за 02.07 отсутствует
A42: Итого | B42: COUNTA из executor_profile_id | D42: Итого | E42: COUNTA из executor_profile_id
A43: 18 | B43: 1 | D43: 6 | E43: 1
A44: Итого | B44: 1 | D44: Итого | E44: 1
A47: Цели S2 вариант 1 | H47: Метрика | I47: lcv_s
A48: вручений | B48: бонус | C48: доплата за вручение | D48: водители на ступени | E48: SR | F48: Затраты | G48: sub/gmv | H48: AVG Fare. Июнь | I48: 2267
A49: 6 | B49: 1400 | C49: =B49/A49 -> 233.33333 | D49: 0 | E49: =D49/$B$17 -> 0 | F49: =B49*D49 -> 0 | H49: 10% от Ср. Чека | I49: 227
A50: 12 | B50: 2200 | C50: =B50/A50 -> 183.33333 | D50: 0 | E50: =D50/$B$17 -> 0 | F50: =B50*D50 -> 0 | H50: GMV. 17/06 | I50: 6620
A51: 18 | B51: 3000 | C51: =B51/A51 -> 166.66667 | D51: 1 | E51: =D51/$B$17 -> 0.03030303 | F51: =B51*D51 -> 3000 | I51: 1686003
D52: Всего: | E52: =SUM(E49:E51) -> 0.03030303 | F52: =SUM(F49:F51) -> 3000 | G52: =F52/I50 -> 0.45317221 | H52: =F52/I51 -> 0.0017793563
A54: Цели S2 вариант 2 дневные | H54: Метрика | I54: lcv_s
A55: вручений | B55: бонус | C55: доплата за вручение | D55: водители на ступени | E55: SR | F55: Затраты | G55: sub/gmv | H55: AVG Fare. Июнь | I55: 2267
A56: 2 | B56: 400 | C56: =B56/A56 -> 200 | D56: 0 | E56: =D56/$B$17 -> 0 | F56: =B56*D56 -> 0 | H56: 10% от Ср. Чека | I56: 227
A57: 3 | B57: 700 | C57: =B57/A57 -> 233.33333 | D57: 0 | E57: =D57/$B$17 -> 0 | F57: =B57*D57 -> 0 | H57: GMV. 17/06 | I57: 6620
A58: 4 | B58: 1000 | C58: =B58/A58 -> 250 | D58: 1 | E58: =D58/$B$17 -> 0.03030303 | F58: =B58*D58 -> 1000 | I58: 1686003
D59: Всего: | E59: =SUM(E56:E58) -> 0.03030303 | F59: =SUM(F56:F58) -> 1000 | G59: =F59/I57 -> 0.1510574 | H59: =F59/I58 -> 0.00059311875
A69: Доходимость S1 за 02.07 | D69: Доходимость S1 за 25.06
A70: Итого | B70: COUNTA из executor_profile_id | D70: Итого | E70: COUNTA из executor_profile_id
A71: 1 | B71: 1 | D71: 1 | E71: 1
A72: 2 | B72: 1 | D72: 3 | E72: 1
A73: 3 | B73: 1 | D73: 6 | E73: 1
A74: 4 | B74: 1 | D74: 7 | E74: 2
A75: 5 | B75: 1 | D75: 8 | E75: 2
A76: 6 | B76: 1 | D76: 9 | E76: 2
A77: 7 | B77: 2 | D77: 10 | E77: 1
A78: 8 | B78: 4 | D78: 14 | E78: 1
A79: 11 | B79: 2 | D79: 16 | E79: 2
A80: 14 | B80: 1 | D80: 21 | E80: 1
A81: 16 | B81: 1 | D81: 24 | E81: 1
A82: 17 | B82: 1 | D82: 31 | E82: 1
A83: 19 | B83: 3 | D83: Итого | E83: 16
A84: 21 | B84: 1
A85: Итого | B85: 21
A88: Цели S1 вариант 1 | H88: Метрика | I88: lcv_s
A89: вручений | B89: бонус | C89: доплата за вручение | D89: водители на ступени | E89: SR | F89: Затраты | G89: sub/gmv | H89: AVG Fare. Июнь | I89: 1253
A90: 15 | B90: 1500 | C90: =B90/A90 -> 100 | D90: 6 | E90: =D90/$B$85 -> 0.28571429 | F90: =B90*D90 -> 9000 | H90: 10% от Ср. Чека | I90: 125
A91: 20 | B91: 2200 | C91: =B91/A91 -> 110 | D91: 1 | E91: =D91/$B$85 -> 0.047619048 | F91: =B91*D91 -> 2200 | H91: GMV. 02/07 | I91: 133071
A92: 25 | B92: 3200 | C92: =B92/A92 -> 128 | D92: 0 | E92: =D92/$B$85 -> 0 | F92: =B92*D92 -> 0 | I92: 1686003
D93: Всего: | E93: =SUM(E90:E92) -> 0.33333333 | F93: =SUM(F90:F92) -> 11200 | G93: =F93/I91 -> 0.084165596 | H93: =F93/I92 -> 0.0066429301
A95: Цели S1 вариант 2 | H95: Метрика | I95: lcv_s
A96: вручений | B96: бонус | C96: доплата за вручение | D96: водители на ступени | E96: SR | F96: Затраты | G96: sub/gmv | H96: AVG Fare. Июнь | I96: 1253 | L96: 45833
A97: 20 | B97: 2000 | C97: =B97/A97 -> 100 | D97: 0 | E97: =D97/$B$85 -> 0 | F97: =B97*D97 -> 0 | H97: 10% от Ср. Чека | I97: 125 | L97: вручений | M97: бонус | N97: доплата за вручение | O97: водители на ступени | P97: SR
A98: 25 | B98: 2900 | C98: =B98/A98 -> 116 | D98: 1 | E98: =D98/$B$85 -> 0.047619048 | F98: =B98*D98 -> 2900 | H98: GMV. 02/07 | I98: 133071 | L98: 15 | M98: 1500 | N98: =M98/L98 -> 100 | O98: 3 | P98: =O98/$E$83 -> 0.1875
A99: 30 | B99: 3900 | C99: =B99/A99 -> 130 | D99: 0 | E99: =D99/$B$85 -> 0 | F99: =B99*D99 -> 0 | I99: 1686003 | L99: 20 | M99: 2200 | N99: =M99/L99 -> 110 | O99: 2 | P99: =O99/$E$83 -> 0.125
D100: Всего: | E100: =SUM(E97:E99) -> 0.047619048 | F100: =SUM(F97:F99) -> 2900 | G100: =F100/I98 -> 0.021792877 | H100: =F100/I99 -> 0.0017200444 | L100: 25 | M100: 3200 | N100: =M100/L100 -> 128 | O100: 1 | P100: =O100/$E$83 -> 0.0625
O101: Всего: | P101: =SUM(P98:P100) -> 0.375
L103: Цели S вариант 2
L104: вручений | M104: бонус | N104: доплата за вручение | O104: водители на ступени | P104: SR
L105: 20 | M105: 2000 | N105: =M105/L105 -> 100 | O105: 1 | P105: =O105/$E$83 -> 0.0625
L106: 25 | M106: 2900 | N106: =M106/L106 -> 116 | O106: 1 | P106: =O106/$E$83 -> 0.0625
L107: 30 | M107: 3900 | N107: =M107/L107 -> 130 | O107: 1 | P107: =O107/$E$83 -> 0.0625
O108: Всего: | P108: =SUM(P105:P107) -> 0.1875

Sheet выгрузка СПб (кузова)
A1: dt | B1: lcv_l | C1: lcv_m | D1: lcv_xl | E1: truck_5t | F1: van
A2: AVG Fare. Май | B2: 2670.4182 | C2: 2059.9928 | D2: 2964.8335 | E2: 1983.6332 | F2: 1475.6222
A3: GMV. 26.05 | B3: 8485381.2 | C3: 17363074 | D3: 3333006.4 | E3: 584373.8 | F3: 21760074 | G3: https://datalens.yandex-team.ru/sne8u5ggtwoih-cdr-utilization-per-option-region?tab=Aj&state=5c2bf175953

Sheet экипажи на 26.06
A1: Город | B1: Кузов | C1: Опция | D1: Версия Экипажей | E1: Квота в неделю | F1: Бонус
A2: Волгоград | B2: М | C2: M2 | D2: 4.0 | E2: 13 | F2: 1000 руб/заказ
A3: Волгоград | B3: L | C3: L1 | D3: 142 | E3: 3 | F3: 1000руб/час
A4: Екатеринбург | B4: L | C4: L2 | D4: 4.0 | E4: 28 | F4: 1000 руб/заказ
A5: Казань | B5: L | C5: L2 | D5: 4.0 | E5: 31 | F5: 1000 руб/заказ
A6: Казань | B6: М | C6: M2 | D6: 4.0 | E6: 30 | F6: 1000 руб/заказ
A7: Казань | B7: XXL | C7: XXL0 | D7: 3.0 | E7: 21 | F7: 1400 руб/час
A8: Красноярск | B8: L | C8: L1 | D8: 3.0 | E8: 21 | F8: 1400 руб/час
A9: Красноярск | B9: S | C9: S1 | D9: 142 | E9: 35 | F9: 800 руб/час
A10: Нижний Новогород | B10: М | C10: M2 | D10: 4.0 | E10: 18 | F10: 1000 руб/заказ
A11: Нижний Новогород | B11: L | C11: L2 | D11: 4.0 | E11: 41 | F11: 1000 руб/заказ
A12: Нижний Новогород | B12: XXL | C12: XXL0 | D12: 3.0 | E12: 14 | F12: 1400 руб/час
A13: Нижний Тагил | B13: М | C13: M1 | D13: 142 | E13: 14 | F13: 700 руб/час
A14: Новосибирск | B14: L | C14: L2 | D14: 4.0 | E14: 35 | F14: 1000 руб/заказ
A15: Омск | B15: L | C15: L2 | D15: 3.0 | E15: 35 | F15: 1200 руб/час
A16: Пермь | B16: М | C16: M2 | D16: 4.0 | E16: 6 | F16: 1000 руб/заказ
A17: Сочи | B17: L | C17: L2 | D17: 3.0 | E17: 28 | F17: 1000 руб/заказ
A18: Сыктывкар | B18: S | C18: S1 | D18: 142 | E18: 7 | F18: 500 руб/час
A19: Сыктывкар | B19: M | C19: M1 | D19: 142 | E19: 7 | F19: 600 руб/час
A20: Тюмень | B20: L | C20: L2 | D20: 4.0 | E20: 35 | F20: 1000 руб/заказ
A21: Уфа | B21: L | C21: L2 | D21: 3.0 | E21: 35 | F21: 1200 руб/час
A22: Челябинск | B22: L | C22: L2 | D22: 4.0 | E22: 28 | F22: 1000 руб/заказ
A23: Шахты | B23: М | C23: M1 | D23: 142 | E23: 7 | F23: 600 руб/час

Sheet слоты

Sheet СПб XL2
A1: дох-сть 09.06 XL2 | D1: as is дневные цели | Q1: 02.06 доходимость XL2
A2: COUNTA из order_id | B2: COUNTA из executor_profile_id | D2: вручений | E2: бонус | F2: доплата за вручение | G2: водители на ступени | H2: SR | I2: Затраты | Q2: COUNTA из order_id | R2: COUNTA из executor_profile_id
A3: 1 | B3: 1 | D3: 2 | E3: 1200 | F3: =E3/D3 -> 600 | G3: 4 | H3: =G3/20 -> 0.2 | I3: =E3*G3 -> 4800 | Q3: 1 | R3: 3
A4: 2 | B4: 4 | D4: 3 | E4: 2300 | F4: =E4/D4 -> 766.66667 | G4: 15 | H4: =G4/20 -> 0.75 | I4: =E4*G4 -> 34500 | Q4: 2 | R4: 3
A5: 3 | B5: 7 | G5: Всего: | H5: =SUM(H2:H4) -> 0.95 | I5: =SUM(I2:I4) -> 39300 | Q5: 3 | R5: 5
A6: 4 | B6: 3 | Q6: 4 | R6: 9
A7: 5 | B7: 4 | D7: to be | Q7: 5 | R7: 7
A8: 6 | B8: 1 | D8: вручений | E8: бонус | F8: доплата за вручение | G8: водители на ступени | H8: SR | I8: Затраты | Q8: 6 | R8: 4
A9: Итого | B9: 20 | D9: 2 | E9: 1200 | F9: =E9/D9 -> 600 | G9: 4 | H9: =G9/20 -> 0.2 | I9: =E9*G9 -> 4800 | Q9: 7 | R9: 5
D10: 3 | E10: 2500 | F10: =E10/D10 -> 833.33333 | G10: 7 | H10: =G10/20 -> 0.35 | I10: =E10*G10 -> 17500 | Q10: 8 | R10: 2
D11: 4 | E11: 4000 | F11: =E11/D11 -> 1000 | G11: 8 | H11: =G11/20 -> 0.4 | I11: =E11*G11 -> 32000 | Q11: 9 | R11: 1
G12: Всего: | H12: =SUM(H9:H11) -> 0.95 | I12: =SUM(I9:I11) -> 54300 | Q12: 10 | R12: 2
Q13: 11 | R13: 2
Q14: 12 | R14: 4
Q15: 13 | R15: 3
Q16: 14 | R16: 1
Q17: 15 | R17: 4
Q18: 17 | R18: 3
Q19: 18 | R19: 1
Q20: 19 | R20: 2
Q21: 20 | R21: 2
Q22: 22 | R22: 1
Q23: Итого | R23: 64

Sheet СПб
A1: Цели XL | C1: Доходимость за 02.06 XL | Q1: Цели L | AG1: Цели M | AI1: Доходимость за 02.06 M | AW1: Цели S | AY1: Доходимость S
C2: COUNTA из order_id | D2: COUNTA из executor_profile_id | F2: 1 вариант целей XL | S2: Доходимость за 02.06 L | V2: 1 вариант целей L | AI2: Кол-во вручений | AJ2: Водителей | AL2: 1 вариант целей M | AY2: Кол-во вручений | AZ2: Водителей | BB2: 1 вариант целей S
C3: 1 | D3: 24 | F3: вручений | G3: бонус | H3: доплата за вручение | I3: водители на ступени | J3: SR | K3: Затраты | L3: sub/gmv | N3: Метрика | O3: lcv_xl | S3: Кол-во вручений | T3: Водителей | V3: вручений | W3: бонус | X3: доплата за вручение | Y3: водители на ступени | Z3: SR | AA3: Затраты | AB3: sub/gmv | AD3: Метрика | AE3: lcv_l | AI3: 1 | AJ3: 94 | AL3: вручений | AM3: бонус | AN3: доплата за вручение | AO3: водители на ступени | AP3: SR | AQ3: Затраты | AR3: sub/gmv | AT3: Метрика | AU3: lcv_m | AY3: 1 | AZ3: 126 | BB3: вручений | BC3: бонус | BD3: доплата за вручение | BE3: водители на ступени | BF3: SR | BG3: Затраты | BH3: sub/gmv | BJ3: Метрика | BK3: van
C4: 2 | D4: 26 | F4: 10 | G4: 2500 | H4: =G4/F4 -> 250 | I4: 38 | J4: =I4/$D$25 -> 0.17117117 | K4: =G4*I4 -> 95000 | N4: AVG Fare. Май | O4: =HLOOKUP(O3,'выгрузка СПб (кузова)'!$B$1:$J$3,2,0) -> 2964.8335 | S4: 1 | T4: 54 | V4: 12 | W4: 2400 | X4: =W4/V4 -> 200 | Y4: 49 | Z4: =Y4/394 -> 0.12436548 | AA4: =W4*Y4 -> 117600 | AD4: AVG Fare. Май | AE4: =HLOOKUP(AE3,'выгрузка СПб (кузова)'!$B$1:$J$3,2,0) -> 2670.4182 | AI4: 2 | AJ4: 69 | AL4: 15 | AM4: 2400 | AN4: =AM4/AL4 -> 160 | AO4: 79 | AP4: =AO4/741 -> 0.10661269 | AQ4: =AM4*AO4 -> 189600 | AT4: AVG Fare. Май | AU4: =HLOOKUP(AU3,'выгрузка СПб (кузова)'!$B$1:$J$3,2,0) -> 2059.9928 | AY4: 2 | AZ4: 89 | BB4: 15 | BC4: 1600 | BD4: =BC4/BB4 -> 106.66667 | BE4: 111 | BF4: =BE4/1041 -> 0.10662824 | BG4: =BC4*BE4 -> 177600 | BJ4: AVG Fare. Май | BK4: =HLOOKUP(BK3,'выгрузка СПб (кузова)'!$B$1:$J$3,2,0) -> 1475.6222
C5: 3 | D5: 27 | F5: 15 | G5: 4000 | H5: =G5/F5 -> 266.66667 | I5: 17 | J5: =I5/$D$25 -> 0.076576577 | K5: =G5*I5 -> 68000 | N5: 10% от Ср. Чека | O5: =O4/10 -> 296.48335 | S5: 2 | T5: 43 | V5: 17 | W5: 3600 | X5: =W5/V5 -> 211.76471 | Y5: 24 | Z5: =Y5/394 -> 0.060913706 | AA5: =W5*Y5 -> 86400 | AD5: 10% от Ср. Чека | AE5: =AE4/10 -> 267.04182 | AI5: 3 | AJ5: 64 | AL5: 20 | AM5: 3600 | AN5: =AM5/AL5 -> 180 | AO5: 55 | AP5: =AO5/741 -> 0.074224022 | AQ5: =AM5*AO5 -> 198000 | AT5: 10% от Ср. Чека | AU5: =AU4/10 -> 205.99928 | AY5: 3 | AZ5: 68 | BB5: 20 | BC5: 2500 | BD5: =BC5/BB5 -> 125 | BE5: 73 | BF5: =BE5/1041 -> 0.07012488 | BG5: =BC5*BE5 -> 182500 | BJ5: 10% от Ср. Чека | BK5: =BK4/10 -> 147.56222
C6: 4 | D6: 18 | F6: 20 | G6: 5800 | H6: =G6/F6 -> 290 | I6: 8 | J6: =I6/$D$25 -> 0.036036036 | K6: =G6*I6 -> 46400 | N6: GMV. 26.05 | O6: =HLOOKUP(O3,'выгрузка СПб (кузова)'!$B$1:$J$3,3,0) -> 3333006.4 | S6: 3 | T6: 42 | V6: 22 | W6: 5200 | X6: =W6/V6 -> 236.36364 | Y6: 15 | Z6: =Y6/394 -> 0.038071066 | AA6: =W6*Y6 -> 78000 | AD6: GMV. 26.05 | AE6: =HLOOKUP(AE3,'выгрузка СПб (кузова)'!$B$1:$J$3,3,0) -> 8485381.2 | AI6: 4 | AJ6: 56 | AL6: 25 | AM6: 5000 | AN6: =AM6/AL6 -> 200 | AO6: 41 | AP6: =AO6/741 -> 0.055330634 | AQ6: =AM6*AO6 -> 205000 | AT6: GMV. 26.05 | AU6: =HLOOKUP(AU3,'выгрузка СПб (кузова)'!$B$1:$J$3,3,0) -> 17363074 | AY6: 4 | AZ6: 59 | BB6: 25 | BC6: 3800 | BD6: =BC6/BB6 -> 152 | BE6: 130 | BF6: =BE6/1041 -> 0.12487992 | BG6: =BC6*BE6 -> 494000 | BJ6: GMV. 26.05 | BK6: =HLOOKUP(BK3,'выгрузка СПб (кузова)'!$B$1:$J$3,3,0) -> 21760074
C7: 5 | D7: 20 | I7: Всего: | J7: =SUM(J4:J6) -> 0.28378378 | K7: =SUM(K4:K6) -> 209400 | L7: =K7/$AE$6 -> 0.024677736 | S7: 4 | T7: 29 | Y7: Всего: | Z7: =SUM(Z4:Z6) -> 0.22335025 | AA7: =SUM(AA4:AA6) -> 282000 | AB7: =AA7/$AE$6 -> 0.033233628 | AI7: 5 | AJ7: 50 | AO7: Всего: | AP7: =SUM(AP4:AP6) -> 0.23616734 | AQ7: =SUM(AQ4:AQ6) -> 592600 | AR7: =AQ7/$AU$6 -> 0.034129901 | AY7: 5 | AZ7: 64 | BE7: Всего: | BF7: =SUM(BF4:BF6) -> 0.30163305 | BG7: =SUM(BG4:BG6) -> 854100 | BH7: =BG7/$BK$6 -> 0.039250786
C8: 6 | D8: 14 | S8: 5 | T8: 24 | AI8: 6 | AJ8: 37 | AY8: 6 | AZ8: 56
C9: 7 | D9: 14 | F9: 2 вариант целей XL | S9: 6 | T9: 22 | V9: 2 вариант целей L | AI9: 7 | AJ9: 27 | AY9: 7 | AZ9: 39 | BB9: 2 вариант целей S
C10: 8 | D10: 8 | F10: вручений | G10: бонус | H10: доплата за вручение | I10: водители на ступени | J10: SR | K10: Затраты | L10: sub/gmv | S10: 7 | T10: 19 | V10: вручений | W10: бонус | X10: доплата за вручение | Y10: водители на ступени | Z10: SR | AA10: Затраты | AB10: sub/gmv | AI10: 8 | AJ10: 23 | AL10: 2 вариант целей M | AY10: 8 | AZ10: 36 | BB10: вручений | BC10: бонус | BD10: доплата за вручение | BE10: водители на ступени | BF10: SR | BG10: Затраты | BH10: sub/gmv
C11: 9 | D11: 8 | F11: 12 | G11: 3000 | H11: =G11/F11 -> 250 | I11: 32 | J11: =I11/$D$25 -> 0.14414414 | K11: =G11*I11 -> 96000 | S11: 8 | T11: 23 | V11: 15 | W11: 3000 | X11: =W11/V11 -> 200 | Y11: 30 | Z11: =Y11/394 -> 0.076142132 | AA11: =W11*Y11 -> 90000 | AI11: 9 | AJ11: 29 | AL11: вручений | AM11: бонус | AN11: доплата за вручение | AO11: водители на ступени | AP11: SR | AQ11: Затраты | AR11: sub/gmv | AY11: 9 | AZ11: 31 | BB11: 20 | BC11: 2200 | BD11: =BC11/BB11 -> 110 | BE11: 73 | BF11: =BE11/1041 -> 0.07012488 | BG11: =BC11*BE11 -> 160600
C12: 10 | D12: 7 | F12: 17 | G12: 4500 | H12: =G12/F12 -> 264.70588 | I12: 13 | J12: =I12/$D$25 -> 0.058558559 | K12: =G12*I12 -> 58500 | S12: 9 | T12: 15 | V12: 20 | W12: 4400 | X12: =W12/V12 -> 220 | Y12: 24 | Z12: =Y12/394 -> 0.060913706 | AA12: =W12*Y12 -> 105600 | AI12: 10 | AJ12: 33 | AL12: 20 | AM12: 3200 | AN12: =AM12/AL12 -> 160 | AO12: 55 | AP12: =AO12/741 -> 0.074224022 | AQ12: =AM12*AO12 -> 176000 | AY12: 10 | AZ12: 35 | BB12: 25 | BC12: 3200 | BD12: =BC12/BB12 -> 128 | BE12: 51 | BF12: =BE12/1041 -> 0.048991354 | BG12: =BC12*BE12 -> 163200
C13: 11 | D13: 6 | F13: 22 | G13: 6400 | H13: =G13/F13 -> 290.90909 | I13: 5 | J13: =I13/$D$25 -> 0.022522523 | K13: =G13*I13 -> 32000 | S13: 10 | T13: 21 | V13: 25 | W13: 6000 | X13: =W13/V13 -> 240 | Y13: 5 | Z13: =Y13/394 -> 0.012690355 | AA13: =W13*Y13 -> 30000 | AI13: 11 | AJ13: 28 | AL13: 25 | AM13: 4400 | AN13: =AM13/AL13 -> 176 | AO13: 22 | AP13: =AO13/741 -> 0.029689609 | AQ13: =AM13*AO13 -> 96800 | AY13: 11 | AZ13: 40 | BB13: 30 | BC13: 4600 | BD13: =BC13/BB13 -> 153.33333 | BE13: 79 | BF13: =BE13/1041 -> 0.075888569 | BG13: =BC13*BE13 -> 363400
C14: 12 | D14: 12 | I14: Всего: | J14: =SUM(J11:J13) -> 0.22522523 | K14: =SUM(K11:K13) -> 186500 | L14: =K14/$AE$6 -> 0.021978977 | S14: 11 | T14: 14 | Y14: Всего: | Z14: =SUM(Z11:Z13) -> 0.14974619 | AA14: =SUM(AA11:AA13) -> 225600 | AB14: =AA14/$AE$6 -> 0.026586902 | AI14: 12 | AJ14: 24 | AL14: 30 | AM14: 6000 | AN14: =AM14/AL14 -> 200 | AO14: 19 | AP14: =AO14/741 -> 0.025641026 | AQ14: =AM14*AO14 -> 114000 | AY14: 12 | AZ14: 29 | BE14: Всего: | BF14: =SUM(BF11:BF13) -> 0.1950048 | BG14: =SUM(BG11:BG13) -> 687200 | BH14: =BG14/$BK$6 -> 0.031580775
C15: 13 | D15: 9 | S15: 12 | T15: 7 | AI15: 13 | AJ15: 13 | AO15: Всего: | AP15: =SUM(AP12:AP14) -> 0.12955466 | AQ15: =SUM(AQ12:AQ14) -> 386800 | AR15: =AQ15/$AU$6 -> 0.022277161 | AY15: 13 | AZ15: 30
C16: 14 | D16: 4 | F16: 3 вариант целей XL | S16: 13 | T16: 10 | V16: 3 вариант целей L | AI16: 14 | AJ16: 19 | AY16: 14 | AZ16: 25 | BB16: 3 вариант целей S
C17: 15 | D17: 6 | F17: вручений | G17: бонус | H17: доплата за вручение | I17: водители на ступени | J17: SR | K17: Затраты | L17: sub/gmv | S17: 14 | T17: 12 | V17: вручений | W17: бонус | X17: доплата за вручение | Y17: водители на ступени | Z17: SR | AA17: Затраты | AB17: sub/gmv | AI17: 15 | AJ17: 23 | AL17: 3 вариант целей M | AY17: 15 | AZ17: 28 | BB17: вручений | BC17: бонус | BD17: доплата за вручение | BE17: водители на ступени | BF17: SR | BG17: Затраты | BH17: sub/gmv
C18: 16 | D18: 1 | F18: 15 | G18: 4000 | H18: =G18/F18 -> 266.66667 | I18: 17 | J18: =I18/$D$25 -> 0.076576577 | K18: =G18*I18 -> 68000 | S18: 15 | T18: 11 | V18: 20 | W18: 4000 | X18: =W18/V18 -> 200 | Y18: 24 | Z18: =Y18/394 -> 0.060913706 | AA18: =W18*Y18 -> 96000 | AI18: 16 | AJ18: 14 | AL18: вручений | AM18: бонус | AN18: доплата за вручение | AO18: водители на ступени | AP18: SR | AQ18: Затраты | AR18: sub/gmv | AY18: 16 | AZ18: 22 | BB18: 25 | BC18: 2800 | BD18: =BC18/BB18 -> 112 | BE18: 51 | BF18: =BE18/1041 -> 0.048991354 | BG18: =BC18*BE18 -> 142800
C19: 17 | D19: 6 | F19: 20 | G19: 5500 | H19: =G19/F19 -> 275 | I19: 7 | J19: =I19/$D$25 -> 0.031531532 | K19: =G19*I19 -> 38500 | S19: 16 | T19: 9 | V19: 25 | W19: 5500 | X19: =W19/V19 -> 220 | Y19: 3 | Z19: =Y19/394 -> 0.0076142132 | AA19: =W19*Y19 -> 16500 | AI19: 17 | AJ19: 14 | AL19: 25 | AM19: 4000 | AN19: =AM19/AL19 -> 160 | AO19: 22 | AP19: =AO19/741 -> 0.029689609 | AQ19: =AM19*AO19 -> 88000 | AY19: 17 | AZ19: 20 | BB19: 30 | BC19: 4000 | BD19: =BC19/BB19 -> 133.33333 | BE19: 35 | BF19: =BE19/1041 -> 0.033621518 | BG19: =BC19*BE19 -> 140000
C20: 18 | D20: 1 | F20: 25 | G20: 7500 | H20: =G20/F20 -> 300 | I20: 1 | J20: =I20/$D$25 -> 0.0045045045 | K20: =G20*I20 -> 7500 | S20: 17 | T20: 2 | V20: 30 | W20: 7200 | X20: =W20/V20 -> 240 | Y20: 2 | Z20: =Y20/394 -> 0.0050761421 | AA20: =W20*Y20 -> 14400 | AI20: 18 | AJ20: 12 | AL20: 30 | AM20: 5500 | AN20: =AM20/AL20 -> 183.33333 | AO20: 12 | AP20: =AO20/741 -> 0.016194332 | AQ20: =AM20*AO20 -> 66000 | AY20: 18 | AZ20: 24 | BB20: 35 | BC20: 5500 | BD20: =BC20/BB20 -> 157.14286 | BE20: 44 | BF20: =BE20/1041 -> 0.042267051 | BG20: =BC20*BE20 -> 242000
C21: 19 | D21: 3 | I21: Всего: | J21: =SUM(J18:J20) -> 0.11261261 | K21: =SUM(K18:K20) -> 114000 | L21: =K21/$AE$6 -> 0.013434871 | S21: 18 | T21: 3 | Y21: Всего: | Z21: =SUM(Z18:Z20) -> 0.073604061 | AA21: =SUM(AA18:AA20) -> 126900 | AB21: =AA21/$AE$6 -> 0.014955132 | AI21: 19 | AJ21: 16 | AL21: 35 | AM21: 7200 | AN21: =AM21/AL21 -> 205.71429 | AO21: 7 | AP21: =AO21/741 -> 0.0094466937 | AQ21: =AM21*AO21 -> 50400 | AY21: 19 | AZ21: 17 | BE21: Всего: | BF21: =SUM(BF18:BF20) -> 0.12487992 | BG21: =SUM(BG18:BG20) -> 524800 | BH21: =BG21/$BK$6 -> 0.024117565
C22: 20 | D22: 3 | S22: 19 | T22: 5 | AI22: 20 | AJ22: 11 | AO22: Всего: | AP22: =SUM(AP19:AP21) -> 0.055330634 | AQ22: =SUM(AQ19:AQ21) -> 204400 | AR22: =AQ22/$AU$6 -> 0.011772109 | AY22: 20 | AZ22: 16
C23: 22 | D23: 4 | S23: 20 | T23: 8 | V23: 4 вариант целей L | AI23: 21 | AJ23: 8 | AY23: 21 | AZ23: 19
C24: 26 | D24: 1 | S24: 21 | T24: 6 | V24: вручений | W24: бонус | X24: доплата за вручение | Y24: водители на ступени | Z24: SR | AA24: Затраты | AB24: sub/gmv | AI24: 22 | AJ24: 14 | AY24: 22 | AZ24: 16
C25: Итого | D25: 222 | S25: 22 | T25: 2 | V25: 25 | W25: 5000 | X25: =W25/V25 -> 200 | Y25: 3 | Z25: =Y25/394 -> 0.0076142132 | AA25: =W25*Y25 -> 15000 | AI25: 23 | AJ25: 7 | AY25: 23 | AZ25: 8
S26: 23 | T26: 5 | V26: 30 | W26: 7000 | X26: =W26/V26 -> 233.33333 | Y26: 1 | Z26: =Y26/394 -> 0.0025380711 | AA26: =W26*Y26 -> 7000 | AI26: 24 | AJ26: 15 | AY26: 24 | AZ26: 14
S27: 24 | T27: 3 | V27: 35 | W27: 10000 | X27: =W27/V27 -> 285.71429 | Y27: 1 | Z27: =Y27/394 -> 0.0025380711 | AA27: =W27*Y27 -> 10000 | AI27: 25 | AJ27: 9 | AY27: 25 | AZ27: 12
S28: 26 | T28: 2 | Y28: Всего: | Z28: =SUM(Z25:Z27) -> 0.012690355 | AA28: =SUM(AA25:AA27) -> 32000 | AB28: =AA28/$AE$6 -> 0.0037711918 | AI28: 26 | AJ28: 4 | AY28: 26 | AZ28: 11
S29: 27 | T29: 1 | AI29: 27 | AJ29: 5 | AY29: 27 | AZ29: 12
S30: 31 | T30: 1 | AI30: 28 | AJ30: 2 | AY30: 28 | AZ30: 6
S31: 33 | T31: 1 | AI31: 29 | AJ31: 2 | AY31: 29 | AZ31: 10
S32: Итого | T32: 394 | AI32: 30 | AJ32: 3 | AY32: 30 | AZ32: 5
AI33: 31 | AJ33: 3 | AY33: 31 | AZ33: 10
AI34: 32 | AJ34: 2 | AY34: 32 | AZ34: 9
AI35: 33 | AJ35: 3 | AY35: 33 | AZ35: 6
AI36: 34 | AJ36: 1 | AY36: 34 | AZ36: 5
AI37: 35 | AJ37: 2 | AY37: 35 | AZ37: 1
AI38: 36 | AJ38: 1 | AY38: 36 | AZ38: 6
AI39: 39 | AJ39: 1 | AY39: 37 | AZ39: 4
AI40: 40 | AJ40: 1 | AY40: 38 | AZ40: 3
AI41: 41 | AJ41: 1 | AY41: 39 | AZ41: 5
AI42: 43 | AJ42: 1 | AY42: 40 | AZ42: 1
AI43: Итого | AJ43: 741 | AY43: 41 | AZ43: 3
AY44: 42 | AZ44: 2
AY45: 43 | AZ45: 1
AY46: 44 | AZ46: 1
AY47: 45 | AZ47: 3
AY48: 46 | AZ48: 1
AY49: 48 | AZ49: 3
AY50: 49 | AZ50: 1
AY51: 51 | AZ51: 2
AY52: 54 | AZ52: 1
AY53: 55 | AZ53: 3
AY54: 59 | AZ54: 1
AY55: 61 | AZ55: 1
AY56: 71 | AZ56: 1
AY57: Итого | AZ57: 1041

Sheet ЕКБ van
A1: Доходимость S
A2: COUNTA из order_id | B2: COUNTA из executor_profile_id
A3: 1 | B3: 18
A4: 2 | B4: 14 | E4: van | M4: Цели М | P4: Цели Л
A5: 3 | B5: 22 | E5: вручений | F5: бонус | G5: доплата за вручение | H5: водители на ступени | I5: SR | J5: Затраты | K5: sub/gmv | M5: вручений | N5: бонус | P5: вручений | Q5: бонус
A6: 4 | B6: 17 | D6: шаг 10 | E6: 25 | F6: 3000 | G6: =F6/E6 -> 120 | H6: 20 | I6: =H6/265 -> 0.075471698 | J6: =F6*H6 -> 60000 | M6: 18 | N6: 3000 | P6: 15 | Q6: 3000
A7: 5 | B7: 13 | E7: 30 | F7: 4500 | G7: =F7/E7 -> 150 | H7: 13 | I7: =H7/265 -> 0.049056604 | J7: =F7*H7 -> 58500 | M7: 24 | N7: 4800 | P7: 20 | Q7: 4800
A8: 6 | B8: 7 | E8: 35 | F8: 6000 | G8: =F8/E8 -> 171.42857 | H8: 32 | I8: =H8/265 -> 0.12075472 | J8: =F8*H8 -> 192000 | M8: 30 | N8: 6900 | P8: 25 | Q8: 7000
A9: 7 | B9: 6 | H9: Всего: | I9: =SUM(I6:I8) -> 0.24528302 | J9: =SUM(J6:J8) -> 310500 | K9: =J9/M16 -> 0.095833333
A10: 8 | B10: 5
A11: 9 | B11: 13
A12: 10 | B12: 9 | E12: van
A13: 11 | B13: 5 | E13: вручений | F13: бонус | G13: доплата за вручение | H13: водители на ступени | I13: SR | J13: Затраты | K13: sub/gmv | L13: Метрика | M13: S
A14: 12 | B14: 9 | E14: 25 | F14: 2200 | G14: =F14/E14 -> 88 | H14: 33 | I14: =H14/265 -> 0.1245283 | J14: =F14*H14 -> 72600 | L14: AVG Fare. Май | M14: 900
A15: 13 | B15: 5 | E15: 35 | F15: 3500 | G15: =F15/E15 -> 100 | H15: 20 | I15: =H15/265 -> 0.075471698 | J15: =F15*H15 -> 70000
A16: 14 | B16: 4 | E16: 45 | F16: 5000 | G16: =F16/E16 -> 111.11111 | H16: 12 | I16: =H16/265 -> 0.045283019 | J16: =F16*H16 -> 60000 | L16: GMV. 26.05 | M16: 3240000
A17: 15 | B17: 6 | H17: Всего: | I17: =SUM(I14:I16) -> 0.24528302 | J17: =SUM(J14:J16) -> 202600 | K17: =J17/M16 -> 0.062530864
A18: 16 | B18: 7
A19: 17 | B19: 3
A20: 18 | B20: 6 | E20: van
A21: 19 | B21: 5 | E21: вручений | F21: бонус | G21: доплата за вручение | H21: водители на ступени | I21: SR | J21: Затраты | K21: sub/gmv
A22: 20 | B22: 6 | D22: шаг 10 | E22: 30 | F22: 3000 | G22: =F22/E22 -> 100 | H22: 27 | I22: =H22/265 -> 0.10188679 | J22: =F22*H22 -> 81000
A23: 21 | B23: 8 | E23: 40 | F23: 4500 | G23: =F23/E23 -> 112.5 | H23: 9 | I23: =H23/265 -> 0.033962264 | J23: =F23*H23 -> 40500
A24: 22 | B24: 3 | E24: 50 | F24: 6000 | G24: =F24/E24 -> 120 | H24: 9 | I24: =H24/265 -> 0.033962264 | J24: =F24*H24 -> 54000
A25: 23 | B25: 3 | H25: Всего: | I25: =SUM(I22:I24) -> 0.16981132 | J25: =SUM(J22:J24) -> 175500 | K25: =J25/M16 -> 0.054166667
A26: 24 | B26: 6
A27: 25 | B27: 4
A28: 26 | B28: 4
A29: 27 | B29: 5
A30: 28 | B30: 2
A31: 29 | B31: 5
A32: 30 | B32: 1
A33: 31 | B33: 1
A34: 32 | B34: 6
A35: 33 | B35: 3
A36: 34 | B36: 2
A37: 35 | B37: 6
A38: 36 | B38: 1 | H38: Цели Van Екатеринбург
A39: 37 | B39: 3 | H39: вручений | I39: бонус | J39: доплата за вручение | K39: водители на ступени | L39: SR | M39: Затраты | N39: sub/gmv | O39: Метрика | P39: S
A40: 38 | B40: 4 | H40: 25 | I40: 2200 | J40: 88 | K40: 33 | L40: 0.1245283 | M40: 72600 | O40: AVG Fare. Май | P40: 900
A41: 40 | B41: 1 | H41: 35 | I41: 3500 | J41: 100 | K41: 20 | L41: 0.075471698 | M41: 70000
A42: 42 | B42: 3 | H42: 45 | I42: 5000 | J42: 111.11111 | K42: 12 | L42: 0.045283019 | M42: 60000 | O42: GMV. 26.05 | P42: 3240000
A43: 44 | B43: 2 | K43: Всего: | L43: 0.24528302 | M43: 202600 | N43: 0.062530864
A44: 45 | B44: 1
A45: 47 | B45: 1 | H45: Цели М Екатеринбург
A46: 49 | B46: 1 | H46: вручений | I46: бонус | J46: доплата за вручение | K46: водители на ступени | L46: SR | M46: Затраты | N46: sub/gmv | O46: Метрика
A47: 51 | B47: 2 | H47: 18 | I47: 3000 | J47: 170 | K47: 21 | L47: 0.079545455 | M47: 63000 | N47: 0.03 | O47: AVG Fare. Май | P47: 1270
A48: 53 | B48: 2 | H48: 24 | I48: 4800 | J48: 200 | K48: 11 | L48: 0.041666667 | M48: 52800 | N48: 0.023
A49: 54 | B49: 1 | H49: 30 | I49: 6900 | J49: 230 | K49: 19 | L49: 0.071969697 | M49: 131100 | N49: 0.014 | O49: GMV. 26.05 | P49: 3010000
A50: 58 | B50: 1 | K50: Сумма | L50: 0.19318182 | M50: 246900 | N50: 0.082026578
A51: 59 | B51: 1
A52: 61 | B52: 1 | H52: Цели L Екаеринбург
A53: 62 | B53: 1 | H53: вручений | I53: бонус | J53: доплата за вручение | K53: водители на ступени | L53: SR | M53: Затраты | N53: sub/gmv | O53: Метрика
A54: Итого | B54: 265 | H54: 15 | I54: 3000 | J54: 200 | K54: 13 | L54: 0.077380952 | M54: 39000 | N54: 0.064 | O54: AVG Fare. Май | P54: 1870
H55: 20 | I55: 4800 | J55: 240 | K55: 0 | L55: 0 | M55: 0 | N55: 0.016
H56: 25 | I56: 7000 | J56: 280 | K56: 16 | L56: 0.095238095 | M56: 112000 | N56: 0.012 | O56: GMV. 26.05 | P56: 1574300
K57: Сумма | L57: 0.17261905 | M57: 151000 | N57: 0.092
H59: Цели L Екаеринбург
H60: вручений | I60: бонус | J60: доплата за вручение | K60: водители на ступени | L60: SR | M60: Затраты | N60: sub/gmv | O60: Метрика
H61: 2 | I61: 1800 | J61: 900 | K61: 2 | L61: 1 | M61: 3600 | N61: 0.064 | O61: AVG Fare. Май | P61: 3636
H62: 3 | I62: 3600 | J62: 1200 | K62: 0 | L62: 0 | M62: 0 | N62: 0.016 | O62: GMV. | P62: 35000
K63: Сумма | L63: 1 | M63: =SUM(M61:M62) -> 3600 | N63: 0.092

Sheet Цели ЕКБ М
A1: КУЗОВ М | E1: Avg Fare за май | F1: 1270 | G1: GMV | H1: 3010000 | K1: https://datalens.yandex-team.ru/sne8u5ggtwoih-cdr-utilization-per-option-region?tab=Aj&state=950700d31042
A2: Вручений | B2: Водителей
A3: 1 | B3: 20 | D3: dxgy to be
A4: 2 | B4: 17 | D4: вручений | E4: бонус | F4: доплата за вручение | G4: водители на ступени | H4: SR | I4: Затраты | J4: sub/gmv | K4: =I8/H1 -> 0.051827243
A5: 3 | B5: 18 | D5: 22 | E5: 3000 | F5: =E5/D5 -> 136.36364 | G5: 19 | H5: =G5/264 -> 0.071969697 | I5: =G5*E5 -> 57000
A6: 4 | B6: 22 | D6: 30 | E6: 4500 | F6: =E6/D6 -> 150 | G6: 10 | H6: =G6/264 -> 0.037878788 | I6: =G6*E6 -> 45000
A7: 5 | B7: 9 | D7: 38 | E7: 6000 | F7: =E7/D7 -> 157.89474 | G7: 9 | H7: =G7/264 -> 0.034090909 | I7: =G7*E7 -> 54000
A8: 6 | B8: 11 | G8: Сумма | H8: =SUM(H5:H7) -> 0.14393939 | I8: =SUM(I5:I7) -> 156000
A9: 7 | B9: 9
A10: 8 | B10: 17
A11: 9 | B11: 13 | D11: dxgy to be
A12: 10 | B12: 11 | D12: вручений | E12: бонус | F12: доплата за вручение | G12: водители на ступени | H12: SR | I12: Затраты | J12: sub/gmv | K12: =I16/H1 -> 0.055315615
A13: 11 | B13: 18 | D13: 20 | E13: 2500 | F13: =E13/D13 -> 125 | G13: 26 | H13: =G13/264 -> 0.098484848 | I13: =G13*E13 -> 65000
A14: 12 | B14: 3 | D14: 30 | E14: 4500 | F14: =E14/D14 -> 150 | G14: 11 | H14: =G14/264 -> 0.041666667 | I14: =G14*E14 -> 49500
A15: 13 | B15: 6 | D15: 40 | E15: 6500 | F15: =E15/D15 -> 162.5 | G15: 8 | H15: =G15/264 -> 0.03030303 | I15: =G15*E15 -> 52000
A16: 14 | B16: 10 | G16: Сумма | H16: =SUM(H13:H15) -> 0.17045455 | I16: =SUM(I13:I15) -> 166500
A17: 15 | B17: 10
A18: 16 | B18: 12
A19: 17 | B19: 4 | D19: dxgy to be
A20: 18 | B20: 5 | D20: вручений | E20: бонус | F20: доплата за вручение | G20: водители на ступени | H20: SR | I20: Затраты | J20: sub/gmv
A21: 19 | B21: 4 | D21: 18 | E21: 3000 | F21: 170 | G21: 21 | H21: =G21/264 -> 0.079545455 | I21: =G21*E21 -> 63000 | J21: =I24/H1 -> 0.082026578
A22: 20 | B22: 5 | D22: 24 | E22: =D22*F22 -> 4800 | F22: 200 | G22: 11 | H22: =G22/264 -> 0.041666667 | I22: =G22*E22 -> 52800
A23: 21 | B23: 2 | D23: 30 | E23: =D23*F23 -> 6900 | F23: 230 | G23: 19 | H23: =G23/264 -> 0.071969697 | I23: =G23*E23 -> 131100
A24: 22 | B24: 2 | G24: Сумма | H24: =SUM(H21:H23) -> 0.19318182 | I24: =SUM(I21:I23) -> 246900
A25: 23 | B25: 3
A26: 24 | B26: 5
A27: 25 | B27: 2
A28: 26 | B28: 2 | I28: 350000
A29: 27 | B29: 2
A30: 28 | B30: 2
A31: 29 | B31: 1
A32: 30 | B32: 2
A33: 31 | B33: 2
A34: 32 | B34: 1
A35: 33 | B35: 2
A36: 34 | B36: 2
A37: 35 | B37: 1
A38: 38 | B38: 1
A39: 41 | B39: 1
A40: 42 | B40: 1
... A45: 58 | B45: 1
A46: Итого | B46: 264
A48: КУЗОВ М1
A49: Вручений | B49: Водители
A50: 1 | B50: 5 | E50: Avg Fare за май | F50: 1810 | G50: GMV | H50: 806100
A51: 2 | B51: 1
A52: 3 | B52: 3 | D52: dxgy to be
A53: 4 | B53: 8 | D53: вручений | E53: бонус | F53: доплата за вручение | G53: водители на ступени | H53: SR | I53: Затраты | J53: sub/gmv | K53: =I57/H50 -> 0.12827193
A54: 5 | B54: 3 | D54: 20 | E54: 3600 | F54: =E54/D54 -> 180 | G54: 13 | H54: =G54/103 -> 0.12621359 | I54: =G54*E54 -> 46800
A55: 6 | B55: 2 | D55: 30 | E55: 5800 | F55: =E55/D55 -> 193.33333 | G55: 7 | H55: =G55/103 -> 0.067961165 | I55: =G55*E55 -> 40600
A56: 7 | B56: 5 | D56: 40 | E56: 8000 | F56: =E56/D56 -> 200 | G56: 2 | H56: =G56/103 -> 0.019417476 | I56: =G56*E56 -> 16000
A57: 8 | B57: 9 | G57: Сумма | H57: =SUM(H54:H56) -> 0.21359223 | I57: =SUM(I54:I56) -> 103400
A58: 9 | B58: 4
A59: 10 | B59: 2
A60: 11 | B60: 8 | D60: dxgy to be
A61: 12 | B61: 1 | D61: вручений | E61: бонус | F61: доплата за вручение | G61: водители на ступени | H61: SR | I61: Затраты | J61: sub/gmv | K61: =I65/H50 -> 0.14911301
A62: 13 | B62: 4 | D62: 18 | E62: 3200 | F62: =E62/D62 -> 177.77778 | G62: 16 | H62: =G62/103 -> 0.15533981 | I62: =G62*E62 -> 51200
A63: 14 | B63: 9 | D63: 26 | E63: 5000 | F63: =E63/D63 -> 192.30769 | G63: 7 | H63: =G63/103 -> 0.067961165 | I63: =G63*E63 -> 35000
A64: 15 | B64: 5 | D64: 34 | E64: 6800 | F64: =E64/D64 -> 200 | G64: 5 | H64: =G64/103 -> 0.048543689 | I64: =G64*E64 -> 34000
A65: 16 | B65: 5 | G65: Сумма | H65: =SUM(H62:H64) -> 0.27184466 | I65: =SUM(I62:I64) -> 120200
A66: 17 | B66: 1
A67: 18 | B67: 3
A68: 19 | B68: 3
A69: 20 | B69: 3
A70: 21 | B70: 1
A71: 23 | B71: 1
A72: 24 | B72: 4
A73: 25 | B73: 1
A74: 26 | B74: 2
A75: 29 | B75: 1
A76: 30 | B76: 1
A77: 31 | B77: 2
... A82: 45 | B82: 1
A83: Итого | B83: 103
A90: КУЗОВ М2
A91: Вручений | B91: Водителей
A92: 1 | B92: 1
A93: 2 | B93: 2 | E93: Avg Fare за май | F93: 2435 | G93: GMV | H93: 714340
A94: 3 | B94: 3
A95: 4 | B95: 4
A96: 5 | B96: 1 | D96: dxgy to be
A97: 6 | B97: 2 | D97: вручений | E97: бонус | F97: доплата за вручение | G97: водители на ступени | H97: SR | I97: Затраты | J97: sub/gmv | K97: =I101/H93 -> 0.060195425
A98: 7 | B98: 1 | D98: 18 | E98: 3500 | F98: =E98/D98 -> 194.44444 | G98: 4 | H98: =G98/37 -> 0.10810811 | I98: =G98*E98 -> 14000
A99: 9 | B99: 1 | D99: 23 | E99: 5000 | F99: =E99/D99 -> 217.3913 | G99: 3 | H99: =G99/37 -> 0.081081081 | I99: =G99*E99 -> 15000
A100: 10 | B100: 1 | D100: 28 | E100: 7000 | F100: =E100/D100 -> 250 | G100: 2 | H100: =G100/37 -> 0.054054054 | I100: =G100*E100 -> 14000
A101: 11 | B101: 4 | G101: Сумма | H101: =SUM(H98:H100) -> 0.24324324 | I101: =SUM(I98:I100) -> 43000
A102: 12 | B102: 1
A103: 14 | B103: 1
A104: 15 | B104: 3
A105: 16 | B105: 2
A106: 17 | B106: 2
A107: 18 | B107: 1
A108: 19 | B108: 1
A109: 22 | B109: 1
A110: 23 | B110: 1
A111: 27 | B111: 2
A112: 28 | B112: 1
A113: 30 | B113: 1
A114: Итого | B114: 37

Sheet Цели ЕКБ L
A1: Кузов L | E1: Avg Fare за май | F1: 1870 | G1: GMV | H1: 1574300 | K1: https://datalens.yandex-team.ru/sne8u5ggtwoih-cdr-utilization-per-option-region?tab=Aj&state=950700d31042
A2: Вручений | B2: Водителей
A3: 1 | B3: 12 | D3: dxgy to be
A4: 2 | B4: 18 | D4: вручений | E4: бонус | F4: доплата за вручение | G4: водители на ступени | H4: SR | I4: Затраты | J4: sub/gmv | K4: Доплата в М0
A5: 3 | B5: 10 | D5: 15 | E5: =F5*D5 -> 3000 | F5: 200 | G5: 13 | H5: =G5/168 -> 0.077380952 | I5: =G5*E5 -> 39000 | J5: =I8/H1 -> 0.095915645 | K5: 122.72727
A6: 4 | B6: 17 | D6: 20 | E6: =F6*D6 -> 4800 | F6: 240 | G6: 0 | H6: =G6/168 -> 0 | I6: =G6*E6 -> 0 | K6: 133.33333
A7: 5 | B7: 10 | D7: 25 | E7: =F7*D7 -> 7000 | F7: 280 | G7: 16 | H7: =G7/168 -> 0.095238095 | I7: =G7*E7 -> 112000 | K7: 144.73684
A8: 6 | B8: 14 | G8: Сумма | H8: =SUM(H5:H7) -> 0.17261905 | I8: =SUM(I5:I7) -> 151000
A9: 7 | B9: 7
A10: 8 | B10: 7
A11: 9 | B11: 3 | D11: dxgy to be
A12: 10 | B12: 5 | D12: вручений | E12: бонус | F12: доплата за вручение | G12: водители на ступени | H12: SR | I12: Затраты | J12: sub/gmv
A13: 11 | B13: 2 | D13: 18 | E13: 3000 | F13: =E13/D13 -> 166.66667 | G13: 17 | H13: =G13/168 -> 0.10119048 | I13: =G13*E13 -> 51000 | J13: =I16/H1 -> 0.096296767
A14: 12 | B14: 8 | D14: 24 | E14: 4200 | F14: =E14/D14 -> 175 | G14: 3 | H14: =G14/168 -> 0.017857143 | I14: =G14*E14 -> 12600
A15: 13 | B15: 4 | D15: 30 | E15: 5500 | F15: =E15/D15 -> 183.33333 | G15: 16 | H15: =G15/168 -> 0.095238095 | I15: =G15*E15 -> 88000
A16: 14 | B16: 4 | G16: Сумма | H16: =SUM(H13:H15) -> 0.21428571 | I16: =SUM(I13:I15) -> 151600
A17: 15 | B17: 2
A18: 16 | B18: 5
A19: 17 | B19: 4 | D19: dxgy to be
A20: 18 | B20: 5 | D20: вручений | E20: бонус | F20: доплата за вручение | G20: водители на ступени | H20: SR | I20: Затраты | J20: sub/gmv
A21: 19 | B21: 2 | D21: 20 | E21: 3000 | F21: =E21/D21 -> 150 | G21: 10 | H21: =G21/168 -> 0.05952381 | I21: =G21*E21 -> 30000 | J21: =I24/H1 -> 0.08194118
A22: 20 | B22: 3 | D22: 25 | E22: 4200 | F22: =E22/D22 -> 168 | G22: 3 | H22: =G22/168 -> 0.017857143 | I22: =G22*E22 -> 12600
A23: 21 | B23: 4 | D23: 30 | E23: 5400 | F23: =E23/D23 -> 180 | G23: 16 | H23: =G23/168 -> 0.095238095 | I23: =G23*E23 -> 86400
A24: 22 | B24: 1 | G24: Сумма | H24: =SUM(H21:H23) -> 0.17261905 | I24: =SUM(I21:I23) -> 129000
A25: 23 | B25: 2
A26: 24 | B26: 3
A27: 30 | B27: 7
A28: 32 | B28: 1
A29: 34 | B29: 1
A30: 36 | B30: 2
A31: 37 | B31: 1
A32: 42 | B32: 1
A33: 44 | B33: 1
A34: 45 | B34: 1
A35: 52 | B35: 1
A36: Итого | B36: 168
E37: Avg Fare за май | F37: 2620 | G37: GMV | H37: 443700
A38: Кузов L1
A39: Вручений | B39: Водителей | D39: dxgy to be
A40: 1 | B40: 4 | D40: вручений | E40: бонус | F40: доплата за вручение | G40: водители на ступени | H40: SR | I40: Затраты | J40: sub/gmv | K40: Доплата в М1
A41: 2 | B41: 4 | D41: 25 | E41: 4000 | F41: =E41/D41 -> 160 | G41: 0 | H41: =G41/45 -> 0 | I41: =G41*E41 -> 0 | J41: =I44/H37 -> 0.14086094 | K41: 180
A42: 3 | B42: 1 | D42: 30 | E42: 5500 | F42: =E42/D42 -> 183.33333 | G42: 5 | H42: =G42/45 -> 0.11111111 | I42: =G42*E42 -> 27500 | K42: 193.33333
A43: 4 | B43: 2 | D43: 35 | E43: 7000 | F43: =E43/D43 -> 200 | G43: 5 | H43: =G43/45 -> 0.11111111 | I43: =G43*E43 -> 35000 | K43: 200
A44: 6 | B44: 2 | G44: Сумма | H44: =SUM(H41:H43) -> 0.22222222 | I44: =SUM(I41:I43) -> 62500
A45: 7 | B45: 2
A46: 8 | B46: 2
A47: 10 | B47: 2 | D47: dxgy to be
A48: 12 | B48: 2 | D48: вручений | E48: бонус | F48: доплата за вручение | G48: водители на ступени | H48: SR | I48: Затраты | J48: sub/gmv
A49: 13 | B49: 1 | D49: 20 | E49: 3000 | F49: =E49/D49 -> 150 | G49: 7 | H49: =G49/45 -> 0.15555556 | I49: =G49*E49 -> 21000 | J49: =I52/H37 -> 0.18255578
A50: 16 | B50: 3 | D50: 25 | E50: 4500 | F50: =E50/D50 -> 180 | G50: 0 | H50: =G50/45 -> 0 | I50: =G50*E50 -> 0
A51: 18 | B51: 2 | D51: 30 | E51: 6000 | F51: =E51/D51 -> 200 | G51: 10 | H51: =G51/45 -> 0.22222222 | I51: =G51*E51 -> 60000
A52: 19 | B52: 1 | G52: Сумма | H52: =SUM(H49:H51) -> 0.37777778 | I52: =SUM(I49:I51) -> 81000
A53: 20 | B53: 2
A54: 21 | B54: 2
A55: 23 | B55: 1
A56: 24 | B56: 2
A57: 30 | B57: 3
A58: 32 | B58: 1
A59: 34 | B59: 1
A60: 36 | B60: 2
A61: 37 | B61: 1
A62: 42 | B62: 1
A63: 44 | B63: 1
A64: Итого | B64: 45
E65: Avg Fare за май | F65: 3100 | G65: GMV | H65: 421275
A66: Кузов L2
A67: Вручений | B67: Водителей | D67: dxgy to be
A68: 1 | B68: 1 | D68: вручений | E68: бонус | F68: доплата за вручение | G68: водители на ступени | H68: SR | I68: Затраты | J68: sub/gmv | K68: доплата за вручение М2
A69: 2 | B69: 1 | D69: 15 | E69: 4000 | F69: =E69/D69 -> 266.66667 | G69: 4 | H69: =G69/34 -> 0.11764706 | I69: =G69*E69 -> 16000 | J69: =I72/H65 -> 0.18989971 | K69: 194.44444
A70: 3 | B70: 3 | D70: 20 | E70: 6000 | F70: =E70/D70 -> 300 | G70: 4 | H70: =G70/34 -> 0.11764706 | I70: =G70*E70 -> 24000 | K70: 217.3913
A71: 4 | B71: 2 | D71: 25 | E71: 8000 | F71: =E71/D71 -> 320 | G71: 5 | H71: =G71/34 -> 0.14705882 | I71: =G71*E71 -> 40000 | K71: 250
A72: 5 | B72: 1 | G72: Сумма | H72: =SUM(H69:H71) -> 0.38235294 | I72: =SUM(I69:I71) -> 80000
A73: 6 | B73: 5
A74: 8 | B74: 1
A75: 10 | B75: 1
A76: 12 | B76: 2
A77: 13 | B77: 1
A78: 14 | B78: 3
A79: 15 | B79: 1
A80: 16 | B80: 1
A81: 17 | B81: 1
A82: 18 | B82: 1
A83: 20 | B83: 1
A84: 21 | B84: 1
... A89: 52 | B89: 1
A90: Итого | B90: 34

Sheet Цели Оренбург
A1: 26.05 Доходимость S | D1: C Понедельника
A2: COUNTA из order_id | B2: COUNTA из executor_profile_id
A3: 1 | B3: 2 | D3: dxgy S кузова as is
A4: 3 | B4: 1 | D4: вручений | E4: бонус | F4: доплата за вручение | G4: водители на ступени | H4: SR | I4: Затраты | J4: sub/gmv | L4: Метрика | M4: van
A5: 5 | B5: 1 | D5: 15 | E5: 1500 | F5: =E5/D5 -> 100 | G5: 1 | H5: =G5/$B$10 -> 0.125 | I5: =E5*G5 -> 1500 | L5: AVG Fare. Май | M5: =HLOOKUP(M4,'выгрузка Оренбург (кузова)'!$B$1:$J$3,2,0) -> 537.75819
A6: 9 | B6: 1 | D6: 20 | E6: 2500 | F6: =E6/D6 -> 125 | G6: 0 | H6: =G6/$B$10 -> 0 | I6: =E6*G6 -> 0 | L6: 10% от Ср. Чека | M6: =M5/10 -> 53.775819
A7: 15 | B7: 1 | D7: 25 | E7: 4000 | F7: =E7/D7 -> 160 | G7: 2 | H7: =G7/$B$10 -> 0.25 | I7: =E7*G7 -> 8000 | L7: GMV. 26.05 | M7: =HLOOKUP(M4,'выгрузка Оренбург (кузова)'!$B$1:$J$3,3,0) -> 70688.407
A8: 25 | B8: 1 | G8: Всего: | H8: =SUM(H5:H7) -> 0.375 | I8: =SUM(I5:I7) -> 9500 | J8: =I8/$M$7 -> 0.13439262 | L8: CDR. 26.05 | M8: =HLOOKUP(M4,'выгрузка Оренбург (кузова)'!$B$1:$J$4,4,0) -> 0.55555556
A9: 27 | B9: 1
A10: Итого | B10: 8
A12: 26.05 Доходимость M | D12: dxgy M кузова as is
A13: COUNTA из order_id | B13: COUNTA из executor_profile_id | D13: вручений | E13: бонус | F13: доплата за вручение | G13: водители на ступени | H13: SR | I13: Затраты | J13: sub/gmv | L13: Метрика | M13: lcv_m
A14: 1 | B14: 2 | D14: 15 | E14: 1800 | F14: =E14/D14 -> 120 | G14: 1 | H14: =G14/$B$25 -> 0.066666667 | I14: =E14*G14 -> 1800 | L14: AVG Fare. Май | M14: =HLOOKUP(M13,'выгрузка Оренбург (кузова)'!$B$1:$J$3,2,0) -> 748.34428
A15: 2 | B15: 2 | D15: 20 | E15: 2900 | F15: =E15/D15 -> 145 | G15: 0 | H15: =G15/$B$25 -> 0 | I15: =E15*G15 -> 0 | L15: 10% от Ср. Чека | M15: =M14/10 -> 74.834428
A16: 3 | B16: 1 | D16: 25 | E16: 4200 | F16: =E16/D16 -> 168 | G16: 3 | H16: =G16/$B$25 -> 0.2 | I16: =E16*G16 -> 12600 | L16: GMV. 26.05 | M16: =HLOOKUP(M13,'выгрузка Оренбург (кузова)'!$B$1:$J$3,3,0) -> 131583.6
A17: 4 | B17: 1 | G17: Всего: | H17: =SUM(H14:H16) -> 0.26666667 | I17: =SUM(I14:I16) -> 14400 | J17: =I17/$M$16 -> 0.10943613 | L17: CDR. 26.05 | M17: =HLOOKUP(M13,'выгрузка Оренбург (кузова)'!$B$1:$J$4,4,0) -> 0.77021277
A18: 5 | B18: 3
A19: 8 | B19: 1
A20: 13 | B20: 1
A21: 18 | B21: 1
A22: 25 | B22: 1
A23: 33 | B23: 1
A24: 37 | B24: 1
A25: Итого | B25: 15
A27: 26.05 Доходимость L | D27: dxgy L кузова as is
A28: COUNTA из order_id | B28: COUNTA из executor_profile_id | D28: вручений | E28: бонус | F28: доплата за вручение | G28: водители на ступени | H28: SR | I28: Затраты | J28: sub/gmv | L28: Метрика | M28: lcv_l
A29: 1 | B29: 1 | D29: 5 | E29: 1000 | F29: =E29/D29 -> 200 | G29: 0 | H29: =G29/$B$34 -> 0 | I29: =E29*G29 -> 0 | L29: AVG Fare. Май | M29: =HLOOKUP(M28,'выгрузка Оренбург (кузова)'!$B$1:$J$3,2,0) -> 966.48684
A30: 2 | B30: 1 | D30: 10 | E30: 2000 | F30: =E30/D30 -> 200 | G30: 0 | H30: =G30/$B$34 -> 0 | I30: =E30*G30 -> 0 | L30: 10% от Ср. Чека | M30: =M29/10 -> 96.648684
A31: 17 | B31: 1 | D31: 15 | E31: 3000 | F31: =E31/D31 -> 200 | G31: 3 | H31: =G31/$B$34 -> 0.6 | I31: =E31*G31 -> 9000 | L31: GMV. 26.05 | M31: =HLOOKUP(M28,'выгрузка Оренбург (кузова)'!$B$1:$J$3,3,0) -> 25442
A32: 21 | B32: 1 | G32: Всего: | H32: =SUM(H29:H31) -> 0.6 | I32: =SUM(I29:I31) -> 9000 | J32: =I32/$M$31 -> 0.35374577 | L32: CDR. 26.05 | M32: =HLOOKUP(M28,'выгрузка Оренбург (кузова)'!$B$1:$J$4,4,0) -> 0.64285714
A33: 37 | B33: 1
A34: Итого | B34: 5

Sheet Цели Омск
A2: COUNTA из order_id | B2: COUNTA из executor_profile_id | E2: dxgy M as is
A3: 1 | B3: 11 | E3: вручений | F3: бонус | G3: доплата за вручение | H3: водители на ступени | I3: SR | J3: Затраты | K3: sub/gmv | M3: Метрика | N3: lcv_m
A4: 2 | B4: 7 | E4: 15 | F4: 2800 | G4: =F4/E4 -> 186.66667 | H4: 6 | I4: =H4/$B$25 -> 0.066666667 | J4: =F4*H4 -> 16800 | M4: AVG Fare. Май | N4: =HLOOKUP(N3,'выгрузка Омск (кузова)'!$B$1:$J$3,2,0) -> 1266.7325
A5: 3 | B5: 9 | E5: 20 | F5: 4200 | G5: =F5/E5 -> 210 | H5: 2 | I5: =H5/$B$25 -> 0.022222222 | J5: =F5*H5 -> 8400 | M5: 10% от Ср. Чека | N5: =N4/10 -> 126.67325
A6: 4 | B6: 3 | E6: 25 | F6: 5800 | G6: =F6/E6 -> 232 | H6: 4 | I6: =H6/$B$25 -> 0.044444444 | J6: =F6*H6 -> 23200 | M6: GMV. 26.05 | N6: =HLOOKUP(N3,'выгрузка Омск (кузова)'!$B$1:$J$3,3,0) -> 1095174.2
A7: 5 | B7: 4 | H7: Всего: | I7: =SUM(I4:I6) -> 0.13333333 | J7: =SUM(J4:J6) -> 48400 | K7: =J7/$N$6 -> 0.044193883
A8: 6 | B8: 7
A9: 7 | B9: 7
A10: 8 | B10: 4
A11: 9 | B11: 4
A12: 10 | B12: 6
A13: 11 | B13: 2
A14: 12 | B14: 3
A15: 13 | B15: 3
A16: 14 | B16: 8
A17: 15 | B17: 3
A18: 17 | B18: 1
A19: 18 | B19: 2
... A24: 29 | B24: 1
A25: Итого | B25: 90
A30: Доходимость S за 26.05
A31: COUNTA из order_id | B31: COUNTA из executor_profile_id
A32: 1 | B32: 7 | L32: Метрика | M32: van
A33: 2 | B33: 6 | L33: AVG Fare. Май | M33: =HLOOKUP(M32,'выгрузка Омск (кузова)'!$B$1:$J$3,2,0) -> 846.60579
A34: 3 | B34: 9 | L34: 10% от Ср. Чека | M34: =M33/10 -> 84.660579
A35: 4 | B35: 4 | L35: GMV. 26.05 | M35: =HLOOKUP(M32,'выгрузка Омск (кузова)'!$B$1:$J$3,3,0) -> 710297.37
A36: 5 | B36: 4
A37: 6 | B37: 2 | E37: Доплата от 100 рублей | M37: Доплата от 80 рублей
A38: 7 | B38: 5
A39: 8 | B39: 2 | E39: 1 вариант целей на S | M39: 4 вариант целей на S
A40: 9 | B40: 2 | E40: вручений | F40: бонус | G40: доплата за вручение | H40: водители на ступени | I40: SR | J40: Затраты | K40: sub/gmv | M40: вручений | N40: бонус | O40: доплата за вручение | P40: водители на ступени | Q40: SR | R40: Затраты | S40: sub/gmv
A41: 10 | B41: 5 | E41: 15 | F41: 1500 | G41: =F41/E41 -> 100 | H41: 8 | I41: =H41/$B$57 -> 0.10958904 | J41: =F41*H41 -> 12000 | M41: 15 | N41: 1200 | O41: =N41/M41 -> 80 | P41: 8 | Q41: =P41/$B$57 -> 0.10958904 | R41: =N41*P41 -> 9600
A42: 11 | B42: 4 | E42: 20 | F42: 2500 | G42: =F42/E42 -> 125 | H42: 3 | I42: =H42/$B$57 -> 0.04109589 | J42: =F42*H42 -> 7500 | M42: 20 | N42: 2000 | O42: =N42/M42 -> 100 | P42: 3 | Q42: =P42/$B$57 -> 0.04109589 | R42: =N42*P42 -> 6000
A43: 12 | B43: 1 | E43: 25 | F43: 3500 | G43: =F43/E43 -> 140 | H43: 7 | I43: =H43/$B$57 -> 0.095890411 | J43: =F43*H43 -> 24500 | M43: 25 | N43: 3000 | O43: =N43/M43 -> 120 | P43: 7 | Q43: =P43/$B$57 -> 0.095890411 | R43: =N43*P43 -> 21000
A44: 13 | B44: 3 | H44: Всего: | I44: =SUM(I41:I43) -> 0.24657534 | J44: =SUM(J41:J43) -> 44000 | K44: =J44/$M$35 -> 0.061945886 | P44: Всего: | Q44: =SUM(Q41:Q43) -> 0.24657534 | R44: =SUM(R41:R43) -> 36600 | S44: =R44/$M$35 -> 0.051527714
A45: 14 | B45: 1
A46: 15 | B46: 3 | E46: 2 вариант целей на S | M46: 5 вариант целей на S
A47: 16 | B47: 3 | E47: вручений | F47: бонус | G47: доплата за вручение | H47: водители на ступени | I47: SR | J47: Затраты | K47: sub/gmv | M47: вручений | N47: бонус | O47: доплата за вручение | P47: водители на ступени | Q47: SR | R47: Затраты | S47: sub/gmv
A48: 18 | B48: 2 | E48: 17 | F48: 1800 | G48: =F48/E48 -> 105.88235 | H48: 4 | I48: =H48/$B$57 -> 0.054794521 | J48: =F48*H48 -> 7200 | M48: 17 | N48: 1400 | O48: =N48/M48 -> 82.352941 | P48: 4 | Q48: =P48/$B$57 -> 0.054794521 | R48: =N48*P48 -> 5600
A49: 21 | B49: 2 | E49: 22 | F49: 2800 | G49: =F49/E49 -> 127.27273 | H49: 2 | I49: =H49/$B$57 -> 0.02739726 | J49: =F49*H49 -> 5600 | M49: 22 | N49: 2400 | O49: =N49/M49 -> 109.09091 | P49: 2 | Q49: =P49/$B$57 -> 0.02739726 | R49: =N49*P49 -> 4800
A50: 23 | B50: 1 | E50: 27 | F50: 3800 | G50: =F50/E50 -> 140.74074 | H50: 7 | I50: =H50/$B$57 -> 0.095890411 | J50: =F50*H50 -> 26600 | M50: 27 | N50: 3400 | O50: =N50/M50 -> 125.92593 | P50: 7 | Q50: =P50/$B$57 -> 0.095890411 | R50: =N50*P50 -> 23800
A51: 28 | B51: 1 | H51: Всего: | I51: =SUM(I48:I50) -> 0.17808219 | J51: =SUM(J48:J50) -> 39400 | K51: =J51/$M$35 -> 0.055469725 | P51: Всего: | Q51: =SUM(Q48:Q50) -> 0.17808219 | R51: =SUM(R48:R50) -> 34200 | S51: =R51/$M$35 -> 0.048148848
A52: 32 | B52: 1
A53: 33 | B53: 1 | E53: 3 вариант целей на S | M53: 6 вариант целей на S
A54: 36 | B54: 1 | E54: вручений | F54: бонус | G54: доплата за вручение | H54: водители на ступени | I54: SR | J54: Затраты | K54: sub/gmv | M54: вручений | N54: бонус | O54: доплата за вручение | P54: водители на ступени | Q54: SR | R54: Затраты | S54: sub/gmv
A55: 41 | B55: 1 | E55: 20 | F55: 2200 | G55: =F55/E55 -> 110 | H55: 3 | I55: =H55/$B$57 -> 0.04109589 | J55: =F55*H55 -> 6600 | M55: 20 | N55: 1800 | O55: =N55/M55 -> 90 | P55: 3 | Q55: =P55/$B$57 -> 0.04109589 | R55: =N55*P55 -> 5400
A56: 42 | B56: 2 | E56: 25 | F56: 3200 | G56: =F56/E56 -> 128 | H56: 1 | I56: =H56/$B$57 -> 0.01369863 | J56: =F56*H56 -> 3200 | M56: 25 | N56: 2800 | O56: =N56/M56 -> 112 | P56: 1 | Q56: =P56/$B$57 -> 0.01369863 | R56: =N56*P56 -> 2800
A57: Итого | B57: 73 | E57: 30 | F57: 4400 | G57: =F57/E57 -> 146.66667 | H57: 6 | I57: =H57/$B$57 -> 0.082191781 | J57: =F57*H57 -> 26400 | M57: 30 | N57: 3800 | O57: =N57/M57 -> 126.66667 | P57: 6 | Q57: =P57/$B$57 -> 0.082191781 | R57: =N57*P57 -> 22800
H58: Всего: | I58: =SUM(I55:I57) -> 0.1369863 | J58: =SUM(J55:J57) -> 36200 | K58: =J58/$M$35 -> 0.05096457 | P58: Всего: | Q58: =SUM(Q55:Q57) -> 0.1369863 | R58: =SUM(R55:R57) -> 31000 | S58: =R58/$M$35 -> 0.043643692

Sheet выгрузка Оренбург (кузова)
A1: dt | B1: lcv_l | C1: lcv_m | D1: van | E1: Деш источник
A2: AVG Fare. Май | B2: 966.48684 | C2: 748.34428 | D2: 537.75819 | E2: https://datalens.yandex-team.ru/sne8u5ggtwoih-cdr-utilization-per-option-region?tab=Aj&state=e90ef374959
A3: GMV. 26.05 | B3: 25442 | C3: 131583.6 | D3: 70688.407 | E3: https://datalens.yandex-team.ru/sne8u5ggtwoih-cdr-utilization-per-option-region?tab=Aj&state=978ad817959
A4: CDR. 26.05 | B4: 0.64285714 | C4: 0.77021277 | D4: 0.55555556 | E4: https://datalens.yandex-team.ru/sne8u5ggtwoih-cdr-utilization-per-option-region?tab=Aj&state=978ad817959

Sheet выгрузка Омск (кузова)
A1: Cargo Size | B1: lcv_l | C1: lcv_m | D1: van | E1: Деш источник
A2: AVG Fare. Май | B2: 1672.9866 | C2: 1266.7325 | D2: 846.60579 | E2: https://datalens.yandex-team.ru/sne8u5ggtwoih-cdr-utilization-per-option-region?tab=Aj&state=b05d22461079
A3: GMV. 26.05 | B3: 443274.6 | C3: 1095174.2 | D3: 710297.37

Sheet выгрузка Sochi (кузова)
A1: dt | B1: lcv_l | C1: lcv_m | D1: van | E1: Деш источник
A2: AVG Fare. Май | B2: 1803.7448 | C2: 1376.1094 | D2: 863.99867 | E2: https://datalens.yandex-team.ru/sne8u5ggtwoih-cdr-utilization-per-option-region?tab=Aj&state=47b527981080
A3: GMV. 02.06 | B3: 229176.4 | C3: 785505.8 | D3: 807415.4 | E3: https://datalens.yandex-team.ru/t9j0q9xdumu4g-cargo-mm-on-demand?state=40e374e8915

Sheet выгрузка Красноярск
A1: dt | B1: lcv_l_0 | C1: lcv_l_1 | D1: lcv_l_2 | E1: lcv_m_0 | F1: lcv_m_1 | G1: lcv_m_2 | H1: van_0 | I1: van_1 | J1: van_2 | K1: Деш источник
A2: AVG Fare. Май | B2: 1544.0027 | C2: 2147.5293 | D2: 3752.3939 | E2: 1157.3651 | F2: 1836.9653 | G2: 2859.9235 | H2: 855.4743 | I2: 1180.7424 | J2: 2502.7273 | K2: https://datalens.yandex-team.ru/sne8u5ggtwoih-cdr-utilization-per-option-region?tab=Aj&state=14c2c1851096
A3: GMV. 26.05 | B3: 243405.6 | C3: 33554 | D3: 84953.2 | E3: 561985.8 | F3: 179787 | G3: 153256.6 | H3: 349568 | I3: 158956.4 | J3: 5671 | K3: https://datalens.yandex-team.ru/sne8u5ggtwoih-cdr-utilization-per-option-region?tab=Aj&state=68ad4e6c1095

Sheet выгрузка Sochi (Op)
A1: dt | B1: lcv_l_0 | C1: lcv_l_1 | D1: lcv_l_2 | E1: lcv_m_0 | F1: lcv_m_1 | G1: lcv_m_2 | H1: van_0 | I1: van_1 | J1: van_2 | K1: Деш источник
A2: AVG Fare. Май | B2: 1533.1907 | C2: 1904.5556 | D2: 3080.9695 | E2: 1153.7841 | F2: 1842.3063 | G2: 2433.3441 | H2: 737.17158 | I2: 1381.9903 | J2: 2099.1375 | K2: https://datalens.yandex-team.ru/sne8u5ggtwoih-cdr-utilization-per-option-region?tab=Aj&state=a97ac29b1090
A3: GMV. 02.06 | B3: 161360 | C3: 34210.4 | D3: 33606 | E3: 504607.4 | F3: 191720.6 | G3: 89177.8 | H3: 599179.6 | I3: 199896.8 | J3: 8339 | K3: https://datalens.yandex-team.ru/t9j0q9xdumu4g-cargo-mm-on-demand?state=40e374e8915

Sheet Сочи L
A1: Цели на всю L
A3: Доходимость L за 02.06 | D3: 1 вариант целей L | L3: Метрика | M3: lcv_l
A4: COUNTA из order_id | B4: COUNTA из executor_profile_id | D4: вручений | E4: бонус | F4: доплата за вручение | G4: водители на ступени | H4: SR | I4: Затраты | J4: sub/gmv | L4: AVG Fare. Май | M4: =HLOOKUP(M3,'выгрузка Sochi (кузова)'!$B$1:$J$3,2,0) -> 1803.7448
A5: 1 | B5: 2 | D5: 15 | E5: 2800 | F5: =E5/D5 -> 186.66667 | G5: 0 | H5: =G5/$B$18 -> 0 | I5: =E5*G5 -> 0 | L5: 10% от Ср. Чека | M5: =M4/10 -> 180.37448
A6: 3 | B6: 1 | D6: 20 | E6: 4200 | F6: =E6/D6 -> 210 | G6: 2 | H6: =G6/$B$18 -> 0.10526316 | I6: =E6*G6 -> 8400 | L6: GMV. 26.05 | M6: =HLOOKUP(M3,'выгрузка Sochi (кузова)'!$B$1:$J$3,3,0) -> 229176.4
A7: 4 | B7: 3 | D7: 25 | E7: 6000 | F7: =E7/D7 -> 240 | G7: 0 | H7: =G7/$B$18 -> 0 | I7: =E7*G7 -> 0
A8: 5 | B8: 1 | G8: Всего: | H8: =SUM(H5:H7) -> 0.10526316 | I8: =SUM(I5:I7) -> 8400 | J8: =I8/$M$6 -> 0.036652989
A9: 6 | B9: 2
A10: 7 | B10: 1 | D10: 2 вариант целей L
A11: 8 | B11: 2 | D11: вручений | E11: бонус | F11: доплата за вручение | G11: водители на ступени | H11: SR | I11: Затраты | J11: sub/gmv
A12: 11 | B12: 2 | D12: 12 | E12: 2200 | F12: =E12/D12 -> 183.33333 | G12: 2 | H12: =G12/$B$18 -> 0.10526316 | I12: =E12*G12 -> 4400
A13: 12 | B13: 1 | D13: 17 | E13: 3600 | F13: =E13/D13 -> 211.76471 | G13: 1 | H13: =G13/$B$18 -> 0.052631579 | I13: =E13*G13 -> 3600
A14: 14 | B14: 1 | D14: 22 | E14: 5200 | F14: =E14/D14 -> 236.36364 | G14: 2 | H14: =G14/$B$18 -> 0.10526316 | I14: =E14*G14 -> 10400
A15: 19 | B15: 1 | G15: Всего: | H15: =SUM(H12:H14) -> 0.26315789 | I15: =SUM(I12:I14) -> 18400 | J15: =I15/$M$6 -> 0.080287499
A16: 23 | B16: 1
A17: 24 | B17: 1
A18: Итого | B18: 19
A41: DXGY L0 | P41: https://datalens.yandex-team.ru/am8u3uq2e7ow2-cancels-corporate-clients-c2c?tab=p8&state=be7867ca2671
A42: Доходимость L0 за 02.06 | D42: 1 вариант целей L0
A43: COUNTA из order_id | B43: COUNTA из executor_profile_id | D43: вручений | E43: бонус | F43: доплата за вручение | G43: водители на ступени | H43: SR | I43: Затраты | J43: sub/gmv | L43: Метрика | M43: lcv_l_0
A44: 1 | B44: 2 | D44: 10 | E44: 1500 | F44: =E44/D44 -> 150 | G44: 2 | H44: =G44/$B$53 -> 0.16666667 | I44: =E44*G44 -> 3000 | L44: AVG Fare. Май | M44: =HLOOKUP(M43,'выгрузка Sochi (Op)'!$B$1:$J$3,2,0) -> 1533.1907
A45: 3 | B45: 1 | D45: 15 | E45: 2500 | F45: =E45/D45 -> 166.66667 | G45: 0 | H45: =G45/$B$53 -> 0 | I45: =E45*G45 -> 0 | L45: 10% от Ср. Чека | M45: =M44/10 -> 153.31907
A46: 4 | B46: 3 | D46: 20 | E46: 3500 | F46: =E46/D46 -> 175 | G46: 1 | H46: =G46/$B$53 -> 0.083333333 | I46: =E46*G46 -> 3500 | L46: GMV. 26.05 | M46: =HLOOKUP(M43,'выгрузка Sochi (Op)'!$B$1:$J$3,3,0) -> 161360
A47: 5 | B47: 1 | G47: Всего: | H47: =SUM(H44:H46) -> 0.25 | I47: =SUM(I44:I46) -> 6500 | J47: =I47/$M$46 -> 0.040282598
A48: 6 | B48: 1
A49: 8 | B49: 1 | D49: 2 вариант целей L0
A50: 11 | B50: 1 | D50: вручений | E50: бонус | F50: доплата за вручение | G50: водители на ступени | H50: SR | I50: Затраты | J50: sub/gmv
A51: 12 | B51: 1 | D51: 15 | E51: 2200 | F51: =E51/D51 -> 146.66667 | G51: 0 | H51: =G51/$B$53 -> 0 | I51: =E51*G51 -> 0
A52: 23 | B52: 1 | D52: 20 | E52: 3200 | F52: =E52/D52 -> 160 | G52: 1 | H52: =G52/$B$53 -> 0.083333333 | I52: =E52*G52 -> 3200
A53: Итого | B53: 12 | D53: 25 | E53: 4500 | F53: =E53/D53 -> 180 | G53: 0 | H53: =G53/$B$53 -> 0 | I53: =E53*G53 -> 0
G54: Всего: | H54: =SUM(H51:H53) -> 0.083333333 | I54: =SUM(I51:I53) -> 3200 | J54: =I54/$M$46 -> 0.019831433
A59: DXGY L1
A61: Доходимость L1 за 02.06 | D61: 1 вариант целей L1
A62: COUNTA из order_id | B62: COUNTA из executor_profile_id | D62: вручений | E62: бонус | F62: доплата за вручение | G62: водители на ступени | H62: SR | I62: Затраты | J62: sub/gmv | L62: Метрика | M62: lcv_l_1
A63: 6 | B63: 1 | D63: 8 | E63: 1500 | F63: =E63/D63 -> 187.5 | G63: 1 | I63: =E63*G63 -> 1500 | L63: AVG Fare. Май | M63: =HLOOKUP(M62,'выгрузка Sochi (Op)'!$B$1:$J$3,2,0) -> 1904.5556
A64: 8 | B64: 1 | D64: 13 | E64: 2500 | F64: =E64/D64 -> 192.30769 | G64: 0 | I64: =E64*G64 -> 0 | L64: 10% от Ср. Чека | M64: =M63/10 -> 190.45556
A65: 24 | B65: 1 | D65: 17 | E65: 4000 | F65: =E65/D65 -> 235.29412 | G65: 1 | I65: =E65*G65 -> 4000 | L65: GMV. 26.05 | M65: =HLOOKUP(M62,'выгрузка Sochi (Op)'!$B$1:$J$3,3,0) -> 34210.4
A66: Итого | B66: 3 | G66: Всего: | H66: =SUM(H63:H65) -> 0 | I66: =SUM(I63:I65) -> 5500 | J66: =I66/$M$65 -> 0.16076982
D68: 2 вариант целей L1
D69: вручений | E69: бонус | F69: доплата за вручение | G69: водители на ступени | H69: SR | I69: Затраты | J69: sub/gmv
D70: 10 | E70: 2000 | F70: =E70/D70 -> 200 | G70: 0 | I70: =E70*G70 -> 0
D71: 15 | E71: 3200 | F71: =E71/D71 -> 213.33333 | G71: 0 | I71: =E71*G71 -> 0
D72: 20 | E72: 4800 | F72: =E72/D72 -> 240 | G72: 1 | I72: =E72*G72 -> 4800
G73: Всего: | H73: =SUM(H70:H72) -> 0 | I73: =SUM(I70:I72) -> 4800 | J73: =I73/$M$65 -> 0.14030821
D75: 3 вариант целей L1
D76: вручений | E76: бонус | F76: доплата за вручение | G76: водители на ступени | H76: SR | I76: Затраты | J76: sub/gmv
D77: 15 | E77: 2700 | F77: =E77/D77 -> 180 | G77: 0 | I77: =E77*G77 -> 0
D78: 20 | E78: 4000 | F78: =E78/D78 -> 200 | G78: 1 | I78: =E78*G78 -> 4000
D79: 25 | E79: 5500 | F79: =E79/D79 -> 220 | G79: 0 | I79: =E79*G79 -> 0
G80: Всего: | H80: =SUM(H77:H79) -> 0 | I80: =SUM(I77:I79) -> 4000 | J80: =I80/$M$65 -> 0.11692351
A84: DXGY L2
A86: Доходимость L2 за 02.06 | D86: 1 вариант целей L2 | L86: Метрика | M86: lcv_l_2
A87: COUNTA из order_id | B87: COUNTA из executor_profile_id | D87: вручений | E87: бонус | F87: доплата за вручение | G87: водители на ступени | H87: SR | I87: Затраты | J87: sub/gmv | L87: AVG Fare. Май | M87: =HLOOKUP(M86,'выгрузка Sochi (Op)'!$B$1:$J$3,2,0) -> 3080.9695
A88: 7 | B88: 1 | D88: 10 | E88: 2500 | F88: =E88/D88 -> 250 | G88: 2 | H88: =G88/$B$92 -> 0.5 | I88: =E88*G88 -> 5000 | L88: 10% от Ср. Чека | M88: =M87/10 -> 308.09695
A89: 11 | B89: 1 | D89: 15 | E89: 4000 | F89: =E89/D89 -> 266.66667 | G89: 1 | H89: =G89/$B$92 -> 0.25 | I89: =E89*G89 -> 4000 | L89: GMV. 26.05 | M89: =HLOOKUP(M86,'выгрузка Sochi (Op)'!$B$1:$J$3,3,0) -> 33606
A90: 14 | B90: 1 | D90: 20 | E90: 6000 | F90: =E90/D90 -> 300 | G90: 0 | H90: =G90/$B$92 -> 0 | I90: =E90*G90 -> 0
A91: 19 | B91: 1 | G91: Всего: | H91: =SUM(H88:H90) -> 0.75 | I91: =SUM(I88:I90) -> 9000 | J91: =I91/$M$89 -> 0.26780932
A92: Итого | B92: 4

Sheet Красноярск
A1: Доходимость S1 за 26.05 | D1: 1 вариант целей S1 | O1: lcv_l_0 | P1: lcv_l_1 | Q1: lcv_l_2 | R1: lcv_m_0 | S1: lcv_m_1 | T1: lcv_m_2 | U1: van_0 | V1: van_1 | W1: van_2
A2: COUNTA из order_id | B2: COUNTA из executor_profile_id | D2: вручений | E2: бонус | F2: доплата за вручение | G2: водители на ступени | H2: SR | I2: Затраты | J2: sub/gmv | L2: Метрика | M2: van_1
A3: 1 | B3: 1 | D3: 30 | E3: 3000 | F3: =E3/D3 -> 100 | G3: 1 | H3: =G3/$B$20 -> 0.04 | I3: =E3*G3 -> 3000 | L3: AVG Fare. Май | M3: =HLOOKUP(M2,'выгрузка Красноярск'!$B$1:$J$3,2,0) -> 1180.7424
A4: 2 | B4: 2 | D4: 35 | E4: 4000 | F4: =E4/D4 -> 114.28571 | G4: 0 | H4: =G4/$B$20 -> 0 | I4: =E4*G4 -> 0 | L4: 10% от Ср. Чека | M4: =M3/10 -> 118.07424
A5: 3 | B5: 1 | D5: 40 | E5: 5000 | F5: =E5/D5 -> 125 | G5: 0 | H5: =G5/$B$20 -> 0 | I5: =E5*G5 -> 0 | L5: GMV. 26.05 | M5: =HLOOKUP(M2,'выгрузка Красноярск'!$B$1:$J$3,3,0) -> 158956.4
A6: 4 | B6: 1 | G6: Всего: | H6: =SUM(H3:H5) -> 0.04 | I6: =SUM(I3:I5) -> 3000 | J6: =I6/$M$5 -> 0.0188731
A7: 6 | B7: 1 | L7: Conf Del и Fail rate S1 (c2c)
A8: 7 | B8: 3 | D8: 2 вариант целей S1
A9: 8 | B9: 1 | D9: вручений | E9: бонус | F9: доплата за вручение | G9: водители на ступени | H9: SR | I9: Затраты | J9: sub/gmv
A10: 10 | B10: 3 | D10: 25 | E10: 2500 | F10: =E10/D10 -> 100 | G10: 5 | H10: =G10/$B$20 -> 0.2 | I10: =E10*G10 -> 12500
A11: 11 | B11: 1 | D11: 30 | E11: 3500 | F11: =E11/D11 -> 116.66667 | G11: 1 | H11: =G11/$B$20 -> 0.04 | I11: =E11*G11 -> 3500
A12: 14 | B12: 2 | D12: 35 | E12: 4500 | F12: =E12/D12 -> 128.57143 | G12: 0 | H12: =G12/$B$20 -> 0 | I12: =E12*G12 -> 0
A13: 16 | B13: 2 | G13: Всего: | H13: =SUM(H10:H12) -> 0.24 | I13: =SUM(I10:I12) -> 16000 | J13: =I13/$M$5 -> 0.10065653
A14: 17 | B14: 1
A15: 22 | B15: 1
A16: 24 | B16: 1
A17: 27 | B17: 2
A18: 29 | B18: 1
A19: 32 | B19: 1
A20: Итого | B20: 25
A24: В M0 и M1 всё хорошо
Q26: lcv_l_0 | R26: lcv_l_1 | S26: lcv_l_2 | T26: lcv_m_0 | U26: lcv_m_1 | V26: lcv_m_2 | W26: van_0 | X26: van_1 | Y26: van_2
A27: Доходимость L0 за 26.05 | D27: 1 вариант целей L0
A28: COUNTA из order_id | B28: COUNTA из executor_profile_id | D28: вручений | E28: бонус | F28: доплата за вручение | G28: водители на ступени | H28: SR | I28: Затраты | J28: sub/gmv | L28: Метрика | M28: lcv_l_0
A29: 1 | B29: 6 | D29: 15 | E29: 2100 | F29: =E29/D29 -> 140 | G29: 2 | H29: =G29/$B$40 -> 0.074074074 | I29: =E29*G29 -> 4200 | L29: AVG Fare. Май | M29: =HLOOKUP(M28,'выгрузка Красноярск'!$B$1:$J$3,2,0) -> 1544.0027
A30: 2 | B30: 2 | D30: 20 | E30: 3200 | F30: =E30/D30 -> 160 | G30: 0 | H30: =G30/$B$40 -> 0 | I30: =E30*G30 -> 0 | L30: 10% от Ср. Чека | M30: =M29/10 -> 154.40027
A31: 3 | B31: 1 | D31: 25 | E31: 4500 | F31: =E31/D31 -> 180 | G31: 0 | H31: =G31/$B$40 -> 0 | I31: =E31*G31 -> 0 | L31: GMV. 26.05 | M31: =HLOOKUP(M28,'выгрузка Красноярск'!$B$1:$J$3,3,0) -> 243405.6
A32: 4 | B32: 3 | G32: Всего: | H32: =SUM(H29:H31) -> 0.074074074 | I32: =SUM(I29:I31) -> 4200 | J32: =I32/$M$31 -> 0.017255149
A33: 5 | B33: 3
A34: 7 | B34: 1
A35: 8 | B35: 1 | D35: 2 вариант целей L0
A36: 9 | B36: 4 | D36: вручений | E36: бонус | F36: доплата за вручение | G36: водители на ступени | H36: SR | I36: Затраты | J36: sub/gmv
A37: 10 | B37: 2 | D37: 10 | E37: 2000 | F37: =E37/D37 -> 200 | G37: 4 | H37: =G37/$B$40 -> 0.14814815 | I37: =E37*G37 -> 8000
A38: 11 | B38: 2 | D38: 15 | E38: 3000 | F38: =E38/D38 -> 200 | G38: 2 | H38: =G38/$B$40 -> 0.074074074 | I38: =E38*G38 -> 6000
A39: 18 | B39: 2 | D39: 20 | E39: 4000 | F39: =E39/D39 -> 200 | G39: 0 | H39: =G39/$B$40 -> 0 | I39: =E39*G39 -> 0
A40: Итого | B40: 27 | G40: Всего: | H40: =SUM(H37:H39) -> 0.22222222 | I40: =SUM(I37:I39) -> 14000 | J40: =I40/$M$31 -> 0.057517165 | L40: Conf Del и Fail rate L0 (c2c)
A60: Доходимость L1 за 26.05 | D60: 1 вариант целей L1
A61: COUNTA из order_id | B61: COUNTA из executor_profile_id | D61: вручений | E61: бонус | F61: доплата за вручение | G61: водители на ступени | H61: SR | I61: Затраты | J61: sub/gmv | L61: Метрика | M61: lcv_l_1
A62: 1 | B62: 1 | D62: 10 | E62: 2000 | F62: =E62/D62 -> 200 | G62: 0 | H62: =G62/$B$67 -> 0 | I62: =E62*G62 -> 0 | L62: AVG Fare. Май | M62: =HLOOKUP(M61,'выгрузка Красноярск'!$B$1:$J$3,2,0) -> 2147.5293 | P62: lcv_l_0 | Q62: lcv_l_1 | R62: lcv_l_2 | S62: lcv_m_0 | T62: lcv_m_1 | U62: lcv_m_2 | V62: van_0 | W62: van_1 | X62: van_2
A63: 2 | B63: 1 | D63: 15 | E63: 3400 | F63: =E63/D63 -> 226.66667 | G63: 1 | H63: =G63/$B$67 -> 0.14285714 | I63: =E63*G63 -> 3400 | L63: 10% от Ср. Чека | M63: =M62/10 -> 214.75293
A64: 5 | B64: 3 | D64: 20 | E64: 5000 | F64: =E64/D64 -> 250 | G64: 0 | H64: =G64/$B$67 -> 0 | I64: =E64*G64 -> 0 | L64: GMV. 26.05 | M64: =HLOOKUP(M61,'выгрузка Красноярск'!$B$1:$J$3,3,0) -> 33554
A65: 8 | B65: 1 | G65: Всего: | H65: =SUM(H62:H64) -> 0.14285714 | I65: =SUM(I62:I64) -> 3400 | J65: =I65/$M$64 -> 0.1013292
A66: 18 | B66: 1 | L66: Conf Del и Fail rate L1 (c2c)
A67: Итого | B67: 7 | D67: 2 вариант целей L1
D68: вручений | E68: бонус | F68: доплата за вручение | G68: водители на ступени | H68: SR | I68: Затраты | J68: sub/gmv
D69: 8 | E69: 1500 | F69: =E69/D69 -> 187.5 | G69: 1 | H69: =G69/$B$67 -> 0.14285714 | I69: =E69*G69 -> 1500
D70: 13 | E70: 2800 | F70: =E70/D70 -> 215.38462 | G70: 0 | H70: =G70/$B$67 -> 0 | I70: =E70*G70 -> 0
D71: 17 | E71: 4000 | F71: =E71/D71 -> 235.29412 | G71: 1 | H71: =G71/$B$67 -> 0.14285714 | I71: =E71*G71 -> 4000
G72: Всего: | H72: =SUM(H69:H71) -> 0.28571429 | I72: =SUM(I69:I71) -> 5500 | J72: =I72/$M$64 -> 0.16391488
P85: lcv_l_0 | Q85: lcv_l_1 | R85: lcv_l_2 | S85: lcv_m_0 | T85: lcv_m_1 | U85: lcv_m_2 | V85: van_0 | W85: van_1 | X85: van_2
A86: Доходимость M2 за 26.05 | D86: 1 вариант целей M2
A87: COUNTA из order_id | B87: COUNTA из executor_profile_id | D87: вручений | E87: бонус | F87: доплата за вручение | G87: водители на ступени | H87: SR | I87: Затраты | J87: sub/gmv | L87: Метрика | M87: lcv_m_2
A88: 1 | B88: 1 | D88: 10 | E88: 2000 | F88: =E88/D88 -> 200 | G88: 4 | H88: =G88/$B$121 -> 0.66666667 | I88: =E88*G88 -> 8000 | L88: AVG Fare. Май | M88: =HLOOKUP(M87,'выгрузка Красноярск'!$B$1:$J$3,2,0) -> 2859.9235
A89: 2 | B89: 1 | D89: 15 | E89: 3500 | F89: =E89/D89 -> 233.33333 | G89: 0 | H89: =G89/$B$121 -> 0 | I89: =E89*G89 -> 0 | L89: 10% от Ср. Чека | M89: =M88/10 -> 285.99235
A90: 3 | B90: 1 | D90: 20 | E90: 5500 | F90: =E90/D90 -> 275 | G90: 1 | H90: =G90/$B$121 -> 0.16666667 | I90: =E90*G90 -> 5500 | L90: GMV. 26.05 | M90: =HLOOKUP(M87,'выгрузка Красноярск'!$B$1:$J$3,3,0) -> 153256.6
A91: 10 | B91: 2 | G91: Всего: | H91: =SUM(H88:H90) -> 0.83333333 | I91: =SUM(I88:I90) -> 13500 | J91: =I91/$M$90 -> 0.08808756
A92: 11 | B92: 2
A93: 26 | B93: 1 | D93: 2 вариант целей M2
A94: Итого | B94: 8 | D94: вручений | E94: бонус | F94: доплата за вручение | G94: водители на ступени | H94: SR | I94: Затраты | J94: sub/gmv
D95: 15 | E95: 2500 | F95: =E95/D95 -> 166.66667 | G95: 0 | H95: =G95/$B$121 -> 0 | I95: =E95*G95 -> 0
D96: 20 | E96: 4000 | F96: =E96/D96 -> 200 | G96: 0 | H96: =G96/$B$121 -> 0 | I96: =E96*G96 -> 0 | L96: Conf Del и Fail rate M2 (c2c)
D97: 25 | E97: 6000 | F97: =E97/D97 -> 240 | G97: 1 | H97: =G97/$B$121 -> 0.16666667 | I97: =E97*G97 -> 6000
G98: Всего: | H98: =SUM(H95:H97) -> 0.16666667 | I98: =SUM(I95:I97) -> 6000 | J98: =I98/$M$90 -> 0.039150027
D100: 3 вариант целей M2
D101: вручений | E101: бонус | F101: доплата за вручение | G101: водители на ступени | H101: SR | I101: Затраты | J101: sub/gmv
D102: 20 | E102: 3500 | F102: =E102/D102 -> 175 | G102: 0 | H102: =G102/$B$121 -> 0 | I102: =E102*G102 -> 0
D103: 25 | E103: 5000 | F103: =E103/D103 -> 200 | G103: 1 | H103: =G103/$B$121 -> 0.16666667 | I103: =E103*G103 -> 5000
D104: 30 | E104: 7000 | F104: =E104/D104 -> 233.33333 | G104: 0 | H104: =G104/$B$121 -> 0 | I104: =E104*G104 -> 0
G105: Всего: | H105: =SUM(H102:H104) -> 0.16666667 | I105: =SUM(I102:I104) -> 5000 | J105: =I105/$M$90 -> 0.032625022
A113: Доходимость L2 за 26.05 | D113: 1 вариант целей L2
A114: COUNTA из order_id | B114: COUNTA из executor_profile_id | D114: вручений | E114: бонус | F114: доплата за вручение | G114: водители на ступени | H114: SR | I114: Затраты | J114: sub/gmv | L114: Метрика | M114: lcv_l_2
A115: 4 | B115: 1 | D115: 10 | E115: 2500 | F115: =E115/D115 -> 250 | G115: 3 | H115: =G115/$B$121 -> 0.5 | I115: =E115*G115 -> 7500 | L115: AVG Fare. Май | M115: =HLOOKUP(M114,'выгрузка Красноярск'!$B$1:$J$3,2,0) -> 3752.3939
A116: 6 | B116: 1 | D116: 15 | E116: 4000 | F116: =E116/D116 -> 266.66667 | G116: 1 | H116: =G116/$B$121 -> 0.16666667 | I116: =E116*G116 -> 4000 | L116: 10% от Ср. Чека | M116: =M115/10 -> 375.23939
A117: 10 | B117: 1 | D117: 20 | E117: 6000 | F117: =E117/D117 -> 300 | G117: 0 | H117: =G117/$B$121 -> 0 | I117: =E117*G117 -> 0 | L117: GMV. 26.05 | M117: =HLOOKUP(M114,'выгрузка Красноярск'!$B$1:$J$3,3,0) -> 84953.2
A118: 11 | B118: 1 | G118: Всего: | H118: =SUM(H115:H117) -> 0.66666667 | I118: =SUM(I115:I117) -> 11500 | J118: =I118/$M$117 -> 0.13536865
A119: 12 | B119: 1
A120: 15 | B120: 1 | D120: 2 вариант целей L2 | L120: Conf Del и Fail rate L2 (c2c)
A121: Итого | B121: 6 | D121: вручений | E121: бонус | F121: доплата за вручение | G121: водители на ступени | H121: SR | I121: Затраты | J121: sub/gmv
D122: 15 | E122: 3500 | F122: =E122/D122 -> 233.33333 | G122: 1 | H122: =G122/$B$121 -> 0.16666667 | I122: =E122*G122 -> 3500
D123: 20 | E123: 5000 | F123: =E123/D123 -> 250 | G123: 0 | H123: =G123/$B$121 -> 0 | I123: =E123*G123 -> 0
D124: 25 | E124: 7000 | F124: =E124/D124 -> 280 | G124: 0 | H124: =G124/$B$121 -> 0 | I124: =E124*G124 -> 0
G125: Всего: | H125: =SUM(H122:H124) -> 0.16666667 | I125: =SUM(I122:I124) -> 3500 | J125: =I125/$M$117 -> 0.041199154
F140: Цели L Красноярск
F141: вручений | G141: бонус | H141: доплата за вручение | I141: водители на ступени | J141: SR | K141: Затраты | L141: sub/gmv | M141: Метрика | N141: lcv_l_0
F142: 10 | G142: 2000 | H142: 200 | I142: 4 | J142: 0.14814815 | K142: 8000 | M142: AVG Fare. Май | N142: 1544.0027
F143: 15 | G143: 3000 | H143: 200 | I143: 2 | J143: 0.074074074 | K143: 6000 | M143: 10% от Ср. Чека | N143: 154.40027
F144: 20 | G144: 4000 | H144: 200 | I144: 0 | J144: 0 | K144: 0 | M144: GMV. 26.05 | N144: 243405.6
I145: Всего: | J145: 0.22222222 | K145: 14000 | L145: 0.057517165

Sheet Красноярск1606
A1: COUNTA из order_id | B1: COUNTA из executor_profile_id | D1: 1 вариант целей M
A2: 1 | B2: 1 | D2: вручений | E2: бонус | F2: доплата за вручение | G2: водители на ступени | H2: SR | I2: Затраты | J2: sub/gmv | L2: Метрика | M2: lcv_m
A3: 2 | B3: 9 | D3: 15 | E3: 1700 | F3: =E3/D3 -> 113.33333 | G3: 2 | H3: =G3/53 -> 0.037735849 | I3: =E3*G3 -> 3400 | L3: AVG Fare. Май | M3: 1359
A4: 3 | B4: 5 | D4: 20 | E4: 2700 | F4: =E4/D4 -> 135 | G4: 2 | H4: =G4/53 -> 0.037735849 | I4: =E4*G4 -> 5400 | L4: 10% от Ср. Чека | M4: 136
A5: 4 | B5: 6 | D5: 25 | E5: 3500 | F5: =E5/D5 -> 140 | G5: 5 | H5: =G5/53 -> 0.094339623 | I5: =E5*G5 -> 17500 | L5: GMV. 16/06 | M5: 852066
A6: 5 | B6: 4 | G6: Всего: | H6: =SUM(H3:H5) -> 0.16981132 | I6: =SUM(I3:I5) -> 26300 | J6: =I6/$M$5 -> 0.030866154
A7: 6 | B7: 2
A8: 8 | B8: 4
A9: 9 | B9: 2 | D9: 2 вариант целей M
A10: 10 | B10: 4 | D10: вручений | E10: бонус | F10: доплата за вручение | G10: водители на ступени | H10: SR | I10: Затраты | J10: sub/gmv
A11: 11 | B11: 2 | D11: 12 | E11: 2000 | F11: =E11/D11 -> 166.66667 | G11: 7 | H11: =G11/53 -> 0.13207547 | I11: =E11*G11 -> 14000
A12: 12 | B12: 2 | D12: 17 | E12: 3000 | F12: =E12/D12 -> 176.47059 | G12: 1 | H12: =G12/53 -> 0.018867925 | I12: =E12*G12 -> 3000
A13: 13 | B13: 3 | D13: 23 | E13: 4500 | F13: =E13/D13 -> 195.65217 | G13: 6 | H13: =G13/53 -> 0.11320755 | I13: =E13*G13 -> 27000
A14: 14 | B14: 1 | G14: Всего: | H14: =SUM(H11:H13) -> 0.26415094 | I14: =SUM(I11:I13) -> 44000 | J14: =I14/$M$5 -> 0.051639192
A15: 16 | B15: 1
A16: 17 | B16: 1
A17: 23 | B17: 1
A18: 24 | B18: 1
A19: 33 | B19: 3
A20: 45 | B20: 1
A21: Итого | B21: 53

Sheet Цели Омск (F)
A2: Доходимость M | D2: 1 вариант целей m
A3: Кол-во вручений | B3: Водителей | D3: вручений | E3: бонус | F3: доплата за вручение | G3: водители на ступени | H3: SR | I3: Затраты | J3: sub/gmv
A4: 1 | B4: 17 | D4: 16 | E4: 3100 | F4: =E4/D4 -> 193.75 | G4: 8 | H4: =G4/123 -> 0.06504065 | I4: =E4*G4 -> 24800
A5: 2 | B5: 25 | D5: 21 | E5: 4500 | F5: =E5/D5 -> 214.28571 | G5: 4 | H5: =G5/123 -> 0.032520325 | I5: =E5*G5 -> 18000
A6: 3 | B6: 6 | D6: 26 | E6: 5800 | F6: =E6/D6 -> 223.07692 | G6: 1 | H6: =G6/123 -> 0.0081300813 | I6: =E6*G6 -> 5800
A7: 4 | B7: 9 | G7: Всего: | H7: =SUM(H4:H6) -> 0.10569106 | I7: =SUM(I4:I6) -> 48600 | J7: =I7/$M$21 -> 0.041236628
A8: 5 | B8: 12
A9: 6 | B9: 9 | D9: 2 вариант целей m
A10: 7 | B10: 7 | D10: вручений | E10: бонус | F10: доплата за вручение | G10: водители на ступени | H10: SR | I10: Затраты | J10: sub/gmv
A11: 8 | B11: 1 | D11: 12 | E11: 3000 | F11: =E11/D11 -> 250 | G11: 13 | H11: =G11/123 -> 0.10569106 | I11: =E11*G11 -> 39000
A12: 9 | B12: 1 | D12: 17 | E12: 4000 | F12: =E12/D12 -> 235.29412 | G12: 6 | H12: =G12/123 -> 0.048780488 | I12: =E12*G12 -> 24000
A13: 10 | B13: 6 | D13: 22 | E13: 5500 | F13: =E13/D13 -> 250 | G13: 5 | H13: =G13/123 -> 0.040650407 | I13: =E13*G13 -> 27500
A14: 11 | B14: 6 | G14: Всего: | H14: =SUM(H11:H13) -> 0.19512195 | I14: =SUM(I11:I13) -> 90500 | J14: =I14/$M$21 -> 0.076788371
A15: 12 | B15: 5
A16: 13 | B16: 4
A17: 14 | B17: 2 | D17: 3 вариант целей m (экономный)
A18: 16 | B18: 2 | D18: вручений | E18: бонус | F18: доплата за вручение | G18: водители на ступени | H18: SR | I18: Затраты | J18: sub/gmv | L18: Метрика | M18: lcv_m
A19: 17 | B19: 1 | D19: 15 | E19: 2500 | F19: =E19/D19 -> 166.66667 | G19: 8 | H19: =G19/123 -> 0.06504065 | I19: =E19*G19 -> 20000 | L19: AVG Fare. Май | M19: 1830
A20: 18 | B20: 1 | D20: 20 | E20: 3700 | F20: =E20/D20 -> 185 | G20: 3 | H20: =G20/123 -> 0.024390244 | I20: =E20*G20 -> 11100 | L20: 10% от Ср. Чека | M20: =M19/10 -> 183
A21: 19 | B21: 4 | D21: 25 | E21: 5000 | F21: =E21/D21 -> 200 | G21: 2 | H21: =G21/123 -> 0.016260163 | I21: =E21*G21 -> 10000 | L21: GMV. 02.06 | M21: 1178563.9
A22: 22 | B22: 1 | G22: Всего: | H22: =SUM(H19:H21) -> 0.10569106 | I22: =SUM(I19:I21) -> 41100 | J22: =I22/$M$21 -> 0.034872951
A23: 23 | B23: 1
A24: 24 | B24: 1 | D24: 4 вариант целей m (дороже)
A25: 25 | B25: 1 | D25: вручений | E25: бонус | F25: доплата за вручение | G25: водители на ступени | H25: SR | I25: Затраты | J25: sub/gmv
A26: 32 | B26: 1 | D26: 15 | E26: 2800 | F26: =E26/D26 -> 186.66667 | G26: 8 | H26: =G26/123 -> 0.06504065 | I26: =E26*G26 -> 22400
A27: Итого | B27: 123 | D27: 20 | E27: 4200 | F27: =E27/D27 -> 210 | G27: 3 | H27: =G27/123 -> 0.024390244 | I27: =E27*G27 -> 12600
D28: 25 | E28: 5800 | F28: =E28/D28 -> 232 | G28: 2 | H28: =G28/123 -> 0.016260163 | I28: =E28*G28 -> 11600
G29: Всего: | H29: =SUM(H26:H28) -> 0.10569106 | I29: =SUM(I26:I28) -> 46600 | J29: =I29/$M$21 -> 0.039539647
D31: 5 вариант целей m (богатый)
D32: вручений | E32: бонус | F32: доплата за вручение | G32: водители на ступени | H32: SR | I32: Затраты | J32: sub/gmv
D33: 15 | E33: 3000 | F33: =E33/D33 -> 200 | G33: 8 | H33: =G33/123 -> 0.06504065 | I33: =E33*G33 -> 24000
D34: 20 | E34: 4500 | F34: =E34/D34 -> 225 | G34: 3 | H34: =G34/123 -> 0.024390244 | I34: =E34*G34 -> 13500
D35: 25 | E35: 6000 | F35: =E35/D35 -> 240 | G35: 2 | H35: =G35/123 -> 0.016260163 | I35: =E35*G35 -> 12000
G36: Всего: | H36: =SUM(H33:H35) -> 0.10569106 | I36: =SUM(I33:I35) -> 49500 | J36: =I36/$M$21 -> 0.042000269

Sheet НН XL2
A1: 45810 | F1: Avg Fare за май | G1: 3536.43 | H1: GMV | I1: 53275 | M1: Dynamics - CDR & Utilization per Option Region - Yandex DataLens
A2: Кол-во вручений | B2: Водителей
A3: 2 | B3: 1 | F3: вручений | G3: бонус | H3: доплата за вручение | I3: водители на ступени | J3: SR | K3: Затраты
A4: 2 | B4: 1 | F4: 2 | G4: 1500 | H4: =G4/F4 -> 750 | I4: 1 | J4: =I4/3 -> 0.33333333 | K4: =G4*I4 -> 1500
F5: 3 | G5: 3000 | H5: =G5/F5 -> 1000 | I5: 1 | J5: =I5/3 -> 0.33333333 | K5: =G5*I5 -> 3000
B6: 2
I7: Всего: | J7: =SUM(J4:J6) -> 0.66666667 | K7: =SUM(K4:K6) -> 4500
K8: =K7/I1 -> 0.084467386
A9: 45817
A10: Кол-во вручений | B10: Водителей | F10: вручений | G10: бонус | H10: доплата за вручение | I10: водители на ступени | J10: SR | K10: Затраты
A11: 2 | B11: 1 | F11: 2 | G11: 1200 | H11: =G11/F11 -> 600 | I11: 1 | J11: =I11/3 -> 0.33333333 | K11: =G11*I11 -> 1200
A12: 4 | B12: 1 | F12: 3 | G12: 2600 | H12: =G12/F12 -> 866.66667 | I12: 1 | J12: =I12/3 -> 0.33333333 | K12: =G12*I12 -> 2600
B14: 2 | I14: Всего: | J14: =SUM(J11:J13) -> 0.66666667 | K14: =SUM(K11:K13) -> 3800
A15: 45818 | K15: =K14/I8 -> #DIV/0!
A16: Кол-во вручений | B16: Водителей
A17: 1 | B17: 1
A18: 4 | B18: 1
B20: 2

Sheet Цели НиНо
A1: Доходимость L1 за 26.05 | D1: 1 вариант целей L1 | R1: lcv_l_0 | S1: lcv_l_1 | T1: lcv_l_2 | U1: lcv_m_0 | V1: lcv_m_1 | W1: lcv_m_2 | X1: lcv_xl_0 | Y1: lcv_xl_1 | Z1: lcv_xl_2 | AA1: truck_5t_0 | AB1: van_0 | AC1: van_1 | AD1: van_2
A2: COUNTA из order_id | B2: COUNTA из executor_profile_id | D2: вручений | E2: бонус | F2: доплата за вручение | G2: водители на ступени | H2: SR | I2: Затраты | J2: sub/gmv | M2: Метрика | N2: lcv_l_1
A3: 2 | B3: 1 | D3: 15 | E3: 2700 | F3: =E3/D3 -> 180 | G3: 2 | H3: =G3/$B$16 -> 0.125 | I3: =E3*G3 -> 5400 | M3: AVG Fare. Май | N3: =HLOOKUP(N2,'выгрузка НиНо'!$B$1:$N$3,2,0) -> 2144.8471
A4: 5 | B4: 1 | D4: 20 | E4: 4000 | F4: =E4/D4 -> 200 | G4: 1 | H4: =G4/$B$16 -> 0.0625 | I4: =E4*G4 -> 4000 | M4: 10% от Ср. Чека | N4: =N3/10 -> 214.48471
A5: 6 | B5: 1 | D5: 25 | E5: 6000 | F5: =E5/D5 -> 240 | G5: 1 | H5: =G5/$B$16 -> 0.0625 | I5: =E5*G5 -> 6000 | M5: GMV. 26.05 | N5: =HLOOKUP(N2,'выгрузка НиНо'!$B$1:$N$3,3,0) -> 218774.4
A6: 7 | B6: 1 | G6: Всего: | H6: =SUM(H3:H5) -> 0.25 | I6: =SUM(I3:I5) -> 15400 | J6: =I6/$N$5 -> 0.070392148
A7: 8 | B7: 2 | M7: Conf Del и Fail rate L1 (c2c)
A8: 9 | B8: 2 | D8: 2 вариант целей L1
A9: 10 | B9: 1 | D9: вручений | E9: бонус | F9: доплата за вручение | G9: водители на ступени | H9: SR | I9: Затраты | J9: sub/gmv
A10: 11 | B10: 1 | D10: 18 | E10: 3500 | F10: =E10/D10 -> 194.44444 | G10: 2 | H10: =G10/$B$16 -> 0.125 | I10: =E10*G10 -> 7000
A11: 14 | B11: 2 | D11: 23 | E11: 5000 | F11: =E11/D11 -> 217.3913 | G11: 0 | H11: =G11/$B$16 -> 0 | I11: =E11*G11 -> 0
A12: 15 | B12: 1 | D12: 28 | E12: 6500 | F12: =E12/D12 -> 232.14286 | G12: 1 | H12: =G12/$B$16 -> 0.0625 | I12: =E12*G12 -> 6500
A13: 18 | B13: 1 | G13: Всего: | H13: =SUM(H10:H12) -> 0.1875 | I13: =SUM(I10:I12) -> 13500 | J13: =I13/$N$5 -> 0.061707403
A14: 21 | B14: 1
A15: 34 | B15: 1
A16: Итого | B16: 16
K18: 200000 | L18: 8285000
L19: =K18/L18 -> 0.024140012
A23: Доходимость M2 за 26.05 | D23: 1 вариант целей M2
A24: COUNTA из order_id | B24: COUNTA из executor_profile_id | D24: вручений | E24: бонус | F24: доплата за вручение | G24: водители на ступени | H24: SR | I24: Затраты | J24: sub/gmv | M24: Метрика | N24: lcv_m_2
A25: 1 | B25: 2 | D25: 15 | E25: 2500 | F25: =E25/D25 -> 166.66667 | G25: 2 | H25: =G25/$B$35 -> 0.14285714 | I25: =E25*G25 -> 5000 | M25: AVG Fare. Май | N25: =HLOOKUP(N24,'выгрузка НиНо'!$B$1:$N$3,2,0) -> 2763.2966
A26: 2 | B26: 2 | D26: 20 | E26: 4000 | F26: =E26/D26 -> 200 | G26: 1 | H26: =G26/$B$35 -> 0.071428571 | I26: =E26*G26 -> 4000 | M26: 10% от Ср. Чека | N26: =N25/10 -> 276.32966
A27: 3 | B27: 2 | D27: 25 | E27: 6500 | F27: =E27/D27 -> 260 | G27: 3 | H27: =G27/$B$35 -> 0.21428571 | I27: =E27*G27 -> 19500 | M27: GMV. 26.05 | N27: =HLOOKUP(N24,'выгрузка НиНо'!$B$1:$N$3,3,0) -> 491866.8
A28: 11 | B28: 2 | G28: Всего: | H28: =SUM(H25:H27) -> 0.42857143 | I28: =SUM(I25:I27) -> 28500 | J28: =I28/$N$27 -> 0.057942516
A29: 12 | B29: 1 | M29: Conf Del и Fail rate M2 (c2c)
A30: 14 | B30: 1 | D30: 2 вариант целей M2
A31: 16 | B31: 1 | D31: вручений | E31: бонус | F31: доплата за вручение | G31: водители на ступени | H31: SR | I31: Затраты | J31: sub/gmv
A32: 26 | B32: 1 | D32: 15 | E32: 2500 | F32: =E32/D32 -> 166.66667 | H32: =G32/$B$35 -> 0 | I32: =E32*G32 -> 0
A33: 31 | B33: 1 | D33: 20 | E33: 4000 | F33: =E33/D33 -> 200 | H33: =G33/$B$35 -> 0 | I33: =E33*G33 -> 0
A34: 44 | B34: 1 | D34: 25 | E34: 6000 | F34: =E34/D34 -> 240 | H34: =G34/$B$35 -> 0 | I34: =E34*G34 -> 0
A35: Итого | B35: 14 | G35: Всего: | H35: =SUM(H32:H34) -> 0 | I35: =SUM(I32:I34) -> 0 | J35: =I35/$N$27 -> 0
D37: 3 вариант целей M2
D38: вручений | E38: бонус | F38: доплата за вручение | G38: водители на ступени | H38: SR | I38: Затраты | J38: sub/gmv
D39: 20 | E39: 3500 | F39: =E39/D39 -> 175 | H39: =G39/$B$35 -> 0 | I39: =E39*G39 -> 0
D40: 25 | E40: 5000 | F40: =E40/D40 -> 200 | H40: =G40/$B$35 -> 0 | I40: =E40*G40 -> 0
D41: 30 | E41: 7000 | F41: =E41/D41 -> 233.33333 | H41: =G41/$B$35 -> 0 | I41: =E41*G41 -> 0
G42: Всего: | H42: =SUM(H39:H41) -> 0 | I42: =SUM(I39:I41) -> 0 | J42: =I42/$N$27 -> 0
A48: COUNTA из order_id | B48: COUNTA из executor_profile_id
A49: 2 | B49: 1 | D49: 1 вариант целей L1
A50: 5 | B50: 1 | D50: вручений | E50: бонус | F50: доплата за вручение | G50: водители на ступени | H50: SR | I50: Затраты | J50: sub/gmv | L50: Метрика | M50: lcv_l_1
A51: 6 | B51: 1 | D51: 10 | E51: 2000 | F51: =E51/D51 -> 200 | G51: 4 | H51: =G51/$B$62 -> 0.25 | I51: =E51*G51 -> 8000 | L51: AVG Fare. Май | M51: =HLOOKUP(M50,'выгрузка НиНо'!$B$1:$N$3,2,0) -> 2144.8471
A52: 7 | B52: 1 | D52: 15 | E52: 3400 | F52: =E52/D52 -> 226.66667 | G52: 2 | H52: =G52/$B$62 -> 0.125 | I52: =E52*G52 -> 6800 | L52: 10% от Ср. Чека | M52: =M51/10 -> 214.48471
A53: 8 | B53: 2 | D53: 20 | E53: 5000 | F53: =E53/D53 -> 250 | G53: 2 | H53: =G53/$B$62 -> 0.125 | I53: =E53*G53 -> 10000 | L53: GMV. 26.05 | M53: =HLOOKUP(M50,'выгрузка НиНо'!$B$1:$N$3,3,0) -> 218774.4
A54: 9 | B54: 2 | G54: Всего: | H54: =SUM(H51:H53) -> 0.5 | I54: =SUM(I51:I53) -> 24800 | J54: =I54/$M$53 -> 0.11335878
A55: 10 | B55: 1
A56: 11 | B56: 1 | D56: 1 вариант целей L1
A57: 14 | B57: 2 | D57: вручений | E57: бонус | F57: доплата за вручение | G57: водители на ступени | H57: SR | I57: Затраты | J57: sub/gmv
A58: 15 | B58: 1 | D58: 10 | E58: 2000 | F58: =E58/D58 -> 200 | G58: 4 | H58: =G58/$B$62 -> 0.25 | I58: =E58*G58 -> 8000
A59: 18 | B59: 1 | D59: 15 | E59: 3400 | F59: =E59/D59 -> 226.66667 | G59: 2 | H59: =G59/$B$62 -> 0.125 | I59: =E59*G59 -> 6800
A60: 21 | B60: 1 | D60: 20 | E60: 5000 | F60: =E60/D60 -> 250 | G60: 2 | H60: =G60/$B$62 -> 0.125 | I60: =E60*G60 -> 10000
A61: 34 | B61: 1 | G61: Всего: | H61: =SUM(H58:H60) -> 0.5 | I61: =SUM(I58:I60) -> 24800 | J61: =I61/$M$53 -> 0.11335878
A62: Итого | B62: 16
A70: COUNTA из order_id | B70: COUNTA из executor_profile_id | D70: 1 вариант целей L2 | M70: Метрика | N70: lcv_l_2
A71: 3 | B71: 1 | D71: вручений | E71: бонус | F71: доплата за вручение | G71: водители на ступени | H71: SR | I71: Затраты | J71: sub/gmv | M71: AVG Fare. Май | N71: =HLOOKUP(N70,'выгрузка НиНо'!$B$1:$N$3,2,0) -> 2358.5103
A72: 5 | B72: 1 | D72: 10 | E72: 2500 | F72: =E72/D72 -> 250 | H72: =G72/$B$83 -> 0 | I72: =E72*G72 -> 0 | M72: 10% от Ср. Чека | N72: =N71/10 -> 235.85103
A73: 13 | B73: 1 | D73: 15 | E73: 4000 | F73: =E73/D73 -> 266.66667 | H73: =G73/$B$83 -> 0 | I73: =E73*G73 -> 0 | M73: GMV. 26.05 | N73: =HLOOKUP(N70,'выгрузка НиНо'!$B$1:$N$3,3,0) -> 341984
A74: 14 | B74: 2 | D74: 20 | E74: 6000 | F74: =E74/D74 -> 300 | H74: =G74/$B$83 -> 0 | I74: =E74*G74 -> 0
A75: 17 | B75: 1 | G75: Всего: | H75: =SUM(H72:H74) -> 0 | I75: =SUM(I72:I74) -> 0 | J75: =I75/$N$73 -> 0
A76: 18 | B76: 1
A77: 21 | B77: 1 | D77: 2 вариант целей L2
A78: 24 | B78: 1 | D78: вручений | E78: бонус | F78: доплата за вручение | G78: водители на ступени | H78: SR | I78: Затраты | J78: sub/gmv
A79: 31 | B79: 1 | D79: 20 | E79: 3500 | F79: =E79/D79 -> 175 | G79: 2 | H79: =G79/$B$83 -> 0.15384615 | I79: =E79*G79 -> 7000
A80: 38 | B80: 1 | D80: 25 | E80: 5000 | F80: =E80/D80 -> 200 | G80: 0 | H80: =G80/$B$83 -> 0 | I80: =E80*G80 -> 0
A81: 48 | B81: 1 | D81: 30 | E81: 7000 | F81: =E81/D81 -> 233.33333 | G81: 4 | H81: =G81/$B$83 -> 0.30769231 | I81: =E81*G81 -> 28000
A82: 55 | B82: 1 | G82: Всего: | H82: =SUM(H79:H81) -> 0.46153846 | I82: =SUM(I79:I81) -> 35000 | J82: =I82/$N$73 -> 0.10234397
A83: Итого | B83: 13
A88: COUNTA из order_id | B88: COUNTA из executor_profile_id | D88: 1 вариант целей M0_M1 | M88: Метрика | N88: lcv_m_0 | P88: Метрика | Q88: lcv_m_1
A89: 1 | B89: 16 | D89: вручений | E89: бонус | F89: доплата за вручение | G89: водители на ступени | H89: SR | I89: Затраты | J89: sub/gmv | M89: AVG Fare. Май | N89: =HLOOKUP(N88,'выгрузка НиНо'!$B$1:$N$3,2,0) -> 1241.4503 | P89: AVG Fare. Май | Q89: =HLOOKUP(Q88,'выгрузка НиНо'!$B$1:$N$3,2,0) -> 2000.5749
A90: 2 | B90: 6 | D90: 25 | E90: 3000 | F90: =E90/D90 -> 120 | G90: 10 | H90: =G90/$B$122 -> 0.069444444 | I90: =E90*G90 -> 30000 | M90: 10% от Ср. Чека | N90: =N89/10 -> 124.14503 | P90: 10% от Ср. Чека | Q90: =Q89/10 -> 200.05749
A91: 3 | B91: 10 | D91: 30 | E91: 4000 | F91: =E91/D91 -> 133.33333 | G91: 5 | H91: =G91/$B$122 -> 0.034722222 | I91: =E91*G91 -> 20000 | M91: GMV. 26.05 | N91: =HLOOKUP(N88,'выгрузка НиНо'!$B$1:$N$3,3,0) -> 2300407.4 | P91: GMV. 26.05 | Q91: =HLOOKUP(Q88,'выгрузка НиНо'!$B$1:$N$3,3,0) -> 622178.8
A92: 4 | B92: 16 | D92: 35 | E92: 6000 | F92: =E92/D92 -> 171.42857 | G92: 4 | H92: =G92/$B$122 -> 0.027777778 | I92: =E92*G92 -> 24000
A93: 5 | B93: 9 | G93: Всего: | H93: =SUM(H90:H92) -> 0.13194444 | I93: =SUM(I90:I92) -> 74000 | J93: =I93/$N$94 -> 0.02532004
A94: 6 | B94: 10 | N94: =N91+Q91 -> 2922586.2
A95: 7 | B95: 3
A96: 8 | B96: 1
A97: 9 | B97: 6 | D97: 1 вариант целей M0_M1_M2
A98: 10 | B98: 4 | D98: вручений | E98: бонус | F98: доплата за вручение | G98: водители на ступени | H98: SR | I98: Затраты | J98: sub/gmv
A99: 11 | B99: 7 | D99: 20 | E99: 3000 | F99: =E99/D99 -> 150 | G99: 10 | H99: =G99/$B$122 -> 0.069444444 | I99: =E99*G99 -> 30000
A100: 12 | B100: 4 | D100: 25 | E100: 4000 | F100: =E100/D100 -> 160 | G100: 5 | H100: =G100/$B$122 -> 0.034722222 | I100: =E100*G100 -> 20000
A101: 13 | B101: 7 | D101: 30 | E101: 6000 | F101: =E101/D101 -> 200 | G101: 4 | H101: =G101/$B$122 -> 0.027777778 | I101: =E101*G101 -> 24000
A102: 14 | B102: 3 | G102: Всего: | H102: =SUM(H99:H101) -> 0.13194444 | I102: =SUM(I99:I101) -> 74000 | J102: =I102/$N$94 -> 0.02532004
A103: 15 | B103: 3
A104: 16 | B104: 1
A105: 17 | B105: 3
A106: 18 | B106: 3
A107: 19 | B107: 1
A108: 20 | B108: 4
A109: 21 | B109: 1
A110: 23 | B110: 4
A111: 24 | B111: 3
A112: 25 | B112: 4
A113: 27 | B113: 3
A114: 28 | B114: 1
... A121: 43 | B121: 1
A122: Итого | B122: 144

Sheet выгрузка НиНо
A1: dt | B1: lcv_l_0 | C1: lcv_l_1 | D1: lcv_l_2 | E1: lcv_m_0 | F1: lcv_m_1 | G1: lcv_m_2 | H1: lcv_xl_0 | I1: lcv_xl_1 | J1: lcv_xl_2 | K1: truck_5t_0 | L1: van_0 | M1: van_1 | N1: van_2
A2: AVG Fare. Май | B2: 1610.7345 | C2: 2144.8471 | D2: 2358.5103 | E2: 1241.4503 | F2: 2000.5749 | G2: 2763.2966 | H2: 1961.4072 | I2: 3277.2857 | J2: 2751.8333 | K2: 2201.73 | L2: 918.8445 | M2: 1309.8585 | N2: 2272.8533 | O2: https://datalens.yandex-team.ru/sne8u5ggtwoih-cdr-utilization-per-option-region?tab=Aj&state=e84872a11171
A3: GMV. 26.05 | B3: 1518922.6 | C3: 218774.4 | D3: 341984 | E3: 2300407.4 | F3: 622178.8 | G3: 491866.8 | H3: 382474.4 | I3: 68823 | J3: 16511 | K3: 132103.8 | L3: 1561116.8 | M3: 595985.6 | N3: 34092.8 | O3: https://datalens.yandex-team.ru/sne8u5ggtwoih-cdr-utilization-per-option-region?tab=Aj&state=666ccf9b1170

Sheet Цели Уфа
A1: Доходимость S | E1: 1 вариант целей S | M1: Доходимость M | P1: 1 вариант целей M | AA1: Доходимость L | AN1: Доходимость XL
A2: COUNTA из order_id | B2: COUNTA из executor_profile_id | E2: вручений | F2: бонус | G2: доплата за вручение | H2: водители на ступени | I2: SR | J2: Затраты | K2: sub/gmv | P2: вручений | Q2: бонус | R2: доплата за вручение | S2: водители на ступени | T2: SR | U2: Затраты | V2: sub/gmv | AA2: Кол-во вручений | AB2: Водителей | AD2: 1 вариант целей L | AN2: Кол-во вручений | AO2: Водителей | AQ2: 1 вариант целей XL
A3: 1 | B3: 2 | E3: 15 | F3: 2200 | G3: 147 | H3: 2 | M3: Кол-во вручений | N3: Водителей | P3: 10 | Q3: 1800 | R3: =Q3/P3 -> 180 | S3: 15 | T3: =S3/85 -> 0.17647059 | U3: =S3*Q3 -> 27000 | X3: Метрика | Y3: lcv_M | AA3: 1 | AB3: 3 | AD3: вручений | AE3: бонус | AF3: доплата за вручение | AG3: водители на ступени | AH3: SR | AI3: Затраты | AJ3: sub/gmv | AK3: Метрика | AL3: lcv_l | AN3: 1 | AO3: 1 | AQ3: вручений | AR3: бонус | AS3: доплата за вручение | AT3: водители на ступени | AU3: SR | AV3: Затраты | AW3: sub/gmv | AY3: Метрика | AZ3: lcv_xl
A4: 2 | B4: 8 | E4: 20 | F4: 3200 | G4: 160 | H4: 3 | M4: 1 | N4: 11 | P4: 15 | Q4: 2300 | R4: =Q4/P4 -> 153.33333 | S4: 13 | T4: =S4/85 -> 0.15294118 | U4: =S4*Q4 -> 29900 | X4: AVG Fare. Май | Y4: 1210 | AA4: 2 | AB4: 6 | AD4: 15 | AE4: 2500 | AF4: =AE4/AD4 -> 166.66667 | AG4: 3 | AH4: =AG4/65 -> 0.046153846 | AI4: =AE4*AG4 -> 7500 | AK4: AVG Fare. Май | AL4: 1550 | AN4: 2 | AO4: 2 | AQ4: 12 | AR4: 2000 | AS4: =AR4/AQ4 -> 166.66667 | AT4: 6 | AU4: =AT4/29 -> 0.20689655 | AV4: =AR4*AT4 -> 12000 | AY4: AVG Fare. Май | AZ4: 2230
A5: 3 | B5: 3 | E5: 25 | F5: 4200 | G5: 168 | H5: 1 | M5: 2 | N5: 13 | P5: 20 | Q5: 3200 | R5: =Q5/P5 -> 160 | S5: 7 | T5: =S5/85 -> 0.082352941 | U5: =S5*Q5 -> 22400 | AA5: 3 | AB5: 6 | AD5: 20 | AE5: 4000 | AF5: =AE5/AD5 -> 200 | AG5: 4 | AH5: =AG5/65 -> 0.061538462 | AI5: =AE5*AG5 -> 16000 | AN5: 3 | AO5: 1 | AQ5: 17 | AR5: 3500 | AS5: =AR5/AQ5 -> 205.88235 | AT5: 0 | AU5: =AT5/29 -> 0 | AV5: =AR5*AT5 -> 0
A6: 4 | B6: 5 | H6: Всего: | M6: 3 | N6: 4 | S6: Всего: | T6: =SUM(T3:T5) -> 0.41176471 | U6: =SUM(U3:U5) -> 79300 | V6: =U6/Y6 -> 0.066592209 | X6: GMV. 26.05 | Y6: 1190830 | AA6: 4 | AB6: 9 | AD6: 25 | AE6: 6500 | AF6: =AE6/AD6 -> 260 | AG6: 2 | AH6: =AG6/65 -> 0.030769231 | AI6: =AE6*AG6 -> 13000 | AK6: GMV. 26.05 | AL6: 742350 | AN6: 4 | AO6: 1 | AQ6: 22 | AR6: 5000 | AS6: =AR6/AQ6 -> 227.27273 | AT6: 2 | AU6: =AT6/29 -> 0.068965517 | AV6: =AR6*AT6 -> 10000 | AY6: GMV. 26.05 | AZ6: 181233
A7: 5 | B7: 6 | M7: 4 | N7: 3 | AA7: 5 | AB7: 10 | AG7: Всего: | AH7: =SUM(AH4:AH6) -> 0.13846154 | AI7: =SUM(AI4:AI6) -> 36500 | AJ7: =AI7/$AL$6 -> 0.049168182 | AN7: 5 | AO7: 5 | AT7: Всего: | AU7: =SUM(AU4:AU6) -> 0.27586207 | AV7: =SUM(AV4:AV6) -> 22000 | AW7: =AV7/$AZ$6 -> 0.1213907
A8: 6 | B8: 3 | E8: 2 вариант целей S | M8: 5 | N8: 4 | P8: 2 вариант целей M | AA8: 6 | AB8: 4 | AN8: 6 | AO8: 3
A9: 7 | B9: 2 | E9: вручений | F9: бонус | G9: доплата за вручение | H9: водители на ступени | I9: SR | J9: Затраты | K9: sub/gmv | M9: 6 | N9: 5 | P9: вручений | Q9: бонус | R9: доплата за вручение | S9: водители на ступени | T9: SR | U9: Затраты | V9: sub/gmv | AA9: 7 | AB9: 5 | AD9: 2вариант целей L | AN9: 7 | AO9: 2
A10: 8 | B10: 4 | E10: 20 | F10: 1800 | G10: 90 | H10: 3 | M10: 7 | N10: 3 | P10: 12 | Q10: 1700 | R10: =Q10/P10 -> 141.66667 | S10: 15 | T10: =S10/85 -> 0.17647059 | U10: =S10*Q10 -> 25500 | AA10: 8 | AB10: 2 | AD10: вручений | AE10: бонус | AF10: доплата за вручение | AG10: водители на ступени | AH10: SR | AI10: Затраты | AJ10: sub/gmv | AN10: 8 | AO10: 1
A11: 9 | B11: 2 | E11: 30 | F11: 3000 | G11: 100 | H11: 2 | M11: 8 | N11: 4 | P11: 17 | Q11: 2500 | R11: =Q11/P11 -> 147.05882 | S11: 7 | T11: =S11/85 -> 0.082352941 | U11: =S11*Q11 -> 17500 | AA11: 9 | AB11: 1 | AD11: 12 | AE11: 2500 | AF11: =AE11/AD11 -> 208.33333 | AG11: 6 | AH11: =AG11/65 -> 0.092307692 | AI11: =AE11*AG11 -> 15000 | AN11: 9 | AO11: 2 | AQ11: 2 вариант целей XL
A12: 10 | B12: 3 | E12: 45 | F12: 4700 | G12: 105 | H12: 1 | M12: 9 | N12: 3 | P12: 22 | Q12: 4000 | R12: =Q12/P12 -> 181.81818 | S12: 6 | T12: =S12/85 -> 0.070588235 | U12: =S12*Q12 -> 24000 | AA12: 10 | AB12: 5 | AD12: 17 | AE12: 4000 | AF12: =AE12/AD12 -> 235.29412 | AG12: 4 | AH12: =AG12/65 -> 0.061538462 | AI12: =AE12*AG12 -> 16000 | AN12: 11 | AO12: 3 | AQ12: вручений | AR12: бонус | AS12: доплата за вручение | AT12: водители на ступени | AU12: SR | AV12: Затраты | AW12: sub/gmv
A13: 11 | B13: 3 | H13: Всего: | M13: 10 | N13: 2 | S13: Всего: | T13: =SUM(T10:T12) -> 0.32941176 | U13: =SUM(U10:U12) -> 67000 | V13: =U13/Y6 -> 0.056263279 | AA13: 11 | AB13: 1 | AD13: 22 | AE13: 6500 | AF13: =AE13/AD13 -> 295.45455 | AG13: 3 | AH13: =AG13/65 -> 0.046153846 | AI13: =AE13*AG13 -> 19500 | AN13: 12 | AO13: 1 | AQ13: 15 | AR13: 2500 | AS13: =AR13/AQ13 -> 166.66667 | AT13: 1 | AU13: =AT13/29 -> 0.034482759 | AV13: =AR13*AT13 -> 2500
A14: 12 | B14: 2 | M14: 11 | N14: 5 | AA14: 12 | AB14: 2 | AG14: Всего: | AH14: =SUM(AH11:AH13) -> 0.2 | AI14: =SUM(AI11:AI13) -> 50500 | AJ14: =AI14/$AL$6 -> 0.068027211 | AN14: 13 | AO14: 2 | AQ14: 20 | AR14: 4000 | AS14: =AR14/AQ14 -> 200 | AT14: 1 | AU14: =AT14/29 -> 0.034482759 | AV14: =AR14*AT14 -> 4000
A15: 13 | B15: 2 | M15: 12 | N15: 2 | AA15: 14 | AB15: 2 | AN15: 14 | AO15: 2 | AQ15: 25 | AR15: 6500 | AS15: =AR15/AQ15 -> 260 | AT15: 1 | AU15: =AT15/29 -> 0.034482759 | AV15: =AR15*AT15 -> 6500 | AY15: Метрика | AZ15: lcv_xl_1
A16: 14 | B16: 1 | M16: 13 | N16: 1 | P16: 2 вариант целей M | AA16: 15 | AB16: 1 | AD16: 2вариант целей L | AN16: 16 | AO16: 1 | AT16: Всего: | AU16: =SUM(AU13:AU15) -> 0.10344828 | AV16: =SUM(AV13:AV15) -> 13000 | AW16: =AV16/$AZ$6 -> 0.071730866 | AY16: AVG Fare. Май | AZ16: 2555
A17: 15 | B17: 2 | M17: 14 | N17: 5 | P17: вручений | Q17: бонус | R17: доплата за вручение | S17: водители на ступени | T17: SR | U17: Затраты | V17: sub/gmv | AA17: 16 | AB17: 1 | AD17: вручений | AE17: бонус | AF17: доплата за вручение | AG17: водители на ступени | AH17: SR | AI17: Затраты | AJ17: sub/gmv | AN17: 24 | AO17: 1
A18: 19 | B18: 1 | M18: 15 | N18: 3 | P18: 15 | Q18: 1700 | R18: =Q18/P18 -> 113.33333 | S18: 13 | T18: =S18/85 -> 0.15294118 | U18: =S18*Q18 -> 22100 | AA18: 18 | AB18: 1 | AD18: 10 | AE18: 2500 | AF18: =AE18/AD18 -> 250 | AG18: 10 | AH18: =AG18/65 -> 0.15384615 | AI18: =AE18*AG18 -> 25000 | AN18: 31 | AO18: 1 | AY18: GMV. 26.05 | AZ18: 11132
A19: 20 | B19: 3 | M19: 16 | N19: 4 | P19: 20 | Q19: 2500 | R19: =Q19/P19 -> 125 | S19: 3 | T19: =S19/85 -> 0.035294118 | U19: =S19*Q19 -> 7500 | AA19: 20 | AB19: 1 | AD19: 15 | AE19: 4000 | AF19: =AE19/AD19 -> 266.66667 | AG19: 3 | AH19: =AG19/65 -> 0.046153846 | AI19: =AE19*AG19 -> 12000 | AN19: Итого | AO19: 29
A20: 21 | B20: 1 | M20: 17 | N20: 2 | P20: 25 | Q20: 4000 | R20: =Q20/P20 -> 160 | S20: 4 | T20: =S20/85 -> 0.047058824 | U20: =S20*Q20 -> 16000 | AA20: 21 | AB20: 2 | AD20: 20 | AE20: 6500 | AF20: =AE20/AD20 -> 325 | AG20: 6 | AH20: =AG20/65 -> 0.092307692 | AI20: =AE20*AG20 -> 39000
A21: 22 | B21: 1 | M21: 18 | N21: 2 | S21: Всего: | T21: =SUM(T18:T20) -> 0.23529412 | U21: =SUM(U18:U20) -> 45600 | V21: =U21/$Y$6 -> 0.038292619 | AA21: 23 | AB21: 1 | AG21: Всего: | AH21: =SUM(AH18:AH20) -> 0.29230769 | AI21: =SUM(AI18:AI20) -> 76000 | AJ21: =AI21/$AL$6 -> 0.10237758
A22: 23 | B22: 4 | M22: 19 | N22: 2 | AA22: 29 | AB22: 1
A23: 24 | B23: 1 | M23: 20 | N23: 1 | AA23: 54 | AB23: 1
A24: 27 | B24: 2 | M24: 23 | N24: 2 | AA24: Итого | AB24: 65
A25: 28 | B25: 2 | M25: 25 | N25: 1
A26: 35 | B26: 1 | M26: 29 | N26: 1
A27: 40 | B27: 1 | M27: 37 | N27: 1
A28: Итого | B28: 65 | M28: 38 | N28: 1
M29: Итого | N29: 85
M36: Доходимость M1
AA37: Доходимость L1
M38: Кол-во вручений | N38: Водителей
M39: 1 | N39: 1 | P39: 1 вариант целей M1 | X39: Метрика | Y39: lcv_M1 | AA39: Кол-во вручений | AB39: Водителей | AD39: 2вариант целей L1
M40: 2 | N40: 2 | P40: вручений | Q40: бонус | R40: доплата за вручение | S40: водители на ступени | T40: SR | U40: Затраты | V40: sub/gmv | X40: AVG Fare. Май | Y40: 1910 | AA40: 2 | AB40: 1 | AD40: вручений | AE40: бонус | AF40: доплата за вручение | AG40: водители на ступени | AH40: SR | AI40: Затраты | AJ40: sub/gmv | AK40: Метрика | AL40: lcv_l_1
M41: 3 | N41: 1 | P41: 15 | Q41: 2500 | R41: =Q41/P41 -> 166.66667 | S41: 7 | T41: =S41/30 -> 0.23333333 | U41: =Q41*S41 -> 17500 | AA41: 3 | AB41: 2 | AD41: 10 | AE41: 2500 | AF41: =AE41/AD41 -> 250 | AG41: 2 | AH41: =AG41/12 -> 0.16666667 | AI41: =AE41*AG41 -> 5000 | AK41: AVG Fare. Май | AL41: 2500
M42: 4 | N42: 1 | P42: 20 | Q42: 4000 | R42: =Q42/P42 -> 200 | S42: 1 | T42: =S42/30 -> 0.033333333 | U42: =Q42*S42 -> 4000 | X42: GMV. 26.05 | Y42: 256365 | AA42: 4 | AB42: 1 | AD42: 15 | AE42: 4000 | AF42: =AE42/AD42 -> 266.66667 | AG42: 0 | AH42: =AG42/12 -> 0 | AI42: =AE42*AG42 -> 0
M43: 5 | N43: 1 | P43: 25 | Q43: 6500 | R43: =Q43/P43 -> 260 | S43: 3 | T43: =S43/30 -> 0.1 | U43: =Q43*S43 -> 19500 | AA43: 7 | AB43: 3 | AD43: 20 | AE43: 6000 | AF43: =AE43/AD43 -> 300 | AG43: 2 | AH43: =AG43/12 -> 0.16666667 | AI43: =AE43*AG43 -> 12000 | AK43: GMV. 26.05 | AL43: 122781
M44: 6 | N44: 2 | S44: Всего: | T44: =SUM(T41:T43) -> 0.36666667 | U44: =SUM(U41:U43) -> 41000 | V44: =U44/Y42 -> 0.15992823 | AA44: 8 | AB44: 1 | AG44: Всего: | AH44: =SUM(AH41:AH43) -> 0.33333333 | AI44: =SUM(AI41:AI43) -> 17000 | AJ44: =AI44/AL43 -> 0.1384579
M45: 7 | N45: 2 | AA45: 10 | AB45: 2
M46: 8 | N46: 1 | AA46: 21 | AB46: 1
M47: 9 | N47: 2 | P47: 1 вариант целей M1 | AA47: 23 | AB47: 1
M48: 10 | N48: 1 | P48: вручений | Q48: бонус | R48: доплата за вручение | S48: водители на ступени | T48: SR | U48: Затраты | V48: sub/gmv | AA48: Итого | AB48: 12
M49: 11 | N49: 2 | P49: 17 | Q49: 2500 | R49: =Q49/P49 -> 147.05882 | S49: 3 | T49: =S49/30 -> 0.1 | U49: =Q49*S49 -> 7500
M50: 13 | N50: 1 | P50: 22 | Q50: 3500 | R50: =Q50/P50 -> 159.09091 | S50: 2 | T50: =S50/30 -> 0.066666667 | U50: =Q50*S50 -> 7000
M51: 14 | N51: 2 | P51: 27 | Q51: 5000 | R51: =Q51/P51 -> 185.18519 | S51: 2 | T51: =S51/30 -> 0.066666667 | U51: =Q51*S51 -> 10000
M52: 15 | N52: 2 | S52: Всего: | T52: =SUM(T49:T51) -> 0.23333333 | U52: =SUM(U49:U51) -> 24500 | V52: =U52/Y42 -> 0.095566868
M53: 16 | N53: 2
M54: 17 | N54: 1 | P54: 1 вариант целей M1
M55: 18 | N55: 2 | P55: вручений | Q55: бонус | R55: доплата за вручение | S55: водители на ступени | T55: SR | U55: Затраты | V55: sub/gmv
M56: 23 | N56: 1 | P56: 20 | Q56: 2500 | R56: =Q56/P56 -> 125 | S56: 1 | T56: =S56/30 -> 0.033333333 | U56: =Q56*S56 -> 2500
M57: 25 | N57: 1 | P57: 25 | Q57: 4000 | R57: =Q57/P57 -> 160 | S57: 1 | T57: =S57/30 -> 0.033333333 | U57: =Q57*S57 -> 4000
M58: 29 | N58: 1 | P58: 30 | Q58: 6500 | R58: =Q58/P58 -> 216.66667 | S58: 1 | T58: =S58/30 -> 0.033333333 | U58: =Q58*S58 -> 6500
M59: 38 | N59: 1 | S59: Всего: | T59: =SUM(T56:T58) -> 0.1 | U59: =SUM(U56:U58) -> 13000 | V59: =U59/Y49 -> #DIV/0!
M60: Итого | N60: 30
M64: Доходимость M2 | AA64: Доходимость L2
AA65: Кол-во вручений | AB65: Водителей | AD65: 2вариант целей L2
M66: Кол-во вручений | N66: Водителей | P66: 1 вариант целей M2 | X66: Метрика | Y66: lcv_M2 | AA66: 5 | AB66: 2 | AD66: вручений | AE66: бонус | AF66: доплата за вручение | AG66: водители на ступени | AH66: SR | AI66: Затраты | AJ66: sub/gmv | AK66: Метрика | AL66: lcv_l_2
M67: 1 | N67: 1 | P67: вручений | Q67: бонус | R67: доплата за вручение | S67: водители на ступени | T67: SR | U67: Затраты | V67: sub/gmv | X67: AVG Fare. Май | Y67: 2643 | AA67: 6 | AB67: 1 | AD67: 10 | AE67: 2700 | AF67: =AE67/AD67 -> 270 | AG67: 2 | AH67: =AG67/8 -> 0.25 | AI67: =AE67*AG67 -> 5400 | AK67: AVG Fare. Май | AL67: 3430
M68: 2 | N68: 1 | P68: 15 | Q68: 3000 | R68: =Q68/P68 -> 200 | S68: 1 | T68: =S68/8 -> 0.125 | U68: =Q68*S68 -> 3000 | AA68: 9 | AB68: 1 | AD68: 15 | AE68: 4500 | AF68: =AE68/AD68 -> 300 | AG68: 1 | AH68: =AG68/8 -> 0.125 | AI68: =AE68*AG68 -> 4500
M69: 5 | N69: 1 | P69: 20 | Q69: 4500 | R69: =Q69/P69 -> 225 | S69: 0 | T69: =S69/8 -> 0 | U69: =Q69*S69 -> 0 | X69: GMV. 26.05 | Y69: 201331 | AA69: 10 | AB69: 1 | AD69: 20 | AE69: 6500 | AF69: =AE69/AD69 -> 325 | AG69: 1 | AH69: =AG69/8 -> 0.125 | AI69: =AE69*AG69 -> 6500 | AK69: GMV. 26.05 | AL69: 124342
M70: 6 | N70: 1 | P70: 25 | Q70: 6500 | R70: =Q70/P70 -> 260 | S70: 1 | T70: =S70/8 -> 0.125 | U70: =Q70*S70 -> 6500 | AA70: 12 | AB70: 1 | AG70: Всего: | AH70: =SUM(AH67:AH69) -> 0.5 | AI70: =SUM(AI67:AI69) -> 16400 | AJ70: =AI70/AL69 -> 0.13189429
M71: 11 | N71: 1 | S71: Всего: | T71: =SUM(T68:T70) -> 0.25 | U71: =SUM(U68:U70) -> 9500 | V71: =U71/Y69 -> 0.047185977 | AA71: 16 | AB71: 1
M72: 14 | N72: 1 | AA72: 21 | AB72: 1
M73: 17 | N73: 1 | P73: 1 вариант целей M2 | AA73: Итого | AB73: 8 | AD73: 2вариант целей L2
M74: 37 | N74: 1 | P74: вручений | Q74: бонус | R74: доплата за вручение | S74: водители на ступени | T74: SR | U74: Затраты | V74: sub/gmv | W74: Метрика | X74: lcv_M2 | AD74: вручений | AE74: бонус | AF74: доплата за вручение | AG74: водители на ступени | AH74: SR | AI74: Затраты | AJ74: sub/gmv
M75: Итого | N75: 8 | P75: 12 | Q75: 2500 | R75: =Q75/P75 -> 208.33333 | S75: 1 | T75: =S75/8 -> 0.125 | U75: =Q75*S75 -> 2500 | W75: AVG Fare. Май | X75: 2643 | AD75: 12 | AE75: 2700 | AF75: =AE75/AD75 -> 225 | AG75: 1 | AH75: =AG75/8 -> 0.125 | AI75: =AE75*AG75 -> 2700
P76: 17 | Q76: 4000 | R76: =Q76/P76 -> 235.29412 | S76: 1 | T76: =S76/8 -> 0.125 | U76: =Q76*S76 -> 4000 | AD76: 17 | AE76: 4500 | AF76: =AE76/AD76 -> 264.70588 | AG76: 2 | AH76: =AG76/8 -> 0.25 | AI76: =AE76*AG76 -> 9000
P77: 22 | Q77: 6500 | R77: =Q77/P77 -> 295.45455 | S77: 1 | T77: =S77/8 -> 0.125 | U77: =Q77*S77 -> 6500 | W77: GMV. 26.05 | X77: 201331 | AD77: 22 | AE77: 6500 | AF77: =AE77/AD77 -> 295.45455 | AG77: 0 | AH77: =AG77/8 -> 0 | AI77: =AE77*AG77 -> 0
S78: Всего: | T78: =SUM(T75:T77) -> 0.375 | U78: =SUM(U75:U77) -> 13000 | V78: =U78/Y69 -> 0.064570285 | AG78: Всего: | AH78: =SUM(AH75:AH77) -> 0.375 | AI78: =SUM(AI75:AI77) -> 11700 | AJ78: =AI78/AL69 -> 0.094095318
Q86: Цели M1 Уфа
Q87: вручений | R87: бонус | S87: доплата за вручение | T87: водители на ступени | U87: SR | V87: Затраты | W87: sub/gmv | X87: Метрика | Y87: lcv_M1
Q88: 17 | R88: 2500 | S88: 147.05882 | T88: 3 | U88: 0.1 | V88: 7500 | X88: AVG Fare. Май | Y88: 1910
Q89: 22 | R89: 3500 | S89: 159.09091 | T89: 2 | U89: 0.066666667 | V89: 7000
Q90: 27 | R90: 5000 | S90: 185.18519 | T90: 2 | U90: 0.066666667 | V90: 10000 | X90: GMV. 26.05 | Y90: 256365
T91: Всего: | U91: 0.23333333 | V91: 24500 | W91: 0.095566868
Q93: Цели M2 Уфа
Q94: вручений | R94: бонус | S94: доплата за вручение | T94: водители на ступени | U94: SR | V94: Затраты | W94: sub/gmv | X94: Метрика | Y94: lcv_M2
Q95: 15 | R95: 3000 | S95: 200 | T95: 1 | U95: 0.125 | V95: 3000 | X95: AVG Fare. Май | Y95: 2643
Q96: 20 | R96: 4500 | S96: 225 | T96: 0 | U96: 0 | V96: 0
Q97: 25 | R97: 6500 | S97: 260 | T97: 1 | U97: 0.125 | V97: 6500 | X97: GMV. 26.05 | Y97: 201331
T98: Всего: | U98: 0.25 | V98: 9500 | W98: 0.047185977
Q100: Цели L2 Уфа
Q101: вручений | R101: бонус | S101: доплата за вручение | T101: водители на ступени | U101: SR | V101: Затраты | W101: sub/gmv | X101: Метрика | Y101: lcv_l_2
Q102: 10 | R102: 2700 | S102: 270 | T102: 2 | U102: 0.25 | V102: 5400 | X102: AVG Fare. Май | Y102: 3430
Q103: 15 | R103: 4500 | S103: 300 | T103: 1 | U103: 0.125 | V103: 4500
Q104: 20 | R104: 6500 | S104: 325 | T104: 1 | U104: 0.125 | V104: 6500 | X104: GMV. 26.05 | Y104: 124342
T105: Всего: | U105: 0.5 | V105: 16400 | W105: 0.13189429
Q107: Цели XL Уфа
Q108: вручений | R108: бонус | S108: доплата за вручение | T108: водители на ступени | U108: SR | V108: Затраты | W108: sub/gmv | X108: Метрика | Y108: lcv_xl
Q109: 12 | R109: 2500 | S109: 208.33333 | T109: 6 | U109: 0.20689655 | V109: 15000 | X109: AVG Fare. Май | Y109: 2230
Q110: 17 | R110: 4000 | S110: 235.29412 | T110: 0 | U110: 0 | V110: 0
Q111: 22 | R111: 6500 | S111: 295.45455 | T111: 2 | U111: 0.068965517 | V111: 13000 | X111: GMV. 26.05 | Y111: 181233
T112: Всего: | U112: 0.27586207 | V112: 28000 | W112: 0.15449725

Sheet Цели Самара
A1: Доходимость S2 | I1: Доходимость M2 | P1: Доходимость L | Y1: Доходимость XL
A3: Кол-во вручений | B3: Водителей | I3: Кол-во вручений | J3: Водителей | P3: Кол-во вручений | Q3: Водителей | Y3: Кол-во вручений | Z3: Водителей
A4: 4 | B4: 1 | I4: 2 | J4: 2 | P4: 1 | Q4: 5 | Y4: 2 | Z4: 1
A5: 11 | B5: 1 | I5: 3 | J5: 5 | P5: 2 | Q5: 11 | Y5: 3 | Z5: 3
A6: 14 | B6: 1 | I6: 4 | J6: 1 | P6: 3 | Q6: 8 | Y6: 4 | Z6: 2
A7: 28 | B7: 1 | I7: 5 | J7: 2 | P7: 4 | Q7: 6 | Y7: 6 | Z7: 1
A8: Итого | B8: 4 | I8: 6 | J8: 1 | P8: 5 | Q8: 2 | Y8: 7 | Z8: 2
I9: 7 | J9: 3 | P9: 6 | Q9: 2 | Y9: 12 | Z9: 2
I10: 9 | J10: 2 | P10: 7 | Q10: 3 | Y10: 13 | Z10: 1
I11: 10 | J11: 2 | P11: 9 | Q11: 3 | Y11: 14 | Z11: 4
I12: 11 | J12: 2 | P12: 10 | Q12: 2 | Y12: 15 | Z12: 1
I13: 12 | J13: 1 | P13: 11 | Q13: 3 | Y13: 16 | Z13: 1
I14: 15 | J14: 1 | P14: 12 | Q14: 1 | Y14: 17 | Z14: 1
I15: 17 | J15: 1 | P15: 13 | Q15: 1 | Y15: 20 | Z15: 2
I16: 26 | J16: 1 | P16: 14 | Q16: 2 | Y16: 22 | Z16: 1
I17: 33 | J17: 1 | P17: 15 | Q17: 1 | Y17: 23 | Z17: 1
I18: Итого | J18: 25 | P18: 16 | Q18: 1 | Y18: 43 | Z18: 1
P19: 19 | Q19: 3 | Y19: Итого | Z19: 24
P20: 20 | Q20: 2
P21: 21 | Q21: 2
P22: 22 | Q22: 2 | Y22: 1 вариант целей xl
A23: 1 вариант целей S2 | P23: 23 | Q23: 1 | Y23: вручений | Z23: бонус | AA23: доплата за вручение | AB23: водители на ступени | AC23: SR | AD23: Затраты | AE23: sub/gmv
A24: вручений | B24: бонус | C24: доплата за вручение | D24: водители на ступени | E24: SR | F24: Затраты | G24: sub/gmv | P24: 25 | Q24: 1 | Y24: 20 | Z24: 4500 | AA24: =Z24/Y24 -> 225 | AB24: 2 | AC24: =AB24/24 -> 0.083333333 | AD24: =Z24*AB24 -> 9000
A25: 10 | B25: 1500 | C25: =B25/A25 -> 150 | D25: 1 | E25: =D25/4 -> 0.25 | F25: =B25*D25 -> 1500 | P25: 28 | Q25: 2 | Y25: 25 | Z25: 5800 | AA25: =Z25/Y25 -> 232 | AB25: 2 | AC25: =AB25/24 -> 0.083333333 | AD25: =Z25*AB25 -> 11600
A26: 15 | B26: 2600 | C26: =B26/A26 -> 173.33333 | D26: 1 | E26: =D26/4 -> 0.25 | F26: =B26*D26 -> 2600 | P26: 30 | Q26: 1 | Y26: 30 | Z26: 7000 | AA26: =Z26/Y26 -> 233.33333 | AB26: 1 | AC26: =AB26/24 -> 0.041666667 | AD26: =Z26*AB26 -> 7000
A27: 20 | B27: 3800 | C27: =B27/A27 -> 190 | D27: 1 | E27: =D27/4 -> 0.25 | F27: =B27*D27 -> 3800 | P27: 31 | Q27: 1 | AB27: Всего: | AC27: =SUM(AC24:AC26) -> 0.20833333 | AD27: =SUM(AD24:AD26) -> 27600 | AE27: =AD27/$Z$40 -> 0.15066654
D28: Всего: | E28: =SUM(E25:E27) -> 0.75 | F28: =SUM(F25:F27) -> 7900 | G28: =F28/$B$41 -> 0.20103827 | P28: 32 | Q28: 1
P29: 35 | Q29: 1 | Y29: 2 вариант целей xl
A30: 2 вариант целей S2 | P30: Итого | Q30: 68 | Y30: вручений | Z30: бонус | AA30: доплата за вручение | AB30: водители на ступени | AC30: SR | AD30: Затраты | AE30: sub/gmv
A31: вручений | B31: бонус | C31: доплата за вручение | D31: водители на ступени | E31: SR | F31: Затраты | G31: sub/gmv | Y31: 17 | Z31: 4800 | AA31: =Z31/Y31 -> 282.35294 | AB31: 1 | AC31: =AB31/24 -> 0.041666667 | AD31: =Z31*AB31 -> 4800
A32: 14 | B32: 2500 | C32: =B32/A32 -> 178.57143 | D32: 1 | E32: =D32/4 -> 0.25 | F32: =B32*D32 -> 2500 | Q32: 1 вариант целей l | Y32: 22 | Z32: 6400 | AA32: =Z32/Y32 -> 290.90909 | AB32: 3 | AC32: =AB32/24 -> 0.125 | AD32: =Z32*AB32 -> 19200
A33: 19 | B33: 3500 | C33: =B33/A33 -> 184.21053 | D33: 0 | E33: =D33/4 -> 0 | F33: =B33*D33 -> 0 | I33: 1 вариант целей m2 | Q33: вручений | R33: бонус | S33: доплата за вручение | T33: водители на ступени | U33: SR | V33: Затраты | W33: sub/gmv | Y33: 27 | Z33: 8000 | AA33: =Z33/Y33 -> 296.2963 | AB33: 1 | AC33: =AB33/24 -> 0.041666667 | AD33: =Z33*AB33 -> 8000
A34: 24 | B34: 4800 | C34: =B34/A34 -> 200 | D34: 1 | E34: =D34/4 -> 0.25 | F34: =B34*D34 -> 4800 | I34: вручений | J34: бонус | K34: доплата за вручение | L34: водители на ступени | M34: SR | N34: Затраты | O34: sub/gmv | Q34: 20 | R34: 4000 | S34: =R34/Q34 -> 200 | T34: 7 | U34: =T34/68 -> 0.10294118 | V34: =R34*T34 -> 28000 | AB34: Всего: | AC34: =SUM(AC31:AC33) -> 0.20833333 | AD34: =SUM(AD31:AD33) -> 32000 | AE34: =AD34/$Z$40 -> 0.17468584
D35: Всего: | E35: =SUM(E32:E34) -> 0.5 | F35: =SUM(F32:F34) -> 7300 | G35: =F35/$B$41 -> 0.18576954 | I35: 12 | J35: 2500 | K35: =J35/I35 -> 208.33333 | L35: 1 | M35: =L35/25 -> 0.04 | N35: =J35*L35 -> 2500 | Q35: 25 | R35: 5000 | S35: =R35/Q35 -> 200 | T35: 3 | U35: =T35/68 -> 0.044117647 | V35: =R35*T35 -> 15000
I36: 17 | J36: 3800 | K36: =J36/I36 -> 223.52941 | L36: 2 | M36: =L36/25 -> 0.08 | N36: =J36*L36 -> 7600 | Q36: 30 | R36: 6500 | S36: =R36/Q36 -> 216.66667 | T36: 4 | U36: =T36/68 -> 0.058823529 | V36: =R36*T36 -> 26000
I37: 22 | J37: 5200 | K37: =J37/I37 -> 236.36364 | L37: 2 | M37: =L37/25 -> 0.08 | N37: =J37*L37 -> 10400 | T37: Всего: | U37: =SUM(U34:U36) -> 0.20588235 | V37: =SUM(V34:V36) -> 69000 | W37: =V37/$R$50 -> 0.077172144 | Y37: Метрика | Z37: lcv_xl
A38: Метрика | B38: lcv_s2 | L38: Всего: | M38: =SUM(M35:M37) -> 0.2 | N38: =SUM(N35:N37) -> 20500 | O38: =N38/$J$51 -> 0.065579854 | Y38: AVG Fare. Май | Z38: 2757
A39: AVG Fare. Май | B39: 1979 | Q39: 2 вариант целей l
I40: 2 вариант целей m2 | Q40: вручений | R40: бонус | S40: доплата за вручение | T40: водители на ступени | U40: SR | V40: Затраты | W40: sub/gmv | Y40: GMV. 26.05 | Z40: 183186
A41: GMV. 26.05 | B41: 39296 | I41: вручений | J41: бонус | K41: доплата за вручение | L41: водители на ступени | M41: SR | N41: Затраты | O41: sub/gmv | Q41: 16 | R41: 3200 | S41: =R41/Q41 -> 200 | T41: 1 | U41: =T41/68 -> 0.014705882 | V41: =R41*T41 -> 3200
I42: 15 | J42: 3000 | K42: =J42/I42 -> 200 | L42: 1 | M42: =L42/25 -> 0.04 | N42: =J42*L42 -> 3000 | Q42: 23 | R42: 5000 | S42: =R42/Q42 -> 217.3913 | T42: 9 | U42: =T42/68 -> 0.13235294 | V42: =R42*T42 -> 45000
I43: 20 | J43: 4500 | K43: =J43/I43 -> 225 | L43: 1 | M43: =L43/25 -> 0.04 | N43: =J43*L43 -> 4500 | Q43: 30 | R43: 6800 | S43: =R43/Q43 -> 226.66667 | T43: 8 | U43: =T43/68 -> 0.11764706 | V43: =R43*T43 -> 54400
A44: Dynamics - CDR & Utilization per Option Region - Yandex DataLens | I44: 25 | J44: 5900 | K44: =J44/I44 -> 236 | L44: 2 | M44: =L44/25 -> 0.08 | N44: =J44*L44 -> 11800 | T44: Всего: | U44: =SUM(U41:U43) -> 0.26470588 | V44: =SUM(V41:V43) -> 102600 | W44: =V44/$R$50 -> 0.11475162
L45: Всего: | M45: =SUM(M42:M44) -> 0.16 | N45: =SUM(N42:N44) -> 19300 | O45: =N45/$J$51 -> 0.061741033
Q47: Метрика | R47: lcv_l
I48: Метрика | J48: lcv_m2 | Q48: AVG Fare. Май | R48: 2423
I49: AVG Fare. Май | J49: 2369
Q50: GMV. 26.05 | R50: 894105
I51: GMV. 26.05 | J51: 312596

Sheet Цели Пермь
A1: Доходимость M | K1: Доходимость L
A2: Кол-во вручений | B2: Водителей | K2: Кол-во вручений | L2: Водителей
A3: 1 | B3: 19 | K3: 1 | L3: 8
A4: 2 | B4: 9 | K4: 2 | L4: 4
A5: 3 | B5: 9 | K5: 3 | L5: 5
A6: 4 | B6: 7 | K6: 4 | L6: 3
A7: 5 | B7: 5 | K7: 5 | L7: 4
A8: 6 | B8: 4 | K8: 6 | L8: 2
A9: 7 | B9: 5 | K9: 7 | L9: 2
A10: 8 | B10: 5 | K10: 8 | L10: 1
A11: 9 | B11: 2 | K11: 10 | L11: 2
A12: 10 | B12: 7 | K12: 11 | L12: 1
A13: 11 | B13: 2 | K13: 12 | L13: 1
A14: 13 | B14: 1 | K14: 13 | L14: 2
... A20: 21 | B20: 3 | K20: 25 | L20: 3
A21: 23 | B21: 2 | K21: Итого | L21: 45
A22: 24 | B22: 1
A23: 25 | B23: 1
A24: 26 | B24: 2 | K24: 1 вариант целей l
A25: 30 | B25: 1 | K25: вручений | L25: бонус | M25: доплата за вручение | N25: водители на ступени | O25: SR | P25: Затраты | Q25: sub/gmv
A26: 32 | B26: 1 | K26: 15 | L26: 3500 | M26: =L26/K26 -> 233.33333 | N26: 2 | O26: =N26/45 -> 0.044444444 | P26: =L26*N26 -> 7000
A27: 34 | B27: 1 | K27: 20 | L27: 5000 | M27: =L27/K27 -> 250 | N27: 4 | O27: =N27/45 -> 0.088888889 | P27: =L27*N27 -> 20000
A28: 40 | B28: 1 | K28: 25 | L28: 7000 | M28: =L28/K28 -> 280 | N28: 3 | O28: =N28/45 -> 0.066666667 | P28: =L28*N28 -> 21000
A29: Итого | B29: 103 | N29: Всего: | O29: =SUM(O26:O28) -> 0.2 | P29: =SUM(P26:P28) -> 48000 | Q29: =P29/$L$42 -> 0.082752628
A31: 1 вариант целей m | K31: 2 вариант целей l
A32: вручений | B32: бонус | C32: доплата за вручение | D32: водители на ступени | E32: SR | F32: Затраты | G32: sub/gmv | K32: вручений | L32: бонус | M32: доплата за вручение | N32: водители на ступени | O32: SR | P32: Затраты | Q32: sub/gmv
A33: 16 | B33: 3100 | C33: =B33/A33 -> 193.75 | D33: 4 | E33: =D33/103 -> 0.038834951 | F33: =B33*D33 -> 12400 | K33: 12 | L33: 3200 | M33: =L33/K33 -> 266.66667 | N33: 1 | O33: =N33/45 -> 0.022222222 | P33: =L33*N33 -> 3200
A34: 21 | B34: 4500 | C34: =B34/A34 -> 214.28571 | D34: 8 | E34: =D34/103 -> 0.077669903 | F34: =B34*D34 -> 36000 | K34: 17 | L34: 4500 | M34: =L34/K34 -> 264.70588 | N34: 3 | O34: =N34/45 -> 0.066666667 | P34: =L34*N34 -> 13500
A35: 26 | B35: 5800 | C35: =B35/A35 -> 223.07692 | D35: 10 | E35: =D35/103 -> 0.097087379 | F35: =B35*D35 -> 58000 | K35: 22 | L35: 6500 | M35: =L35/K35 -> 295.45455 | N35: 9 | O35: =N35/45 -> 0.2 | P35: =L35*N35 -> 58500
D36: Всего: | E36: =SUM(E33:E35) -> 0.21359223 | F36: =SUM(F33:F35) -> 106400 | G36: =F36/$B$49 -> 0.06749055 | N36: Всего: | O36: =SUM(O33:O35) -> 0.28888889 | P36: =SUM(P33:P35) -> 75200 | Q36: =P36/$L$42 -> 0.12964578
A38: 2 вариант целей m
A39: вручений | B39: бонус | C39: доплата за вручение | D39: водители на ступени | E39: SR | F39: Затраты | G39: sub/gmv | K39: Метрика | L39: lcv_l
A40: 25 | B40: 3000 | C40: =B40/A40 -> 120 | D40: 2 | E40: =D40/103 -> 0.019417476 | F40: =B40*D40 -> 6000 | K40: AVG Fare. Май | L40: 2357
A41: 30 | B41: 4000 | C41: =B41/A41 -> 133.33333 | D41: 5 | E41: =D41/103 -> 0.048543689 | F41: =B41*D41 -> 20000
A42: 35 | B42: 5500 | C42: =B42/A42 -> 157.14286 | D42: 1 | E42: =D42/103 -> 0.0097087379 | F42: =B42*D42 -> 5500 | K42: GMV. 02.06 | L42: 580042
D43: Всего: | E43: =SUM(E40:E42) -> 0.077669903 | F43: =SUM(F40:F42) -> 31500 | G43: =F43/$B$49 -> 0.019980755
A46: Метрика | B46: lcv_m
A47: AVG Fare. Май | B47: 1777
A49: GMV. 02.06 | B49: 1576517

Sheet Цели Саратов
A2: Доходимость M1 | O2: Доходимость M2
A3: Кол-во вручений | B3: Водителей | O3: Кол-во вручений | P3: Водителей
A4: 1 | B4: 1 | O4: 1 | P4: 1
A5: 3 | B5: 2 | O5: 2 | P5: 1
A6: 6 | B6: 3 | O6: 3 | P6: 1
A7: 7 | B7: 1 | O7: 17 | P7: 1
A8: 8 | B8: 1 | O8: 19 | P8: 1
A9: 9 | B9: 1 | O9: Итого | P9: 5
A10: 10 | B10: 2
A11: 11 | B11: 4
A12: 14 | B12: 2
A13: 15 | B13: 3
A14: 19 | B14: 1
A15: 22 | B15: 1
A16: 23 | B16: 1 | O16: 1 вариант целей m2
A17: 25 | B17: 1 | O17: вручений | P17: бонус | Q17: доплата за вручение | R17: водители на ступени | S17: SR | T17: Затраты | U17: sub/gmv
A18: 26 | B18: 1 | O18: 15 | P18: 3000 | Q18: =P18/O18 -> 200 | R18: 0 | S18: =R18/6 -> 0 | T18: =P18*R18 -> 0
A19: 28 | B19: 1 | O19: 20 | P19: 4500 | Q19: =P19/O19 -> 225 | R19: 1 | S19: =R19/6 -> 0.16666667 | T19: =P19*R19 -> 4500
A20: Итого | B20: 26 | O20: 25 | P20: 6000 | Q20: =P20/O20 -> 240 | R20: 1 | S20: =R20/6 -> 0.16666667 | T20: =P20*R20 -> 6000
R21: Всего: | S21: =SUM(S18:S20) -> 0.33333333 | T21: =SUM(T18:T20) -> 10500 | U21: =T21/312000 -> 0.033653846
O23: 2 вариант целей m2
A24: 1 вариант целей m1 | O24: вручений | P24: бонус | Q24: доплата за вручение | R24: водители на ступени | S24: SR | T24: Затраты | U24: sub/gmv
A25: вручений | B25: бонус | C25: доплата за вручение | D25: водители на ступени | E25: SR | F25: Затраты | G25: sub/gmv | Q25: =P25/O25 -> #DIV/0! | S25: =R26/103 -> 0 | T25: =P25*R26 -> 0
A26: 18 | B26: 2800 | C26: =B26/A26 -> 155.55556 | D26: 1 | E26: =D26/26 -> 0.038461538 | F26: =B26*D26 -> 2800 | Q26: =P26/O26 -> #DIV/0! | S26: =R27/103 -> 0 | T26: =P26*R27 -> 0
A27: 23 | B27: 4000 | C27: =B27/A27 -> 173.91304 | D27: 3 | E27: =D27/26 -> 0.11538462 | F27: =B27*D27 -> 12000 | Q27: =P27/O27 -> #DIV/0! | S27: =R28/103 -> #VALUE! | T27: =P27*R28 -> #VALUE!
A28: 28 | B28: 5500 | C28: =B28/A28 -> 196.42857 | D28: 1 | E28: =D28/26 -> 0.038461538 | F28: =B28*D28 -> 5500 | R28: Всего: | S28: =SUM(S25:S27) -> #VALUE! | T28: =SUM(T25:T27) -> #VALUE! | U28: =T28/$B$49 -> #VALUE!
D29: Всего: | E29: =SUM(E26:E28) -> 0.19230769 | F29: =SUM(F26:F28) -> 20300 | G29: =F29/280000 -> 0.0725
A31: 2 вариант целей m1 | O31: Метрика | P31: lcv_m
A32: вручений | B32: бонус | C32: доплата за вручение | D32: водители на ступени | E32: SR | F32: Затраты | G32: sub/gmv | O32: AVG Fare. Май
C33: =B33/A33 -> #DIV/0! | E33: =D34/103 -> 0 | F33: =B33*D34 -> 0
C34: =B34/A34 -> #DIV/0! | E34: =D35/103 -> 0 | F34: =B34*D35 -> 0 | O34: GMV. 02.06 | P34: 312000
C35: =B35/A35 -> #DIV/0! | E35: =D36/103 -> #VALUE! | F35: =B35*D36 -> #VALUE!
D36: Всего: | E36: =SUM(E33:E35) -> #VALUE! | F36: =SUM(F33:F35) -> #VALUE! | G36: =F36/$B$49 -> #VALUE!
A39: Метрика | B39: lcv_m
A40: AVG Fare. Май
A42: GMV. 02.06 | B42: 280000

Sheet Цели Новосиб
A4: Доходимость S2 | N4: Доходимость M1
U5: надо цели | X5: Доходимость L1
A6: Кол-во вручений | B6: Водителей | N6: Кол-во вручений | O6: Водителей | AD6: надо цели
A7: 3 | B7: 1 | N7: 1 | O7: 5 | X7: Кол-во вручений | Y7: Водителей
A8: 4 | B8: 1 | N8: 2 | O8: 4 | X8: 1 | Y8: 5
A9: 5 | B9: 2 | N9: 3 | O9: 7 | X9: 3 | Y9: 2
A10: 6 | B10: 1 | N10: 4 | O10: 7 | X10: 4 | Y10: 1
A11: 8 | B11: 2 | N11: 5 | O11: 2 | X11: 5 | Y11: 1
A12: 13 | B12: 1 | N12: 6 | O12: 6 | X12: 6 | Y12: 1
A13: 16 | B13: 1 | N13: 7 | O13: 4 | X13: 7 | Y13: 3
A14: 17 | B14: 1 | N14: 8 | O14: 2 | X14: 9 | Y14: 1
A15: 65 | B15: 1 | N15: 9 | O15: 3 | X15: 12 | Y15: 1 | Z15: 1 вариант целей L1
A16: Итого | B16: 11 | N16: 10 | O16: 3 | X16: 13 | Y16: 1 | Z16: вручений | AA16: бонус | AB16: доплата за вручение | AC16: водители на ступени | AD16: SR | AE16: Затраты | AF16: sub/gmv
N17: 12 | O17: 6 | X17: 14 | Y17: 1 | Z17: 25 | AA17: 3200 | AB17: =AA17/Z17 -> 128 | AC17: 1 | AD17: =AC17/33 -> 0.03030303 | AE17: =AA17*AC17 -> 3200
E18: надо цели | N18: 13 | O18: 3 | X18: 15 | Y18: 1 | Z18: 30 | AA18: 4000 | AB18: =AA18/Z18 -> 133.33333 | AC18: 2 | AD18: =AC18/33 -> 0.060606061 | AE18: =AA18*AC18 -> 8000
N19: 14 | O19: 1 | X19: 17 | Y19: 1 | Z19: 35 | AA19: 5200 | AB19: =AA19/Z19 -> 148.57143 | AC19: 3 | AD19: =AC19/33 -> 0.090909091 | AE19: =AA19*AC19 -> 15600
N20: 15 | O20: 3 | X20: 18 | Y20: 3 | AC20: Всего: | AD20: =SUM(AD17:AD19) -> 0.18181818 | AE20: =SUM(AE17:AE19) -> 26800 | AF20: =AE20/$AA$33 -> 0.1009827
N21: 16 | O21: 4 | X21: 19 | Y21: 1
N22: 17 | O22: 3 | P22: 1 вариант целей M1 | X22: 21 | Y22: 3 | Z22: 2 вариант целей L1
N23: 18 | O23: 4 | P23: вручений | Q23: бонус | R23: доплата за вручение | S23: водители на ступени | T23: SR | U23: Затраты | V23: sub/gmv | X23: 22 | Y23: 1 | Z23: вручений | AA23: бонус | AB23: доплата за вручение | AC23: водители на ступени | AD23: SR | AE23: Затраты | AF23: sub/gmv
N24: 19 | O24: 1 | P24: 25 | Q24: 2500 | R24: =Q24/P24 -> 100 | S24: 3 | T24: =S24/91 -> 0.032967033 | U24: =Q24*S24 -> 7500 | X24: 27 | Y24: 1 | Z24: 29 | AA24: 2700 | AB24: =AA24/Z24 -> 93.103448 | AC24: 1 | AD24: =AC24/33 -> 0.03030303 | AE24: =AA24*AC24 -> 2700
N25: 20 | O25: 1 | P25: 31 | Q25: 3500 | R25: =Q25/P25 -> 112.90323 | S25: 7 | T25: =S25/91 -> 0.076923077 | U25: =Q25*S25 -> 24500 | X25: 33 | Y25: 1 | Z25: 34 | AA25: 3900 | AB25: =AA25/Z25 -> 114.70588 | AC25: 3 | AD25: =AC25/33 -> 0.090909091 | AE25: =AA25*AC25 -> 11700
N26: 21 | O26: 1 | P26: 37 | Q26: 5000 | R26: =Q26/P26 -> 135.13514 | S26: 8 | T26: =S26/91 -> 0.087912088 | U26: =Q26*S26 -> 40000 | X26: 34 | Y26: 1 | Z26: 39 | AA26: 5000 | AB26: =AA26/Z26 -> 128.20513 | AC26: 1 | AD26: =AC26/33 -> 0.03030303 | AE26: =AA26*AC26 -> 5000
N27: 22 | O27: 1 | S27: Всего: | T27: =SUM(T24:T26) -> 0.1978022 | U27: =SUM(U24:U26) -> 72000 | V27: =U27/$Q$40 -> 0.070685324 | X27: 35 | Y27: 1 | AC27: Всего: | AD27: =SUM(AD24:AD26) -> 0.15151515 | AE27: =SUM(AE24:AE26) -> 19400 | AF27: =AE27/$AA$33 -> 0.073099415
N28: 23 | O28: 1 | X28: 37 | Y28: 1
N29: 24 | O29: 2 | P29: 2 вариант целей M1 | X29: 39 | Y29: 1
N30: 25 | O30: 1 | P30: вручений | Q30: бонус | R30: доплата за вручение | S30: водители на ступени | T30: SR | U30: Затраты | V30: sub/gmv | X30: Итого | Y30: 33 | Z30: Метрика | AA30: lcv_l1
N31: 26 | O31: 2 | P31: 30 | Q31: 3000 | R31: =Q31/P31 -> 100 | S31: 2 | T31: =S31/91 -> 0.021978022 | U31: =Q31*S31 -> 6000 | Z31: AVG Fare. Май | AA31: 2457
N32: 27 | O32: 2 | P32: 35 | Q32: 4000 | R32: =Q32/P32 -> 114.28571 | S32: 4 | T32: =S32/91 -> 0.043956044 | U32: =Q32*S32 -> 16000
N33: 28 | O33: 1 | P33: 40 | Q33: 5000 | R33: =Q33/P33 -> 125 | S33: 4 | T33: =S33/91 -> 0.043956044 | U33: =Q33*S33 -> 20000 | Z33: GMV. 26.05 | AA33: 265392
A34: 1 вариант целей S2 | N34: 29 | O34: 1 | S34: Всего: | T34: =SUM(T31:T33) -> 0.10989011 | U34: =SUM(U31:U33) -> 42000 | V34: =U34/$Q$40 -> 0.041233105
A35: вручений | B35: бонус | C35: доплата за вручение | D35: водители на ступени | E35: SR | F35: Затраты | G35: sub/gmv | N35: 30 | O35: 1
A36: 8 | B36: 1000 | C36: =B36/A36 -> 125 | D36: 2 | E36: =D36/11 -> 0.18181818 | F36: =B36*D36 -> 2000 | N36: 34 | O36: 1
A37: 15 | B37: 1900 | C37: =B37/A37 -> 126.66667 | D37: 1 | E37: =D37/11 -> 0.090909091 | F37: =B37*D37 -> 1900 | N37: 37 | O37: 2 | P37: Метрика | Q37: lcv_m1 | X37: Доходимость L2
A38: 22 | B38: 2600 | C38: =B38/A38 -> 118.18182 | D38: 2 | E38: =D38/11 -> 0.18181818 | F38: =B38*D38 -> 5200 | N38: 38 | O38: 2 | P38: AVG Fare. Май | Q38: 1764.59
D39: Всего: | E39: =SUM(E36:E38) -> 0.45454545 | F39: =SUM(F36:F38) -> 9100 | G39: =F39/$B$52 -> 0.104 | N39: 40 | O39: 1 | AD39: надо цели
N40: 42 | O40: 1 | P40: GMV. 26.05 | Q40: 1018599 | X40: Кол-во вручений | Y40: Водителей
A41: 2 вариант целей S2 | N41: 43 | O41: 1 | X41: 1 | Y41: 1
A42: вручений | B42: бонус | C42: доплата за вручение | D42: водители на ступени | E42: SR | F42: Затраты | G42: sub/gmv | N42: 45 | O42: 1 | X42: 2 | Y42: 1
A43: 15 | B43: 2200 | C43: =B43/A43 -> 146.66667 | D43: 2 | E43: =D43/11 -> 0.18181818 | F43: =B43*D43 -> 4400 | N43: Итого | O43: 91 | X43: 3 | Y43: 2
A44: 20 | B44: 3000 | C44: =B44/A44 -> 150 | D44: 1 | E44: =D44/11 -> 0.090909091 | F44: =B44*D44 -> 3000 | X44: 4 | Y44: 2
A45: 25 | B45: 4500 | C45: =B45/A45 -> 180 | D45: 1 | E45: =D45/11 -> 0.090909091 | F45: =B45*D45 -> 4500 | X45: 5 | Y45: 2
D46: Всего: | E46: =SUM(E43:E45) -> 0.36363636 | F46: =SUM(F43:F45) -> 11900 | G46: =F46/$B$52 -> 0.136 | X46: 7 | Y46: 3
X47: 8 | Y47: 1
X48: 10 | Y48: 3
A49: Метрика | B49: lcv_s2 | X49: 11 | Y49: 3
A50: AVG Fare. Май | B50: 2218 | X50: 12 | Y50: 1
X51: 13 | Y51: 1
A52: GMV. 26.05 | B52: 87500 | X52: 14 | Y52: 1
X53: 17 | Y53: 1
X54: 18 | Y54: 2
A55: Доходимость S | F55: Запущено! | N55: Доходимость M2 | X55: 19 | Y55: 1 | Z55: 1 вариант целей L2
A56: COUNTA из order_id | B56: COUNTA из executor_profile_id | D56: 1 вариант целей S | T56: надо цели | X56: 20 | Y56: 1 | Z56: вручений | AA56: бонус | AB56: доплата за вручение | AC56: водители на ступени | AD56: SR | AE56: Затраты | AF56: sub/gmv
A57: 1 | B57: 20 | D57: вручений | E57: бонус | F57: доплата за вручение | G57: водители на ступени | H57: SR | I57: Затраты | J57: sub/gmv | K57: Метрика | L57: lcv_s | N57: Кол-во вручений | O57: Водителей | X57: 21 | Y57: 1 | Z57: 20 | AA57: 4500 | AB57: =AA57/Z57 -> 225 | AC57: 4 | AD57: =AC57/35 -> 0.11428571 | AE57: =AA57*AC57 -> 18000
A58: 2 | B58: 16 | D58: 32 | E58: 3000 | F58: =E58/D58 -> 93.75 | G58: 23 | H58: =G58/314 -> 0.073248408 | I58: =E58*G58 -> 69000 | K58: AVG Fare. Май | L58: 857 | N58: 1 | O58: 4 | X58: 22 | Y58: 1 | Z58: 25 | AA58: 6000 | AB58: =AA58/Z58 -> 240 | AC58: 1 | AD58: =AC58/35 -> 0.028571429 | AE58: =AA58*AC58 -> 6000
A59: 3 | B59: 13 | D59: 42 | E59: 4500 | F59: =E59/D59 -> 107.14286 | G59: 14 | H59: =G59/314 -> 0.044585987 | I59: =E59*G59 -> 63000 | N59: 3 | O59: 1 | X59: 23 | Y59: 1 | Z59: 30 | AA59: 7500 | AB59: =AA59/Z59 -> 250 | AC59: 5 | AD59: =AC59/35 -> 0.14285714 | AE59: =AA59*AC59 -> 37500
A60: 4 | B60: 17 | D60: 52 | E60: 6000 | F60: =E60/D60 -> 115.38462 | G60: 14 | H60: =G60/314 -> 0.044585987 | I60: =E60*G60 -> 84000 | K60: GMV. 26.05 | L60: 3872500 | N60: 4 | O60: 2 | X60: 28 | Y60: 1 | AC60: Всего: | AD60: =SUM(AD57:AD59) -> 0.28571429 | AE60: =SUM(AE57:AE59) -> 61500 | AF60: =AE60/$AA$73 -> 0.094886614
A61: 5 | B61: 18 | G61: Всего: | H61: =SUM(H58:H60) -> 0.16242038 | I61: =SUM(I58:I60) -> 216000 | J61: =I61/L60 -> 0.055777921 | N61: 5 | O61: 3 | X61: 30 | Y61: 1
A62: 6 | B62: 16 | N62: 6 | O62: 4 | X62: 31 | Y62: 1 | Z62: 2 вариант целей L2
A63: 7 | B63: 8 | D63: 1 вариант целей S | N63: 7 | O63: 3 | X63: 32 | Y63: 1 | Z63: вручений | AA63: бонус | AB63: доплата за вручение | AC63: водители на ступени | AD63: SR | AE63: Затраты | AF63: sub/gmv
A64: 8 | B64: 8 | D64: вручений | E64: бонус | F64: доплата за вручение | G64: водители на ступени | H64: SR | I64: Затраты | J64: sub/gmv | N64: 8 | O64: 1 | X64: 35 | Y64: 1 | Z64: 25 | AA64: 3500 | AB64: =AA64/Z64 -> 140 | AC64: 1 | AD64: =AC64/35 -> 0.028571429 | AE64: =AA64*AC64 -> 3500
