Workbook

Sheet Общая расходов (4)
B1: sub dxgy | F1: gmv | J1: sub dxgy / gmv опции | N1: sub dxgy / gmv total
A2: Кузов/опция | B2: Week 1 | C2: Week 2 | D2: Week 3 | E2: Week 4 | F2: Week 1 | G2: Week 2 | H2: Week 3 | I2: Week 4 | J2: Week 1 | K2: Week 2 | L2: Week 3 | M2: Week 4 | N2: Week 1 | O2: Week 2 | P2: Week 3 | Q2: Week 4
A3: M2 | B3: 10000 | C3: 8300 | D3: 6300 | E3: 30000 | F3: 59703 | G3: 48384 | H3: 87989.6 | I3: 95662.8 | J3: =B3/F3 -> 0.16749577 | K3: =C3/G3 -> 0.17154431 | L3: =D3/H3 -> 0.071599371 | M3: =E3/I3 -> 0.31360153 | N3: 0.005509277 | O3: 0.005709547 | P3: 0.003924737 | Q3: 0.019917116
A4: L | B4: 89000 | C4: 63000 | D4: 75000 | E4: 70500 | F4: 388208.8 | G4: 315327.32 | H4: 370709 | I4: 332148.8 | J4: =B4/F4 -> 0.22925807 | K4: =C4/G4 -> 0.19979239 | L4: =D4/H4 -> 0.20231502 | M4: =E4/I4 -> 0.21225427 | N4: 0.049032565 | O4: 0.043337525 | P4: 0.04672306 | Q4: 0.046805222
A5: Total | B5: =SUM(B3:B4) -> 99000 | C5: =SUM(C3:C4) -> 71300 | D5: =SUM(D3:D4) -> 81300 | E5: =SUM(E3:E4) -> 100500 | F5: =SUM(F3:F4) -> 447911.8 | G5: =SUM(G3:G4) -> 363711.32 | H5: =SUM(H3:H4) -> 458698.6 | I5: =SUM(I3:I4) -> 427811.6 | N5: =SUM(N3:N4) -> 0.054541842 | O5: =SUM(O3:O4) -> 0.049047072 | P5: =SUM(P3:P4) -> 0.050647797 | Q5: =SUM(Q3:Q4) -> 0.066722337

Sheet Опция M2 (ПН)
B1: Расходы на цели M2 без отсева | F1: Метрики M2 | W1: CDR&Util | X1: горение
A2: Неделя | B2: sub dxgy | C2: sub dxgy / gmv опции | D2: sub dxgy / gmv total | E2: NI / GMV опции | F2: SR | G2: SR 3 ступени | H2: CDR | I2: Com_del | J2: WoW | K2: Доставки водителей | L2: WoW | M2: Водители | N2: SH active | O2: Utilization | P2: AVG Fare | Q2: GMV | R2: GMV total
A3: 45789 | B3: =G19 -> 12800 | C3: =IFERROR(B3/Q3,0) -> 0.13560615 | D3: =IFERROR(B3/R3,0) -> 0.006385833 | E3: =VLOOKUP($A3,'m2'!$A:$H,2,0) -> 0.12 | F3: =F19 -> 0.23076923 | G3: =F18 -> 0.15384615 | H3: =VLOOKUP($A3,'m2'!$A:$H,3,0) -> 0.74 | I3: =VLOOKUP($A3,'m2'!$A:$H,4,0) -> 38 | J3: =IFERROR(I3/#REF!-1,"-") -> - | K3: =K27 -> 112 | L3: =IFERROR(K3/#REF!-1,"-") -> - | M3: =J27 -> 13 | N3: =VLOOKUP($A3,'m2'!$A:$H,5,0) -> 97 | O3: =VLOOKUP($A3,'m2'!$A:$H,6,0) -> 0.42 | P3: =VLOOKUP($A3,'m2'!$A:$H,7,0) -> 2484 | Q3: =VLOOKUP($A3,'m2'!$A:$H,8,0) -> 94391 | R3: =VLOOKUP(A3,total!A:B,2,0) -> 2004437
A4: 45810 | B4: =G25 -> 10000 | C4: =IFERROR(B4/Q4,0) -> 0.16749577 | D4: =IFERROR(B4/R4,0) -> 0.0050437495 | E4: =VLOOKUP($A4,'m2'!$A:$H,2,0) -> 0.11 | F4: =F25 -> 0.4 | G4: =F24 -> 0.2 | H4: =VLOOKUP($A4,'m2'!$A:$H,3,0) -> 0.59 | I4: =VLOOKUP($A4,'m2'!$A:$H,4,0) -> 21 | J4: =IFERROR(I4/#REF!-1,"-") -> - | K4: =N22 -> 45 | L4: =IFERROR(K4/K3-1,"-") -> -0.59821429 | M4: =M22 -> 5 | N4: =VLOOKUP($A4,'m2'!$A:$H,5,0) -> 56 | O4: =VLOOKUP($A4,'m2'!$A:$H,6,0) -> 0.54 | P4: =VLOOKUP($A4,'m2'!$A:$H,7,0) -> 2843 | Q4: =VLOOKUP($A4,'m2'!$A:$H,8,0) -> 59703 | R4: =VLOOKUP(A4,total!A:B,2,0) -> 1982652
A5: 45817 | B5: =G31 -> 8300 | C5: =IFERROR(B5/Q5,0) -> 0.17154431 | D5: =IFERROR(B5/R5,0) -> 0.0051273023 | E5: =VLOOKUP($A5,'m2'!$A:$H,2,0) -> 0.18 | F5: =F31 -> 0.28571429 | G5: =F30 -> 0.14285714 | H5: =VLOOKUP($A5,'m2'!$A:$H,3,0) -> 0.71 | I5: =VLOOKUP($A5,'m2'!$A:$H,4,0) -> 20 | J5: =IFERROR(I5/I4-1,"-") -> -0.047619048 | K5: =Q23 -> 67 | L5: =IFERROR(K5/K4-1,"-") -> 0.48888889 | M5: =P23 -> 7 | N5: =VLOOKUP($A5,'m2'!$A:$H,5,0) -> 86 | O5: =VLOOKUP($A5,'m2'!$A:$H,6,0) -> 0.66 | P5: =VLOOKUP($A5,'m2'!$A:$H,7,0) -> 2419 | Q5: =VLOOKUP($A5,'m2'!$A:$H,8,0) -> 48384 | R5: =VLOOKUP(A5,total!A:B,2,0) -> 1618785
A6: 45824 | B6: =G37 -> 6300 | C6: =IFERROR(B6/Q6,0) -> 0.071599859 | D6: =IFERROR(B6/R6,0) -> 0.0035480784 | E6: =VLOOKUP($A6,'m2'!$A:$H,2,0) -> 0.16 | F6: =F37 -> 0.28571429 | G6: =F36 -> 0 | H6: =VLOOKUP($A6,'m2'!$A:$H,3,0) -> 0.66 | I6: =VLOOKUP($A6,'m2'!$A:$H,4,0) -> 30 | J6: =IFERROR(I6/I5-1,"-") -> 0.5 | K6: =T23 -> 54 | L6: =IFERROR(K6/K5-1,"-") -> -0.19402985 | M6: =S23 -> 7 | N6: =VLOOKUP($A6,'m2'!$A:$H,5,0) -> 78 | O6: =VLOOKUP($A6,'m2'!$A:$H,6,0) -> 0.59 | P6: =VLOOKUP($A6,'m2'!$A:$H,7,0) -> 2933 | Q6: =VLOOKUP($A6,'m2'!$A:$H,8,0) -> 87989 | R6: =VLOOKUP(A6,total!A:B,2,0) -> 1775609 | S6: GMV водителей M2 | T6: sub/gmv 2
A7: 45831 | B7: =G43 -> 30000 | C7: =IFERROR(B7/Q7,0) -> 0.31360415 | D7: =IFERROR(B7/R7,0) -> 0.018347861 | E7: =VLOOKUP($A7,'m2'!$A:$H,2,0) -> 0.04 | F7: =F43 -> 0.625 | G7: =F42 -> 0.625 | H7: =VLOOKUP($A7,'m2'!$A:$H,3,0) -> 0.79 | I7: =VLOOKUP($A7,'m2'!$A:$H,4,0) -> 39 | J7: =IFERROR(I7/I6-1,"-") -> 0.3 | K7: =W24 -> 156 | L7: =IFERROR(K7/K6-1,"-") -> 1.8888889 | M7: =V24 -> 8 | N7: =VLOOKUP($A7,'m2'!$A:$H,5,0) -> 104 | O7: =VLOOKUP($A7,'m2'!$A:$H,6,0) -> 0.62 | P7: =VLOOKUP($A7,'m2'!$A:$H,7,0) -> 2453 | Q7: =VLOOKUP($A7,'m2'!$A:$H,8,0) -> 95662 | R7: =VLOOKUP(A7,total!A:B,2,0) -> 1635068 | S7: 172326 | T7: =B7/S7 -> 0.17408865
A8: 45838 | B8: =G49 -> 28000 | C8: =IFERROR(B8/Q8,0) -> 0.3732338 | D8: =IFERROR(B8/R8,0) -> 0.016341862 | E8: =VLOOKUP($A8,'m2'!$A:$H,2,0) -> 0.05 | F8: =F49 -> 0.625 | G8: =F48 -> 0.5 | H8: =VLOOKUP($A8,'m2'!$A:$H,3,0) -> 0.79 | I8: =VLOOKUP($A8,'m2'!$A:$H,4,0) -> 32 | J8: =IFERROR(I8/I7-1,"-") -> -0.17948718 | K8: =Z25 -> 147 | L8: =IFERROR(K8/K7-1,"-") -> -0.057692308 | M8: =Y25 -> 8 | N8: =VLOOKUP($A8,'m2'!$A:$H,5,0) -> 126 | O8: =VLOOKUP($A8,'m2'!$A:$H,6,0) -> 0.69 | P8: =VLOOKUP($A8,'m2'!$A:$H,7,0) -> 2344 | Q8: =VLOOKUP($A8,'m2'!$A:$H,8,0) -> 75020 | R8: =VLOOKUP(A8,total!A:B,2,0) -> 1713391
A9: 45845 | B9: =G55 -> 16600 | C9: =IFERROR(B9/Q9,0) -> 0.30736756 | D9: =IFERROR(B9/R9,0) -> 0.0093545264 | E9: =VLOOKUP($A9,'m2'!$A:$H,2,0) -> 0.11 | F9: =F55 -> 0.8 | G9: =F54 -> 0.4 | H9: =VLOOKUP($A9,'m2'!$A:$H,3,0) -> 0.61 | I9: =VLOOKUP($A9,'m2'!$A:$H,4,0) -> 21 | J9: =IFERROR(I9/I8-1,"-") -> -0.34375 | K9: =AC21 -> 89 | L9: =IFERROR(K9/K8-1,"-") -> -0.39455782 | M9: =AB21 -> 5 | N9: =VLOOKUP($A9,'m2'!$A:$H,5,0) -> 81 | O9: =VLOOKUP($A9,'m2'!$A:$H,6,0) -> 0.67 | P9: =VLOOKUP($A9,'m2'!$A:$H,7,0) -> 2572 | Q9: =VLOOKUP($A9,'m2'!$A:$H,8,0) -> 54007 | R9: =VLOOKUP(A9,total!A:B,2,0) -> 1774542
A10: 45852 | B10: =G61 -> 12000 | C10: =IFERROR(B10/Q10,0) -> 0.33629459 | D10: =IFERROR(B10/R10,0) -> 0.0068200612 | E10: =VLOOKUP($A10,'m2'!$A:$H,2,0) -> 0.11 | F10: =F61 -> 1 | G10: =F60 -> 1 | H10: =VLOOKUP($A10,'m2'!$A:$H,3,0) -> 0.81 | I10: =VLOOKUP($A10,'m2'!$A:$H,4,0) -> 13 | J10: =IFERROR(I10/I9-1,"-") -> -0.38095238 | K10: =AF19 -> 42 | L10: =IFERROR(K10/K9-1,"-") -> -0.52808989 | M10: =AE19 -> 2 | N10: =VLOOKUP($A10,'m2'!$A:$H,5,0) -> 57 | O10: =VLOOKUP($A10,'m2'!$A:$H,6,0) -> 0.75 | P10: =VLOOKUP($A10,'m2'!$A:$H,7,0) -> 2745 | Q10: =VLOOKUP($A10,'m2'!$A:$H,8,0) -> 35683 | R10: =VLOOKUP(A10,total!A:B,2,0) -> 1759515
A11: 45859 | B11: =G67 -> 12300 | C11: =IFERROR(B11/Q11,0) -> 0.45540375 | D11: =IFERROR(B11/R11,0) -> 0.0069708962 | E11: =VLOOKUP($A11,'m2'!$A:$H,2,0) -> 0.14 | F11: =F67 -> 0.6 | G11: =F66 -> 0.2 | H11: =VLOOKUP($A11,'m2'!$A:$H,3,0) -> 0.67 | I11: =VLOOKUP($A11,'m2'!$A:$H,4,0) -> 11 | J11: =IFERROR(I11/I10-1,"-") -> -0.15384615 | K11: =AI22 -> 62 | L11: =IFERROR(K11/K10-1,"-") -> 0.47619048 | M11: =AH22 -> 5 | N11: =VLOOKUP($A11,'m2'!$A:$H,5,0) -> 55 | O11: =VLOOKUP($A11,'m2'!$A:$H,6,0) -> 0.74 | P11: =VLOOKUP($A11,'m2'!$A:$H,7,0) -> 2455 | Q11: =VLOOKUP($A11,'m2'!$A:$H,8,0) -> 27009 | R11: =VLOOKUP(A11,total!A:B,2,0) -> 1764479
A12: 45866 | B12: =G73 -> 22000 | C12: =IFERROR(B12/Q12,0) -> 0.31854051 | D12: =IFERROR(B12/R12,0) -> 0.013859027 | E12: =VLOOKUP($A12,'m2'!$A:$H,2,0) -> 0.12 | F12: =F73 -> 0.66666667 | G12: =F72 -> 0.5 | H12: =VLOOKUP($A12,'m2'!$A:$H,3,0) -> 0.68 | I12: =VLOOKUP($A12,'m2'!$A:$H,4,0) -> 28 | J12: =IFERROR(I12/I11-1,"-") -> 1.5454545 | K12: =AL23 -> 130 | L12: =IFERROR(K12/K11-1,"-") -> 1.0967742 | M12: =AK23 -> 6 | N12: =VLOOKUP($A12,'m2'!$A:$H,5,0) -> 108 | O12: =VLOOKUP($A12,'m2'!$A:$H,6,0) -> 0.66 | P12: =VLOOKUP($A12,'m2'!$A:$H,7,0) -> 2467 | Q12: =VLOOKUP($A12,'m2'!$A:$H,8,0) -> 69065 | R12: =VLOOKUP(A12,total!A:B,2,0) -> 1587413
A15: dxgy M2 as is 12.05 (старые цели) | B15: вручений | C15: бонус | D15: доплата за вручение | E15: водители на ступени | F15: SR | G15: Затраты | I15: Доходимость M2 с 12.05 | L15: Доходимость M2 с 02.06 | O15: Доходимость M2 с 09.06 | R15: Доходимость M2 с 16.06 | U15: Доходимость M2 с 23.06 | X15: Доходимость M2 с 30.06 | AA15: Доходимость M2 с 07.07 | AD15: Доходимость M2 с 14.07 | AG15: Доходимость M2 с 21.07 | AJ15: Доходимость M2 с 28.07
B16: 10 | C16: 1600 | D16: =C16/B16 -> 160 | E16: 1 | F16: =E16/$J$27 -> 0.076923077 | G16: =C16*E16 -> 1600 | I16: COUNTA из order_id | J16: COUNTA из executor_profile_id | L16: Итого | M16: COUNTA из executor_profile_id
B17: 15 | C17: 3200 | D17: =C17/B17 -> 213.33333 | E17: 0 | F17: =E17/$J$27 -> 0 | G17: =C17*E17 -> 0 | I17: 1 | J17: 2 | L17: 1 | M17: 1
B18: 20 | C18: 5600 | D18: =C18/B18 -> 280 | E18: 2 | F18: =E18/$J$27 -> 0.15384615 | G18: =C18*E18 -> 11200 | I18: 2 | J18: 1 | L18: 2 | M18: 1
E19: Всего: | F19: =SUM(F16:F18) -> 0.23076923 | G19: =SUM(G16:G18) -> 12800 | I19: 3 | J19: 2 | L19: 3 | M19: 1 | AF19: {=SUMPRODUCT(AD17:AD18,AE17:AE18)} -> 42
I20: 4 | J20: 1 | L20: 17 | M20: 1
A21: dxgy M2 as is 02.06 (1 неделя) | B21: вручений | C21: бонус | D21: доплата за вручение | E21: водители на ступени | F21: SR | G21: Затраты | I21: 5 | J21: 2 | L21: 22 | M21: 1 | AC21: {=SUMPRODUCT(AA17:AA20,AB17:AB20)} -> 89
B22: 10 | C22: 2300 | D22: =C22/B22 -> 230 | E22: 0 | F22: =E22/$M$22 -> 0 | G22: =C22*E22 -> 0 | I22: 6 | J22: 1 | L22: Итого | M22: 5 | N22: {=SUMPRODUCT(L17:L21,M17:M21)} -> 45 | AI22: {=SUMPRODUCT(AG17:AG21,AH17:AH21)} -> 62
B23: 15 | C23: 4000 | D23: =C23/B23 -> 266.66667 | E23: 1 | F23: =E23/$M$22 -> 0.2 | G23: =C23*E23 -> 4000 | I23: 9 | J23: 1 | Q23: {=SUMPRODUCT(O17:O22,P17:P22)} -> 67 | T23: {=SUMPRODUCT(R17:R22,S17:S22)} -> 54 | AL23: {=SUMPRODUCT(AJ15:AJ22,AK15:AK22)} -> 130
B24: 20 | C24: 6000 | D24: =C24/B24 -> 300 | E24: 1 | F24: =E24/$M$22 -> 0.2 | G24: =C24*E24 -> 6000 | I24: 11 | J24: 1 | W24: {=SUMPRODUCT(U17:U23,V17:V23)} -> 156
E25: Всего: | F25: =SUM(F22:F24) -> 0.4 | G25: =SUM(G22:G24) -> 10000 | I25: 21 | J25: 1 | Z25: {=SUMPRODUCT(X17:X24,Y17:Y24)} -> 147
I26: 41 | J26: 1
A27: dxgy M2 as is 09.06 (2 неделя) | B27: вручений | C27: бонус | D27: доплата за вручение | E27: водители на ступени | F27: SR | G27: Затраты | I27: Итого | J27: 13 | K27: {=SUMPRODUCT(I17:I26,J17:J26)} -> 112
B28: 10 | C28: 2300 | D28: =C28/B28 -> 230 | E28: 1 | F28: =E28/$P$23 -> 0.14285714 | G28: =C28*E28 -> 2300
B29: 15 | C29: 4000 | D29: =C29/B29 -> 266.66667 | E29: 0 | F29: =E29/$P$23 -> 0 | G29: =C29*E29 -> 0
B30: 20 | C30: 6000 | D30: =C30/B30 -> 300 | E30: 1 | F30: =E30/$P$23 -> 0.14285714 | G30: =C30*E30 -> 6000
E31: Всего: | F31: =SUM(F28:F30) -> 0.28571429 | G31: =SUM(G28:G30) -> 8300
A33: dxgy M2 as is 16.06 (3 неделя) | B33: вручений | C33: бонус | D33: доплата за вручение | E33: водители на ступени | F33: SR | G33: Затраты
B34: 10 | C34: 2300 | D34: =C34/B34 -> 230 | E34: 1 | F34: =E34/$S$23 -> 0.14285714 | G34: =C34*E34 -> 2300
B35: 15 | C35: 4000 | D35: =C35/B35 -> 266.66667 | E35: 1 | F35: =E35/$S$23 -> 0.14285714 | G35: =C35*E35 -> 4000
B36: 20 | C36: 6000 | D36: =C36/B36 -> 300 | E36: 0 | F36: =E36/$S$23 -> 0 | G36: =C36*E36 -> 0
E37: Всего: | F37: =SUM(F34:F36) -> 0.28571429 | G37: =SUM(G34:G36) -> 6300
A39: dxgy M2 as is 23.06 (4 неделя) | B39: вручений | C39: бонус | D39: доплата за вручение | E39: водители на ступени | F39: SR | G39: Затраты
B40: 10 | C40: 2300 | D40: =C40/B40 -> 230 | E40: 0 | F40: =E40/$V$24 -> 0 | G40: =C40*E40 -> 0
B41: 15 | C41: 4000 | D41: =C41/B41 -> 266.66667 | E41: 0 | F41: =E41/$V$24 -> 0 | G41: =C41*E41 -> 0
B42: 20 | C42: 6000 | D42: =C42/B42 -> 300 | E42: 5 | F42: =E42/$V$24 -> 0.625 | G42: =C42*E42 -> 30000
E43: Всего: | F43: =SUM(F40:F42) -> 0.625 | G43: =SUM(G40:G42) -> 30000
A45: dxgy M2 as is 30.06 (5 неделя) | B45: вручений | C45: бонус | D45: доплата за вручение | E45: водители на ступени | F45: SR | G45: Затраты
B46: 10 | C46: 2300 | D46: =C46/B46 -> 230 | E46: 0 | F46: =E46/$Y$25 -> 0 | G46: =C46*E46 -> 0
B47: 15 | C47: 4000 | D47: =C47/B47 -> 266.66667 | E47: 1 | F47: =E47/$Y$25 -> 0.125 | G47: =C47*E47 -> 4000
B48: 20 | C48: 6000 | D48: =C48/B48 -> 300 | E48: 4 | F48: =E48/$Y$25 -> 0.5 | G48: =C48*E48 -> 24000
E49: Всего: | F49: =SUM(F46:F48) -> 0.625 | G49: =SUM(G46:G48) -> 28000
A51: dxgy M2 as is 07.07 (6 неделя) | B51: вручений | C51: бонус | D51: доплата за вручение | E51: водители на ступени | F51: SR | G51: Затраты
B52: 10 | C52: 2300 | D52: =C52/B52 -> 230 | E52: 2 | F52: =E52/$AB$21 -> 0.4 | G52: =C52*E52 -> 4600
B53: 15 | C53: 4000 | D53: =C53/B53 -> 266.66667 | E53: 0 | F53: =E53/$AB$21 -> 0 | G53: =C53*E53 -> 0
B54: 20 | C54: 6000 | D54: =C54/B54 -> 300 | E54: 2 | F54: =E54/$AB$21 -> 0.4 | G54: =C54*E54 -> 12000
E55: Всего: | F55: =SUM(F52:F54) -> 0.8 | G55: =SUM(G52:G54) -> 16600
A57: dxgy M2 as is 14.07 (7 неделя) | B57: вручений | C57: бонус | D57: доплата за вручение | E57: водители на ступени | F57: SR | G57: Затраты
B58: 10 | C58: 2300 | D58: =C58/B58 -> 230 | E58: 0 | F58: =E58/$AE$19 -> 0 | G58: =C58*E58 -> 0
B59: 15 | C59: 4000 | D59: =C59/B59 -> 266.66667 | E59: 0 | F59: =E59/$AE$19 -> 0 | G59: =C59*E59 -> 0
B60: 20 | C60: 6000 | D60: =C60/B60 -> 300 | E60: 2 | F60: =E60/$AE$19 -> 1 | G60: =C60*E60 -> 12000
E61: Всего: | F61: =SUM(F58:F60) -> 1 | G61: =SUM(G58:G60) -> 12000
A63: dxgy M2 as is 21.07 (8 неделя) | B63: вручений | C63: бонус | D63: доплата за вручение | E63: водители на ступени | F63: SR | G63: Затраты
B64: 10 | C64: 2300 | D64: =C64/B64 -> 230 | E64: 1 | F64: =E64/5 -> 0.2 | G64: =C64*E64 -> 2300
B65: 15 | C65: 4000 | D65: =C65/B65 -> 266.66667 | E65: 1 | F65: =E65/5 -> 0.2 | G65: =C65*E65 -> 4000
B66: 20 | C66: 6000 | D66: =C66/B66 -> 300 | E66: 1 | F66: =E66/5 -> 0.2 | G66: =C66*E66 -> 6000
E67: Всего: | F67: =SUM(F64:F66) -> 0.6 | G67: =SUM(G64:G66) -> 12300
A69: dxgy M2 as is 28.07 (9 неделя) | B69: вручений | C69: бонус | D69: доплата за вручение | E69: водители на ступени | F69: SR | G69: Затраты
B70: 10 | C70: 2300 | D70: =C70/B70 -> 230 | E70: 0 | F70: =E70/$M$12 -> 0 | G70: =C70*E70 -> 0
B71: 15 | C71: 4000 | D71: =C71/B71 -> 266.66667 | E71: 1 | F71: =E71/$M$12 -> 0.16666667 | G71: =C71*E71 -> 4000
B72: 20 | C72: 6000 | D72: =C72/B72 -> 300 | E72: 3 | F72: =E72/$M$12 -> 0.5 | G72: =C72*E72 -> 18000
E73: Всего: | F73: =SUM(F70:F72) -> 0.66666667 | G73: =SUM(G70:G72) -> 22000
A75: dxgy M2 as is 04.08 (1 неделя) | B75: вручений | C75: бонус | D75: доплата за вручение | E75: водители на ступени | F75: SR | G75: Затраты | I75: to be | J75: вручений | K75: бонус | L75: доплата за вручение | M75: водители на ступени | N75: SR | O75: Затраты
B76: 10 | C76: 2500 | D76: =C76/B76 -> 250 | F76: =E76/5 -> 0 | G76: =C76*E76 -> 0 | J76: 12 | K76: 3000 | L76: =K76/J76 -> 250 | M76: 0 | N76: =M76/$M$12 -> 0 | O76: =K76*M76 -> 0
B77: 15 | C77: 4500 | D77: =C77/B77 -> 300 | F77: =E77/5 -> 0 | G77: =C77*E77 -> 0 | J77: 18 | K77: 5000 | L77: =K77/J77 -> 277.77778 | M77: 1 | N77: =M77/$M$12 -> 0.16666667 | O77: =K77*M77 -> 5000
B78: 20 | C78: 6500 | D78: =C78/B78 -> 325 | F78: =E78/5 -> 0 | G78: =C78*E78 -> 0 | J78: 24 | K78: 7500 | L78: =K78/J78 -> 312.5 | M78: 3 | N78: =M78/$M$12 -> 0.5 | O78: =K78*M78 -> 22500
E79: Всего: | F79: =SUM(F76:F78) -> 0 | G79: =SUM(G76:G78) -> 0 | M79: Всего: | N79: =SUM(N76:N78) -> 0.66666667 | O79: =SUM(O76:O78) -> 27500
A81: https://datalens.yandex-team.ru/am8u3uq2e7ow2-cancels-corporate-clients-c2c?tab=p8&state=7572b9802704 | B81: M0 | G81: M1 | L81: M2

Sheet L кузов (ПН)
B1: Расходы на цели L без отсева | F1: Метрики L
A2: Неделя | B2: sub dxgy | C2: sub dxgy / gmv опции | D2: sub dxgy / gmv total | E2: NI / GMV опции | F2: SR | G2: SR 3 ступени | H2: CDR | I2: Com_del | J2: WoW | K2: Доставки водителей | L2: WoW | M2: Водители | N2: SH active | O2: Utilization | P2: AVG Fare | Q2: GMV | R2: GMV total
A3: 45796 | B3: 0 | C3: =IFERROR(B3/Q3,0) -> 0 | D3: =IFERROR(B3/R3,0) -> 0 | E3: =VLOOKUP($A3,l!$A:$H,2,0) -> 0.17 | F3: =F19 -> 0.34042553 | G3: =F18 -> 0.063829787 | H3: =VLOOKUP($A3,l!$A:$H,3,0) -> 0.77 | I3: =VLOOKUP($A3,l!$A:$H,4,0) -> 259 | J3: =IFERROR(I3/#REF!-1,"-") -> - | K3: =K35 -> 395 | L3: =IFERROR(K3/#REF!-1,"-") -> - | M3: =J35 -> 47 | N3: =VLOOKUP($A3,l!$A:$H,5,0) -> 360 | O3: =VLOOKUP($A3,l!$A:$H,6,0) -> 0.6 | P3: =VLOOKUP($A3,l!$A:$H,7,0) -> 1388 | Q3: =VLOOKUP($A3,l!$A:$H,8,0) -> 359478 | R3: =VLOOKUP(A3,total!A:B,2,0) -> 1880629
A4: 45810 | B4: =G25 -> 89000 | C4: =IFERROR(B4/Q4,0) -> 0.22926031 | D4: =IFERROR(B4/R4,0) -> 0.04488937 | E4: =VLOOKUP($A4,l!$A:$H,2,0) -> 0.1 | F4: =F25 -> 0.46153846 | G4: =F24 -> 0.20512821 | H4: =VLOOKUP($A4,l!$A:$H,3,0) -> 0.78 | I4: =VLOOKUP($A4,l!$A:$H,4,0) -> 276 | J4: =IFERROR(I4/I3-1,"-") -> 0.065637066 | K4: =N36 -> 417 | L4: =IFERROR(K4/K3-1,"-") -> 0.055696203 | M4: =M36 -> 39 | N4: =VLOOKUP($A4,l!$A:$H,5,0) -> 332 | O4: =VLOOKUP($A4,l!$A:$H,6,0) -> 0.59 | P4: =VLOOKUP($A4,l!$A:$H,7,0) -> 1407 | Q4: =VLOOKUP($A4,l!$A:$H,8,0) -> 388205 | R4: =VLOOKUP(A4,total!A:B,2,0) -> 1982652
A5: 45817 | B5: =G31 -> 63000 | C5: =IFERROR(B5/Q5,0) -> 0.19979386 | D5: =IFERROR(B5/R5,0) -> 0.038918077 | E5: =VLOOKUP($A5,l!$A:$H,2,0) -> 0.13 | F5: =F31 -> 0.37837838 | G5: =F30 -> 0.16216216 | H5: =VLOOKUP($A5,l!$A:$H,3,0) -> 0.65 | I5: =VLOOKUP($A5,l!$A:$H,4,0) -> 222 | J5: =IFERROR(I5/I4-1,"-") -> -0.19565217 | K5: =Q35 -> 365 | L5: =IFERROR(K5/K4-1,"-") -> -0.12470024 | M5: =P35 -> 37 | N5: =VLOOKUP($A5,l!$A:$H,5,0) -> 270 | O5: =VLOOKUP($A5,l!$A:$H,6,0) -> 0.62 | P5: =VLOOKUP($A5,l!$A:$H,7,0) -> 1420 | Q5: =VLOOKUP($A5,l!$A:$H,8,0) -> 315325 | R5: =VLOOKUP(A5,total!A:B,2,0) -> 1618785
A6: 45824 | B6: =G37 -> 75000 | C6: =IFERROR(B6/Q6,0) -> 0.20231666 | D6: =IFERROR(B6/R6,0) -> 0.042239029 | E6: =VLOOKUP($A6,l!$A:$H,2,0) -> 0.1 | F6: =F37 -> 0.43902439 | G6: =F36 -> 0.097560976 | H6: =VLOOKUP($A6,l!$A:$H,3,0) -> 0.85 | I6: =VLOOKUP($A6,l!$A:$H,4,0) -> 247 | J6: =IFERROR(I6/I5-1,"-") -> 0.11261261 | K6: =T35 -> 383 | L6: =IFERROR(K6/K5-1,"-") -> 0.049315068 | M6: =S35 -> 41 | N6: =VLOOKUP($A6,l!$A:$H,5,0) -> 304 | O6: =VLOOKUP($A6,l!$A:$H,6,0) -> 0.53 | P6: =VLOOKUP($A6,l!$A:$H,7,0) -> 1501 | Q6: =VLOOKUP($A6,l!$A:$H,8,0) -> 370706 | R6: =VLOOKUP(A6,total!A:B,2,0) -> 1775609 | S6: gmv водителей L | T6: sub/gmv
A7: 45831 | B7: =G43 -> 70500 | C7: =IFERROR(B7/Q7,0) -> 0.21265942 | D7: =IFERROR(B7/R7,0) -> 0.043117473 | E7: =VLOOKUP($A7,l!$A:$H,2,0) -> 0.07 | F7: =F43 -> 0.425 | G7: =F42 -> 0.15 | H7: =VLOOKUP($A7,l!$A:$H,3,0) -> 0.76 | I7: =VLOOKUP($A7,l!$A:$H,4,0) -> 232 | J7: =IFERROR(I7/I6-1,"-") -> -0.060728745 | K7: =W37 -> 382 | L7: =IFERROR(K7/K6-1,"-") -> -0.0026109661 | M7: =V37 -> 40 | N7: =VLOOKUP($A7,l!$A:$H,5,0) -> 315 | O7: =VLOOKUP($A7,l!$A:$H,6,0) -> 0.55 | P7: =VLOOKUP($A7,l!$A:$H,7,0) -> 1429 | Q7: =VLOOKUP($A7,l!$A:$H,8,0) -> 331516 | R7: =VLOOKUP(A7,total!A:B,2,0) -> 1635068 | S7: 484036.99 | T7: =B7/S7 -> 0.14565003
A8: 45838 | B8: =G49 -> 57000 | C8: =IFERROR(B8/Q8,0) -> 0.15751644 | D8: =IFERROR(B8/R8,0) -> 0.033267363 | E8: =VLOOKUP($A8,l!$A:$H,2,0) -> 0.08 | F8: =F49 -> 0.28 | G8: =F48 -> 0.1 | H8: =VLOOKUP($A8,l!$A:$H,3,0) -> 0.71 | I8: =VLOOKUP($A8,l!$A:$H,4,0) -> 243 | J8: =IFERROR(I8/I7-1,"-") -> 0.047413793 | K8: =Z34 -> 388 | L8: =IFERROR(K8/K7-1,"-") -> 0.015706806 | M8: =Y34 -> 50 | N8: =VLOOKUP($A8,l!$A:$H,5,0) -> 303 | O8: =VLOOKUP($A8,l!$A:$H,6,0) -> 0.61 | P8: =VLOOKUP($A8,l!$A:$H,7,0) -> 1489 | Q8: =VLOOKUP($A8,l!$A:$H,8,0) -> 361867 | R8: =VLOOKUP(A8,total!A:B,2,0) -> 1713391
A9: 45845 | B9: =G55 -> 72000 | C9: =IFERROR(B9/Q9,0) -> 0.22139609 | D9: =IFERROR(B9/R9,0) -> 0.040573849 | E9: =VLOOKUP($A9,l!$A:$H,2,0) -> 0.08 | F9: =F55 -> 0.51612903 | G9: =F54 -> 0.19354839 | H9: =VLOOKUP($A9,l!$A:$H,3,0) -> 0.63 | I9: =VLOOKUP($A9,l!$A:$H,4,0) -> 219 | J9: =IFERROR(I9/I8-1,"-") -> -0.098765432 | K9: =AC37 -> 360 | L9: =IFERROR(K9/K8-1,"-") -> -0.072164948 | M9: =AB37 -> 31 | N9: =VLOOKUP($A9,l!$A:$H,5,0) -> 286 | O9: =VLOOKUP($A9,l!$A:$H,6,0) -> 0.72 | P9: =VLOOKUP($A9,l!$A:$H,7,0) -> 1485 | Q9: =VLOOKUP($A9,l!$A:$H,8,0) -> 325209 | R9: =VLOOKUP(A9,total!A:B,2,0) -> 1774542
A10: 45852 | B10: =G61 -> 74500 | C10: =IFERROR(B10/Q10,0) -> 0.23469963 | D10: =IFERROR(B10/R10,0) -> 0.042341213 | E10: =VLOOKUP($A10,l!$A:$H,2,0) -> 0.09 | F10: =F61 -> 0.51515152 | G10: =F60 -> 0.12121212 | H10: =VLOOKUP($A10,l!$A:$H,3,0) -> 0.72 | I10: =VLOOKUP($A10,l!$A:$H,4,0) -> 228 | J10: =IFERROR(I10/I9-1,"-") -> 0.04109589 | K10: =AF35 -> 343 | L10: =IFERROR(K10/K9-1,"-") -> -0.047222222 | M10: =AE35 -> 33 | N10: =VLOOKUP($A10,l!$A:$H,5,0) -> 273 | O10: =VLOOKUP($A10,l!$A:$H,6,0) -> 0.63 | P10: =VLOOKUP($A10,l!$A:$H,7,0) -> 1392 | Q10: =VLOOKUP($A10,l!$A:$H,8,0) -> 317427 | R10: =VLOOKUP(A10,total!A:B,2,0) -> 1759515
A11: 45859 | B11: =G67 -> 83000 | C11: =IFERROR(B11/Q11,0) -> 0.23502827 | D11: =IFERROR(B11/R11,0) -> 0.047039381 | E11: =VLOOKUP($A11,l!$A:$H,2,0) -> 0.11 | F11: =F67 -> 0.55 | G11: =F66 -> 0.125 | H11: =VLOOKUP($A11,l!$A:$H,3,0) -> 0.66 | I11: =VLOOKUP($A11,l!$A:$H,4,0) -> 244 | J11: =IFERROR(I11/I10-1,"-") -> 0.070175439 | K11: =AI39 -> 432 | L11: =IFERROR(K11/K10-1,"-") -> 0.25947522 | M11: =AH39 -> 40 | N11: =VLOOKUP($A11,l!$A:$H,5,0) -> 318 | O11: =VLOOKUP($A11,l!$A:$H,6,0) -> 0.66 | P11: =VLOOKUP($A11,l!$A:$H,7,0) -> 1447 | Q11: =VLOOKUP($A11,l!$A:$H,8,0) -> 353149 | R11: =VLOOKUP(A11,total!A:B,2,0) -> 1764479
A12: 45866 | B12: =G73 -> 74500 | C12: =IFERROR(B12/Q12,0) -> 0.24870224 | D12: =IFERROR(B12/R12,0) -> 0.046931706 | E12: =VLOOKUP($A12,l!$A:$H,2,0) -> 0.11 | F12: =F73 -> 0.425 | G12: =F72 -> 0.175 | H12: =VLOOKUP($A12,l!$A:$H,3,0) -> 0.75 | I12: =VLOOKUP($A12,l!$A:$H,4,0) -> 202 | J12: =IFERROR(I12/I11-1,"-") -> -0.17213115 | K12: =AL33 -> 353 | L12: =IFERROR(K12/K11-1,"-") -> -0.18287037 | M12: =AK33 -> 37 | N12: =VLOOKUP($A12,l!$A:$H,5,0) -> 278 | O12: =VLOOKUP($A12,l!$A:$H,6,0) -> 0.67 | P12: =VLOOKUP($A12,l!$A:$H,7,0) -> 1483 | Q12: =VLOOKUP($A12,l!$A:$H,8,0) -> 299555 | R12: =VLOOKUP(A12,total!A:B,2,0) -> 1587413
A15: dxgy L as is 19.05 (до запуска) | B15: вручений | C15: бонус | D15: доплата за вручение | E15: водители на ступени | F15: SR | I15: Доходимость L с 19.05 | L15: Доходимость L с 02.06 | O15: Доходимость L с 09.06 | R15: Доходимость L с 16.06 | U15: Доходимость L с 23.06 | X15: Доходимость L с 30.06 | AA15: Доходимость L с 07.07 | AD15: Доходимость L с 14.07 | AG15: Доходимость L с 21.07 | AJ15: Доходимость L с 28.07
B16: 10 | E16: 9 | F16: =E16/$J$35 -> 0.19148936 | I16: COUNTA из order_id | J16: COUNTA из executor_profile_id
B17: 15 | E17: 4 | F17: =E17/$J$35 -> 0.085106383 | I17: 1 | J17: 5
B18: 20 | E18: 3 | F18: =E18/$J$35 -> 0.063829787 | I18: 2 | J18: 5
E19: Всего: | F19: =SUM(F16:F18) -> 0.34042553 | I19: 4 | J19: 1
I20: 5 | J20: 5
A21: dxgy L as is 02.06 (1 неделя) | B21: вручений | C21: бонус | D21: доплата за вручение | E21: водители на ступени | F21: SR | G21: Затраты | I21: 6 | J21: 3
B22: 10 | C22: 2500 | D22: =C22/B22 -> 250 | E22: 4 | F22: =E22/$M$36 -> 0.1025641 | G22: =C22*E22 -> 10000 | I22: 7 | J22: 4
B23: 15 | C23: 4500 | D23: =C23/B23 -> 300 | E23: 6 | F23: =E23/$M$36 -> 0.15384615 | G23: =C23*E23 -> 27000 | I23: 8 | J23: 4
B24: 20 | C24: 6500 | D24: =C24/B24 -> 325 | E24: 8 | F24: =E24/$M$36 -> 0.20512821 | G24: =C24*E24 -> 52000 | I24: 9 | J24: 4
E25: Всего: | F25: =SUM(F22:F24) -> 0.46153846 | G25: =SUM(G22:G24) -> 89000 | I25: 10 | J25: 3
I26: 11 | J26: 2
A27: dxgy L as is 09.06 (2 неделя) | B27: вручений | C27: бонус | D27: доплата за вручение | E27: водители на ступени | F27: SR | G27: Затраты | I27: 12 | J27: 1
B28: 10 | C28: 2500 | D28: =C28/B28 -> 250 | E28: 6 | F28: =E28/$P$35 -> 0.16216216 | G28: =C28*E28 -> 15000 | I28: 13 | J28: 1
B29: 15 | C29: 4500 | D29: =C29/B29 -> 300 | E29: 2 | F29: =E29/$P$35 -> 0.054054054 | G29: =C29*E29 -> 9000 | I29: 14 | J29: 2
B30: 20 | C30: 6500 | D30: =C30/B30 -> 325 | E30: 6 | F30: =E30/$P$35 -> 0.16216216 | G30: =C30*E30 -> 39000 | I30: 15 | J30: 1
E31: Всего: | F31: =SUM(F28:F30) -> 0.37837838 | G31: =SUM(G28:G30) -> 63000 | I31: 16 | J31: 1
I32: 17 | J32: 2
A33: dxgy L as is 16.06 (3 неделя) | B33: вручений | C33: бонус | D33: доплата за вручение | E33: водители на ступени | F33: SR | G33: Затраты | I33: 20 | J33: 2 | AL33: {=SUMPRODUCT(AJ15:AJ32,AK15:AK32)} -> 353
B34: 10 | C34: 2500 | D34: =C34/B34 -> 250 | E34: 7 | F34: =E34/$S$35 -> 0.17073171 | G34: =C34*E34 -> 17500 | I34: 27 | J34: 1 | Z34: {=SUMPRODUCT(X17:X33,Y17:Y33)} -> 388
B35: 15 | C35: 4500 | D35: =C35/B35 -> 300 | E35: 7 | F35: =E35/$S$35 -> 0.17073171 | G35: =C35*E35 -> 31500 | I35: Итого | J35: 47 | K35: {=SUMPRODUCT(I17:I34,J17:J34)} -> 395 | Q35: {=SUMPRODUCT(O17:O34,P17:P34)} -> 365 | T35: {=SUMPRODUCT(R17:R34,S17:S34)} -> 383 | AF35: {=SUMPRODUCT(AD17:AD34,AE17:AE34)} -> 343
B36: 20 | C36: 6500 | D36: =C36/B36 -> 325 | E36: 4 | F36: =E36/$S$35 -> 0.097560976 | G36: =C36*E36 -> 26000 | N36: {=SUMPRODUCT(L17:L35,M17:M35)} -> 417
E37: Всего: | F37: =SUM(F34:F36) -> 0.43902439 | G37: =SUM(G34:G36) -> 75000 | W37: {=SUMPRODUCT(U17:U36,V17:V36)} -> 382 | AC37: {=SUMPRODUCT(AA17:AA36,AB17:AB36)} -> 360
A39: dxgy L as is 23.06 (4 неделя) | B39: вручений | C39: бонус | D39: доплата за вручение | E39: водители на ступени | F39: SR | G39: Затраты | AI39: {=SUMPRODUCT(AG17:AG38,AH17:AH38)} -> 432
B40: 10 | C40: 2500 | D40: =C40/B40 -> 250 | E40: 9 | F40: =E40/$V$37 -> 0.225 | G40: =C40*E40 -> 22500
B41: 15 | C41: 4500 | D41: =C41/B41 -> 300 | E41: 2 | F41: =E41/$V$37 -> 0.05 | G41: =C41*E41 -> 9000
B42: 20 | C42: 6500 | D42: =C42/B42 -> 325 | E42: 6 | F42: =E42/$V$37 -> 0.15 | G42: =C42*E42 -> 39000
E43: Всего: | F43: =SUM(F40:F42) -> 0.425 | G43: =SUM(G40:G42) -> 70500
A45: dxgy L as is 30.06 (5 неделя) | B45: вручений | C45: бонус | D45: доплата за вручение | E45: водители на ступени | F45: SR | G45: Затраты
B46: 10 | C46: 2500 | D46: =C46/B46 -> 250 | E46: 8 | F46: =E46/$Y$34 -> 0.16 | G46: =C46*E46 -> 20000
B47: 15 | C47: 4500 | D47: =C47/B47 -> 300 | E47: 1 | F47: =E47/$Y$34 -> 0.02 | G47: =C47*E47 -> 4500
B48: 20 | C48: 6500 | D48: =C48/B48 -> 325 | E48: 5 | F48: =E48/$Y$34 -> 0.1 | G48: =C48*E48 -> 32500
E49: Всего: | F49: =SUM(F46:F48) -> 0.28 | G49: =SUM(G46:G48) -> 57000
A51: dxgy L as is 07.07 (6 неделя) | B51: вручений | C51: бонус | D51: доплата за вручение | E51: водители на ступени | F51: SR | G51: Затраты
B52: 10 | C52: 2500 | D52: =C52/B52 -> 250 | E52: 6 | F52: =E52/$AB$37 -> 0.19354839 | G52: =C52*E52 -> 15000
B53: 15 | C53: 4500 | D53: =C53/B53 -> 300 | E53: 4 | F53: =E53/$AB$37 -> 0.12903226 | G53: =C53*E53 -> 18000
B54: 20 | C54: 6500 | D54: =C54/B54 -> 325 | E54: 6 | F54: =E54/$AB$37 -> 0.19354839 | G54: =C54*E54 -> 39000
E55: Всего: | F55: =SUM(F52:F54) -> 0.51612903 | G55: =SUM(G52:G54) -> 72000
A57: dxgy L as is 14.07 (7 неделя) | B57: вручений | C57: бонус | D57: доплата за вручение | E57: водители на ступени | F57: SR | G57: Затраты
B58: 10 | C58: 2500 | D58: =C58/B58 -> 250 | E58: 5 | F58: =E58/$AE$35 -> 0.15151515 | G58: =C58*E58 -> 12500
B59: 15 | C59: 4500 | D59: =C59/B59 -> 300 | E59: 8 | F59: =E59/$AE$35 -> 0.24242424 | G59: =C59*E59 -> 36000
B60: 20 | C60: 6500 | D60: =C60/B60 -> 325 | E60: 4 | F60: =E60/$AE$35 -> 0.12121212 | G60: =C60*E60 -> 26000
E61: Всего: | F61: =SUM(F58:F60) -> 0.51515152 | G61: =SUM(G58:G60) -> 74500
A63: dxgy L as is 21.07 (8 неделя) | B63: вручений | C63: бонус | D63: доплата за вручение | E63: водители на ступени | F63: SR | G63: Затраты
B64: 10 | C64: 2500 | D64: =C64/B64 -> 250 | E64: 13 | F64: =E64/40 -> 0.325 | G64: =C64*E64 -> 32500
B65: 15 | C65: 4500 | D65: =C65/B65 -> 300 | E65: 4 | F65: =E65/40 -> 0.1 | G65: =C65*E65 -> 18000
B66: 20 | C66: 6500 | D66: =C66/B66 -> 325 | E66: 5 | F66: =E66/40 -> 0.125 | G66: =C66*E66 -> 32500
E67: Всего: | F67: =SUM(F64:F66) -> 0.55 | G67: =SUM(G64:G66) -> 83000
A69: dxgy L as is 28.07 (9 неделя) | B69: вручений | C69: бонус | D69: доплата за вручение | E69: водители на ступени | F69: SR | G69: Затраты
B70: 10 | C70: 2500 | D70: =C70/B70 -> 250 | E70: 8 | F70: =E70/40 -> 0.2 | G70: =C70*E70 -> 20000
B71: 15 | C71: 4500 | D71: =C71/B71 -> 300 | E71: 2 | F71: =E71/40 -> 0.05 | G71: =C71*E71 -> 9000
B72: 20 | C72: 6500 | D72: =C72/B72 -> 325 | E72: 7 | F72: =E72/40 -> 0.175 | G72: =C72*E72 -> 45500
E73: Всего: | F73: =SUM(F70:F72) -> 0.425 | G73: =SUM(G70:G72) -> 74500
A75: dxgy L as is 04.07 (1 неделя) | B75: вручений | C75: бонус | D75: доплата за вручение | E75: водители на ступени | F75: SR | G75: Затраты
B76: 14 | C76: 3500 | D76: =C76/B76 -> 250 | G76: =C76*E76 -> 0
B77: 19 | C77: 5700 | D77: =C77/B77 -> 300 | G77: =C77*E77 -> 0
B78: 24 | C78: 7800 | D78: =C78/B78 -> 325 | G78: =C78*E78 -> 0
E79: Всего: | F79: =SUM(F76:F78) -> 0 | G79: =SUM(G76:G78) -> 0
A81: https://datalens.yandex-team.ru/am8u3uq2e7ow2-cancels-corporate-clients-c2c?tab=p8&state=7572b9802704 | B81: L0 | G81: L1 | L81: L2 (не работает)

Sheet total
A1: дата | B1: gmv
A2: 45789 | B2: 2004437
A3: 45796 | B3: 1880629
A4: 45810 | B4: 1982652
A5: 45817 | B5: 1618785
A6: 45824 | B6: 1775609
A7: 45831 | B7: 1635068
A8: 45838 | B8: 1713391
A9: 45845 | B9: 1774542
A10: 45852 | B10: 1759515
A11: 45859 | B11: 1764479
A12: 45866 | B12: 1587413

Sheet m2
A1: Неделя | B1: NI/GMV | C1: CDR | D1: Com_del | E1: SH active | F1: Utilization | G1: AVG fare | H1: GMV
A2: 45789 | B2: 0.12 | C2: 0.74 | D2: 38 | E2: 97 | F2: 0.42 | G2: 2484 | H2: 94391
A3: 45810 | B3: 0.11 | C3: 0.59 | D3: 21 | E3: 56 | F3: 0.54 | G3: 2843 | H3: 59703
A4: 45817 | B4: 0.18 | C4: 0.71 | D4: 20 | E4: 86 | F4: 0.66 | G4: 2419 | H4: 48384
A5: 45824 | B5: 0.16 | C5: 0.66 | D5: 30 | E5: 78 | F5: 0.59 | G5: 2933 | H5: 87989
A6: 45831 | B6: 0.04 | C6: 0.79 | D6: 39 | E6: 104 | F6: 0.62 | G6: 2453 | H6: 95662
A7: 45838 | B7: 0.05 | C7: 0.79 | D7: 32 | E7: 126 | F7: 0.69 | G7: 2344 | H7: 75020
A8: 45845 | B8: 0.11 | C8: 0.61 | D8: 21 | E8: 81 | F8: 0.67 | G8: 2572 | H8: 54007
A9: 45852 | B9: 0.11 | C9: 0.81 | D9: 13 | E9: 57 | F9: 0.75 | G9: 2745 | H9: 35683
A10: 45859 | B10: 0.14 | C10: 0.67 | D10: 11 | E10: 55 | F10: 0.74 | G10: 2455 | H10: 27009
A11: 45866 | B11: 0.12 | C11: 0.68 | D11: 28 | E11: 108 | F11: 0.66 | G11: 2467 | H11: 69065

Sheet l
A1: Неделя | B1: NI/GMV | C1: CDR | D1: Com_del | E1: SH active | F1: Utilization | G1: AVG fare | H1: GMV
A2: 45796 | B2: 0.17 | C2: 0.77 | D2: 259 | E2: 360 | F2: 0.6 | G2: 1388 | H2: 359478
A3: 45810 | B3: 0.1 | C3: 0.78 | D3: 276 | E3: 332 | F3: 0.59 | G3: 1407 | H3: 388205
A4: 45817 | B4: 0.13 | C4: 0.65 | D4: 222 | E4: 270 | F4: 0.62 | G4: 1420 | H4: 315325
A5: 45824 | B5: 0.1 | C5: 0.85 | D5: 247 | E5: 304 | F5: 0.53 | G5: 1501 | H5: 370706
A6: 45831 | B6: 0.07 | C6: 0.76 | D6: 232 | E6: 315 | F6: 0.55 | G6: 1429 | H6: 331516
A7: 45838 | B7: 0.08 | C7: 0.71 | D7: 243 | E7: 303 | F7: 0.61 | G7: 1489 | H7: 361867
A8: 45845 | B8: 0.08 | C8: 0.63 | D8: 219 | E8: 286 | F8: 0.72 | G8: 1485 | H8: 325209
A9: 45852 | B9: 0.09 | C9: 0.72 | D9: 228 | E9: 273 | F9: 0.63 | G9: 1392 | H9: 317427
A10: 45859 | B10: 0.11 | C10: 0.66 | D10: 244 | E10: 318 | F10: 0.66 | G10: 1447 | H10: 353149
A11: 45866 | B11: 0.11 | C11: 0.75 | D11: 202 | E11: 278 | F11: 0.67 | G11: 1483 | H11: 299555

Sheet доставки 28.07
A1: local date | B1: order_id | C1: executor_profile_id | D1: cargo size & loaders
A2: 45872 | B2: cargo_5f67b6e1534e47edafd6f235654dfb9b | C2: fe2424fee7c94c7d99e590405d31f4d5 | D2: lcv_m_1 | S2: Опция
A3: 45872 | B3: 1494c9854885c547ae413de483c8edc0 | C3: 531abfae2a844d0e8d849f01764100b3 | D3: lcv_m_0 | S3: =IF(H3>0,"L1",IF(G3>0,"L0",IF(L3>0,"M2",IF(K3>0,"M1",IF(J3>0,"M0",IF(P3>0,"S2",IF(O3>0,"S1","S0"))))))) -> S0
A4: 45872 | B4: cargo_052dfbdba83e42fa8cd125aba26b96bc | C4: ac155a25222e4a39bf30ac55c685de05 | D4: lcv_m_1 | S4: =IF(H4>0,"L1",IF(G4>0,"L0",IF(L4>0,"M2",IF(K4>0,"M1",IF(J4>0,"M0",IF(P4>0,"S2",IF(O4>0,"S1","S0"))))))) -> S0
A5: 45872 | B5: cargo_928ade5ddcd14057b75d71a602531fc9 | C5: 9952efb6ba8640c79b02e19c3e999e59 | D5: van_0 | S5: =IF(H5>0,"L1",IF(G5>0,"L0",IF(L5>0,"M2",IF(K5>0,"M1",IF(J5>0,"M0",IF(P5>0,"S2",IF(O5>0,"S1","S0"))))))) -> M0
A6: 45872 | B6: cargo_50dd2042390c41c58c0415ebb0ccce97 | C6: 9d96a86d8ea74fa3a2925b98429257e6 | D6: lcv_m_0 | S6: =IF(H6>0,"L1",IF(G6>0,"L0",IF(L6>0,"M2",IF(K6>0,"M1",IF(J6>0,"M0",IF(P6>0,"S2",IF(O6>0,"S1","S0"))))))) -> M0
A7: 45872 | B7: cargo_7c2959c87a3140f1987fd78a498f98d7 | C7: d13f74bbcea74f61a462d35d931d636e | D7: lcv_l_0 | S7: =IF(H7>0,"L1",IF(G7>0,"L0",IF(L7>0,"M2",IF(K7>0,"M1",IF(J7>0,"M0",IF(P7>0,"S2",IF(O7>0,"S1","S0"))))))) -> L0
A8: 45872 | B8: cargo_22aa0db23093422390d59b75772c5c5f | C8: 1c732902212440b3803eb1ad755fe065 | D8: lcv_m_0 | S8: =IF(H8>0,"L1",IF(G8>0,"L0",IF(L8>0,"M2",IF(K8>0,"M1",IF(J8>0,"M0",IF(P8>0,"S2",IF(O8>0,"S1","S0"))))))) -> M0
A9: 45872 | B9: cargo_e063083b22b842888350e1901d087fba | C9: 0ace786a3e68478ebddf962774267abc | D9: lcv_l_0 | S9: =IF(H9>0,"L1",IF(G9>0,"L0",IF(L9>0,"M2",IF(K9>0,"M1",IF(J9>0,"M0",IF(P9>0,"S2",IF(O9>0,"S1","S0"))))))) -> L0
A10: 45872 | B10: cargo_3933bca0ea464e7ca15e3311c95c7b31 | C10: 67faba600c584a54b19cb68d7c2b3d2d | D10: lcv_m_1 | S10: =IF(H10>0,"L1",IF(G10>0,"L0",IF(L10>0,"M2",IF(K10>0,"M1",IF(J10>0,"M0",IF(P10>0,"S2",IF(O10>0,"S1","S0"))))))) -> L0
A11: 45872 | B11: cargo_0774a813c9e04882b3737eb813128f31 | C11: 5679ff0c8c8242a39f76eb3af3f98715 | D11: lcv_m_1 | S11: =IF(H11>0,"L1",IF(G11>0,"L0",IF(L11>0,"M2",IF(K11>0,"M1",IF(J11>0,"M0",IF(P11>0,"S2",IF(O11>0,"S1","S0"))))))) -> L0
A12: 45872 | B12: cargo_cd0b463ada5f42b3b84863bb06a3aff3 | C12: 64110b0b40514acf82f306e89b4188f5 | D12: van_0 | S12: =IF(H12>0,"L1",IF(G12>0,"L0",IF(L12>0,"M2",IF(K12>0,"M1",IF(J12>0,"M0",IF(P12>0,"S2",IF(O12>0,"S1","S0"))))))) -> S1
A13: 45872 | B13: be540ff4a96125d18deb26ddd55d26d0 | C13: 9d8253d1cb83424e8ece6370e8a012e3 | D13: van_0 | S13: =IF(H13>0,"L1",IF(G13>0,"L0",IF(L13>0,"M2",IF(K13>0,"M1",IF(J13>0,"M0",IF(P13>0,"S2",IF(O13>0,"S1","S0"))))))) -> M1
A14: 45872 | B14: cargo_0d363c0fb1cc459393fda634e68a2584 | C14: 6e2bf08c41b04db2a216a3f96d4c70aa | D14: lcv_m_0 | S14: =IF(H14>0,"L1",IF(G14>0,"L0",IF(L14>0,"M2",IF(K14>0,"M1",IF(J14>0,"M0",IF(P14>0,"S2",IF(O14>0,"S1","S0"))))))) -> L0
... A154: 45871 | B154: cargo_e929060ccbb14b9faf9519ac847fc305 | C154: 6e2bf08c41b04db2a216a3f96d4c70aa | D154: lcv_m_0 | S154: =IF(H154>0,"L1",IF(G154>0,"L0",IF(L154>0,"M2",IF(K154>0,"M1",IF(J154>0,"M0",IF(P154>0,"S2",IF(O154>0,"S1","S0"))))))) -> L1
A155: 45871 | B155: cargo_eaa2195baf6643f3901c6892ea17d465 | C155: 7d2963bc795448a09bb5c580c8e368d0 | D155: lcv_m_0
A156: 45871 | B156: 98acf403829ed8d5a7c6da7b0cc134e2 | C156: b5f2cc3a58de4b36b74ff11eed597a04 | D156: van_0
A157: 45871 | B157: cargo_3bf3522b88074f609c4cda7cef25760d | C157: e2c0e8c53f7b4d6ebe6f0221dacff82e | D157: van_0
A158: 45871 | B158: cargo_09a18103d88340eabc82305461c36324 | C158: 0d6cdc563d6041b8accc0f5379b3f3a3 | D158: van_1
A159: 45871 | B159: cargo_c8d70ee485324df893e3d2309b3fb419 | C159: fd22b809fea641e1b355e24799513c6e | D159: lcv_l_0
A160: 45871 | B160: cargo_0f7df0c6369a45e1a81ed27eaa032350 | C160: 9fd9bb5a62a648c0835c9f610288ee81 | D160: lcv_m_0
A161: 45871 | B161: cargo_c618e8ac61e9452a89683cb9d4520a76 | C161: 7d2963bc795448a09bb5c580c8e368d0 | D161: lcv_l_1
A162: 45871 | B162: cargo_3e7f0badeda345b6a492950050dccd87 | C162: 480998867935429b9849aff305f3f317 | D162: van_0
A163: 45871 | B163: cargo_273a66610d0e4911b2cf8e768182c3d3 | C163: 9d96a86d8ea74fa3a2925b98429257e6 | D163: lcv_m_0
A164: 45871 | B164: cargo_83d9e40be315473f95752a438b58f078 | C164: b291823aaee54358b67b9814cab7413b | D164: lcv_l_0
A165: 45871 | B165: cargo_d16243de0cb94b6997105a790b8fb69b | C165: d2b498f52fe44fb9a52ab7f533de4dd6 | D165: van_0
A166: 45871 | B166: cargo_582cbd821cf64f2190048f77192d6d72 | C166: 8d5377e5172c4dbbac76936f5011100b | D166: lcv_m_0
... A1369: 45866 | B1369: cargo_debf513c36904e8a9902baef4ab16d05 | C1369: 4ffa81da56e84e49acb11efb55b12d0e | D1369: lcv_l_0

Sheet доставки 21.07
A1: local date | B1: claim_uuid | C1: zone | D1: order_id | E1: executor_profile_id | F1: cargo size & loaders
A2: 45865 | B2: 01984b29ec74877182142c05cf40f301 | C2: saratov | D2: cargo_c5224dfc439b4ad0a7c26355b8449794 | E2: de27ce64ccf34e43bea14be25dd7f773 | F2: lcv_l_0 | U2: Опция
A3: 45865 | B3: 01984ac534b681eb8c83629a49c89b01 | C3: engels | D3: 6f4d46f9e22b215ab70d73ae9367a0b5 | E3: aab2aee5c9e946288845fe45ae11276b | F3: lcv_m_0 | U3: =IF(J3>0,"L1",IF(I3>0,"L0",IF(N3>0,"M2",IF(M3>0,"M1",IF(L3>0,"M0",IF(R3>0,"S2",IF(Q3>0,"S1","S0"))))))) -> L0
A4: 45865 | B4: 01984b75d4df815aa512b65afa7b8801 | C4: saratov | D4: cargo_8d16c716773a499389dad21a89540dab | E4: 390192fe2ffe46fc9b7d8a60e4b84059 | F4: lcv_m_0 | U4: =IF(J4>0,"L1",IF(I4>0,"L0",IF(N4>0,"M2",IF(M4>0,"M1",IF(L4>0,"M0",IF(R4>0,"S2",IF(Q4>0,"S1","S0"))))))) -> S1
A5: 45865 | B5: 01984b56a7c6815e8a9e856874515201 | C5: saratov | D5: cargo_c25c904889014b6696d892dee94390ea | E5: 1c732902212440b3803eb1ad755fe065 | F5: lcv_m_0 | U5: =IF(J5>0,"L1",IF(I5>0,"L0",IF(N5>0,"M2",IF(M5>0,"M1",IF(L5>0,"M0",IF(R5>0,"S2",IF(Q5>0,"S1","S0"))))))) -> S1
A6: 45865 | B6: 01984a3ab8368796af6bb9ef783c0101 | C6: saratov | D6: cargo_34039d866d8d4fa583598a8fc8a112e8 | E6: 1c732902212440b3803eb1ad755fe065 | F6: lcv_m_2 | U6: =IF(J6>0,"L1",IF(I6>0,"L0",IF(N6>0,"M2",IF(M6>0,"M1",IF(L6>0,"M0",IF(R6>0,"S2",IF(Q6>0,"S1","S0"))))))) -> M0
A7: 45865 | B7: 01984b07c783801bb5ecc79c82884c01 | C7: saratov | D7: cargo_630463a6cbf74410bcea932fb8fe0d48 | E7: e2c0e8c53f7b4d6ebe6f0221dacff82e | F7: van_0 | U7: =IF(J7>0,"L1",IF(I7>0,"L0",IF(N7>0,"M2",IF(M7>0,"M1",IF(L7>0,"M0",IF(R7>0,"S2",IF(Q7>0,"S1","S0"))))))) -> S0
A8: 45865 | B8: 01984c4ce3e48140b09a31bdf9e06101 | C8: saratov | D8: cargo_693c58f6c6e9429ca95b0ce8b7533ce4 | E8: f89af7b26a1241fa9a3a6ec9925de4fa | F8: van_0 | U8: =IF(J8>0,"L1",IF(I8>0,"L0",IF(N8>0,"M2",IF(M8>0,"M1",IF(L8>0,"M0",IF(R8>0,"S2",IF(Q8>0,"S1","S0"))))))) -> M0
A9: 45865 | B9: 01984a5b9d55870ab418a20028d84b04 | C9: saratov | D9: cargo_419ea000b7c84bbd88d0f767bbbc0f3e | E9: 652a10794db649fd9890bc7a8d63339a | F9: van_1 | U9: =IF(J9>0,"L1",IF(I9>0,"L0",IF(N9>0,"M2",IF(M9>0,"M1",IF(L9>0,"M0",IF(R9>0,"S2",IF(Q9>0,"S1","S0"))))))) -> M0
A10: 45865 | B10: 01984a5b9d55870ab418a20028d84b04 | C10: saratov | D10: cargo_419ea000b7c84bbd88d0f767bbbc0f3e | E10: 652a10794db649fd9890bc7a8d63339a | F10: van_1 | U10: =IF(J10>0,"L1",IF(I10>0,"L0",IF(N10>0,"M2",IF(M10>0,"M1",IF(L10>0,"M0",IF(R10>0,"S2",IF(Q10>0,"S1","S0"))))))) -> L0
A11: 45865 | B11: 01984a5b9d55870ab418a20028d84b04 | C11: saratov | D11: cargo_419ea000b7c84bbd88d0f767bbbc0f3e | E11: 652a10794db649fd9890bc7a8d63339a | F11: van_1 | U11: =IF(J11>0,"L1",IF(I11>0,"L0",IF(N11>0,"M2",IF(M11>0,"M1",IF(L11>0,"M0",IF(R11>0,"S2",IF(Q11>0,"S1","S0"))))))) -> L0
A12: 45865 | B12: 01984a5b9d55870ab418a20028d84b04 | C12: saratov | D12: cargo_419ea000b7c84bbd88d0f767bbbc0f3e | E12: 652a10794db649fd9890bc7a8d63339a | F12: van_1 | U12: =IF(J12>0,"L1",IF(I12>0,"L0",IF(N12>0,"M2",IF(M12>0,"M1",IF(L12>0,"M0",IF(R12>0,"S2",IF(Q12>0,"S1","S0"))))))) -> L0
A13: 45865 | B13: 01984a5b9d55870ab418a20028d84b04 | C13: saratov | D13: cargo_419ea000b7c84bbd88d0f767bbbc0f3e | E13: 652a10794db649fd9890bc7a8d63339a | F13: van_1 | U13: =IF(J13>0,"L1",IF(I13>0,"L0",IF(N13>0,"M2",IF(M13>0,"M1",IF(L13>0,"M0",IF(R13>0,"S2",IF(Q13>0,"S1","S0"))))))) -> L0
A14: 45865 | B14: 01984a5b9d55870ab418a20028d84b04 | C14: saratov | D14: cargo_419ea000b7c84bbd88d0f767bbbc0f3e | E14: 652a10794db649fd9890bc7a8d63339a | F14: van_1 | U14: =IF(J14>0,"L1",IF(I14>0,"L0",IF(N14>0,"M2",IF(M14>0,"M1",IF(L14>0,"M0",IF(R14>0,"S2",IF(Q14>0,"S1","S0"))))))) -> L0
... A159: 45865 | B159: 01984c613c4e8077b7a833040536ec01 | C159: saratov | D159: cargo_8046ce274e8444cbbbdeb871c4d693d4 | E159: 8d5377e5172c4dbbac76936f5011100b | F159: lcv_m_0 | U159: =IF(J159>0,"L1",IF(I159>0,"L0",IF(N159>0,"M2",IF(M159>0,"M1",IF(L159>0,"M0",IF(R159>0,"S2",IF(Q159>0,"S1","S0"))))))) -> L1
A160: 45865 | B160: 01984bd40ee6831fb0488dcf40eec001 | C160: saratov | D160: cargo_18c842773caa47a3b690182e310bd5d6 | E160: af73fccdb0cd4bee893d810f4a384da9 | F160: van_0
A161: 45865 | B161: 01984ba2bc01846188418625f6138001 | C161: saratov | D161: cargo_5e90d8f4c1b1428283f3814b06aa7c9b | E161: fd22b809fea641e1b355e24799513c6e | F161: lcv_m_0
A162: 45865 | B162: 01984b6da83c80ecba99379f2f27b901 | C162: saratov | D162: cargo_cf8586aa9ef847c599ce7a9f60bfd5e4 | E162: 480998867935429b9849aff305f3f317 | F162: van_0
A163: 45865 | B163: 01984bb1d8e487efa3758eeedda97201 | C163: saratov | D163: cargo_4c40b86b0b364288a1e811d73af40660 | E163: 43aee2ffd5ef4544be51a6aafb5faa08 | F163: van_0
A164: 45865 | B164: 01984ba51fbf814592aba5ce1fd5fa01 | C164: saratov | D164: cargo_1c3a46e9f6544d9f983eef9dda6f4eaa | E164: 8ef5ed46bff04a06b700b78c6e9db386 | F164: lcv_m_0
A165: 45865 | B165: 01984be28ede85589d6db263fe571301 | C165: saratov | D165: cargo_2324e9d0b6d64ca0b8443d70d42ad3f0 | E165: 598eed6f4fba447b9cda7c21a794ce78 | F165: lcv_m_0
A166: 45865 | B166: 01984a37dad88113a59f444197538b01 | C166: saratov | D166: cargo_12147dc6a20d4cbd99c9e4f80e1d0d19 | E166: 2bda7a36b086424a94cb76a4752da00d | F166: lcv_m_0
A167: 45865 | B167: 01984ae8f7118261beaf2ab76868d401 | C167: saratov | D167: cargo_e8a6d19c157e4d2f9739db6fbca3ce17 | E167: 5679ff0c8c8242a39f76eb3af3f98715 | F167: lcv_m_0
A168: 45865 | B168: 01984a30891086298a92d7d67b8b4901 | C168: saratov | D168: cargo_63f62e14d0ba47a28bf4f21067d3d3da | E168: 2c6a62221cba421eb6403a320e933d4a | F168: van_0
A169: 45865 | B169: 01984bf62b908638ab2c8a688f11f901 | C169: saratov | D169: cargo_73a00c62605c459a896e535f54829dcd | E169: 6e2bf08c41b04db2a216a3f96d4c70aa | F169: van_0
A170: 45865 | B170: 01984af0542383a4ab429086622dd401 | C170: saratov | D170: cargo_b0575e1978c34c609740088c26819f74 | E170: 2bda7a36b086424a94cb76a4752da00d | F170: lcv_m_0
A171: 45865 | B171: 01984ad9354183ed9a3f2f02fe0ce301 | C171: saratov | D171: cargo_e0bf51219b39422291f622041260a822 | E171: 480998867935429b9849aff305f3f317 | F171: van_0
... A1666: 45859 | B1666: 01982c492d6385a6a60d4548de724201 | C1666: saratov | D1666: cargo_d2ab4e6ce6a341eeb3c000ce70125156 | E1666: 86486545c9c048d3853320a3ca6d7cb8 | F1666: lcv_m_0

Sheet доставки 14.07
A1: local date | B1: order_id | C1: executor_profile_id | D1: cargo size & loaders
A2: 45858 | B2: cargo_2ea1e753d6064d27ac50fbc9dfa309c7 | C2: e6e89feb151e4fd0b66b7e15c053243b | D2: lcv_m_0 | S2: Опция
A3: 45858 | B3: cargo_fd7aa84bd89d49ab8b9613b9ef46f9a7 | C3: 2bf1c6d7cb9f477a96946a8c9401421b | D3: lcv_m_0 | S3: =IF(H3>0,"L1",IF(G3>0,"L0",IF(L3>0,"M2",IF(K3>0,"M1",IF(J3>0,"M0",IF(P3>0,"S2",IF(O3>0,"S1","S0"))))))) -> L0
A4: 45858 | B4: cargo_ebe5f7cde2ea4d45a1ea7426e4ecdff9 | C4: 2bf1c6d7cb9f477a96946a8c9401421b | D4: van_0 | S4: =IF(H4>0,"L1",IF(G4>0,"L0",IF(L4>0,"M2",IF(K4>0,"M1",IF(J4>0,"M0",IF(P4>0,"S2",IF(O4>0,"S1","S0"))))))) -> S1
A5: 45858 | B5: cargo_8f6bcef0ec2b4aceab7a499daf63cb08 | C5: 9952efb6ba8640c79b02e19c3e999e59 | D5: van_0 | S5: =IF(H5>0,"L1",IF(G5>0,"L0",IF(L5>0,"M2",IF(K5>0,"M1",IF(J5>0,"M0",IF(P5>0,"S2",IF(O5>0,"S1","S0"))))))) -> M0
A6: 45858 | B6: 8e8bfe576f0dcfe6a881fca3fdb1792f | C6: f2b3ddf771be42c09fee6483e038c7c9 | D6: lcv_m_0 | S6: =IF(H6>0,"L1",IF(G6>0,"L0",IF(L6>0,"M2",IF(K6>0,"M1",IF(J6>0,"M0",IF(P6>0,"S2",IF(O6>0,"S1","S0"))))))) -> S0
A7: 45858 | B7: cargo_7298caed61b7495b953129a4a036c4ad | C7: e6e89feb151e4fd0b66b7e15c053243b | D7: lcv_m_1 | S7: =IF(H7>0,"L1",IF(G7>0,"L0",IF(L7>0,"M2",IF(K7>0,"M1",IF(J7>0,"M0",IF(P7>0,"S2",IF(O7>0,"S1","S0"))))))) -> M0
A8: 45858 | B8: cargo_4f3afa5c702045a4b4405f86872526d7 | C8: e702867727604d1b8b3bf3f7347766d8 | D8: van_0 | S8: =IF(H8>0,"L1",IF(G8>0,"L0",IF(L8>0,"M2",IF(K8>0,"M1",IF(J8>0,"M0",IF(P8>0,"S2",IF(O8>0,"S1","S0"))))))) -> M0
A9: 45858 | B9: 1c6114524c898bfa915035ce002d0c96 | C9: 535d9350676257c735d972486de9e8e5 | D9: van_0 | S9: =IF(H9>0,"L1",IF(G9>0,"L0",IF(L9>0,"M2",IF(K9>0,"M1",IF(J9>0,"M0",IF(P9>0,"S2",IF(O9>0,"S1","S0"))))))) -> L0
A10: 45858 | B10: cargo_1d60788f257a4f6a87e7ec1c4d73f253 | C10: ea97cac05ecd43b9a54bf20d55ad073a | D10: lcv_m_0 | S10: =IF(H10>0,"L1",IF(G10>0,"L0",IF(L10>0,"M2",IF(K10>0,"M1",IF(J10>0,"M0",IF(P10>0,"S2",IF(O10>0,"S1","S0"))))))) -> M0
A11: 45858 | B11: cargo_a7c2073ff41a4964862a13a4d8bc2245 | C11: 2bf1c6d7cb9f477a96946a8c9401421b | D11: lcv_m_0 | S11: =IF(H11>0,"L1",IF(G11>0,"L0",IF(L11>0,"M2",IF(K11>0,"M1",IF(J11>0,"M0",IF(P11>0,"S2",IF(O11>0,"S1","S0"))))))) -> L1
A12: 45858 | B12: cargo_2afa6dcc5e194a2c8597f5694dbf3c2f | C12: 43aee2ffd5ef4544be51a6aafb5faa08 | D12: van_0 | S12: =IF(H12>0,"L1",IF(G12>0,"L0",IF(L12>0,"M2",IF(K12>0,"M1",IF(J12>0,"M0",IF(P12>0,"S2",IF(O12>0,"S1","S0"))))))) -> L0
A13: 45858 | B13: 1c3853bfe85d3c6abb78349bdb4f1df2 | C13: 1000d7fc3e91483ca6f56b18398c510d | D13: van_0 | S13: =IF(H13>0,"L1",IF(G13>0,"L0",IF(L13>0,"M2",IF(K13>0,"M1",IF(J13>0,"M0",IF(P13>0,"S2",IF(O13>0,"S1","S0"))))))) -> S1
A14: 45858 | B14: cargo_fe3b42c75b55448ea83ac23311050f4e | C14: b6ce04a817334101bd1db64011d57fc2 | D14: lcv_l_0 | S14: =IF(H14>0,"L1",IF(G14>0,"L0",IF(L14>0,"M2",IF(K14>0,"M1",IF(J14>0,"M0",IF(P14>0,"S2",IF(O14>0,"S1","S0"))))))) -> S0
... A171: 45857 | B171: cargo_0cf2cf4b99dc494c8a2f716dcc02c98b | C171: 69bfc39130f44ff78211b5fff3485a82 | D171: van_1 | S171: =IF(H171>0,"L1",IF(G171>0,"L0",IF(L171>0,"M2",IF(K171>0,"M1",IF(J171>0,"M0",IF(P171>0,"S2",IF(O171>0,"S1","S0"))))))) -> L1
A172: 45857 | B172: cargo_9158488721cb48578235eeab6ab3fe1e | C172: fd52dd96e8924c71b56cb473ff655e2b | D172: van_0
A173: 45857 | B173: 7b672c21d05e80c6b6257d4f25ecb3dc | C173: b5f2cc3a58de4b36b74ff11eed597a04 | D173: van_1
A174: 45857 | B174: cargo_4b1bcfd5d11c4af1846d7862908cebd3 | C174: 67faba600c584a54b19cb68d7c2b3d2d | D174: lcv_m_0
A175: 45857 | B175: cargo_a1fb1d35028748d097aac56e32280abe | C175: d8ce288155104264aca009718920caa4 | D175: lcv_m_0
A176: 45857 | B176: cargo_a83553f2e83e4c12826f1f424358387c | C176: 5a5a018e33a71918d47af4663dc5d194 | D176: van_0
A177: 45857 | B177: cargo_3d2ee96373c8428e9106227224321c81 | C177: fd52dd96e8924c71b56cb473ff655e2b | D177: van_0
A178: 45857 | B178: cargo_307e42ed36404f0fbb57b03ffa85266e | C178: afa643511e1d452d8960ee85809d9f89 | D178: lcv_m_0
A179: 45857 | B179: cargo_f7a6f64607cd49dcb12317f9c67fd100 | C179: 2cfad911fbe443b2a3ab8bb280388c8f | D179: lcv_m_0
A180: 45857 | B180: cargo_3b5e24d208bf4253bcc13decccf7dae1 | C180: e6e89feb151e4fd0b66b7e15c053243b | D180: lcv_m_0
A181: 45857 | B181: cargo_39fb1244d79f47b7b349559bf1642fe0 | C181: 0d6cdc563d6041b8accc0f5379b3f3a3 | D181: van_0
A182: 45857 | B182: cargo_1dcf71cea0094f24b536199fb0db7f8d | C182: ac155a25222e4a39bf30ac55c685de05 | D182: lcv_m_0
A183: 45857 | B183: cargo_2297a0a87fb54cf2b9bb07519cbdc35c | C183: 1f6e2c740b5b4d91806b7d0ff3fdbd36 | D183: lcv_m_0
... A1594: 45852 | B1594: cargo_23222ae93e644bc8b62d8ee2f6647ac5 | C1594: 6b11fa5ff1e04276bc744a86c63b6791 | D1594: van_0

Sheet доставки 07.07
A1: local date | B1: order_id | C1: executor_profile_id | D1: cargo size & loaders
A2: 45851 | B2: cargo_5158e0a4abe9496691f666ad77787909 | C2: 2bda7a36b086424a94cb76a4752da00d | D2: lcv_m_0 | S2: Опция
A3: 45851 | B3: cargo_ad5b33d35ada4b1ebdecd8a69975d617 | C3: 1c732902212440b3803eb1ad755fe065 | D3: lcv_m_0 | S3: =IF(H3>0,"L1",IF(G3>0,"L0",IF(L3>0,"M2",IF(K3>0,"M1",IF(J3>0,"M0",IF(P3>0,"S2",IF(O3>0,"S1","S0"))))))) -> L0
A4: 45851 | B4: cargo_d8cca9a49ea74b799d52dbc5abde46ed | C4: 1c732902212440b3803eb1ad755fe065 | D4: lcv_m_0 | S4: =IF(H4>0,"L1",IF(G4>0,"L0",IF(L4>0,"M2",IF(K4>0,"M1",IF(J4>0,"M0",IF(P4>0,"S2",IF(O4>0,"S1","S0"))))))) -> S0
A5: 45851 | B5: cargo_f60196e8fa784936a0ef956404d5a997 | C5: af73fccdb0cd4bee893d810f4a384da9 | D5: van_0 | S5: =IF(H5>0,"L1",IF(G5>0,"L0",IF(L5>0,"M2",IF(K5>0,"M1",IF(J5>0,"M0",IF(P5>0,"S2",IF(O5>0,"S1","S0"))))))) -> M2
A6: 45851 | B6: cargo_c434ada3b9b440beb0f795d0e0da9f38 | C6: ac155a25222e4a39bf30ac55c685de05 | D6: lcv_m_1 | S6: =IF(H6>0,"L1",IF(G6>0,"L0",IF(L6>0,"M2",IF(K6>0,"M1",IF(J6>0,"M0",IF(P6>0,"S2",IF(O6>0,"S1","S0"))))))) -> S0
A7: 45851 | B7: cargo_e6754c2d83fd4dc8a888958f8eccecd6 | C7: 390192fe2ffe46fc9b7d8a60e4b84059 | D7: lcv_m_0 | S7: =IF(H7>0,"L1",IF(G7>0,"L0",IF(L7>0,"M2",IF(K7>0,"M1",IF(J7>0,"M0",IF(P7>0,"S2",IF(O7>0,"S1","S0"))))))) -> M0
A8: 45851 | B8: cargo_e222bf51c49a4b49a8a42c1c28ab98fc | C8: 0bcd8de748aa44d3914e82d5db2b7f44 | D8: van_0 | S8: =IF(H8>0,"L1",IF(G8>0,"L0",IF(L8>0,"M2",IF(K8>0,"M1",IF(J8>0,"M0",IF(P8>0,"S2",IF(O8>0,"S1","S0"))))))) -> S0
A9: 45851 | B9: cargo_483258d10cde4f398cf22cd07864f434 | C9: 013ab8149527487b9630ed3f68c057a1 | D9: van_0 | S9: =IF(H9>0,"L1",IF(G9>0,"L0",IF(L9>0,"M2",IF(K9>0,"M1",IF(J9>0,"M0",IF(P9>0,"S2",IF(O9>0,"S1","S0"))))))) -> M0
A10: 45851 | B10: cargo_a6a7cb1fff8340049eaec8e18ab78757 | C10: 60bc4fc9e0993495045b9b8652bddd16 | D10: lcv_m_0 | S10: =IF(H10>0,"L1",IF(G10>0,"L0",IF(L10>0,"M2",IF(K10>0,"M1",IF(J10>0,"M0",IF(P10>0,"S2",IF(O10>0,"S1","S0"))))))) -> M0
A11: 45851 | B11: cargo_4003859f47d14b9abf19cc94b87d52e1 | C11: 2bda7a36b086424a94cb76a4752da00d | D11: lcv_m_0 | S11: =IF(H11>0,"L1",IF(G11>0,"L0",IF(L11>0,"M2",IF(K11>0,"M1",IF(J11>0,"M0",IF(P11>0,"S2",IF(O11>0,"S1","S0"))))))) -> S0
A12: 45851 | B12: cargo_4fc5570ad9f1413790083e80704999a0 | C12: c6ba6ac670714a6d8fc7b62fdd06e1a2 | D12: lcv_l_1 | S12: =IF(H12>0,"L1",IF(G12>0,"L0",IF(L12>0,"M2",IF(K12>0,"M1",IF(J12>0,"M0",IF(P12>0,"S2",IF(O12>0,"S1","S0"))))))) -> M0
A13: 45851 | B13: e1b89d389668cf7bb21c35a722e7fa54 | C13: cf899fb8497a4478811c368bb27a9d19 | D13: van_0 | S13: =IF(H13>0,"L1",IF(G13>0,"L0",IF(L13>0,"M2",IF(K13>0,"M1",IF(J13>0,"M0",IF(P13>0,"S2",IF(O13>0,"S1","S0"))))))) -> L0
A14: 45851 | B14: cargo_1d9d1b56221b42d6b3dd129af7e27d86 | C14: 52fa0e9e0902446fb3d2f6b43e6495de | D14: van_0 | S14: =IF(H14>0,"L1",IF(G14>0,"L0",IF(L14>0,"M2",IF(K14>0,"M1",IF(J14>0,"M0",IF(P14>0,"S2",IF(O14>0,"S1","S0"))))))) -> L0
... A158: 45850 | B158: cargo_e41a2a13784647e1857180278f33d21b | C158: 5a5a018e33a71918d47af4663dc5d194 | D158: van_0 | S158: =IF(H158>0,"L1",IF(G158>0,"L0",IF(L158>0,"M2",IF(K158>0,"M1",IF(J158>0,"M0",IF(P158>0,"S2",IF(O158>0,"S1","S0"))))))) -> L1
A159: 45850 | B159: cargo_e42270d4b5cd4506a0735f1f8187ad18 | C159: a501dc5d0bf44be2abaa3ae5908127b9 | D159: lcv_m_0
A160: 45850 | B160: cargo_e530882c55f040ebb8e0cd1e1cbe1833 | C160: 701fa8b350a64f6cb12571fe2a3e0dcf | D160: lcv_m_1
A161: 45850 | B161: 1136ded0aceebe5390071dcc9ac81865 | C161: 177e0f6a9d8d4713bdf8d7d2e0866f89 | D161: van_0
A162: 45850 | B162: 40a09231a05cbc528ddebf47ef174e0b | C162: a0f5b51d62a04c0683e13e1099f10e1a | D162: van_0
A163: 45850 | B163: cargo_8589fe66a37f4329bff97b8896acd087 | C163: 2c6a62221cba421eb6403a320e933d4a | D163: van_0
A164: 45850 | B164: cargo_4f179c35af7a4fac95b1a21c4676b6e2 | C164: 652a10794db649fd9890bc7a8d63339a | D164: van_0
A165: 45850 | B165: 87705436fc583c53b34d562e2bdaa7ea | C165: 0292ffeb008441c08465b6dd1f088950 | D165: lcv_m_0
A166: 45850 | B166: cargo_47205f32dc0548e3a78dd8680b98ef34 | C166: 2599044e4d8d47e0937662dfbfd98e14 | D166: lcv_l_0
A167: 45850 | B167: cargo_64c7946e00b344d9abc062089dda5f5a | C167: 2bf1c6d7cb9f477a96946a8c9401421b | D167: lcv_m_0
A168: 45850 | B168: cargo_9456d83166d34b4d8128e886459e18e0 | C168: 6da55f98c2ff4d8d9e6dadf40aa107b6 | D168: lcv_m_0
A169: 45850 | B169: cargo_03d105c4814145c5b5fe5c6c8a5b2ade | C169: 390192fe2ffe46fc9b7d8a60e4b84059 | D169: lcv_m_0
A170: 45850 | B170: cargo_45954156a9924f39b2b3356214f16be1 | C170: 874e93aac8fe41c1ab6621da610593e8 | D170: lcv_l_0
... A1520: 45845 | B1520: 0157e59c8fd1ecc99bff69620cc4418b | C1520: f679cf018fc04fdebdcfebcba3f8f732 | D1520: van_0

Sheet доставки 30.06
A1: local date | B1: order_id | C1: executor_profile_id | D1: cargo size & loaders
A2: 45844 | B2: d4632ab5b270d54db3132c43b9c5eeb3 | C2: 6e2bf08c41b04db2a216a3f96d4c70aa | D2: lcv_m_0 | S2: Опция
A3: 45844 | B3: cargo_935b6d09ee8344d983d6642da290ea9f | C3: 64de69d8fab1431b995e51b497df50cb | D3: lcv_m_1 | S3: =IF(H3>0,"L1",IF(G3>0,"L0",IF(L3>0,"M2",IF(K3>0,"M1",IF(J3>0,"M0",IF(P3>0,"S2",IF(O3>0,"S1","S0"))))))) -> L0
A4: 45844 | B4: 64ef8dc6da992bbe9b7ad6241114a886 | C4: 2a479c547a854027b2fb7736991065fc | D4: lcv_l_1 | S4: =IF(H4>0,"L1",IF(G4>0,"L0",IF(L4>0,"M2",IF(K4>0,"M1",IF(J4>0,"M0",IF(P4>0,"S2",IF(O4>0,"S1","S0"))))))) -> S0
A5: 45844 | B5: cargo_d62104796d554681af749a23501e62d6 | C5: 6d32ee446087486688b0a66acba8f7e7 | D5: lcv_m_0 | S5: =IF(H5>0,"L1",IF(G5>0,"L0",IF(L5>0,"M2",IF(K5>0,"M1",IF(J5>0,"M0",IF(P5>0,"S2",IF(O5>0,"S1","S0"))))))) -> S1
A6: 45844 | B6: cargo_f1046e324b1e42709ca2d808f242222d | C6: 4ca11f9532ef43679dfd4196e9b811e2 | D6: lcv_l_0 | S6: =IF(H6>0,"L1",IF(G6>0,"L0",IF(L6>0,"M2",IF(K6>0,"M1",IF(J6>0,"M0",IF(P6>0,"S2",IF(O6>0,"S1","S0"))))))) -> M0
A7: 45844 | B7: f6971cd6236fcba2b654f170b4768247 | C7: c8445943a0614fa88139c5df4c8df7e5 | D7: van_0 | S7: =IF(H7>0,"L1",IF(G7>0,"L0",IF(L7>0,"M2",IF(K7>0,"M1",IF(J7>0,"M0",IF(P7>0,"S2",IF(O7>0,"S1","S0"))))))) -> S0
A8: 45844 | B8: cargo_6657fb9dd6bb43678b3068dd8737bbfe | C8: 2bf1c6d7cb9f477a96946a8c9401421b | D8: lcv_m_0 | S8: =IF(H8>0,"L1",IF(G8>0,"L0",IF(L8>0,"M2",IF(K8>0,"M1",IF(J8>0,"M0",IF(P8>0,"S2",IF(O8>0,"S1","S0"))))))) -> M0
A9: 45844 | B9: cargo_f0702a66322746f89a3a7d2eeda6205a | C9: e2c0e8c53f7b4d6ebe6f0221dacff82e | D9: van_0 | S9: =IF(H9>0,"L1",IF(G9>0,"L0",IF(L9>0,"M2",IF(K9>0,"M1",IF(J9>0,"M0",IF(P9>0,"S2",IF(O9>0,"S1","S0"))))))) -> M0
A10: 45844 | B10: f05ef9b15fe02d31b4945adfb525cd98 | C10: 1000d7fc3e91483ca6f56b18398c510d | D10: van_0 | S10: =IF(H10>0,"L1",IF(G10>0,"L0",IF(L10>0,"M2",IF(K10>0,"M1",IF(J10>0,"M0",IF(P10>0,"S2",IF(O10>0,"S1","S0"))))))) -> S0
A11: 45844 | B11: cargo_35933cd21d764ad7b0dd2e96284b42d7 | C11: 2bf1c6d7cb9f477a96946a8c9401421b | D11: lcv_m_0 | S11: =IF(H11>0,"L1",IF(G11>0,"L0",IF(L11>0,"M2",IF(K11>0,"M1",IF(J11>0,"M0",IF(P11>0,"S2",IF(O11>0,"S1","S0"))))))) -> M0
A12: 45844 | B12: 728ad1df7efd830094260a0daada2e93 | C12: 6e2bf08c41b04db2a216a3f96d4c70aa | D12: van_0 | S12: =IF(H12>0,"L1",IF(G12>0,"L0",IF(L12>0,"M2",IF(K12>0,"M1",IF(J12>0,"M0",IF(P12>0,"S2",IF(O12>0,"S1","S0"))))))) -> L0
A13: 45844 | B13: cargo_2c25d689e3b6471d88e8494ac0c170cf | C13: ac155a25222e4a39bf30ac55c685de05 | D13: lcv_m_0 | S13: =IF(H13>0,"L1",IF(G13>0,"L0",IF(L13>0,"M2",IF(K13>0,"M1",IF(J13>0,"M0",IF(P13>0,"S2",IF(O13>0,"S1","S0"))))))) -> M0
A14: 45844 | B14: cargo_9961f4c898ab42c1a0a9a8d6ced872f6 | C14: 40772a3017454770a01192f2bc7df995 | D14: lcv_m_0 | S14: =IF(H14>0,"L1",IF(G14>0,"L0",IF(L14>0,"M2",IF(K14>0,"M1",IF(J14>0,"M0",IF(P14>0,"S2",IF(O14>0,"S1","S0"))))))) -> L1
... A180: 45843 | B180: cargo_20c89ad4bc354135a57935cc0fd51eb5 | C180: 2bf1c6d7cb9f477a96946a8c9401421b | D180: lcv_m_0 | S180: =IF(H180>0,"L1",IF(G180>0,"L0",IF(L180>0,"M2",IF(K180>0,"M1",IF(J180>0,"M0",IF(P180>0,"S2",IF(O180>0,"S1","S0"))))))) -> L1
A181: 45843 | B181: cargo_812dcd965b4f4222817bc6257b638cd9 | C181: c6ba6ac670714a6d8fc7b62fdd06e1a2 | D181: lcv_m_0
A182: 45843 | B182: cargo_2dc0636165a04763aa55ba5ce6af6c60 | C182: 338e6dbd97524199a522729757af4149 | D182: lcv_m_0
A183: 45843 | B183: cargo_2220cdfadb304b059f2bde325681bd49 | C183: 506ef9701a4443d6ab3661acf1cbecc9 | D183: van_0
A184: 45843 | B184: cargo_36663ccbc8e64189a25eb1f8a5da2b12 | C184: e01e717546134bdf86dc681d6304eea4 | D184: lcv_m_0
A185: 45843 | B185: cargo_acac47675b0f4ddcbd703150030107df | C185: 64de69d8fab1431b995e51b497df50cb | D185: lcv_m_0
A186: 45843 | B186: cargo_bb6dea09b97342d0984e81531b920418 | C186: 64de69d8fab1431b995e51b497df50cb | D186: lcv_m_0
A187: 45843 | B187: 2b11887356e9c3a2808e0aef13039b78 | C187: 2f9076a1f39f40a181d235cbc7bf5c09 | D187: lcv_m_0
A188: 45843 | B188: cargo_9da51396c37a4898aebf91fc71e978ed | C188: 2c6a62221cba421eb6403a320e933d4a | D188: van_0
A189: 45843 | B189: cargo_498ebad9bf65433e8935f3032198723e | C189: 64de69d8fab1431b995e51b497df50cb | D189: van_0
A190: 45843 | B190: cargo_e741cc3a073c4adb81e102053b434a66 | C190: dae54236a25b411f9ad7d24c24c40398 | D190: lcv_m_0
A191: 45843 | B191: cargo_14aeec9ab45e40988035cf2df14e94bd | C191: 2bf1c6d7cb9f477a96946a8c9401421b | D191: lcv_m_0
A192: 45843 | B192: cargo_dcce2e93f3ea4e6891fe5314d23e0402 | C192: e2c0e8c53f7b4d6ebe6f0221dacff82e | D192: van_1
... A1547: 45838 | B1547: cargo_f2ab3a584b6e4d558c54c9913e543679 | C1547: 710797c9d2c74f399b0ede42e556eb98 | D1547: lcv_l_0

Sheet выгрузка m2&L
A1: https://datalens.yandex-team.ru/t9j0q9xdumu4g-cargo-mm-on-demand?state=293717ba1015 | C1: AVG Fare | I1: CDR | O1: GMV | U1: Доставки
A2: City | B2: Cargo Size | C2: 45789 | D2: 45796 | E2: 45810 | F2: 45817 | G2: 45824 | H2: 45831 | I2: 45789 | J2: 45796 | K2: 45810 | L2: 45817 | M2: 45824 | N2: 45831 | O2: 45789 | P2: 45796 | Q2: 45810 | R2: 45817 | S2: 45824 | T2: 45831 | U2: 45789 | V2: 45796 | W2: 45810 | X2: 45817 | Y2: 45824 | Z2: 45831
A3: Saratov | B3: lcv_m2 | C3: 2483.93 | E3: 2843 | F3: 2419.2 | G3: 2932.99 | H3: 2452.89 | I3: 0.7037 | K3: 0.4773 | L3: 0.5714 | M3: 0.6383 | N3: 0.7222 | O3: 94389.22 | Q3: 59703 | R3: 48384 | S3: 87989.6 | T3: 95662.8 | U3: 38 | W3: 21 | X3: 20 | Y3: 30 | Z3: 39
A4: Saratov | B4: lcv_l | D4: 1387.96 | E4: 1406.55 | F4: 1420.39 | G4: 1500.85 | H4: 1431.68 | J4: 0.7507 | K4: 0.7688 | L4: 0.6201 | M4: 0.8179 | N4: 0.7342 | P4: 359480.4 | Q4: 388208.8 | R4: 315327.32 | S4: 370709 | T4: 332148.8 | V4: 259 | W4: 276 | X4: 222 | Y4: 247 | Z4: 232

Sheet доставки 23.06
A1: local date | B1: order_id | C1: executor_profile_id | D1: cargo size & loaders
A2: 45837 | B2: ee8b0636f8f7333fac1b9e7be92a6f1a | C2: 0a26fd96dc404806b3d90f63040dc6c5 | D2: lcv_m_0 | R2: Опция
A3: 45837 | B3: cargo_645871e6ed22466b839c18422bcff1ea | C3: e2c0e8c53f7b4d6ebe6f0221dacff82e | D3: van_0 | R3: =IF(H3>0,"L1",IF(G3>0,"L0",IF(L3>0,"M2",IF(K3>0,"M1",IF(J3>0,"M0",IF(O3>0,"S1","S0")))))) -> L0
A4: 45837 | B4: cargo_0324b61c25834ee79efa9dcb8c9d6716 | C4: 4ffa81da56e84e49acb11efb55b12d0e | D4: lcv_m_0 | R4: =IF(H4>0,"L1",IF(G4>0,"L0",IF(L4>0,"M2",IF(K4>0,"M1",IF(J4>0,"M0",IF(O4>0,"S1","S0")))))) -> S1
A5: 45837 | B5: cargo_0ec42f00eb354e90878ad3e9e75f987e | C5: c7198737a55f4514a34b9d80eb3897ba | D5: lcv_m_0 | R5: =IF(H5>0,"L1",IF(G5>0,"L0",IF(L5>0,"M2",IF(K5>0,"M1",IF(J5>0,"M0",IF(O5>0,"S1","S0")))))) -> M0
A6: 45837 | B6: 6bb1aec16da2e840a3d8831d3c571325 | C6: f679cf018fc04fdebdcfebcba3f8f732 | D6: van_1 | R6: =IF(H6>0,"L1",IF(G6>0,"L0",IF(L6>0,"M2",IF(K6>0,"M1",IF(J6>0,"M0",IF(O6>0,"S1","S0")))))) -> L0
A7: 45837 | B7: c2c9bd6610de8dda9308b1bf3a3e1a9c | C7: 1000d7fc3e91483ca6f56b18398c510d | D7: van_0 | R7: =IF(H7>0,"L1",IF(G7>0,"L0",IF(L7>0,"M2",IF(K7>0,"M1",IF(J7>0,"M0",IF(O7>0,"S1","S0")))))) -> S0
A8: 45837 | B8: cargo_dde8fdde4e0345caae77f1371659574a | C8: 0ace786a3e68478ebddf962774267abc | D8: lcv_l_1 | R8: =IF(H8>0,"L1",IF(G8>0,"L0",IF(L8>0,"M2",IF(K8>0,"M1",IF(J8>0,"M0",IF(O8>0,"S1","S0")))))) -> M0
A9: 45837 | B9: cargo_afbcef2def1f4d39a91f34e52cc3f72c | C9: 1c732902212440b3803eb1ad755fe065 | D9: lcv_m_0 | R9: =IF(H9>0,"L1",IF(G9>0,"L0",IF(L9>0,"M2",IF(K9>0,"M1",IF(J9>0,"M0",IF(O9>0,"S1","S0")))))) -> M0
A10: 45837 | B10: cargo_8c42cd08052e4e42b6bd4150386f86aa | C10: e01e717546134bdf86dc681d6304eea4 | D10: lcv_m_0 | R10: =IF(H10>0,"L1",IF(G10>0,"L0",IF(L10>0,"M2",IF(K10>0,"M1",IF(J10>0,"M0",IF(O10>0,"S1","S0")))))) -> L0
A11: 45837 | B11: cargo_946482721a1d424d912b25dea9484241 | C11: 2cfad911fbe443b2a3ab8bb280388c8f | D11: lcv_m_0 | R11: =IF(H11>0,"L1",IF(G11>0,"L0",IF(L11>0,"M2",IF(K11>0,"M1",IF(J11>0,"M0",IF(O11>0,"S1","S0")))))) -> S0
A12: 45837 | B12: cargo_54ecbfb9e20b488d97f5f211a311780a | C12: 4b6d2065e9fa4165849c7acf27390ff2 | D12: lcv_l_0 | R12: =IF(H12>0,"L1",IF(G12>0,"L0",IF(L12>0,"M2",IF(K12>0,"M1",IF(J12>0,"M0",IF(O12>0,"S1","S0")))))) -> S0
A13: 45837 | B13: cargo_f103dbc5e68d490cb654095d05ce412b | C13: bd16ff03f213490b83d9cb489567b7e6 | D13: lcv_m_1 | R13: =IF(H13>0,"L1",IF(G13>0,"L0",IF(L13>0,"M2",IF(K13>0,"M1",IF(J13>0,"M0",IF(O13>0,"S1","S0")))))) -> M0
A14: 45837 | B14: cargo_7c22b5e475ec4530947b225d609ab1e3 | C14: 2bda7a36b086424a94cb76a4752da00d | D14: lcv_m_0 | R14: =IF(H14>0,"L1",IF(G14>0,"L0",IF(L14>0,"M2",IF(K14>0,"M1",IF(J14>0,"M0",IF(O14>0,"S1","S0")))))) -> S0
... A180: 45836 | B180: cargo_b7a4261a4c994972ba2f9e7def8821b1 | C180: 3c4313387b834f03b40f2793d52e0a0c | D180: lcv_m_0 | R180: =IF(H180>0,"L1",IF(G180>0,"L0",IF(L180>0,"M2",IF(K180>0,"M1",IF(J180>0,"M0",IF(O180>0,"S1","S0")))))) -> S1
A181: 45836 | B181: cargo_341e8fd2bf58428fbd80ce009ee6e1b5 | C181: 0302b5e4e94d0459d8f3d2357c2cafd2 | D181: lcv_m_0
A182: 45836 | B182: 483ae3e785752623b1441c3e185399fd | C182: 1000d7fc3e91483ca6f56b18398c510d | D182: van_0
A183: 45836 | B183: cargo_003a3909dfb242d48b5963b87522517c | C183: 0302b5e4e94d0459d8f3d2357c2cafd2 | D183: lcv_m_0
A184: 45836 | B184: cargo_1b393e0faa0f480bb19b65be38d85702 | C184: dcc81b81230742f8a4d062e96969d9fe | D184: lcv_m_0
A185: 45836 | B185: cargo_c3f4762e9173413fae5ee5cec311d2e6 | C185: 2cfad911fbe443b2a3ab8bb280388c8f | D185: lcv_m_0
A186: 45836 | B186: cargo_193a5a0360fe42bea630a94b91a9b83d | C186: b291823aaee54358b67b9814cab7413b | D186: lcv_l_0
A187: 45836 | B187: df6c2245584a183e8387532f0d074c80 | C187: 1000d7fc3e91483ca6f56b18398c510d | D187: van_0
A188: 45836 | B188: cargo_abd6fd68d76c4b39b3569483d1032009 | C188: 506ef9701a4443d6ab3661acf1cbecc9 | D188: van_1
A189: 45836 | B189: cargo_8085b07348de4df59bc212baab6ac9f7 | C189: 1c732902212440b3803eb1ad755fe065 | D189: lcv_m_0
A190: 45836 | B190: cargo_849568e02be54dba818df5f1ed075c6b | C190: 598eed6f4fba447b9cda7c21a794ce78 | D190: lcv_m_1
A191: 45836 | B191: cargo_d283f7bb0cc04cd897df9462a948de5a | C191: e2e86993374643a49dd7fc9f96930331 | D191: van_0
A192: 45836 | B192: cargo_1f2badbfa98d4b78a7c1aed53f1c0412 | C192: 79eadb681cea4b3b84b0802e1e2c8d85 | D192: van_0
... A1493: 45831 | B1493: cargo_cfd6e9970e1541ee83c9d025b690d6a8 | C1493: 2a479c547a854027b2fb7736991065fc | D1493: lcv_m_1

Sheet доставки 16.06
A1: local date | B1: order_id | C1: executor_profile_id | D1: cargo size & loaders
A2: 45830 | B2: cargo_92937d55fe444de0aeaba15b8045dd6e | C2: 60bc4fc9e0993495045b9b8652bddd16 | D2: lcv_l_0 | S2: Опция
A3: 45830 | B3: cargo_a6f3c679e539476ab3322716e687f2c3 | C3: 7416395cc4804bc188f75b874fa82a50 | D3: van_0 | S3: =IF(H3>0,"L1",IF(G3>0,"L0",IF(L3>0,"M2",IF(K3>0,"M1",IF(J3>0,"M0",IF(P3>0,"S2",IF(O3>0,"S1","S0"))))))) -> L0
A4: 45830 | B4: 309bf56bbf3fb1bbac72cc5749692e57 | C4: 1e0bb939f4d606adcd2633bb20b6dbec | D4: van_0 | S4: =IF(H4>0,"L1",IF(G4>0,"L0",IF(L4>0,"M2",IF(K4>0,"M1",IF(J4>0,"M0",IF(P4>0,"S2",IF(O4>0,"S1","S0"))))))) -> S1
A5: 45830 | B5: cargo_4df48ad53da840ffb321141912fd26c0 | C5: 52fa0e9e0902446fb3d2f6b43e6495de | D5: van_0 | S5: =IF(H5>0,"L1",IF(G5>0,"L0",IF(L5>0,"M2",IF(K5>0,"M1",IF(J5>0,"M0",IF(P5>0,"S2",IF(O5>0,"S1","S0"))))))) -> S1
A6: 45830 | B6: cargo_3a8a6c59a30141d8935f6036757d16c8 | C6: 338e6dbd97524199a522729757af4149 | D6: lcv_l_0 | S6: =IF(H6>0,"L1",IF(G6>0,"L0",IF(L6>0,"M2",IF(K6>0,"M1",IF(J6>0,"M0",IF(P6>0,"S2",IF(O6>0,"S1","S0"))))))) -> M0
A7: 45830 | B7: cargo_787c93c02c9f46a884a296919c854955 | C7: 8df3d66d0a0e4207b275dd249d0f8f1d | D7: lcv_m_0 | S7: =IF(H7>0,"L1",IF(G7>0,"L0",IF(L7>0,"M2",IF(K7>0,"M1",IF(J7>0,"M0",IF(P7>0,"S2",IF(O7>0,"S1","S0"))))))) -> L0
A8: 45830 | B8: cargo_494c9071fd234c98a619553704bfce4c | C8: dd0ab553ee4345b483b032912f2c652d | D8: van_0 | S8: =IF(H8>0,"L1",IF(G8>0,"L0",IF(L8>0,"M2",IF(K8>0,"M1",IF(J8>0,"M0",IF(P8>0,"S2",IF(O8>0,"S1","S0"))))))) -> S0
A9: 45830 | B9: cargo_cb4b3038b8734a7ca81dd22f52c19035 | C9: 96ab252c98314e29bd319dafd2bf76b6 | D9: lcv_m_0 | S9: =IF(H9>0,"L1",IF(G9>0,"L0",IF(L9>0,"M2",IF(K9>0,"M1",IF(J9>0,"M0",IF(P9>0,"S2",IF(O9>0,"S1","S0"))))))) -> M0
A10: 45830 | B10: cargo_3da8e02102d843f0be1e7f23c4e5366e | C10: 598eed6f4fba447b9cda7c21a794ce78 | D10: lcv_m_2 | S10: =IF(H10>0,"L1",IF(G10>0,"L0",IF(L10>0,"M2",IF(K10>0,"M1",IF(J10>0,"M0",IF(P10>0,"S2",IF(O10>0,"S1","S0"))))))) -> S0
A11: 45830 | B11: cargo_ee91833cf94c4ab980ccde171ad3ff18 | C11: 72a9b7774b6b46ad86dda74dbe8dd254 | D11: lcv_l_0 | S11: =IF(H11>0,"L1",IF(G11>0,"L0",IF(L11>0,"M2",IF(K11>0,"M1",IF(J11>0,"M0",IF(P11>0,"S2",IF(O11>0,"S1","S0"))))))) -> M0
A12: 45830 | B12: cargo_0c6696520cf14c179f6fe11477c9a6c3 | C12: 1c732902212440b3803eb1ad755fe065 | D12: lcv_m_2 | S12: =IF(H12>0,"L1",IF(G12>0,"L0",IF(L12>0,"M2",IF(K12>0,"M1",IF(J12>0,"M0",IF(P12>0,"S2",IF(O12>0,"S1","S0"))))))) -> M0
A13: 45830 | B13: cargo_258f5828890d4f95bba0ca3d216027d3 | C13: 44f7d454e1b041f1b0883e912608ab06 | D13: van_0 | S13: =IF(H13>0,"L1",IF(G13>0,"L0",IF(L13>0,"M2",IF(K13>0,"M1",IF(J13>0,"M0",IF(P13>0,"S2",IF(O13>0,"S1","S0"))))))) -> L0
A14: 45830 | B14: cargo_6904b5ce060f4270b02db241c17df0d8 | C14: 9fd9bb5a62a648c0835c9f610288ee81 | D14: lcv_m_0 | S14: =IF(H14>0,"L1",IF(G14>0,"L0",IF(L14>0,"M2",IF(K14>0,"M1",IF(J14>0,"M0",IF(P14>0,"S2",IF(O14>0,"S1","S0"))))))) -> M0
... A176: 45829 | B176: cargo_a36df56d14524cf9819f7bf49c683018 | C176: 8897c133ac364692913cb67e36aec624 | D176: lcv_m_1 | S176: =IF(H176>0,"L1",IF(G176>0,"L0",IF(L176>0,"M2",IF(K176>0,"M1",IF(J176>0,"M0",IF(P176>0,"S2",IF(O176>0,"S1","S0"))))))) -> S1
A177: 45829 | B177: cargo_c1de1d3388414936b6c6a6ea3405c760 | C177: f244ffbd17f245ada01bea171788aeae | D177: lcv_m_0
A178: 45829 | B178: cargo_2bc0e8f47bc14513bbe7d6db7c92500b | C178: 4ffa81da56e84e49acb11efb55b12d0e | D178: lcv_l_0
A179: 45829 | B179: cargo_e673bd33089b4af0a6bcf0e254f00827 | C179: 2c6a62221cba421eb6403a320e933d4a | D179: van_0
A180: 45829 | B180: c96f0628b481b4f38a1934acf8a3cf40 | C180: 56b95b15fdb04f3a8a3eb8f8fee7175e | D180: lcv_m_0
A181: 45829 | B181: cargo_b6be6d08ef264456aa025d83095a8dd1 | C181: 9fe26e4fb0ed47458a3320decc3d0ff4 | D181: van_0
A182: 45829 | B182: cargo_1c50e094c0054d7cb1c29a5c9f4a2afc | C182: 8df3d66d0a0e4207b275dd249d0f8f1d | D182: lcv_m_0
A183: 45829 | B183: cargo_a3879dc54a1b402786ddc29e2ca4bf01 | C183: dc250620988e45408bf893fb7179a432 | D183: van_1
A184: 45829 | B184: cargo_63463c4cbd95470ca344a45919ae2148 | C184: 338e6dbd97524199a522729757af4149 | D184: lcv_m_0
A185: 45829 | B185: cargo_64927427f6964489ba6978b98783310f | C185: 2a5d78998eb6434a83b048df358e1ecd | D185: lcv_m_0
A186: 45829 | B186: cargo_43860911bf8e43d09dd9ad299d6498bb | C186: 79eadb681cea4b3b84b0802e1e2c8d85 | D186: van_0
A187: 45829 | B187: 76134c539849861d8ee04359611cabf1 | C187: 9ada575c05eb4a858d22840a5bb2af2c | D187: van_0
A188: 45829 | B188: cargo_a3d1916a740343fc93bada8b5a3beb43 | C188: 0d6cdc563d6041b8accc0f5379b3f3a3 | D188: van_0
... A1609: 45824 | B1609: b263d9231be8c998830d25766c0a0a13 | C1609: 92a3e49cdf344a36ae1f972fb0874e02 | D1609: van_0

Sheet доставки 09.06
A1: local date | B1: order_id | C1: executor_profile_id | D1: cargo size & loaders | X1: https://datalens.yandex-team.ru/am8u3uq2e7ow2-cancels-corporate-clients-c2c?tab=vd&state=c9c888a22663
A2: 45823 | B2: cargo_ed4adb982c6a4f35a16d67d92cf9a49a | C2: 701fa8b350a64f6cb12571fe2a3e0dcf | D2: lcv_l_0 | S2: Опция
A3: 45823 | B3: cargo_cc889a4731f34239806b6bbe4b4c18fc | C3: e2e86993374643a49dd7fc9f96930331 | D3: lcv_m_0 | S3: =IF(H3>0,"L1",IF(G3>0,"L0",IF(L3>0,"M2",IF(K3>0,"M1",IF(J3>0,"M0",IF(P3>0,"S2",IF(O3>0,"S1","S0"))))))) -> L0
A4: 45823 | B4: cargo_d3e035f5393e40cf919b63207c5fb855 | C4: 6b8a33b9f0844f68a0a542ab796fe497 | D4: lcv_m_0 | S4: =IF(H4>0,"L1",IF(G4>0,"L0",IF(L4>0,"M2",IF(K4>0,"M1",IF(J4>0,"M0",IF(P4>0,"S2",IF(O4>0,"S1","S0"))))))) -> S1
A5: 45823 | B5: cargo_8edd689365cd42ebaa751c8f89eea170 | C5: 2f006b810d1e4169bf8814ec84debddf | D5: lcv_m_0 | S5: =IF(H5>0,"L1",IF(G5>0,"L0",IF(L5>0,"M2",IF(K5>0,"M1",IF(J5>0,"M0",IF(P5>0,"S2",IF(O5>0,"S1","S0"))))))) -> L0
A6: 45823 | B6: cargo_eea00a7c2c0748d8a28a86c8a749ff4e | C6: 0d6cdc563d6041b8accc0f5379b3f3a3 | D6: van_0 | S6: =IF(H6>0,"L1",IF(G6>0,"L0",IF(L6>0,"M2",IF(K6>0,"M1",IF(J6>0,"M0",IF(P6>0,"S2",IF(O6>0,"S1","S0"))))))) -> S1
A7: 45823 | B7: cargo_81ea56aad28645bba4b66c514b3a132f | C7: 2a479c547a854027b2fb7736991065fc | D7: lcv_m_0 | S7: =IF(H7>0,"L1",IF(G7>0,"L0",IF(L7>0,"M2",IF(K7>0,"M1",IF(J7>0,"M0",IF(P7>0,"S2",IF(O7>0,"S1","S0"))))))) -> M0
A8: 45823 | B8: cargo_ae033078b9ef4415bc4712d515e74eff | C8: 338e6dbd97524199a522729757af4149 | D8: lcv_m_0 | S8: =IF(H8>0,"L1",IF(G8>0,"L0",IF(L8>0,"M2",IF(K8>0,"M1",IF(J8>0,"M0",IF(P8>0,"S2",IF(O8>0,"S1","S0"))))))) -> S0
A9: 45823 | B9: cargo_c65c213f27b24284a34f726542cecbc5 | C9: b7d079fb265c42249ee9a736f8558777 | D9: van_1 | S9: =IF(H9>0,"L1",IF(G9>0,"L0",IF(L9>0,"M2",IF(K9>0,"M1",IF(J9>0,"M0",IF(P9>0,"S2",IF(O9>0,"S1","S0"))))))) -> M0
A10: 45823 | B10: cargo_ad33157087a14e2ab41d3526ddb47220 | C10: 338e6dbd97524199a522729757af4149 | D10: lcv_l_0 | S10: =IF(H10>0,"L1",IF(G10>0,"L0",IF(L10>0,"M2",IF(K10>0,"M1",IF(J10>0,"M0",IF(P10>0,"S2",IF(O10>0,"S1","S0"))))))) -> M0
A11: 45823 | B11: cargo_1865eb449f1e4157b9a2eaecec5daf78 | C11: d9ec55389a3c4b378502b9c8c59bc906 | D11: lcv_m_1 | S11: =IF(H11>0,"L1",IF(G11>0,"L0",IF(L11>0,"M2",IF(K11>0,"M1",IF(J11>0,"M0",IF(P11>0,"S2",IF(O11>0,"S1","S0"))))))) -> L0
A12: 45823 | B12: cargo_3a88e1ea65834c9d8cdd4330da92f582 | C12: 4db3e8685f914b5480751776c484a3eb | D12: van_0 | S12: =IF(H12>0,"L1",IF(G12>0,"L0",IF(L12>0,"M2",IF(K12>0,"M1",IF(J12>0,"M0",IF(P12>0,"S2",IF(O12>0,"S1","S0"))))))) -> M1
A13: 45823 | B13: cargo_053d08646ac44daaa894139054c325be | C13: 60bc4fc9e0993495045b9b8652bddd16 | D13: lcv_l_0 | S13: =IF(H13>0,"L1",IF(G13>0,"L0",IF(L13>0,"M2",IF(K13>0,"M1",IF(J13>0,"M0",IF(P13>0,"S2",IF(O13>0,"S1","S0"))))))) -> L0
A14: 45823 | B14: cargo_5ef4308bfe6a4a2192f46ebcc5d1a861 | C14: 9fd9bb5a62a648c0835c9f610288ee81 | D14: lcv_m_0 | S14: =IF(H14>0,"L1",IF(G14>0,"L0",IF(L14>0,"M2",IF(K14>0,"M1",IF(J14>0,"M0",IF(P14>0,"S2",IF(O14>0,"S1","S0"))))))) -> L0
... A156: 45822 | B156: cargo_e5bedfedc25f4af2a77237470ef87135 | C156: 6b8a33b9f0844f68a0a542ab796fe497 | D156: lcv_m_0 | S156: =IF(H156>0,"L1",IF(G156>0,"L0",IF(L156>0,"M2",IF(K156>0,"M1",IF(J156>0,"M0",IF(P156>0,"S2",IF(O156>0,"S1","S0"))))))) -> S0
A157: 45822 | B157: cargo_9a75a6dbf86e43478711615f95dad39c | C157: 96ab252c98314e29bd319dafd2bf76b6 | D157: lcv_m_0
A158: 45822 | B158: 30242cf1cce7d7deb0b53e059d8c1d8e | C158: 6e2bf08c41b04db2a216a3f96d4c70aa | D158: lcv_m_0
A159: 45822 | B159: cargo_acf9ea5f2e014f8f973d20af22c01378 | C159: b7d079fb265c42249ee9a736f8558777 | D159: van_0
A160: 45822 | B160: 6fdd67ba013b323da889f3c39a02a2c3 | C160: 6e2bf08c41b04db2a216a3f96d4c70aa | D160: lcv_m_0
A161: 45822 | B161: cargo_5435d6916692402db0b4b6d5f5ee1c69 | C161: b7d079fb265c42249ee9a736f8558777 | D161: van_1
A162: 45822 | B162: cargo_2497a3948cf848c5abd5c79db36662d7 | C162: 5b265f4532764b3584ca915f64fafd15 | D162: van_0
A163: 45822 | B163: 8f591b38ff16c3e79f98d33f9af4a3b7 | C163: c828f503619c44bf8d7cc6191f059247 | D163: lcv_m_0
A164: 45822 | B164: 47400cfa9d19e15cabf1637e72ffc9ba | C164: 6e2bf08c41b04db2a216a3f96d4c70aa | D164: lcv_m_0
A165: 45822 | B165: cargo_8fc5decd66c740eeb854bf6ea0e9bd08 | C165: 40772a3017454770a01192f2bc7df995 | D165: lcv_m_0
A166: 45822 | B166: cargo_a26ae71c82134f689c24db2c90fa53fd | C166: 598eed6f4fba447b9cda7c21a794ce78 | D166: lcv_m_2
A167: 45822 | B167: cargo_5a7ef8023a764066a99282cb550fccff | C167: 88d955850c7148bca2a31259ab135a1d | D167: lcv_l_0
A168: 45822 | B168: cargo_788c7e5930ab4b6fb4ada406bd32c9de | C168: e594b6cc6cac46dabdad1c19a68db776 | D168: lcv_l_0
... A1391: 45817 | B1391: cargo_174319839d304ba885f1036ed13d3b6f | C1391: 6c5de6716bb7491284b34dd0d503bf44 | D1391: van_1

Sheet доставки 02.06
A1: local date | B1: order_id | C1: executor_profile_id | D1: cargo size & loaders | Y1: https://datalens.yandex-team.ru/am8u3uq2e7ow2-cancels-corporate-clients-c2c?tab=vd&state=22023bc12663
A2: 45816 | B2: cargo_61d433b04e904f849c2d9572f1a67859 | C2: 652a10794db649fd9890bc7a8d63339a | D2: van_0 | S2: Опция
A3: 45816 | B3: 8a142fa292f2ec9d9102748882b8b57d | C3: dac9bceb8ebb412b82a6d72a485f34af | D3: lcv_m_0 | S3: =IF(H3>0,"L1",IF(G3>0,"L0",IF(L3>0,"M2",IF(K3>0,"M1",IF(J3>0,"M0",IF(P3>0,"S2",IF(O3>0,"S1","S0"))))))) -> L0
A4: 45816 | B4: cargo_9cb9426c409c4c25ad0e9c925a49cf79 | C4: 2bf1c6d7cb9f477a96946a8c9401421b | D4: lcv_m_0 | S4: =IF(H4>0,"L1",IF(G4>0,"L0",IF(L4>0,"M2",IF(K4>0,"M1",IF(J4>0,"M0",IF(P4>0,"S2",IF(O4>0,"S1","S0"))))))) -> S1
A5: 45816 | B5: cargo_7cb0e466946f424eb5fc23276e6418ff | C5: 3c0e77983fd84b7c8e32c4769c1bac70 | D5: van_0 | S5: =IF(H5>0,"L1",IF(G5>0,"L0",IF(L5>0,"M2",IF(K5>0,"M1",IF(J5>0,"M0",IF(P5>0,"S2",IF(O5>0,"S1","S0"))))))) -> S0
A6: 45816 | B6: e3875123e7552ad983e9550f76e8241a | C6: 56b95b15fdb04f3a8a3eb8f8fee7175e | D6: van_0 | S6: =IF(H6>0,"L1",IF(G6>0,"L0",IF(L6>0,"M2",IF(K6>0,"M1",IF(J6>0,"M0",IF(P6>0,"S2",IF(O6>0,"S1","S0"))))))) -> S0
A7: 45816 | B7: cargo_fa3cd340c9704c4590e3d2f06f2fa2a5 | C7: e46fb006e7c949b1b93fa34988988b07 | D7: lcv_m_0 | S7: =IF(H7>0,"L1",IF(G7>0,"L0",IF(L7>0,"M2",IF(K7>0,"M1",IF(J7>0,"M0",IF(P7>0,"S2",IF(O7>0,"S1","S0"))))))) -> M0
A8: 45816 | B8: cargo_ae5a00c4fba347fc9bb8b5b3b494cfa5 | C8: f244ffbd17f245ada01bea171788aeae | D8: lcv_m_0 | S8: =IF(H8>0,"L1",IF(G8>0,"L0",IF(L8>0,"M2",IF(K8>0,"M1",IF(J8>0,"M0",IF(P8>0,"S2",IF(O8>0,"S1","S0"))))))) -> S0
A9: 45816 | B9: cargo_ca841316447446b5a389201c54bb609e | C9: 9838f16f6f3945359c6f0680fb3a61bd | D9: lcv_m_0 | S9: =IF(H9>0,"L1",IF(G9>0,"L0",IF(L9>0,"M2",IF(K9>0,"M1",IF(J9>0,"M0",IF(P9>0,"S2",IF(O9>0,"S1","S0"))))))) -> M0
A10: 45816 | B10: cargo_a0f2ff47f3274906a659046df3dd847e | C10: 2fbac590d9ba4abeb426737abe4ea55e | D10: van_0 | S10: =IF(H10>0,"L1",IF(G10>0,"L0",IF(L10>0,"M2",IF(K10>0,"M1",IF(J10>0,"M0",IF(P10>0,"S2",IF(O10>0,"S1","S0"))))))) -> S0
A11: 45816 | B11: cargo_da9efd3291df4c308285bbfd89fa63bc | C11: 0a030ce8c2874aee98d9763eae221bfa | D11: lcv_m_0 | S11: =IF(H11>0,"L1",IF(G11>0,"L0",IF(L11>0,"M2",IF(K11>0,"M1",IF(J11>0,"M0",IF(P11>0,"S2",IF(O11>0,"S1","S0"))))))) -> M2
A12: 45816 | B12: cargo_20dbf6699f0a4917892f6a708aa2cbbc | C12: 0a030ce8c2874aee98d9763eae221bfa | D12: lcv_m_0 | S12: =IF(H12>0,"L1",IF(G12>0,"L0",IF(L12>0,"M2",IF(K12>0,"M1",IF(J12>0,"M0",IF(P12>0,"S2",IF(O12>0,"S1","S0"))))))) -> M1
A13: 45816 | B13: cargo_92e48933cf29462c903710241be3d5e9 | C13: 2f779543d0aa464fb25f986b6929bf79 | D13: lcv_m_0 | S13: =IF(H13>0,"L1",IF(G13>0,"L0",IF(L13>0,"M2",IF(K13>0,"M1",IF(J13>0,"M0",IF(P13>0,"S2",IF(O13>0,"S1","S0"))))))) -> L0
A14: 45816 | B14: cargo_6bc130fefb7049e38a5184bf86332430 | C14: b22ddf9f58af89564a7ef1f8b0e3db0a | D14: lcv_m_1 | S14: =IF(H14>0,"L1",IF(G14>0,"L0",IF(L14>0,"M2",IF(K14>0,"M1",IF(J14>0,"M0",IF(P14>0,"S2",IF(O14>0,"S1","S0"))))))) -> M0
... A174: 45815 | B174: cargo_94d5854d6bb3429d90cb2e46fd95fafc | C174: dae54236a25b411f9ad7d24c24c40398 | D174: lcv_m_2 | S174: =IF(H174>0,"L1",IF(G174>0,"L0",IF(L174>0,"M2",IF(K174>0,"M1",IF(J174>0,"M0",IF(P174>0,"S2",IF(O174>0,"S1","S0"))))))) -> S0
A175: 45815 | B175: cargo_ac6a9c9f99aa4cd7ac3474a9d2d636cd | C175: 2fac1e26a6afadc0dc0bda360c30133b | D175: lcv_m_0
A176: 45815 | B176: cargo_25425be0eaf64301a3e225a2ebabad79 | C176: e702867727604d1b8b3bf3f7347766d8 | D176: van_1
A177: 45815 | B177: cargo_48d56a512df64f289567d4c1f8859c1f | C177: dae54236a25b411f9ad7d24c24c40398 | D177: lcv_m_1
A178: 45815 | B178: cargo_abd6a90ead42408f8901015e37d79205 | C178: 9fe26e4fb0ed47458a3320decc3d0ff4 | D178: van_0
A179: 45815 | B179: cargo_ed5c64c8d97c4ed09f475978eb39784a | C179: ba76de7a2b2c42a394e1ae7cb229cd53 | D179: lcv_m_0
A180: 45815 | B180: cargo_8054e42f57184cddb9a7eaedbd494840 | C180: 2bf1c6d7cb9f477a96946a8c9401421b | D180: lcv_m_0
A181: 45815 | B181: cargo_7ce29a5a4aa748bb9ac73e54df1ff8d3 | C181: 17bda6b26a754998997dc0ca39a3fc1e | D181: van_1
A182: 45815 | B182: 41202a496405e603bd36e5cd66918cb4 | C182: 21c414c8aa5542c085bc35e787e6fa2f | D182: lcv_l_0
A183: 45815 | B183: cargo_e090a06a61d54f3ab64d6ba91b37494c | C183: 7416395cc4804bc188f75b874fa82a50 | D183: van_0
A184: 45815 | B184: cargo_a87602de805b4b1fbff5dc7c2197158a | C184: 874e93aac8fe41c1ab6621da610593e8 | D184: lcv_m_0
A185: 45815 | B185: cargo_91eb3503a4a4478a9298bc9bf06b9983 | C185: d9ec55389a3c4b378502b9c8c59bc906 | D185: lcv_m_0
A186: 45815 | B186: cargo_adef5dc6e4e848278b84ff31529f5387 | C186: 9fd9bb5a62a648c0835c9f610288ee81 | D186: lcv_m_0
... A1689: 45810 | B1689: cargo_f2b6a48d29bb4efca3b764b6bcd2ddc4 | C1689: 701fa8b350a64f6cb12571fe2a3e0dcf | D1689: lcv_l_1

Sheet дох-сть и gmv 23.06

Sheet доставки со стоимостью 23.06
A1: local date | B1: order_id | C1: executor_profile_id | D1: final price w/o vat | E1: cargo size & loaders | J1: GMV водителя | K1: Опция
A2: 45837 | B2: ee8b0636f8f7333fac1b9e7be92a6f1a | C2: 0a26fd96dc404806b3d90f63040dc6c5 | D2: 821 | E2: lcv_m_0 | J2: =H2*I2 -> 13993 | K2: =VLOOKUP(G2,M:Y,13,0) -> L0
A3: 45837 | B3: cargo_645871e6ed22466b839c18422bcff1ea | C3: e2c0e8c53f7b4d6ebe6f0221dacff82e | D3: 505 | E3: van_0 | J3: =H3*I3 -> 3582 | K3: =VLOOKUP(G3,M:Y,13,0) -> S1 | Y3: =IF(O3>0,"L1",IF(N3>0,"L0",IF(S3>0,"M2",IF(R3>0,"M1",IF(Q3>0,"M0",IF(V3>0,"S1","S0")))))) -> L0
A4: 45837 | B4: cargo_0324b61c25834ee79efa9dcb8c9d6716 | C4: 4ffa81da56e84e49acb11efb55b12d0e | D4: 739 | E4: lcv_m_0 | J4: =H4*I4 -> 12685 | K4: =VLOOKUP(G4,M:Y,13,0) -> M0 | Y4: =IF(O4>0,"L1",IF(N4>0,"L0",IF(S4>0,"M2",IF(R4>0,"M1",IF(Q4>0,"M0",IF(V4>0,"S1","S0")))))) -> S1
A5: 45837 | B5: cargo_0ec42f00eb354e90878ad3e9e75f987e | C5: c7198737a55f4514a34b9d80eb3897ba | D5: 1418 | E5: lcv_m_0 | J5: =H5*I5 -> 1185 | K5: =VLOOKUP(G5,M:Y,13,0) -> L0 | Y5: =IF(O5>0,"L1",IF(N5>0,"L0",IF(S5>0,"M2",IF(R5>0,"M1",IF(Q5>0,"M0",IF(V5>0,"S1","S0")))))) -> M0
A6: 45837 | B6: 6bb1aec16da2e840a3d8831d3c571325 | C6: f679cf018fc04fdebdcfebcba3f8f732 | D6: 1252 | E6: van_1 | J6: =H6*I6 -> 14365 | K6: =VLOOKUP(G6,M:Y,13,0) -> S0 | Y6: =IF(O6>0,"L1",IF(N6>0,"L0",IF(S6>0,"M2",IF(R6>0,"M1",IF(Q6>0,"M0",IF(V6>0,"S1","S0")))))) -> L0
A7: 45837 | B7: c2c9bd6610de8dda9308b1bf3a3e1a9c | C7: 1000d7fc3e91483ca6f56b18398c510d | D7: 1124 | E7: van_0 | J7: =H7*I7 -> 11342 | K7: =VLOOKUP(G7,M:Y,13,0) -> M0 | Y7: =IF(O7>0,"L1",IF(N7>0,"L0",IF(S7>0,"M2",IF(R7>0,"M1",IF(Q7>0,"M0",IF(V7>0,"S1","S0")))))) -> S0
A8: 45837 | B8: cargo_dde8fdde4e0345caae77f1371659574a | C8: 0ace786a3e68478ebddf962774267abc | D8: 1662 | E8: lcv_l_1 | J8: =H8*I8 -> 10983 | K8: =VLOOKUP(G8,M:Y,13,0) -> M0 | Y8: =IF(O8>0,"L1",IF(N8>0,"L0",IF(S8>0,"M2",IF(R8>0,"M1",IF(Q8>0,"M0",IF(V8>0,"S1","S0")))))) -> M0
A9: 45837 | B9: cargo_afbcef2def1f4d39a91f34e52cc3f72c | C9: 1c732902212440b3803eb1ad755fe065 | D9: 878 | E9: lcv_m_0 | J9: =H9*I9 -> 3694 | K9: =VLOOKUP(G9,M:Y,13,0) -> L0 | Y9: =IF(O9>0,"L1",IF(N9>0,"L0",IF(S9>0,"M2",IF(R9>0,"M1",IF(Q9>0,"M0",IF(V9>0,"S1","S0")))))) -> M0
A10: 45837 | B10: cargo_8c42cd08052e4e42b6bd4150386f86aa | C10: e01e717546134bdf86dc681d6304eea4 | D10: 869 | E10: lcv_m_0 | J10: =H10*I10 -> 3954 | K10: =VLOOKUP(G10,M:Y,13,0) -> S0 | Y10: =IF(O10>0,"L1",IF(N10>0,"L0",IF(S10>0,"M2",IF(R10>0,"M1",IF(Q10>0,"M0",IF(V10>0,"S1","S0")))))) -> L0
A11: 45837 | B11: cargo_946482721a1d424d912b25dea9484241 | C11: 2cfad911fbe443b2a3ab8bb280388c8f | D11: 657 | E11: lcv_m_0 | J11: =H11*I11 -> 1376 | K11: =VLOOKUP(G11,M:Y,13,0) -> S0 | Y11: =IF(O11>0,"L1",IF(N11>0,"L0",IF(S11>0,"M2",IF(R11>0,"M1",IF(Q11>0,"M0",IF(V11>0,"S1","S0")))))) -> S0
A12: 45837 | B12: cargo_54ecbfb9e20b488d97f5f211a311780a | C12: 4b6d2065e9fa4165849c7acf27390ff2 | D12: 1115 | E12: lcv_l_0 | J12: =H12*I12 -> 7189 | K12: =VLOOKUP(G12,M:Y,13,0) -> M0 | Y12: =IF(O12>0,"L1",IF(N12>0,"L0",IF(S12>0,"M2",IF(R12>0,"M1",IF(Q12>0,"M0",IF(V12>0,"S1","S0")))))) -> S0
A13: 45837 | B13: cargo_f103dbc5e68d490cb654095d05ce412b | C13: bd16ff03f213490b83d9cb489567b7e6 | D13: 1639 | E13: lcv_m_1 | J13: =H13*I13 -> 1110 | K13: =VLOOKUP(G13,M:Y,13,0) -> S0 | Y13: =IF(O13>0,"L1",IF(N13>0,"L0",IF(S13>0,"M2",IF(R13>0,"M1",IF(Q13>0,"M0",IF(V13>0,"S1","S0")))))) -> M0
A14: 45837 | B14: cargo_7c22b5e475ec4530947b225d609ab1e3 | C14: 2bda7a36b086424a94cb76a4752da00d | D14: 796 | E14: lcv_m_0 | J14: =H14*I14 -> 9771 | K14: =VLOOKUP(G14,M:Y,13,0) -> L0 | Y14: =IF(O14>0,"L1",IF(N14>0,"L0",IF(S14>0,"M2",IF(R14>0,"M1",IF(Q14>0,"M0",IF(V14>0,"S1","S0")))))) -> S0
... A179: 45836 | B179: cargo_dfad91d8ba624bffa0d5593df7570238 | C179: 701fa8b350a64f6cb12571fe2a3e0dcf | D179: 2268 | E179: lcv_m_2 | J179: =H179*I179 -> 3475 | K179: =VLOOKUP(G179,M:Y,13,0) -> S1 | Y179: =IF(O179>0,"L1",IF(N179>0,"L0",IF(S179>0,"M2",IF(R179>0,"M1",IF(Q179>0,"M0",IF(V179>0,"S1","S0")))))) -> M1
A180: 45836 | B180: cargo_b7a4261a4c994972ba2f9e7def8821b1 | C180: 3c4313387b834f03b40f2793d52e0a0c | D180: 1304 | E180: lcv_m_0 | Y180: =IF(O180>0,"L1",IF(N180>0,"L0",IF(S180>0,"M2",IF(R180>0,"M1",IF(Q180>0,"M0",IF(V180>0,"S1","S0")))))) -> S1
A181: 45836 | B181: cargo_341e8fd2bf58428fbd80ce009ee6e1b5 | C181: 0302b5e4e94d0459d8f3d2357c2cafd2 | D181: 657 | E181: lcv_m_0 | Y181: =IF(O181>0,"L1",IF(N181>0,"L0",IF(S181>0,"M2",IF(R181>0,"M1",IF(Q181>0,"M0",IF(V181>0,"S1","S0")))))) -> L1
A182: 45836 | B182: 483ae3e785752623b1441c3e185399fd | C182: 1000d7fc3e91483ca6f56b18398c510d | D182: 697 | E182: van_0
A183: 45836 | B183: cargo_003a3909dfb242d48b5963b87522517c | C183: 0302b5e4e94d0459d8f3d2357c2cafd2 | D183: 1220 | E183: lcv_m_0
A184: 45836 | B184: cargo_1b393e0faa0f480bb19b65be38d85702 | C184: dcc81b81230742f8a4d062e96969d9fe | D184: 1121 | E184: lcv_m_0
A185: 45836 | B185: cargo_c3f4762e9173413fae5ee5cec311d2e6 | C185: 2cfad911fbe443b2a3ab8bb280388c8f | D185: 761 | E185: lcv_m_0
A186: 45836 | B186: cargo_193a5a0360fe42bea630a94b91a9b83d | C186: b291823aaee54358b67b9814cab7413b | D186: 867 | E186: lcv_l_0
A187: 45836 | B187: df6c2245584a183e8387532f0d074c80 | C187: 1000d7fc3e91483ca6f56b18398c510d | D187: 546 | E187: van_0
A188: 45836 | B188: cargo_abd6fd68d76c4b39b3569483d1032009 | C188: 506ef9701a4443d6ab3661acf1cbecc9 | D188: 1129 | E188: van_1
A189: 45836 | B189: cargo_8085b07348de4df59bc212baab6ac9f7 | C189: 1c732902212440b3803eb1ad755fe065 | D189: 576.5 | E189: lcv_m_0
A190: 45836 | B190: cargo_849568e02be54dba818df5f1ed075c6b | C190: 598eed6f4fba447b9cda7c21a794ce78 | D190: 1797 | E190: lcv_m_1
A191: 45836 | B191: cargo_d283f7bb0cc04cd897df9462a948de5a | C191: e2e86993374643a49dd7fc9f96930331 | D191: 505 | E191: van_0
A192: 45836 | B192: cargo_1f2badbfa98d4b78a7c1aed53f1c0412 | C192: 79eadb681cea4b3b84b0802e1e2c8d85 | D192: 515 | E192: van_0
A193: 45836 | B193: cargo_638bd2ed10c441988164c713b2a1ccac | C193: 534ab38c238e4336acae2bc2cd1abf83 | D193: 765 | E193: lcv_m_0
... A1493: 45831 | B1493: cargo_cfd6e9970e1541ee83c9d025b690d6a8 | C1493: 2a479c547a854027b2fb7736991065fc | D1493: 1610 | E1493: lcv_m_1
